Workbook
Name \p: #REF!
Name \p: #REF!
Name __R: #REF!
Name _log2: #REF!
Name _log2: #REF!
Name _log3: #REF!
Name _log3: #REF!
Name _log4: #REF!
Name _log4: #REF!
Name _ph1: #REF!
Name _ph2: #REF!
Name _ph3: #REF!
Name _PH8: #REF!
Name _PH8: #REF!
Name _PH9: #REF!
Name _PH9: #REF!
Name _R: #REF!
Name _R: #REF!
Name _REV1: #REF!
Name _REV1: #REF!
Name a: #REF!
Name a: #REF!
Name aa: #REF!
Name abx: #REF!
Name accessories: #REF!
Name accr: #REF!
Name ACont: #REF!
Name Acont2: #REF!
Name AcquisitionProforma: #REF!
Name ad: #REF!
Name AGENCY_PRICING: #REF!,#REF!,#REF!,#REF!,#REF!,#REF!,#REF!,#REF!,#REF!,#REF!,#REF!,#REF!,#REF!,#REF!,#REF!,#REF!,#REF!,#REF!,#REF!,#REF!,#REF!
Name AGENCY_PRICING2: #REF!,#REF!,#REF!,#REF!,#REF!,#REF!,#REF!,#REF!,#REF!,#REF!,#REF!,#REF!
Name Allowances: #REF!
Name Allowances: #REF!
Name Altcashflow: #REF!
Name Am_2nd: #REF!
Name AMORTIZATION: #REF!
Name Amortization__Yrs: #REF!
Name Amortization__Yrs: #REF!
Name Analysis: #REF!
Name AP: #REF!
Name AP: #REF!
Name AR: #REF!
Name AR: #REF!
Name artwork: #REF!
Name asaasasa: #REF!
Name asbestos: #REF!
Name asdfasdf: #REF!
Name asdfasdf: #REF!
Name asSSAs: #REF!
Name Availability: #REF!
Name Bank: #REF!
Name Bankletter: #REF!
Name bathroom: #REF!
Name Binder: #REF!
Name bldgftprnt: #REF!
Name bldgftprnt: #REF!
Name BORDER: #REF!
Name BORDER: #REF!
Name BRIDGES12LAND: #REF!

Sheet Input CMHC MLI Select
A2: CMHC MLE SELECT
B4: TYPE OF FINANCING | C4: NEW CONSTRUCTION | E4: SHELTER TYPE | F4: Standard Rental Housing
B6: AFFORDABILITY
B8: REGION | C8: Urban Center - Toronto | E8: LOCATION&TYPE | F8: Ontario - Wood Frame 12 units and more
B10: MEDIAN ANNUAL SALARY | C10: =VLOOKUP(C8,DATA!B1:C82,2,FALSE) -> 53900
B11: MAX ANNUAL RENT | C11: =C10*0.3 -> 16170
B12: MAX MONTHLY RENT | C12: =C11/12 -> 1347.5
B14: # UNIT TOTAL | C14: =COUNTIFS(Table102[Rental Rate ($/mth)],">0") -> 170
B15: # UNIT AFFORDABLE | C15: =COUNTIFS(Table102[Market Unit],"No") -> 0
B16: UNIT AFFORDABLE % | C16: =IFERROR(C15/C14,0) -> 0 | D16: =IFERROR(C15/C14,"-") -> 0
B18: POINTS DISTRIBUTION | C18: LEVEL 1 | D18: LEVEL 2 | E18: LEVEL 3
B19: Points | C19: 50 | D19: 70 | E19: 100
B20: % of Units | C20: =IF(C4=DATA!F2,0.1,0.4) -> 0.1 | D20: =IF(C4=DATA!F2,0.15,0.6) -> 0.15 | E20: =IF(C4=DATA!F2,0.25,0.8) -> 0.25
B22: Commitment | C22: 10 YEARS
B24: TOTAL POINTS - AFFORDABILTY | D24: =IF(C16<C20,0,IF(AND(C16>=C20,C16<D20),C19,IF(AND(C16>=D20,C16<E20),D19,E19)))+IF(C16<=C20,0,IF(C22="10 YEARS",0,30)) -> 0
B27: ACCESSIBILITY
B29: POINTS DISTRIBUTION | C29: LEVEL 1 | D29: LEVEL 2
B30: Points | C30: 20 | D30: 30
B31: % UNIT CSA B651-18 or Universal Design | C31: 0.15 | D31: 1
B32: % UNIT CSA B651-18 and Universal Design | C32: N/A | D32: 15% accessible 85% build. Universale Design
B33: Rick Hansen Certification | C33: Score 60%-79% | D33: 80% or more
B35: Accesibility Level | C35: NONE
B37: TOTAL POINTS - ACCESSIBILITY | D37: =IF(C35=C29,20,IF(C35=D29,D30,0)) -> 0
B40: ENERGY EFFICIENCY AND GREENHOUSE GASES REDUCTIONS
B42: POINTS DISTRIBUTION | C42: LEVEL 1 | D42: LEVEL 2 | E42: LEVEL 3
B43: Points | C43: 20 | D43: 35 | E43: 50
B44: =IF(C4=DATA!$F$2,"Better Than 2017 NECB/2015 NBC","EE - GHG Reduction over current performance") -> Better Than 2017 NECB/2015 NBC | C44: =IF(C4=DATA!$F$2,0.2,0.15) -> 0.2 | D44: 0.25 | E44: 0.4
B46: ENERGY EFFICIENCY | C46: LEVEL 3
B48: TOTAL POINTS - ENERGY EFFICIENCY | D48: =IF(C46=C42,30,IF(C46=D42,D43,IF(C46=E42,E43,0))) -> 50
B52: TOTAL POINTS - MLI SELECT | E52: =D48+D37+D24 -> 50
B54: FLEXIBILITIES
B55: Points | C55: LTV | D55: DCR | E55: Amortization
B56: Min 50 points | C56: =IF($C$4=DATA!F$2,"Up to 95%","Up to 85%") -> Up to 95% | D56: 1.1 | E56: Up to 40 years
B57: Min 70 points | C57: =IF($C$4=DATA!F$2,"Up to 95%","Up to 95%") -> Up to 95% | D57: 1.1 | E57: Up to 45 years
B58: Min 100 points | C58: =IF($C$4=DATA!F$2,"Up to 95%","Up to 95%") -> Up to 95% | D58: 1.1 | E58: Up to 50 years
B62: Shelter Type | C62: =IF(F4=DATA!F58,DATA!F58,DATA!I58) -> Standard Rental Housing
B63: Type of Financing | C63: =C4 -> NEW CONSTRUCTION
B64: MLI Select Point | C64: =E52 -> 50
B65: Actual LTV | C65: ='Proforma Construction'!D50 -> 0.75998331
B66: LTV Tier | C66: {=_xlfn.IFS(C65<=65%,65%,C65<=70%,70%,C65<=75%,75%,C65<=80%,80%,C65<=85%,85%,C65<=90%,90%,C65>90%,">90%")} -> 0.8
B67: Base Premium | C67: {=IF(AND(C62="standard rental housing",C63="new construction"),_xlfn.IFS($C$65<=65%,DATA!$K$50,$C$65<=70%,DATA!$K$51,$C$65<=75%,DATA!$K$52,$C$65<=80%,DATA!$K$53,$C$65<=85%,DATA!$K$54,$C$65<=90%,DATA!$K$55,$C$65>90%,DATA!$K$56),IF(AND(C62="standard rental housing",C63="PURCHASE - REFINANCE"),_xlfn.IFS($C$65<=65%,DATA!$L$50,$C$65<=70%,DATA!$L$51,$C$65<=75%,DATA!$L$52,$C$65<=80%,DATA!$L$53,$C$65<=85%,DATA!$L$54,$C$65<=90%,DATA!$L$55,$C$65>90%,DATA!$L$56),IF(AND(C62="all other shelter models",C63="new construction"),_xlfn.IFS($C$65<=65%,DATA!$K$60,$C$65<=70%,DATA!$K$61,$C$65<=75%,DATA!$K$62,$C$65<=80%,DATA!$K$63,$C$65<=85%,DATA!$K$64,$C$65<=90%,DATA!$K$65,$C$65>90%,DATA!$K$66),IF(AND(C62="all other shelter models",C63="PURCHASE - REFINANCE"),_xlfn.IFS($C$65<=65%,DATA!$L$60,$C$65<=70%,DATA!$L$61,$C$65<=75%,DATA!$L$62,$C$65<=80%,DATA!$L$63,$C$65<=85%,DATA!$L$64,$C$65<=90%,DATA!$L$65,$C$65>90%,DATA!$L$66),""))))} -> 0.05
B68: Amortization Surcharge | C68: =0.25%*('Proforma Construction'!G50-25)/5 -> 0.0075
B69: Non Resident Space | C69: =IF(D69="yes",1%,0) -> 0 | D69: NO
B70: Second Mortgage | C70: =IF(D70="yes",1%,0) -> 0 | D70: NO
B71: EGI not Met | C71: =IF(AND(D71="yes",C63="purchase - refinance"),1%,0) -> 0 | D71: NO
B72: Discount | C72: =IF(E52<50,0,IF(E52<70,10%,IF(E52<100,20%,30%))) -> 0.1
B73: Premium | C73: =(C67+C68+C69+C70+C71)*(1-C72) -> 0.05175
B74: Application Fee | C74: =IF(C4="NEW CONSTRUCTION", MIN( 200*MIN(C14,100) + 100*MAX(C14-100,0), 55000), IF(C4="PURCHASE - REFINANCE", MIN( 150*MIN(C14,100) + 100*MAX(C14-100,0), 50000), "" ) ) -> 27000
B75: Amortization | C75: =IF(E52>=100,50,IF(E52>=70,45,40)) -> 40
B77: Expenses | D77: % of EGI | E77: PUPA
B78: Management Fee | D78: =VLOOKUP($F$8,DATA!$K$2:$U$16,6,FALSE) -> 0.0425 | E78: =IFERROR(F78/C14,"-") -> 1469.55 | F78: =D78*'Proforma Construction'!I14 -> 249823.5
B79: Maintenance | D79: =IFERROR(,"-") -> 0 | E79: =VLOOKUP($F$8,DATA!$K$2:$U$16,5,FALSE) -> 830 | F79: =E79*C14 -> 141100
B80: Wages & Salaries | D80: =IFERROR(F80/'Proforma Construction'!I14,"-") -> 0 | E80: =VLOOKUP($F$8,DATA!$K$2:$U$16,7,FALSE) -> 555 | F80: =E80*C52 -> 0
B81: General & Admin | D81: =VLOOKUP($F$8,DATA!$K$2:$U$16,11,FALSE) -> 0.01 | E81: =IFERROR(F81/C95,"-") -> - | F81: =D81*I70 -> 0
B82: Replacement Reserve | D82: =IFERROR(F82/+I70,"-") -> - | E82: 300 | F82: =E82*C14 -> 51000
B83: Replacement Reserve(Garden suite heat pump) | D83: =IFERROR(F83/I70,"-") -> - | E83: =F83/1 -> 190 | F83: 190
B84: Total Operating Expenses | D84: =SUM(F74:F77) -> 0 | E84: 6863 | F84: =SUM(I74:I83) -> 0

Sheet Rent Roll(MLI Select)
A1: Unit Details (start with Unit #, Rental Rate or Unit Size) | L1: Unit Designations? | T1: What's included in the unit/rent?
A2: Unit Type | B2: Residential Stream Source | C2: Basement? | D2: Unit # | E2: Vacant? | F2: Rental Rate ($/mth) | G2: Monthly Rev. Accepted | H2: Annual Rev. Submitted | I2: Annual Rev. Accepted | J2: Unit Size (sq ft) | K2: Floor Area Accepted (SF) | L2: Market Unit | M2: Affordable Unit | N2: Subsidized Unit | O2: Care Services | P2: Affordable Care | Q2: Non-Res. Stream Source | R2: Business Type | S2: Lease Type | T2: Bulk Lease Unit | U2: Den Included Unit | V2: Second Bathroom | W2: Heating | X2: Electricity | Y2: Water | Z2: Washer/Dryer | AA2: Stove/Fridge | AB2: Dishwasher | AC2: Parking | AD2: Furniture | AE2: Other
A3: =IF(Table10[[#This Row],[Unit Type]]=0,"",Table10[[#This Row],[Unit Type]]) -> 1 Bedroom | B3: =IF(Table10[[#This Row],[Residential Stream Source]]=0,"",Table10[[#This Row],[Residential Stream Source]]) | C3: =IF(Table10[[#This Row],[Basement?]]=0,"",Table10[[#This Row],[Basement?]]) | D3: =IF(Table10[[#This Row],[Unit '#]]=0,"",Table10[[#This Row],[Unit '#]]) -> 1 | E3: =IF(Table10[[#This Row],[Vacant?]]=0,"",Table10[[#This Row],[Vacant?]]) -> Yes | F3: =IF(Table10[[#This Row],[Rental Rate ($/mth)]]=0,"",Table10[[#This Row],[Rental Rate ($/mth)]]) -> 2490 | J3: =IF(Table10[[#This Row],[Unit Size (sq ft)]]=0,"",Table10[[#This Row],[Unit Size (sq ft)]]) -> 624 | L3: =Table10[[#This Row],[Market Unit]] -> Yes | M3: =Table10[[#This Row],[Affordable Unit]] -> No | N3: =IF(Table10[[#This Row],[Subsidized Unit]]=0,"",Table10[[#This Row],[Subsidized Unit]]) | O3: =IF(Table10[[#This Row],[Care Services]]=0,"",Table10[[#This Row],[Care Services]]) | P3: =IF(Table10[[#This Row],[Affordable Care]]=0,"",Table10[[#This Row],[Affordable Care]]) | T3: =IF(Table10[[#This Row],[Bulk Lease Unit]]=0,"",Table10[[#This Row],[Bulk Lease Unit]]) | U3: =IF(Table10[[#This Row],[Den Included Unit]]=0,"",Table10[[#This Row],[Den Included Unit]]) | V3: =IF(Table10[[#This Row],[Second Bathroom]]=0,"",Table10[[#This Row],[Second Bathroom]]) | W3: =IF(Table10[[#This Row],[Heating]]=0,"",Table10[[#This Row],[Heating]]) | X3: =IF(Table10[[#This Row],[Electricity]]=0,"",Table10[[#This Row],[Electricity]]) | Y3: =IF(Table10[[#This Row],[Water]]=0,"",Table10[[#This Row],[Water]]) | Z3: =IF(Table10[[#This Row],[Washer/Dryer]]=0,"",Table10[[#This Row],[Washer/Dryer]]) | AA3: =IF(Table10[[#This Row],[Stove/Fridge]]=0,"",Table10[[#This Row],[Stove/Fridge]]) | AB3: =IF(Table10[[#This Row],[Dishwasher]]=0,"",Table10[[#This Row],[Dishwasher]]) | AC3: =IF(Table10[[#This Row],[Parking]]=0,"",Table10[[#This Row],[Parking]]) | AD3: =IF(Table10[[#This Row],[Furniture]]=0,"",Table10[[#This Row],[Furniture]]) -> No | AE3: =IF(Table10[[#This Row],[Other]]=0,"",Table10[[#This Row],[Other]])
A4: =IF(Table10[[#This Row],[Unit Type]]=0,"",Table10[[#This Row],[Unit Type]]) -> 1 Bedroom | B4: =IF(Table10[[#This Row],[Residential Stream Source]]=0,"",Table10[[#This Row],[Residential Stream Source]]) | C4: =IF(Table10[[#This Row],[Basement?]]=0,"",Table10[[#This Row],[Basement?]]) | D4: =IF(Table10[[#This Row],[Unit '#]]=0,"",Table10[[#This Row],[Unit '#]]) -> 2 | E4: =IF(Table10[[#This Row],[Vacant?]]=0,"",Table10[[#This Row],[Vacant?]]) -> Yes | F4: =IF(Table10[[#This Row],[Rental Rate ($/mth)]]=0,"",Table10[[#This Row],[Rental Rate ($/mth)]]) -> 2490 | J4: =IF(Table10[[#This Row],[Unit Size (sq ft)]]=0,"",Table10[[#This Row],[Unit Size (sq ft)]]) -> 624 | L4: =Table10[[#This Row],[Market Unit]] -> Yes | M4: =Table10[[#This Row],[Affordable Unit]] -> No | N4: =IF(Table10[[#This Row],[Subsidized Unit]]=0,"",Table10[[#This Row],[Subsidized Unit]]) | O4: =IF(Table10[[#This Row],[Care Services]]=0,"",Table10[[#This Row],[Care Services]]) | P4: =IF(Table10[[#This Row],[Affordable Care]]=0,"",Table10[[#This Row],[Affordable Care]]) | T4: =IF(Table10[[#This Row],[Bulk Lease Unit]]=0,"",Table10[[#This Row],[Bulk Lease Unit]]) | U4: =IF(Table10[[#This Row],[Den Included Unit]]=0,"",Table10[[#This Row],[Den Included Unit]]) | V4: =IF(Table10[[#This Row],[Second Bathroom]]=0,"",Table10[[#This Row],[Second Bathroom]]) | W4: =IF(Table10[[#This Row],[Heating]]=0,"",Table10[[#This Row],[Heating]]) | X4: =IF(Table10[[#This Row],[Electricity]]=0,"",Table10[[#This Row],[Electricity]]) | Y4: =IF(Table10[[#This Row],[Water]]=0,"",Table10[[#This Row],[Water]]) | Z4: =IF(Table10[[#This Row],[Washer/Dryer]]=0,"",Table10[[#This Row],[Washer/Dryer]]) | AA4: =IF(Table10[[#This Row],[Stove/Fridge]]=0,"",Table10[[#This Row],[Stove/Fridge]]) | AB4: =IF(Table10[[#This Row],[Dishwasher]]=0,"",Table10[[#This Row],[Dishwasher]]) | AC4: =IF(Table10[[#This Row],[Parking]]=0,"",Table10[[#This Row],[Parking]]) | AD4: =IF(Table10[[#This Row],[Furniture]]=0,"",Table10[[#This Row],[Furniture]]) | AE4: =IF(Table10[[#This Row],[Other]]=0,"",Table10[[#This Row],[Other]])
A5: =IF(Table10[[#This Row],[Unit Type]]=0,"",Table10[[#This Row],[Unit Type]]) -> 1 Bedroom | B5: =IF(Table10[[#This Row],[Residential Stream Source]]=0,"",Table10[[#This Row],[Residential Stream Source]]) | C5: =IF(Table10[[#This Row],[Basement?]]=0,"",Table10[[#This Row],[Basement?]]) | D5: =IF(Table10[[#This Row],[Unit '#]]=0,"",Table10[[#This Row],[Unit '#]]) -> 3 | E5: =IF(Table10[[#This Row],[Vacant?]]=0,"",Table10[[#This Row],[Vacant?]]) -> Yes | F5: =IF(Table10[[#This Row],[Rental Rate ($/mth)]]=0,"",Table10[[#This Row],[Rental Rate ($/mth)]]) -> 2490 | J5: =IF(Table10[[#This Row],[Unit Size (sq ft)]]=0,"",Table10[[#This Row],[Unit Size (sq ft)]]) -> 624 | L5: =Table10[[#This Row],[Market Unit]] -> Yes | M5: =Table10[[#This Row],[Affordable Unit]] -> No | N5: =IF(Table10[[#This Row],[Subsidized Unit]]=0,"",Table10[[#This Row],[Subsidized Unit]]) | O5: =IF(Table10[[#This Row],[Care Services]]=0,"",Table10[[#This Row],[Care Services]]) | P5: =IF(Table10[[#This Row],[Affordable Care]]=0,"",Table10[[#This Row],[Affordable Care]]) | T5: =IF(Table10[[#This Row],[Bulk Lease Unit]]=0,"",Table10[[#This Row],[Bulk Lease Unit]]) | U5: =IF(Table10[[#This Row],[Den Included Unit]]=0,"",Table10[[#This Row],[Den Included Unit]]) | V5: =IF(Table10[[#This Row],[Second Bathroom]]=0,"",Table10[[#This Row],[Second Bathroom]]) | W5: =IF(Table10[[#This Row],[Heating]]=0,"",Table10[[#This Row],[Heating]]) | X5: =IF(Table10[[#This Row],[Electricity]]=0,"",Table10[[#This Row],[Electricity]]) | Y5: =IF(Table10[[#This Row],[Water]]=0,"",Table10[[#This Row],[Water]]) | Z5: =IF(Table10[[#This Row],[Washer/Dryer]]=0,"",Table10[[#This Row],[Washer/Dryer]]) | AA5: =IF(Table10[[#This Row],[Stove/Fridge]]=0,"",Table10[[#This Row],[Stove/Fridge]]) | AB5: =IF(Table10[[#This Row],[Dishwasher]]=0,"",Table10[[#This Row],[Dishwasher]]) | AC5: =IF(Table10[[#This Row],[Parking]]=0,"",Table10[[#This Row],[Parking]]) | AD5: =IF(Table10[[#This Row],[Furniture]]=0,"",Table10[[#This Row],[Furniture]]) | AE5: =IF(Table10[[#This Row],[Other]]=0,"",Table10[[#This Row],[Other]])
A6: =IF(Table10[[#This Row],[Unit Type]]=0,"",Table10[[#This Row],[Unit Type]]) -> 1 Bedroom | B6: =IF(Table10[[#This Row],[Residential Stream Source]]=0,"",Table10[[#This Row],[Residential Stream Source]]) | C6: =IF(Table10[[#This Row],[Basement?]]=0,"",Table10[[#This Row],[Basement?]]) | D6: =IF(Table10[[#This Row],[Unit '#]]=0,"",Table10[[#This Row],[Unit '#]]) -> 4 | E6: =IF(Table10[[#This Row],[Vacant?]]=0,"",Table10[[#This Row],[Vacant?]]) -> Yes | F6: =IF(Table10[[#This Row],[Rental Rate ($/mth)]]=0,"",Table10[[#This Row],[Rental Rate ($/mth)]]) -> 2490 | J6: =IF(Table10[[#This Row],[Unit Size (sq ft)]]=0,"",Table10[[#This Row],[Unit Size (sq ft)]]) -> 624 | L6: =Table10[[#This Row],[Market Unit]] -> Yes | M6: =Table10[[#This Row],[Affordable Unit]] -> No | N6: =IF(Table10[[#This Row],[Subsidized Unit]]=0,"",Table10[[#This Row],[Subsidized Unit]]) | O6: =IF(Table10[[#This Row],[Care Services]]=0,"",Table10[[#This Row],[Care Services]]) | P6: =IF(Table10[[#This Row],[Affordable Care]]=0,"",Table10[[#This Row],[Affordable Care]]) | T6: =IF(Table10[[#This Row],[Bulk Lease Unit]]=0,"",Table10[[#This Row],[Bulk Lease Unit]]) | U6: =IF(Table10[[#This Row],[Den Included Unit]]=0,"",Table10[[#This Row],[Den Included Unit]]) | V6: =IF(Table10[[#This Row],[Second Bathroom]]=0,"",Table10[[#This Row],[Second Bathroom]]) | W6: =IF(Table10[[#This Row],[Heating]]=0,"",Table10[[#This Row],[Heating]]) | X6: =IF(Table10[[#This Row],[Electricity]]=0,"",Table10[[#This Row],[Electricity]]) | Y6: =IF(Table10[[#This Row],[Water]]=0,"",Table10[[#This Row],[Water]]) | Z6: =IF(Table10[[#This Row],[Washer/Dryer]]=0,"",Table10[[#This Row],[Washer/Dryer]]) | AA6: =IF(Table10[[#This Row],[Stove/Fridge]]=0,"",Table10[[#This Row],[Stove/Fridge]]) | AB6: =IF(Table10[[#This Row],[Dishwasher]]=0,"",Table10[[#This Row],[Dishwasher]]) | AC6: =IF(Table10[[#This Row],[Parking]]=0,"",Table10[[#This Row],[Parking]]) | AD6: =IF(Table10[[#This Row],[Furniture]]=0,"",Table10[[#This Row],[Furniture]]) | AE6: =IF(Table10[[#This Row],[Other]]=0,"",Table10[[#This Row],[Other]])
A7: =IF(Table10[[#This Row],[Unit Type]]=0,"",Table10[[#This Row],[Unit Type]]) -> 1 Bedroom | B7: =IF(Table10[[#This Row],[Residential Stream Source]]=0,"",Table10[[#This Row],[Residential Stream Source]]) | C7: =IF(Table10[[#This Row],[Basement?]]=0,"",Table10[[#This Row],[Basement?]]) | D7: =IF(Table10[[#This Row],[Unit '#]]=0,"",Table10[[#This Row],[Unit '#]]) -> 5 | E7: =IF(Table10[[#This Row],[Vacant?]]=0,"",Table10[[#This Row],[Vacant?]]) -> Yes | F7: =IF(Table10[[#This Row],[Rental Rate ($/mth)]]=0,"",Table10[[#This Row],[Rental Rate ($/mth)]]) -> 2490 | J7: =IF(Table10[[#This Row],[Unit Size (sq ft)]]=0,"",Table10[[#This Row],[Unit Size (sq ft)]]) -> 624 | L7: =Table10[[#This Row],[Market Unit]] -> Yes | M7: =Table10[[#This Row],[Affordable Unit]] -> No | N7: =IF(Table10[[#This Row],[Subsidized Unit]]=0,"",Table10[[#This Row],[Subsidized Unit]]) | O7: =IF(Table10[[#This Row],[Care Services]]=0,"",Table10[[#This Row],[Care Services]]) | P7: =IF(Table10[[#This Row],[Affordable Care]]=0,"",Table10[[#This Row],[Affordable Care]]) | T7: =IF(Table10[[#This Row],[Bulk Lease Unit]]=0,"",Table10[[#This Row],[Bulk Lease Unit]]) | U7: =IF(Table10[[#This Row],[Den Included Unit]]=0,"",Table10[[#This Row],[Den Included Unit]]) | V7: =IF(Table10[[#This Row],[Second Bathroom]]=0,"",Table10[[#This Row],[Second Bathroom]]) | W7: =IF(Table10[[#This Row],[Heating]]=0,"",Table10[[#This Row],[Heating]]) | X7: =IF(Table10[[#This Row],[Electricity]]=0,"",Table10[[#This Row],[Electricity]]) | Y7: =IF(Table10[[#This Row],[Water]]=0,"",Table10[[#This Row],[Water]]) | Z7: =IF(Table10[[#This Row],[Washer/Dryer]]=0,"",Table10[[#This Row],[Washer/Dryer]]) | AA7: =IF(Table10[[#This Row],[Stove/Fridge]]=0,"",Table10[[#This Row],[Stove/Fridge]]) | AB7: =IF(Table10[[#This Row],[Dishwasher]]=0,"",Table10[[#This Row],[Dishwasher]]) | AC7: =IF(Table10[[#This Row],[Parking]]=0,"",Table10[[#This Row],[Parking]]) | AD7: =IF(Table10[[#This Row],[Furniture]]=0,"",Table10[[#This Row],[Furniture]]) | AE7: =IF(Table10[[#This Row],[Other]]=0,"",Table10[[#This Row],[Other]])
A8: =IF(Table10[[#This Row],[Unit Type]]=0,"",Table10[[#This Row],[Unit Type]]) -> 1 Bedroom | D8: =IF(Table10[[#This Row],[Unit '#]]=0,"",Table10[[#This Row],[Unit '#]]) -> 6 | F8: =IF(Table10[[#This Row],[Rental Rate ($/mth)]]=0,"",Table10[[#This Row],[Rental Rate ($/mth)]]) -> 2490 | J8: =IF(Table10[[#This Row],[Unit Size (sq ft)]]=0,"",Table10[[#This Row],[Unit Size (sq ft)]]) -> 624 | L8: =Table10[[#This Row],[Market Unit]] -> Yes | M8: =Table10[[#This Row],[Affordable Unit]] -> No | N8: =IF(Table10[[#This Row],[Subsidized Unit]]=0,"",Table10[[#This Row],[Subsidized Unit]]) | O8: =IF(Table10[[#This Row],[Care Services]]=0,"",Table10[[#This Row],[Care Services]]) | P8: =IF(Table10[[#This Row],[Affordable Care]]=0,"",Table10[[#This Row],[Affordable Care]]) | T8: =IF(Table10[[#This Row],[Bulk Lease Unit]]=0,"",Table10[[#This Row],[Bulk Lease Unit]]) | U8: =IF(Table10[[#This Row],[Den Included Unit]]=0,"",Table10[[#This Row],[Den Included Unit]]) | V8: =IF(Table10[[#This Row],[Second Bathroom]]=0,"",Table10[[#This Row],[Second Bathroom]]) | W8: =IF(Table10[[#This Row],[Heating]]=0,"",Table10[[#This Row],[Heating]]) | X8: =IF(Table10[[#This Row],[Electricity]]=0,"",Table10[[#This Row],[Electricity]]) | Y8: =IF(Table10[[#This Row],[Water]]=0,"",Table10[[#This Row],[Water]]) | Z8: =IF(Table10[[#This Row],[Washer/Dryer]]=0,"",Table10[[#This Row],[Washer/Dryer]]) | AA8: =IF(Table10[[#This Row],[Stove/Fridge]]=0,"",Table10[[#This Row],[Stove/Fridge]]) | AB8: =IF(Table10[[#This Row],[Dishwasher]]=0,"",Table10[[#This Row],[Dishwasher]]) | AC8: =IF(Table10[[#This Row],[Parking]]=0,"",Table10[[#This Row],[Parking]]) | AD8: =IF(Table10[[#This Row],[Furniture]]=0,"",Table10[[#This Row],[Furniture]]) | AE8: =IF(Table10[[#This Row],[Other]]=0,"",Table10[[#This Row],[Other]])
A9: =IF(Table10[[#This Row],[Unit Type]]=0,"",Table10[[#This Row],[Unit Type]]) -> 1 Bedroom | D9: =IF(Table10[[#This Row],[Unit '#]]=0,"",Table10[[#This Row],[Unit '#]]) -> 7 | F9: =IF(Table10[[#This Row],[Rental Rate ($/mth)]]=0,"",Table10[[#This Row],[Rental Rate ($/mth)]]) -> 2490 | J9: =IF(Table10[[#This Row],[Unit Size (sq ft)]]=0,"",Table10[[#This Row],[Unit Size (sq ft)]]) -> 624 | L9: =Table10[[#This Row],[Market Unit]] -> Yes | M9: =Table10[[#This Row],[Affordable Unit]] -> No | N9: =IF(Table10[[#This Row],[Subsidized Unit]]=0,"",Table10[[#This Row],[Subsidized Unit]]) | O9: =IF(Table10[[#This Row],[Care Services]]=0,"",Table10[[#This Row],[Care Services]]) | P9: =IF(Table10[[#This Row],[Affordable Care]]=0,"",Table10[[#This Row],[Affordable Care]]) | T9: =IF(Table10[[#This Row],[Bulk Lease Unit]]=0,"",Table10[[#This Row],[Bulk Lease Unit]]) | U9: =IF(Table10[[#This Row],[Den Included Unit]]=0,"",Table10[[#This Row],[Den Included Unit]]) | V9: =IF(Table10[[#This Row],[Second Bathroom]]=0,"",Table10[[#This Row],[Second Bathroom]]) | W9: =IF(Table10[[#This Row],[Heating]]=0,"",Table10[[#This Row],[Heating]]) | X9: =IF(Table10[[#This Row],[Electricity]]=0,"",Table10[[#This Row],[Electricity]]) | Y9: =IF(Table10[[#This Row],[Water]]=0,"",Table10[[#This Row],[Water]]) | Z9: =IF(Table10[[#This Row],[Washer/Dryer]]=0,"",Table10[[#This Row],[Washer/Dryer]]) | AA9: =IF(Table10[[#This Row],[Stove/Fridge]]=0,"",Table10[[#This Row],[Stove/Fridge]]) | AB9: =IF(Table10[[#This Row],[Dishwasher]]=0,"",Table10[[#This Row],[Dishwasher]]) | AC9: =IF(Table10[[#This Row],[Parking]]=0,"",Table10[[#This Row],[Parking]]) | AD9: =IF(Table10[[#This Row],[Furniture]]=0,"",Table10[[#This Row],[Furniture]]) | AE9: =IF(Table10[[#This Row],[Other]]=0,"",Table10[[#This Row],[Other]])
A10: =IF(Table10[[#This Row],[Unit Type]]=0,"",Table10[[#This Row],[Unit Type]]) -> 1 Bedroom | D10: =IF(Table10[[#This Row],[Unit '#]]=0,"",Table10[[#This Row],[Unit '#]]) -> 8 | F10: =IF(Table10[[#This Row],[Rental Rate ($/mth)]]=0,"",Table10[[#This Row],[Rental Rate ($/mth)]]) -> 2490 | J10: =IF(Table10[[#This Row],[Unit Size (sq ft)]]=0,"",Table10[[#This Row],[Unit Size (sq ft)]]) -> 624 | L10: =Table10[[#This Row],[Market Unit]] -> Yes | M10: =Table10[[#This Row],[Affordable Unit]] -> No | N10: =IF(Table10[[#This Row],[Subsidized Unit]]=0,"",Table10[[#This Row],[Subsidized Unit]]) | O10: =IF(Table10[[#This Row],[Care Services]]=0,"",Table10[[#This Row],[Care Services]]) | P10: =IF(Table10[[#This Row],[Affordable Care]]=0,"",Table10[[#This Row],[Affordable Care]]) | T10: =IF(Table10[[#This Row],[Bulk Lease Unit]]=0,"",Table10[[#This Row],[Bulk Lease Unit]]) | U10: =IF(Table10[[#This Row],[Den Included Unit]]=0,"",Table10[[#This Row],[Den Included Unit]]) | V10: =IF(Table10[[#This Row],[Second Bathroom]]=0,"",Table10[[#This Row],[Second Bathroom]]) | W10: =IF(Table10[[#This Row],[Heating]]=0,"",Table10[[#This Row],[Heating]]) | X10: =IF(Table10[[#This Row],[Electricity]]=0,"",Table10[[#This Row],[Electricity]]) | Y10: =IF(Table10[[#This Row],[Water]]=0,"",Table10[[#This Row],[Water]]) | Z10: =IF(Table10[[#This Row],[Washer/Dryer]]=0,"",Table10[[#This Row],[Washer/Dryer]]) | AA10: =IF(Table10[[#This Row],[Stove/Fridge]]=0,"",Table10[[#This Row],[Stove/Fridge]]) | AB10: =IF(Table10[[#This Row],[Dishwasher]]=0,"",Table10[[#This Row],[Dishwasher]]) | AC10: =IF(Table10[[#This Row],[Parking]]=0,"",Table10[[#This Row],[Parking]]) | AD10: =IF(Table10[[#This Row],[Furniture]]=0,"",Table10[[#This Row],[Furniture]]) | AE10: =IF(Table10[[#This Row],[Other]]=0,"",Table10[[#This Row],[Other]])
A11: =IF(Table10[[#This Row],[Unit Type]]=0,"",Table10[[#This Row],[Unit Type]]) -> 1 Bedroom | D11: =IF(Table10[[#This Row],[Unit '#]]=0,"",Table10[[#This Row],[Unit '#]]) -> 9 | F11: =IF(Table10[[#This Row],[Rental Rate ($/mth)]]=0,"",Table10[[#This Row],[Rental Rate ($/mth)]]) -> 2490 | J11: =IF(Table10[[#This Row],[Unit Size (sq ft)]]=0,"",Table10[[#This Row],[Unit Size (sq ft)]]) -> 624 | L11: =Table10[[#This Row],[Market Unit]] -> Yes | M11: =Table10[[#This Row],[Affordable Unit]] -> No | N11: =IF(Table10[[#This Row],[Subsidized Unit]]=0,"",Table10[[#This Row],[Subsidized Unit]]) | O11: =IF(Table10[[#This Row],[Care Services]]=0,"",Table10[[#This Row],[Care Services]]) | P11: =IF(Table10[[#This Row],[Affordable Care]]=0,"",Table10[[#This Row],[Affordable Care]]) | T11: =IF(Table10[[#This Row],[Bulk Lease Unit]]=0,"",Table10[[#This Row],[Bulk Lease Unit]]) | U11: =IF(Table10[[#This Row],[Den Included Unit]]=0,"",Table10[[#This Row],[Den Included Unit]]) | V11: =IF(Table10[[#This Row],[Second Bathroom]]=0,"",Table10[[#This Row],[Second Bathroom]]) | W11: =IF(Table10[[#This Row],[Heating]]=0,"",Table10[[#This Row],[Heating]]) | X11: =IF(Table10[[#This Row],[Electricity]]=0,"",Table10[[#This Row],[Electricity]]) | Y11: =IF(Table10[[#This Row],[Water]]=0,"",Table10[[#This Row],[Water]]) | Z11: =IF(Table10[[#This Row],[Washer/Dryer]]=0,"",Table10[[#This Row],[Washer/Dryer]]) | AA11: =IF(Table10[[#This Row],[Stove/Fridge]]=0,"",Table10[[#This Row],[Stove/Fridge]]) | AB11: =IF(Table10[[#This Row],[Dishwasher]]=0,"",Table10[[#This Row],[Dishwasher]]) | AC11: =IF(Table10[[#This Row],[Parking]]=0,"",Table10[[#This Row],[Parking]]) | AD11: =IF(Table10[[#This Row],[Furniture]]=0,"",Table10[[#This Row],[Furniture]]) | AE11: =IF(Table10[[#This Row],[Other]]=0,"",Table10[[#This Row],[Other]])
A12: =IF(Table10[[#This Row],[Unit Type]]=0,"",Table10[[#This Row],[Unit Type]]) -> 1 Bedroom | D12: =IF(Table10[[#This Row],[Unit '#]]=0,"",Table10[[#This Row],[Unit '#]]) -> 10 | F12: =IF(Table10[[#This Row],[Rental Rate ($/mth)]]=0,"",Table10[[#This Row],[Rental Rate ($/mth)]]) -> 2490 | J12: =IF(Table10[[#This Row],[Unit Size (sq ft)]]=0,"",Table10[[#This Row],[Unit Size (sq ft)]]) -> 624 | L12: =Table10[[#This Row],[Market Unit]] -> Yes | M12: =Table10[[#This Row],[Affordable Unit]] -> No | N12: =IF(Table10[[#This Row],[Subsidized Unit]]=0,"",Table10[[#This Row],[Subsidized Unit]]) | O12: =IF(Table10[[#This Row],[Care Services]]=0,"",Table10[[#This Row],[Care Services]]) | P12: =IF(Table10[[#This Row],[Affordable Care]]=0,"",Table10[[#This Row],[Affordable Care]]) | T12: =IF(Table10[[#This Row],[Bulk Lease Unit]]=0,"",Table10[[#This Row],[Bulk Lease Unit]]) | U12: =IF(Table10[[#This Row],[Den Included Unit]]=0,"",Table10[[#This Row],[Den Included Unit]]) | V12: =IF(Table10[[#This Row],[Second Bathroom]]=0,"",Table10[[#This Row],[Second Bathroom]]) | W12: =IF(Table10[[#This Row],[Heating]]=0,"",Table10[[#This Row],[Heating]]) | X12: =IF(Table10[[#This Row],[Electricity]]=0,"",Table10[[#This Row],[Electricity]]) | Y12: =IF(Table10[[#This Row],[Water]]=0,"",Table10[[#This Row],[Water]]) | Z12: =IF(Table10[[#This Row],[Washer/Dryer]]=0,"",Table10[[#This Row],[Washer/Dryer]]) | AA12: =IF(Table10[[#This Row],[Stove/Fridge]]=0,"",Table10[[#This Row],[Stove/Fridge]]) | AB12: =IF(Table10[[#This Row],[Dishwasher]]=0,"",Table10[[#This Row],[Dishwasher]]) | AC12: =IF(Table10[[#This Row],[Parking]]=0,"",Table10[[#This Row],[Parking]]) | AD12: =IF(Table10[[#This Row],[Furniture]]=0,"",Table10[[#This Row],[Furniture]]) | AE12: =IF(Table10[[#This Row],[Other]]=0,"",Table10[[#This Row],[Other]])
A13: =IF(Table10[[#This Row],[Unit Type]]=0,"",Table10[[#This Row],[Unit Type]]) -> 1 Bedroom | D13: =IF(Table10[[#This Row],[Unit '#]]=0,"",Table10[[#This Row],[Unit '#]]) -> 11 | F13: =IF(Table10[[#This Row],[Rental Rate ($/mth)]]=0,"",Table10[[#This Row],[Rental Rate ($/mth)]]) -> 2490 | J13: =IF(Table10[[#This Row],[Unit Size (sq ft)]]=0,"",Table10[[#This Row],[Unit Size (sq ft)]]) -> 624 | L13: =Table10[[#This Row],[Market Unit]] -> Yes | M13: =Table10[[#This Row],[Affordable Unit]] -> No | N13: =IF(Table10[[#This Row],[Subsidized Unit]]=0,"",Table10[[#This Row],[Subsidized Unit]]) | O13: =IF(Table10[[#This Row],[Care Services]]=0,"",Table10[[#This Row],[Care Services]]) | P13: =IF(Table10[[#This Row],[Affordable Care]]=0,"",Table10[[#This Row],[Affordable Care]]) | T13: =IF(Table10[[#This Row],[Bulk Lease Unit]]=0,"",Table10[[#This Row],[Bulk Lease Unit]]) | U13: =IF(Table10[[#This Row],[Den Included Unit]]=0,"",Table10[[#This Row],[Den Included Unit]]) | V13: =IF(Table10[[#This Row],[Second Bathroom]]=0,"",Table10[[#This Row],[Second Bathroom]]) | W13: =IF(Table10[[#This Row],[Heating]]=0,"",Table10[[#This Row],[Heating]]) | X13: =IF(Table10[[#This Row],[Electricity]]=0,"",Table10[[#This Row],[Electricity]]) | Y13: =IF(Table10[[#This Row],[Water]]=0,"",Table10[[#This Row],[Water]]) | Z13: =IF(Table10[[#This Row],[Washer/Dryer]]=0,"",Table10[[#This Row],[Washer/Dryer]]) | AA13: =IF(Table10[[#This Row],[Stove/Fridge]]=0,"",Table10[[#This Row],[Stove/Fridge]]) | AB13: =IF(Table10[[#This Row],[Dishwasher]]=0,"",Table10[[#This Row],[Dishwasher]]) | AC13: =IF(Table10[[#This Row],[Parking]]=0,"",Table10[[#This Row],[Parking]]) | AD13: =IF(Table10[[#This Row],[Furniture]]=0,"",Table10[[#This Row],[Furniture]]) | AE13: =IF(Table10[[#This Row],[Other]]=0,"",Table10[[#This Row],[Other]])
A14: =IF(Table10[[#This Row],[Unit Type]]=0,"",Table10[[#This Row],[Unit Type]]) -> 1 Bedroom | D14: =IF(Table10[[#This Row],[Unit '#]]=0,"",Table10[[#This Row],[Unit '#]]) -> 12 | F14: =IF(Table10[[#This Row],[Rental Rate ($/mth)]]=0,"",Table10[[#This Row],[Rental Rate ($/mth)]]) -> 2490 | J14: =IF(Table10[[#This Row],[Unit Size (sq ft)]]=0,"",Table10[[#This Row],[Unit Size (sq ft)]]) -> 624 | L14: =Table10[[#This Row],[Market Unit]] -> Yes | M14: =Table10[[#This Row],[Affordable Unit]] -> No | N14: =IF(Table10[[#This Row],[Subsidized Unit]]=0,"",Table10[[#This Row],[Subsidized Unit]]) | O14: =IF(Table10[[#This Row],[Care Services]]=0,"",Table10[[#This Row],[Care Services]]) | P14: =IF(Table10[[#This Row],[Affordable Care]]=0,"",Table10[[#This Row],[Affordable Care]]) | T14: =IF(Table10[[#This Row],[Bulk Lease Unit]]=0,"",Table10[[#This Row],[Bulk Lease Unit]]) | U14: =IF(Table10[[#This Row],[Den Included Unit]]=0,"",Table10[[#This Row],[Den Included Unit]]) | V14: =IF(Table10[[#This Row],[Second Bathroom]]=0,"",Table10[[#This Row],[Second Bathroom]]) | W14: =IF(Table10[[#This Row],[Heating]]=0,"",Table10[[#This Row],[Heating]]) | X14: =IF(Table10[[#This Row],[Electricity]]=0,"",Table10[[#This Row],[Electricity]]) | Y14: =IF(Table10[[#This Row],[Water]]=0,"",Table10[[#This Row],[Water]]) | Z14: =IF(Table10[[#This Row],[Washer/Dryer]]=0,"",Table10[[#This Row],[Washer/Dryer]]) | AA14: =IF(Table10[[#This Row],[Stove/Fridge]]=0,"",Table10[[#This Row],[Stove/Fridge]]) | AB14: =IF(Table10[[#This Row],[Dishwasher]]=0,"",Table10[[#This Row],[Dishwasher]]) | AC14: =IF(Table10[[#This Row],[Parking]]=0,"",Table10[[#This Row],[Parking]]) | AD14: =IF(Table10[[#This Row],[Furniture]]=0,"",Table10[[#This Row],[Furniture]]) | AE14: =IF(Table10[[#This Row],[Other]]=0,"",Table10[[#This Row],[Other]])
A15: =IF(Table10[[#This Row],[Unit Type]]=0,"",Table10[[#This Row],[Unit Type]]) -> 1 Bedroom | D15: =IF(Table10[[#This Row],[Unit '#]]=0,"",Table10[[#This Row],[Unit '#]]) -> 13 | F15: =IF(Table10[[#This Row],[Rental Rate ($/mth)]]=0,"",Table10[[#This Row],[Rental Rate ($/mth)]]) -> 2490 | J15: =IF(Table10[[#This Row],[Unit Size (sq ft)]]=0,"",Table10[[#This Row],[Unit Size (sq ft)]]) -> 624 | L15: =Table10[[#This Row],[Market Unit]] -> Yes | M15: =Table10[[#This Row],[Affordable Unit]] -> No | N15: =IF(Table10[[#This Row],[Subsidized Unit]]=0,"",Table10[[#This Row],[Subsidized Unit]]) | O15: =IF(Table10[[#This Row],[Care Services]]=0,"",Table10[[#This Row],[Care Services]]) | P15: =IF(Table10[[#This Row],[Affordable Care]]=0,"",Table10[[#This Row],[Affordable Care]]) | T15: =IF(Table10[[#This Row],[Bulk Lease Unit]]=0,"",Table10[[#This Row],[Bulk Lease Unit]]) | U15: =IF(Table10[[#This Row],[Den Included Unit]]=0,"",Table10[[#This Row],[Den Included Unit]]) | V15: =IF(Table10[[#This Row],[Second Bathroom]]=0,"",Table10[[#This Row],[Second Bathroom]]) | W15: =IF(Table10[[#This Row],[Heating]]=0,"",Table10[[#This Row],[Heating]]) | X15: =IF(Table10[[#This Row],[Electricity]]=0,"",Table10[[#This Row],[Electricity]]) | Y15: =IF(Table10[[#This Row],[Water]]=0,"",Table10[[#This Row],[Water]]) | Z15: =IF(Table10[[#This Row],[Washer/Dryer]]=0,"",Table10[[#This Row],[Washer/Dryer]]) | AA15: =IF(Table10[[#This Row],[Stove/Fridge]]=0,"",Table10[[#This Row],[Stove/Fridge]]) | AB15: =IF(Table10[[#This Row],[Dishwasher]]=0,"",Table10[[#This Row],[Dishwasher]]) | AC15: =IF(Table10[[#This Row],[Parking]]=0,"",Table10[[#This Row],[Parking]]) | AD15: =IF(Table10[[#This Row],[Furniture]]=0,"",Table10[[#This Row],[Furniture]]) | AE15: =IF(Table10[[#This Row],[Other]]=0,"",Table10[[#This Row],[Other]])
A16: =IF(Table10[[#This Row],[Unit Type]]=0,"",Table10[[#This Row],[Unit Type]]) -> 1 Bedroom | D16: =IF(Table10[[#This Row],[Unit '#]]=0,"",Table10[[#This Row],[Unit '#]]) -> 14 | F16: =IF(Table10[[#This Row],[Rental Rate ($/mth)]]=0,"",Table10[[#This Row],[Rental Rate ($/mth)]]) -> 2490 | J16: =IF(Table10[[#This Row],[Unit Size (sq ft)]]=0,"",Table10[[#This Row],[Unit Size (sq ft)]]) -> 624 | L16: =Table10[[#This Row],[Market Unit]] -> Yes | M16: =Table10[[#This Row],[Affordable Unit]] -> No | N16: =IF(Table10[[#This Row],[Subsidized Unit]]=0,"",Table10[[#This Row],[Subsidized Unit]]) | O16: =IF(Table10[[#This Row],[Care Services]]=0,"",Table10[[#This Row],[Care Services]]) | P16: =IF(Table10[[#This Row],[Affordable Care]]=0,"",Table10[[#This Row],[Affordable Care]]) | T16: =IF(Table10[[#This Row],[Bulk Lease Unit]]=0,"",Table10[[#This Row],[Bulk Lease Unit]]) | U16: =IF(Table10[[#This Row],[Den Included Unit]]=0,"",Table10[[#This Row],[Den Included Unit]]) | V16: =IF(Table10[[#This Row],[Second Bathroom]]=0,"",Table10[[#This Row],[Second Bathroom]]) | W16: =IF(Table10[[#This Row],[Heating]]=0,"",Table10[[#This Row],[Heating]]) | X16: =IF(Table10[[#This Row],[Electricity]]=0,"",Table10[[#This Row],[Electricity]]) | Y16: =IF(Table10[[#This Row],[Water]]=0,"",Table10[[#This Row],[Water]]) | Z16: =IF(Table10[[#This Row],[Washer/Dryer]]=0,"",Table10[[#This Row],[Washer/Dryer]]) | AA16: =IF(Table10[[#This Row],[Stove/Fridge]]=0,"",Table10[[#This Row],[Stove/Fridge]]) | AB16: =IF(Table10[[#This Row],[Dishwasher]]=0,"",Table10[[#This Row],[Dishwasher]]) | AC16: =IF(Table10[[#This Row],[Parking]]=0,"",Table10[[#This Row],[Parking]]) | AD16: =IF(Table10[[#This Row],[Furniture]]=0,"",Table10[[#This Row],[Furniture]]) | AE16: =IF(Table10[[#This Row],[Other]]=0,"",Table10[[#This Row],[Other]])
A17: =IF(Table10[[#This Row],[Unit Type]]=0,"",Table10[[#This Row],[Unit Type]]) -> 1 Bedroom | D17: =IF(Table10[[#This Row],[Unit '#]]=0,"",Table10[[#This Row],[Unit '#]]) -> 15 | F17: =IF(Table10[[#This Row],[Rental Rate ($/mth)]]=0,"",Table10[[#This Row],[Rental Rate ($/mth)]]) -> 2490 | J17: =IF(Table10[[#This Row],[Unit Size (sq ft)]]=0,"",Table10[[#This Row],[Unit Size (sq ft)]]) -> 624 | L17: =Table10[[#This Row],[Market Unit]] -> Yes | M17: =Table10[[#This Row],[Affordable Unit]] -> No | N17: =IF(Table10[[#This Row],[Subsidized Unit]]=0,"",Table10[[#This Row],[Subsidized Unit]]) | O17: =IF(Table10[[#This Row],[Care Services]]=0,"",Table10[[#This Row],[Care Services]]) | P17: =IF(Table10[[#This Row],[Affordable Care]]=0,"",Table10[[#This Row],[Affordable Care]]) | T17: =IF(Table10[[#This Row],[Bulk Lease Unit]]=0,"",Table10[[#This Row],[Bulk Lease Unit]]) | U17: =IF(Table10[[#This Row],[Den Included Unit]]=0,"",Table10[[#This Row],[Den Included Unit]]) | V17: =IF(Table10[[#This Row],[Second Bathroom]]=0,"",Table10[[#This Row],[Second Bathroom]]) | W17: =IF(Table10[[#This Row],[Heating]]=0,"",Table10[[#This Row],[Heating]]) | X17: =IF(Table10[[#This Row],[Electricity]]=0,"",Table10[[#This Row],[Electricity]]) | Y17: =IF(Table10[[#This Row],[Water]]=0,"",Table10[[#This Row],[Water]]) | Z17: =IF(Table10[[#This Row],[Washer/Dryer]]=0,"",Table10[[#This Row],[Washer/Dryer]]) | AA17: =IF(Table10[[#This Row],[Stove/Fridge]]=0,"",Table10[[#This Row],[Stove/Fridge]]) | AB17: =IF(Table10[[#This Row],[Dishwasher]]=0,"",Table10[[#This Row],[Dishwasher]]) | AC17: =IF(Table10[[#This Row],[Parking]]=0,"",Table10[[#This Row],[Parking]]) | AD17: =IF(Table10[[#This Row],[Furniture]]=0,"",Table10[[#This Row],[Furniture]]) | AE17: =IF(Table10[[#This Row],[Other]]=0,"",Table10[[#This Row],[Other]])
A18: =IF(Table10[[#This Row],[Unit Type]]=0,"",Table10[[#This Row],[Unit Type]]) -> 1 Bedroom | D18: =IF(Table10[[#This Row],[Unit '#]]=0,"",Table10[[#This Row],[Unit '#]]) -> 16 | F18: =IF(Table10[[#This Row],[Rental Rate ($/mth)]]=0,"",Table10[[#This Row],[Rental Rate ($/mth)]]) -> 2490 | J18: =IF(Table10[[#This Row],[Unit Size (sq ft)]]=0,"",Table10[[#This Row],[Unit Size (sq ft)]]) -> 624 | L18: =Table10[[#This Row],[Market Unit]] -> Yes | M18: =Table10[[#This Row],[Affordable Unit]] -> No | N18: =IF(Table10[[#This Row],[Subsidized Unit]]=0,"",Table10[[#This Row],[Subsidized Unit]]) | O18: =IF(Table10[[#This Row],[Care Services]]=0,"",Table10[[#This Row],[Care Services]]) | P18: =IF(Table10[[#This Row],[Affordable Care]]=0,"",Table10[[#This Row],[Affordable Care]]) | T18: =IF(Table10[[#This Row],[Bulk Lease Unit]]=0,"",Table10[[#This Row],[Bulk Lease Unit]]) | U18: =IF(Table10[[#This Row],[Den Included Unit]]=0,"",Table10[[#This Row],[Den Included Unit]]) | V18: =IF(Table10[[#This Row],[Second Bathroom]]=0,"",Table10[[#This Row],[Second Bathroom]]) | W18: =IF(Table10[[#This Row],[Heating]]=0,"",Table10[[#This Row],[Heating]]) | X18: =IF(Table10[[#This Row],[Electricity]]=0,"",Table10[[#This Row],[Electricity]]) | Y18: =IF(Table10[[#This Row],[Water]]=0,"",Table10[[#This Row],[Water]]) | Z18: =IF(Table10[[#This Row],[Washer/Dryer]]=0,"",Table10[[#This Row],[Washer/Dryer]]) | AA18: =IF(Table10[[#This Row],[Stove/Fridge]]=0,"",Table10[[#This Row],[Stove/Fridge]]) | AB18: =IF(Table10[[#This Row],[Dishwasher]]=0,"",Table10[[#This Row],[Dishwasher]]) | AC18: =IF(Table10[[#This Row],[Parking]]=0,"",Table10[[#This Row],[Parking]]) | AD18: =IF(Table10[[#This Row],[Furniture]]=0,"",Table10[[#This Row],[Furniture]]) | AE18: =IF(Table10[[#This Row],[Other]]=0,"",Table10[[#This Row],[Other]])
A19: =IF(Table10[[#This Row],[Unit Type]]=0,"",Table10[[#This Row],[Unit Type]]) -> 1 Bedroom | D19: =IF(Table10[[#This Row],[Unit '#]]=0,"",Table10[[#This Row],[Unit '#]]) -> 17 | F19: =IF(Table10[[#This Row],[Rental Rate ($/mth)]]=0,"",Table10[[#This Row],[Rental Rate ($/mth)]]) -> 2490 | J19: =IF(Table10[[#This Row],[Unit Size (sq ft)]]=0,"",Table10[[#This Row],[Unit Size (sq ft)]]) -> 624 | L19: =Table10[[#This Row],[Market Unit]] -> Yes | M19: =Table10[[#This Row],[Affordable Unit]] -> No | N19: =IF(Table10[[#This Row],[Subsidized Unit]]=0,"",Table10[[#This Row],[Subsidized Unit]]) | O19: =IF(Table10[[#This Row],[Care Services]]=0,"",Table10[[#This Row],[Care Services]]) | P19: =IF(Table10[[#This Row],[Affordable Care]]=0,"",Table10[[#This Row],[Affordable Care]]) | T19: =IF(Table10[[#This Row],[Bulk Lease Unit]]=0,"",Table10[[#This Row],[Bulk Lease Unit]]) | U19: =IF(Table10[[#This Row],[Den Included Unit]]=0,"",Table10[[#This Row],[Den Included Unit]]) | V19: =IF(Table10[[#This Row],[Second Bathroom]]=0,"",Table10[[#This Row],[Second Bathroom]]) | W19: =IF(Table10[[#This Row],[Heating]]=0,"",Table10[[#This Row],[Heating]]) | X19: =IF(Table10[[#This Row],[Electricity]]=0,"",Table10[[#This Row],[Electricity]]) | Y19: =IF(Table10[[#This Row],[Water]]=0,"",Table10[[#This Row],[Water]]) | Z19: =IF(Table10[[#This Row],[Washer/Dryer]]=0,"",Table10[[#This Row],[Washer/Dryer]]) | AA19: =IF(Table10[[#This Row],[Stove/Fridge]]=0,"",Table10[[#This Row],[Stove/Fridge]]) | AB19: =IF(Table10[[#This Row],[Dishwasher]]=0,"",Table10[[#This Row],[Dishwasher]]) | AC19: =IF(Table10[[#This Row],[Parking]]=0,"",Table10[[#This Row],[Parking]]) | AD19: =IF(Table10[[#This Row],[Furniture]]=0,"",Table10[[#This Row],[Furniture]]) | AE19: =IF(Table10[[#This Row],[Other]]=0,"",Table10[[#This Row],[Other]])
... A27: =IF(Table10[[#This Row],[Unit Type]]=0,"",Table10[[#This Row],[Unit Type]]) -> 1 Bedroom | D27: =IF(Table10[[#This Row],[Unit '#]]=0,"",Table10[[#This Row],[Unit '#]]) -> 25 | F27: =IF(Table10[[#This Row],[Rental Rate ($/mth)]]=0,"",Table10[[#This Row],[Rental Rate ($/mth)]]) -> 2490 | J27: =IF(Table10[[#This Row],[Unit Size (sq ft)]]=0,"",Table10[[#This Row],[Unit Size (sq ft)]]) -> 624 | L27: =Table10[[#This Row],[Market Unit]] -> Yes | M27: =Table10[[#This Row],[Affordable Unit]] -> No | N27: =IF(Table10[[#This Row],[Subsidized Unit]]=0,"",Table10[[#This Row],[Subsidized Unit]]) | O27: =IF(Table10[[#This Row],[Care Services]]=0,"",Table10[[#This Row],[Care Services]]) | P27: =IF(Table10[[#This Row],[Affordable Care]]=0,"",Table10[[#This Row],[Affordable Care]]) | T27: =IF(Table10[[#This Row],[Bulk Lease Unit]]=0,"",Table10[[#This Row],[Bulk Lease Unit]]) | U27: =IF(Table10[[#This Row],[Den Included Unit]]=0,"",Table10[[#This Row],[Den Included Unit]]) | V27: =IF(Table10[[#This Row],[Second Bathroom]]=0,"",Table10[[#This Row],[Second Bathroom]]) | W27: =IF(Table10[[#This Row],[Heating]]=0,"",Table10[[#This Row],[Heating]]) | X27: =IF(Table10[[#This Row],[Electricity]]=0,"",Table10[[#This Row],[Electricity]]) | Y27: =IF(Table10[[#This Row],[Water]]=0,"",Table10[[#This Row],[Water]]) | Z27: =IF(Table10[[#This Row],[Washer/Dryer]]=0,"",Table10[[#This Row],[Washer/Dryer]]) | AA27: =IF(Table10[[#This Row],[Stove/Fridge]]=0,"",Table10[[#This Row],[Stove/Fridge]]) | AB27: =IF(Table10[[#This Row],[Dishwasher]]=0,"",Table10[[#This Row],[Dishwasher]]) | AC27: =IF(Table10[[#This Row],[Parking]]=0,"",Table10[[#This Row],[Parking]]) | AD27: =IF(Table10[[#This Row],[Furniture]]=0,"",Table10[[#This Row],[Furniture]]) | AE27: =IF(Table10[[#This Row],[Other]]=0,"",Table10[[#This Row],[Other]])
A28: =IF(Table10[[#This Row],[Unit Type]]=0,"",Table10[[#This Row],[Unit Type]]) -> 1 Bedroom | B28: =IF(Table10[[#This Row],[Residential Stream Source]]=0,"",Table10[[#This Row],[Residential Stream Source]]) | C28: =IF(Table10[[#This Row],[Basement?]]=0,"",Table10[[#This Row],[Basement?]]) | D28: =IF(Table10[[#This Row],[Unit '#]]=0,"",Table10[[#This Row],[Unit '#]]) -> 26 | E28: =IF(Table10[[#This Row],[Vacant?]]=0,"",Table10[[#This Row],[Vacant?]]) | F28: =IF(Table10[[#This Row],[Rental Rate ($/mth)]]=0,"",Table10[[#This Row],[Rental Rate ($/mth)]]) -> 2490 | J28: =IF(Table10[[#This Row],[Unit Size (sq ft)]]=0,"",Table10[[#This Row],[Unit Size (sq ft)]]) -> 624 | L28: =Table10[[#This Row],[Market Unit]] -> Yes | M28: =Table10[[#This Row],[Affordable Unit]] -> No | N28: =IF(Table10[[#This Row],[Subsidized Unit]]=0,"",Table10[[#This Row],[Subsidized Unit]]) | O28: =IF(Table10[[#This Row],[Care Services]]=0,"",Table10[[#This Row],[Care Services]]) | P28: =IF(Table10[[#This Row],[Affordable Care]]=0,"",Table10[[#This Row],[Affordable Care]]) | T28: =IF(Table10[[#This Row],[Bulk Lease Unit]]=0,"",Table10[[#This Row],[Bulk Lease Unit]]) | U28: =IF(Table10[[#This Row],[Den Included Unit]]=0,"",Table10[[#This Row],[Den Included Unit]]) | V28: =IF(Table10[[#This Row],[Second Bathroom]]=0,"",Table10[[#This Row],[Second Bathroom]]) | W28: =IF(Table10[[#This Row],[Heating]]=0,"",Table10[[#This Row],[Heating]]) | X28: =IF(Table10[[#This Row],[Electricity]]=0,"",Table10[[#This Row],[Electricity]]) | Y28: =IF(Table10[[#This Row],[Water]]=0,"",Table10[[#This Row],[Water]]) | Z28: =IF(Table10[[#This Row],[Washer/Dryer]]=0,"",Table10[[#This Row],[Washer/Dryer]]) | AA28: =IF(Table10[[#This Row],[Stove/Fridge]]=0,"",Table10[[#This Row],[Stove/Fridge]]) | AB28: =IF(Table10[[#This Row],[Dishwasher]]=0,"",Table10[[#This Row],[Dishwasher]]) | AC28: =IF(Table10[[#This Row],[Parking]]=0,"",Table10[[#This Row],[Parking]]) | AD28: =IF(Table10[[#This Row],[Furniture]]=0,"",Table10[[#This Row],[Furniture]]) | AE28: =IF(Table10[[#This Row],[Other]]=0,"",Table10[[#This Row],[Other]])
A29: =IF(Table10[[#This Row],[Unit Type]]=0,"",Table10[[#This Row],[Unit Type]]) -> 1 Bedroom | B29: =IF(Table10[[#This Row],[Residential Stream Source]]=0,"",Table10[[#This Row],[Residential Stream Source]]) | C29: =IF(Table10[[#This Row],[Basement?]]=0,"",Table10[[#This Row],[Basement?]]) | D29: =IF(Table10[[#This Row],[Unit '#]]=0,"",Table10[[#This Row],[Unit '#]]) -> 27 | E29: =IF(Table10[[#This Row],[Vacant?]]=0,"",Table10[[#This Row],[Vacant?]]) | F29: =IF(Table10[[#This Row],[Rental Rate ($/mth)]]=0,"",Table10[[#This Row],[Rental Rate ($/mth)]]) -> 2490 | J29: =IF(Table10[[#This Row],[Unit Size (sq ft)]]=0,"",Table10[[#This Row],[Unit Size (sq ft)]]) -> 624 | L29: =Table10[[#This Row],[Market Unit]] -> Yes | M29: =Table10[[#This Row],[Affordable Unit]] -> No | N29: =IF(Table10[[#This Row],[Subsidized Unit]]=0,"",Table10[[#This Row],[Subsidized Unit]]) | O29: =IF(Table10[[#This Row],[Care Services]]=0,"",Table10[[#This Row],[Care Services]]) | P29: =IF(Table10[[#This Row],[Affordable Care]]=0,"",Table10[[#This Row],[Affordable Care]]) | T29: =IF(Table10[[#This Row],[Bulk Lease Unit]]=0,"",Table10[[#This Row],[Bulk Lease Unit]]) | U29: =IF(Table10[[#This Row],[Den Included Unit]]=0,"",Table10[[#This Row],[Den Included Unit]]) | V29: =IF(Table10[[#This Row],[Second Bathroom]]=0,"",Table10[[#This Row],[Second Bathroom]]) | W29: =IF(Table10[[#This Row],[Heating]]=0,"",Table10[[#This Row],[Heating]]) | X29: =IF(Table10[[#This Row],[Electricity]]=0,"",Table10[[#This Row],[Electricity]]) | Y29: =IF(Table10[[#This Row],[Water]]=0,"",Table10[[#This Row],[Water]]) | Z29: =IF(Table10[[#This Row],[Washer/Dryer]]=0,"",Table10[[#This Row],[Washer/Dryer]]) | AA29: =IF(Table10[[#This Row],[Stove/Fridge]]=0,"",Table10[[#This Row],[Stove/Fridge]]) | AB29: =IF(Table10[[#This Row],[Dishwasher]]=0,"",Table10[[#This Row],[Dishwasher]]) | AC29: =IF(Table10[[#This Row],[Parking]]=0,"",Table10[[#This Row],[Parking]]) | AD29: =IF(Table10[[#This Row],[Furniture]]=0,"",Table10[[#This Row],[Furniture]]) | AE29: =IF(Table10[[#This Row],[Other]]=0,"",Table10[[#This Row],[Other]])
A30: =IF(Table10[[#This Row],[Unit Type]]=0,"",Table10[[#This Row],[Unit Type]]) -> 1 Bedroom | B30: =IF(Table10[[#This Row],[Residential Stream Source]]=0,"",Table10[[#This Row],[Residential Stream Source]]) | C30: =IF(Table10[[#This Row],[Basement?]]=0,"",Table10[[#This Row],[Basement?]]) | D30: =IF(Table10[[#This Row],[Unit '#]]=0,"",Table10[[#This Row],[Unit '#]]) -> 28 | E30: =IF(Table10[[#This Row],[Vacant?]]=0,"",Table10[[#This Row],[Vacant?]]) | F30: =IF(Table10[[#This Row],[Rental Rate ($/mth)]]=0,"",Table10[[#This Row],[Rental Rate ($/mth)]]) -> 2490 | J30: =IF(Table10[[#This Row],[Unit Size (sq ft)]]=0,"",Table10[[#This Row],[Unit Size (sq ft)]]) -> 624 | L30: =Table10[[#This Row],[Market Unit]] -> Yes | M30: =Table10[[#This Row],[Affordable Unit]] -> No | N30: =IF(Table10[[#This Row],[Subsidized Unit]]=0,"",Table10[[#This Row],[Subsidized Unit]]) | O30: =IF(Table10[[#This Row],[Care Services]]=0,"",Table10[[#This Row],[Care Services]]) | P30: =IF(Table10[[#This Row],[Affordable Care]]=0,"",Table10[[#This Row],[Affordable Care]]) | T30: =IF(Table10[[#This Row],[Bulk Lease Unit]]=0,"",Table10[[#This Row],[Bulk Lease Unit]]) | U30: =IF(Table10[[#This Row],[Den Included Unit]]=0,"",Table10[[#This Row],[Den Included Unit]]) | V30: =IF(Table10[[#This Row],[Second Bathroom]]=0,"",Table10[[#This Row],[Second Bathroom]]) | W30: =IF(Table10[[#This Row],[Heating]]=0,"",Table10[[#This Row],[Heating]]) | X30: =IF(Table10[[#This Row],[Electricity]]=0,"",Table10[[#This Row],[Electricity]]) | Y30: =IF(Table10[[#This Row],[Water]]=0,"",Table10[[#This Row],[Water]]) | Z30: =IF(Table10[[#This Row],[Washer/Dryer]]=0,"",Table10[[#This Row],[Washer/Dryer]]) | AA30: =IF(Table10[[#This Row],[Stove/Fridge]]=0,"",Table10[[#This Row],[Stove/Fridge]]) | AB30: =IF(Table10[[#This Row],[Dishwasher]]=0,"",Table10[[#This Row],[Dishwasher]]) | AC30: =IF(Table10[[#This Row],[Parking]]=0,"",Table10[[#This Row],[Parking]]) | AD30: =IF(Table10[[#This Row],[Furniture]]=0,"",Table10[[#This Row],[Furniture]]) | AE30: =IF(Table10[[#This Row],[Other]]=0,"",Table10[[#This Row],[Other]])
A31: =IF(Table10[[#This Row],[Unit Type]]=0,"",Table10[[#This Row],[Unit Type]]) -> 1 Bedroom | B31: =IF(Table10[[#This Row],[Residential Stream Source]]=0,"",Table10[[#This Row],[Residential Stream Source]]) | C31: =IF(Table10[[#This Row],[Basement?]]=0,"",Table10[[#This Row],[Basement?]]) | D31: =IF(Table10[[#This Row],[Unit '#]]=0,"",Table10[[#This Row],[Unit '#]]) -> 29 | E31: =IF(Table10[[#This Row],[Vacant?]]=0,"",Table10[[#This Row],[Vacant?]]) | F31: =IF(Table10[[#This Row],[Rental Rate ($/mth)]]=0,"",Table10[[#This Row],[Rental Rate ($/mth)]]) -> 2490 | J31: =IF(Table10[[#This Row],[Unit Size (sq ft)]]=0,"",Table10[[#This Row],[Unit Size (sq ft)]]) -> 624 | L31: =Table10[[#This Row],[Market Unit]] -> Yes | M31: =Table10[[#This Row],[Affordable Unit]] -> No | N31: =IF(Table10[[#This Row],[Subsidized Unit]]=0,"",Table10[[#This Row],[Subsidized Unit]]) | O31: =IF(Table10[[#This Row],[Care Services]]=0,"",Table10[[#This Row],[Care Services]]) | P31: =IF(Table10[[#This Row],[Affordable Care]]=0,"",Table10[[#This Row],[Affordable Care]]) | T31: =IF(Table10[[#This Row],[Bulk Lease Unit]]=0,"",Table10[[#This Row],[Bulk Lease Unit]]) | U31: =IF(Table10[[#This Row],[Den Included Unit]]=0,"",Table10[[#This Row],[Den Included Unit]]) | V31: =IF(Table10[[#This Row],[Second Bathroom]]=0,"",Table10[[#This Row],[Second Bathroom]]) | W31: =IF(Table10[[#This Row],[Heating]]=0,"",Table10[[#This Row],[Heating]]) | X31: =IF(Table10[[#This Row],[Electricity]]=0,"",Table10[[#This Row],[Electricity]]) | Y31: =IF(Table10[[#This Row],[Water]]=0,"",Table10[[#This Row],[Water]]) | Z31: =IF(Table10[[#This Row],[Washer/Dryer]]=0,"",Table10[[#This Row],[Washer/Dryer]]) | AA31: =IF(Table10[[#This Row],[Stove/Fridge]]=0,"",Table10[[#This Row],[Stove/Fridge]]) | AB31: =IF(Table10[[#This Row],[Dishwasher]]=0,"",Table10[[#This Row],[Dishwasher]]) | AC31: =IF(Table10[[#This Row],[Parking]]=0,"",Table10[[#This Row],[Parking]]) | AD31: =IF(Table10[[#This Row],[Furniture]]=0,"",Table10[[#This Row],[Furniture]]) | AE31: =IF(Table10[[#This Row],[Other]]=0,"",Table10[[#This Row],[Other]])
A32: =IF(Table10[[#This Row],[Unit Type]]=0,"",Table10[[#This Row],[Unit Type]]) -> 1 Bedroom | B32: =IF(Table10[[#This Row],[Residential Stream Source]]=0,"",Table10[[#This Row],[Residential Stream Source]]) | C32: =IF(Table10[[#This Row],[Basement?]]=0,"",Table10[[#This Row],[Basement?]]) | D32: =IF(Table10[[#This Row],[Unit '#]]=0,"",Table10[[#This Row],[Unit '#]]) -> 30 | E32: =IF(Table10[[#This Row],[Vacant?]]=0,"",Table10[[#This Row],[Vacant?]]) | F32: =IF(Table10[[#This Row],[Rental Rate ($/mth)]]=0,"",Table10[[#This Row],[Rental Rate ($/mth)]]) -> 2490 | J32: =IF(Table10[[#This Row],[Unit Size (sq ft)]]=0,"",Table10[[#This Row],[Unit Size (sq ft)]]) -> 624 | L32: =Table10[[#This Row],[Market Unit]] -> Yes | M32: =Table10[[#This Row],[Affordable Unit]] -> No | N32: =IF(Table10[[#This Row],[Subsidized Unit]]=0,"",Table10[[#This Row],[Subsidized Unit]]) | O32: =IF(Table10[[#This Row],[Care Services]]=0,"",Table10[[#This Row],[Care Services]]) | P32: =IF(Table10[[#This Row],[Affordable Care]]=0,"",Table10[[#This Row],[Affordable Care]]) | T32: =IF(Table10[[#This Row],[Bulk Lease Unit]]=0,"",Table10[[#This Row],[Bulk Lease Unit]]) | U32: =IF(Table10[[#This Row],[Den Included Unit]]=0,"",Table10[[#This Row],[Den Included Unit]]) | V32: =IF(Table10[[#This Row],[Second Bathroom]]=0,"",Table10[[#This Row],[Second Bathroom]]) | W32: =IF(Table10[[#This Row],[Heating]]=0,"",Table10[[#This Row],[Heating]]) | X32: =IF(Table10[[#This Row],[Electricity]]=0,"",Table10[[#This Row],[Electricity]]) | Y32: =IF(Table10[[#This Row],[Water]]=0,"",Table10[[#This Row],[Water]]) | Z32: =IF(Table10[[#This Row],[Washer/Dryer]]=0,"",Table10[[#This Row],[Washer/Dryer]]) | AA32: =IF(Table10[[#This Row],[Stove/Fridge]]=0,"",Table10[[#This Row],[Stove/Fridge]]) | AB32: =IF(Table10[[#This Row],[Dishwasher]]=0,"",Table10[[#This Row],[Dishwasher]]) | AC32: =IF(Table10[[#This Row],[Parking]]=0,"",Table10[[#This Row],[Parking]]) | AD32: =IF(Table10[[#This Row],[Furniture]]=0,"",Table10[[#This Row],[Furniture]]) | AE32: =IF(Table10[[#This Row],[Other]]=0,"",Table10[[#This Row],[Other]])
A33: =IF(Table10[[#This Row],[Unit Type]]=0,"",Table10[[#This Row],[Unit Type]]) -> 1 Bedroom | B33: =IF(Table10[[#This Row],[Residential Stream Source]]=0,"",Table10[[#This Row],[Residential Stream Source]]) | C33: =IF(Table10[[#This Row],[Basement?]]=0,"",Table10[[#This Row],[Basement?]]) | D33: =IF(Table10[[#This Row],[Unit '#]]=0,"",Table10[[#This Row],[Unit '#]]) -> 31 | E33: =IF(Table10[[#This Row],[Vacant?]]=0,"",Table10[[#This Row],[Vacant?]]) | F33: =IF(Table10[[#This Row],[Rental Rate ($/mth)]]=0,"",Table10[[#This Row],[Rental Rate ($/mth)]]) -> 2490 | J33: =IF(Table10[[#This Row],[Unit Size (sq ft)]]=0,"",Table10[[#This Row],[Unit Size (sq ft)]]) -> 624 | L33: =Table10[[#This Row],[Market Unit]] -> Yes | M33: =Table10[[#This Row],[Affordable Unit]] -> No | N33: =IF(Table10[[#This Row],[Subsidized Unit]]=0,"",Table10[[#This Row],[Subsidized Unit]]) | O33: =IF(Table10[[#This Row],[Care Services]]=0,"",Table10[[#This Row],[Care Services]]) | P33: =IF(Table10[[#This Row],[Affordable Care]]=0,"",Table10[[#This Row],[Affordable Care]]) | T33: =IF(Table10[[#This Row],[Bulk Lease Unit]]=0,"",Table10[[#This Row],[Bulk Lease Unit]]) | U33: =IF(Table10[[#This Row],[Den Included Unit]]=0,"",Table10[[#This Row],[Den Included Unit]]) | V33: =IF(Table10[[#This Row],[Second Bathroom]]=0,"",Table10[[#This Row],[Second Bathroom]]) | W33: =IF(Table10[[#This Row],[Heating]]=0,"",Table10[[#This Row],[Heating]]) | X33: =IF(Table10[[#This Row],[Electricity]]=0,"",Table10[[#This Row],[Electricity]]) | Y33: =IF(Table10[[#This Row],[Water]]=0,"",Table10[[#This Row],[Water]]) | Z33: =IF(Table10[[#This Row],[Washer/Dryer]]=0,"",Table10[[#This Row],[Washer/Dryer]]) | AA33: =IF(Table10[[#This Row],[Stove/Fridge]]=0,"",Table10[[#This Row],[Stove/Fridge]]) | AB33: =IF(Table10[[#This Row],[Dishwasher]]=0,"",Table10[[#This Row],[Dishwasher]]) | AC33: =IF(Table10[[#This Row],[Parking]]=0,"",Table10[[#This Row],[Parking]]) | AD33: =IF(Table10[[#This Row],[Furniture]]=0,"",Table10[[#This Row],[Furniture]]) | AE33: =IF(Table10[[#This Row],[Other]]=0,"",Table10[[#This Row],[Other]])
A34: =IF(Table10[[#This Row],[Unit Type]]=0,"",Table10[[#This Row],[Unit Type]]) -> 1 Bedroom | B34: =IF(Table10[[#This Row],[Residential Stream Source]]=0,"",Table10[[#This Row],[Residential Stream Source]]) | C34: =IF(Table10[[#This Row],[Basement?]]=0,"",Table10[[#This Row],[Basement?]]) | D34: =IF(Table10[[#This Row],[Unit '#]]=0,"",Table10[[#This Row],[Unit '#]]) -> 32 | E34: =IF(Table10[[#This Row],[Vacant?]]=0,"",Table10[[#This Row],[Vacant?]]) | F34: =IF(Table10[[#This Row],[Rental Rate ($/mth)]]=0,"",Table10[[#This Row],[Rental Rate ($/mth)]]) -> 2490 | J34: =IF(Table10[[#This Row],[Unit Size (sq ft)]]=0,"",Table10[[#This Row],[Unit Size (sq ft)]]) -> 624 | L34: =Table10[[#This Row],[Market Unit]] -> Yes | M34: =Table10[[#This Row],[Affordable Unit]] -> No | N34: =IF(Table10[[#This Row],[Subsidized Unit]]=0,"",Table10[[#This Row],[Subsidized Unit]]) | O34: =IF(Table10[[#This Row],[Care Services]]=0,"",Table10[[#This Row],[Care Services]]) | P34: =IF(Table10[[#This Row],[Affordable Care]]=0,"",Table10[[#This Row],[Affordable Care]]) | T34: =IF(Table10[[#This Row],[Bulk Lease Unit]]=0,"",Table10[[#This Row],[Bulk Lease Unit]]) | U34: =IF(Table10[[#This Row],[Den Included Unit]]=0,"",Table10[[#This Row],[Den Included Unit]]) | V34: =IF(Table10[[#This Row],[Second Bathroom]]=0,"",Table10[[#This Row],[Second Bathroom]]) | W34: =IF(Table10[[#This Row],[Heating]]=0,"",Table10[[#This Row],[Heating]]) | X34: =IF(Table10[[#This Row],[Electricity]]=0,"",Table10[[#This Row],[Electricity]]) | Y34: =IF(Table10[[#This Row],[Water]]=0,"",Table10[[#This Row],[Water]]) | Z34: =IF(Table10[[#This Row],[Washer/Dryer]]=0,"",Table10[[#This Row],[Washer/Dryer]]) | AA34: =IF(Table10[[#This Row],[Stove/Fridge]]=0,"",Table10[[#This Row],[Stove/Fridge]]) | AB34: =IF(Table10[[#This Row],[Dishwasher]]=0,"",Table10[[#This Row],[Dishwasher]]) | AC34: =IF(Table10[[#This Row],[Parking]]=0,"",Table10[[#This Row],[Parking]]) | AD34: =IF(Table10[[#This Row],[Furniture]]=0,"",Table10[[#This Row],[Furniture]]) | AE34: =IF(Table10[[#This Row],[Other]]=0,"",Table10[[#This Row],[Other]])
A35: =IF(Table10[[#This Row],[Unit Type]]=0,"",Table10[[#This Row],[Unit Type]]) -> 1 Bedroom | B35: =IF(Table10[[#This Row],[Residential Stream Source]]=0,"",Table10[[#This Row],[Residential Stream Source]]) | C35: =IF(Table10[[#This Row],[Basement?]]=0,"",Table10[[#This Row],[Basement?]]) | D35: =IF(Table10[[#This Row],[Unit '#]]=0,"",Table10[[#This Row],[Unit '#]]) -> 33 | E35: =IF(Table10[[#This Row],[Vacant?]]=0,"",Table10[[#This Row],[Vacant?]]) | F35: =IF(Table10[[#This Row],[Rental Rate ($/mth)]]=0,"",Table10[[#This Row],[Rental Rate ($/mth)]]) -> 2490 | J35: =IF(Table10[[#This Row],[Unit Size (sq ft)]]=0,"",Table10[[#This Row],[Unit Size (sq ft)]]) -> 624 | L35: =Table10[[#This Row],[Market Unit]] -> Yes | M35: =Table10[[#This Row],[Affordable Unit]] -> No | N35: =IF(Table10[[#This Row],[Subsidized Unit]]=0,"",Table10[[#This Row],[Subsidized Unit]]) | O35: =IF(Table10[[#This Row],[Care Services]]=0,"",Table10[[#This Row],[Care Services]]) | P35: =IF(Table10[[#This Row],[Affordable Care]]=0,"",Table10[[#This Row],[Affordable Care]]) | T35: =IF(Table10[[#This Row],[Bulk Lease Unit]]=0,"",Table10[[#This Row],[Bulk Lease Unit]]) | U35: =IF(Table10[[#This Row],[Den Included Unit]]=0,"",Table10[[#This Row],[Den Included Unit]]) | V35: =IF(Table10[[#This Row],[Second Bathroom]]=0,"",Table10[[#This Row],[Second Bathroom]]) | W35: =IF(Table10[[#This Row],[Heating]]=0,"",Table10[[#This Row],[Heating]]) | X35: =IF(Table10[[#This Row],[Electricity]]=0,"",Table10[[#This Row],[Electricity]]) | Y35: =IF(Table10[[#This Row],[Water]]=0,"",Table10[[#This Row],[Water]]) | Z35: =IF(Table10[[#This Row],[Washer/Dryer]]=0,"",Table10[[#This Row],[Washer/Dryer]]) | AA35: =IF(Table10[[#This Row],[Stove/Fridge]]=0,"",Table10[[#This Row],[Stove/Fridge]]) | AB35: =IF(Table10[[#This Row],[Dishwasher]]=0,"",Table10[[#This Row],[Dishwasher]]) | AC35: =IF(Table10[[#This Row],[Parking]]=0,"",Table10[[#This Row],[Parking]]) | AD35: =IF(Table10[[#This Row],[Furniture]]=0,"",Table10[[#This Row],[Furniture]]) | AE35: =IF(Table10[[#This Row],[Other]]=0,"",Table10[[#This Row],[Other]])
A36: =IF(Table10[[#This Row],[Unit Type]]=0,"",Table10[[#This Row],[Unit Type]]) -> 1 Bedroom | B36: =IF(Table10[[#This Row],[Residential Stream Source]]=0,"",Table10[[#This Row],[Residential Stream Source]]) | C36: =IF(Table10[[#This Row],[Basement?]]=0,"",Table10[[#This Row],[Basement?]]) | D36: =IF(Table10[[#This Row],[Unit '#]]=0,"",Table10[[#This Row],[Unit '#]]) -> 34 | E36: =IF(Table10[[#This Row],[Vacant?]]=0,"",Table10[[#This Row],[Vacant?]]) | F36: =IF(Table10[[#This Row],[Rental Rate ($/mth)]]=0,"",Table10[[#This Row],[Rental Rate ($/mth)]]) -> 2490 | J36: =IF(Table10[[#This Row],[Unit Size (sq ft)]]=0,"",Table10[[#This Row],[Unit Size (sq ft)]]) -> 624 | L36: =Table10[[#This Row],[Market Unit]] -> Yes | M36: =Table10[[#This Row],[Affordable Unit]] -> No | N36: =IF(Table10[[#This Row],[Subsidized Unit]]=0,"",Table10[[#This Row],[Subsidized Unit]]) | O36: =IF(Table10[[#This Row],[Care Services]]=0,"",Table10[[#This Row],[Care Services]]) | P36: =IF(Table10[[#This Row],[Affordable Care]]=0,"",Table10[[#This Row],[Affordable Care]]) | T36: =IF(Table10[[#This Row],[Bulk Lease Unit]]=0,"",Table10[[#This Row],[Bulk Lease Unit]]) | U36: =IF(Table10[[#This Row],[Den Included Unit]]=0,"",Table10[[#This Row],[Den Included Unit]]) | V36: =IF(Table10[[#This Row],[Second Bathroom]]=0,"",Table10[[#This Row],[Second Bathroom]]) | W36: =IF(Table10[[#This Row],[Heating]]=0,"",Table10[[#This Row],[Heating]]) | X36: =IF(Table10[[#This Row],[Electricity]]=0,"",Table10[[#This Row],[Electricity]]) | Y36: =IF(Table10[[#This Row],[Water]]=0,"",Table10[[#This Row],[Water]]) | Z36: =IF(Table10[[#This Row],[Washer/Dryer]]=0,"",Table10[[#This Row],[Washer/Dryer]]) | AA36: =IF(Table10[[#This Row],[Stove/Fridge]]=0,"",Table10[[#This Row],[Stove/Fridge]]) | AB36: =IF(Table10[[#This Row],[Dishwasher]]=0,"",Table10[[#This Row],[Dishwasher]]) | AC36: =IF(Table10[[#This Row],[Parking]]=0,"",Table10[[#This Row],[Parking]]) | AD36: =IF(Table10[[#This Row],[Furniture]]=0,"",Table10[[#This Row],[Furniture]]) | AE36: =IF(Table10[[#This Row],[Other]]=0,"",Table10[[#This Row],[Other]])
A37: =IF(Table10[[#This Row],[Unit Type]]=0,"",Table10[[#This Row],[Unit Type]]) -> 1 Bedroom | B37: =IF(Table10[[#This Row],[Residential Stream Source]]=0,"",Table10[[#This Row],[Residential Stream Source]]) | C37: =IF(Table10[[#This Row],[Basement?]]=0,"",Table10[[#This Row],[Basement?]]) | D37: =IF(Table10[[#This Row],[Unit '#]]=0,"",Table10[[#This Row],[Unit '#]]) -> 35 | E37: =IF(Table10[[#This Row],[Vacant?]]=0,"",Table10[[#This Row],[Vacant?]]) | F37: =IF(Table10[[#This Row],[Rental Rate ($/mth)]]=0,"",Table10[[#This Row],[Rental Rate ($/mth)]]) -> 2490 | J37: =IF(Table10[[#This Row],[Unit Size (sq ft)]]=0,"",Table10[[#This Row],[Unit Size (sq ft)]]) -> 624 | L37: =Table10[[#This Row],[Market Unit]] -> Yes | M37: =Table10[[#This Row],[Affordable Unit]] -> No | N37: =IF(Table10[[#This Row],[Subsidized Unit]]=0,"",Table10[[#This Row],[Subsidized Unit]]) | O37: =IF(Table10[[#This Row],[Care Services]]=0,"",Table10[[#This Row],[Care Services]]) | P37: =IF(Table10[[#This Row],[Affordable Care]]=0,"",Table10[[#This Row],[Affordable Care]]) | T37: =IF(Table10[[#This Row],[Bulk Lease Unit]]=0,"",Table10[[#This Row],[Bulk Lease Unit]]) | U37: =IF(Table10[[#This Row],[Den Included Unit]]=0,"",Table10[[#This Row],[Den Included Unit]]) | V37: =IF(Table10[[#This Row],[Second Bathroom]]=0,"",Table10[[#This Row],[Second Bathroom]]) | W37: =IF(Table10[[#This Row],[Heating]]=0,"",Table10[[#This Row],[Heating]]) | X37: =IF(Table10[[#This Row],[Electricity]]=0,"",Table10[[#This Row],[Electricity]]) | Y37: =IF(Table10[[#This Row],[Water]]=0,"",Table10[[#This Row],[Water]]) | Z37: =IF(Table10[[#This Row],[Washer/Dryer]]=0,"",Table10[[#This Row],[Washer/Dryer]]) | AA37: =IF(Table10[[#This Row],[Stove/Fridge]]=0,"",Table10[[#This Row],[Stove/Fridge]]) | AB37: =IF(Table10[[#This Row],[Dishwasher]]=0,"",Table10[[#This Row],[Dishwasher]]) | AC37: =IF(Table10[[#This Row],[Parking]]=0,"",Table10[[#This Row],[Parking]]) | AD37: =IF(Table10[[#This Row],[Furniture]]=0,"",Table10[[#This Row],[Furniture]]) | AE37: =IF(Table10[[#This Row],[Other]]=0,"",Table10[[#This Row],[Other]])
A38: =IF(Table10[[#This Row],[Unit Type]]=0,"",Table10[[#This Row],[Unit Type]]) -> 1 Bedroom | B38: =IF(Table10[[#This Row],[Residential Stream Source]]=0,"",Table10[[#This Row],[Residential Stream Source]]) | C38: =IF(Table10[[#This Row],[Basement?]]=0,"",Table10[[#This Row],[Basement?]]) | D38: =IF(Table10[[#This Row],[Unit '#]]=0,"",Table10[[#This Row],[Unit '#]]) -> 36 | E38: =IF(Table10[[#This Row],[Vacant?]]=0,"",Table10[[#This Row],[Vacant?]]) | F38: =IF(Table10[[#This Row],[Rental Rate ($/mth)]]=0,"",Table10[[#This Row],[Rental Rate ($/mth)]]) -> 2490 | J38: =IF(Table10[[#This Row],[Unit Size (sq ft)]]=0,"",Table10[[#This Row],[Unit Size (sq ft)]]) -> 624 | L38: =Table10[[#This Row],[Market Unit]] -> Yes | M38: =Table10[[#This Row],[Affordable Unit]] -> No | N38: =IF(Table10[[#This Row],[Subsidized Unit]]=0,"",Table10[[#This Row],[Subsidized Unit]]) | O38: =IF(Table10[[#This Row],[Care Services]]=0,"",Table10[[#This Row],[Care Services]]) | P38: =IF(Table10[[#This Row],[Affordable Care]]=0,"",Table10[[#This Row],[Affordable Care]]) | T38: =IF(Table10[[#This Row],[Bulk Lease Unit]]=0,"",Table10[[#This Row],[Bulk Lease Unit]]) | U38: =IF(Table10[[#This Row],[Den Included Unit]]=0,"",Table10[[#This Row],[Den Included Unit]]) | V38: =IF(Table10[[#This Row],[Second Bathroom]]=0,"",Table10[[#This Row],[Second Bathroom]]) | W38: =IF(Table10[[#This Row],[Heating]]=0,"",Table10[[#This Row],[Heating]]) | X38: =IF(Table10[[#This Row],[Electricity]]=0,"",Table10[[#This Row],[Electricity]]) | Y38: =IF(Table10[[#This Row],[Water]]=0,"",Table10[[#This Row],[Water]]) | Z38: =IF(Table10[[#This Row],[Washer/Dryer]]=0,"",Table10[[#This Row],[Washer/Dryer]]) | AA38: =IF(Table10[[#This Row],[Stove/Fridge]]=0,"",Table10[[#This Row],[Stove/Fridge]]) | AB38: =IF(Table10[[#This Row],[Dishwasher]]=0,"",Table10[[#This Row],[Dishwasher]]) | AC38: =IF(Table10[[#This Row],[Parking]]=0,"",Table10[[#This Row],[Parking]]) | AD38: =IF(Table10[[#This Row],[Furniture]]=0,"",Table10[[#This Row],[Furniture]]) | AE38: =IF(Table10[[#This Row],[Other]]=0,"",Table10[[#This Row],[Other]])
A39: =IF(Table10[[#This Row],[Unit Type]]=0,"",Table10[[#This Row],[Unit Type]]) -> 1 Bedroom | B39: =IF(Table10[[#This Row],[Residential Stream Source]]=0,"",Table10[[#This Row],[Residential Stream Source]]) | C39: =IF(Table10[[#This Row],[Basement?]]=0,"",Table10[[#This Row],[Basement?]]) | D39: =IF(Table10[[#This Row],[Unit '#]]=0,"",Table10[[#This Row],[Unit '#]]) -> 37 | E39: =IF(Table10[[#This Row],[Vacant?]]=0,"",Table10[[#This Row],[Vacant?]]) | F39: =IF(Table10[[#This Row],[Rental Rate ($/mth)]]=0,"",Table10[[#This Row],[Rental Rate ($/mth)]]) -> 2490 | J39: =IF(Table10[[#This Row],[Unit Size (sq ft)]]=0,"",Table10[[#This Row],[Unit Size (sq ft)]]) -> 624 | L39: =Table10[[#This Row],[Market Unit]] -> Yes | M39: =Table10[[#This Row],[Affordable Unit]] -> No | N39: =IF(Table10[[#This Row],[Subsidized Unit]]=0,"",Table10[[#This Row],[Subsidized Unit]]) | O39: =IF(Table10[[#This Row],[Care Services]]=0,"",Table10[[#This Row],[Care Services]]) | P39: =IF(Table10[[#This Row],[Affordable Care]]=0,"",Table10[[#This Row],[Affordable Care]]) | T39: =IF(Table10[[#This Row],[Bulk Lease Unit]]=0,"",Table10[[#This Row],[Bulk Lease Unit]]) | U39: =IF(Table10[[#This Row],[Den Included Unit]]=0,"",Table10[[#This Row],[Den Included Unit]]) | V39: =IF(Table10[[#This Row],[Second Bathroom]]=0,"",Table10[[#This Row],[Second Bathroom]]) | W39: =IF(Table10[[#This Row],[Heating]]=0,"",Table10[[#This Row],[Heating]]) | X39: =IF(Table10[[#This Row],[Electricity]]=0,"",Table10[[#This Row],[Electricity]]) | Y39: =IF(Table10[[#This Row],[Water]]=0,"",Table10[[#This Row],[Water]]) | Z39: =IF(Table10[[#This Row],[Washer/Dryer]]=0,"",Table10[[#This Row],[Washer/Dryer]]) | AA39: =IF(Table10[[#This Row],[Stove/Fridge]]=0,"",Table10[[#This Row],[Stove/Fridge]]) | AB39: =IF(Table10[[#This Row],[Dishwasher]]=0,"",Table10[[#This Row],[Dishwasher]]) | AC39: =IF(Table10[[#This Row],[Parking]]=0,"",Table10[[#This Row],[Parking]]) | AD39: =IF(Table10[[#This Row],[Furniture]]=0,"",Table10[[#This Row],[Furniture]]) | AE39: =IF(Table10[[#This Row],[Other]]=0,"",Table10[[#This Row],[Other]])
... A178: =IF(Table10[[#This Row],[Unit Type]]=0,"",Table10[[#This Row],[Unit Type]]) | B178: =IF(Table10[[#This Row],[Residential Stream Source]]=0,"",Table10[[#This Row],[Residential Stream Source]]) | C178: =IF(Table10[[#This Row],[Basement?]]=0,"",Table10[[#This Row],[Basement?]]) | D178: =IF(Table10[[#This Row],[Unit '#]]=0,"",Table10[[#This Row],[Unit '#]]) -> 176 | E178: =IF(Table10[[#This Row],[Vacant?]]=0,"",Table10[[#This Row],[Vacant?]]) | F178: =IF(Table10[[#This Row],[Rental Rate ($/mth)]]=0,"",Table10[[#This Row],[Rental Rate ($/mth)]]) | J178: =IF(Table10[[#This Row],[Unit Size (sq ft)]]=0,"",Table10[[#This Row],[Unit Size (sq ft)]]) | L178: =Table10[[#This Row],[Market Unit]] | M178: =Table10[[#This Row],[Affordable Unit]] | N178: =IF(Table10[[#This Row],[Subsidized Unit]]=0,"",Table10[[#This Row],[Subsidized Unit]]) | O178: =IF(Table10[[#This Row],[Care Services]]=0,"",Table10[[#This Row],[Care Services]]) | P178: =IF(Table10[[#This Row],[Affordable Care]]=0,"",Table10[[#This Row],[Affordable Care]]) | T178: =IF(Table10[[#This Row],[Bulk Lease Unit]]=0,"",Table10[[#This Row],[Bulk Lease Unit]]) | U178: =IF(Table10[[#This Row],[Den Included Unit]]=0,"",Table10[[#This Row],[Den Included Unit]]) | V178: =IF(Table10[[#This Row],[Second Bathroom]]=0,"",Table10[[#This Row],[Second Bathroom]]) | W178: =IF(Table10[[#This Row],[Heating]]=0,"",Table10[[#This Row],[Heating]]) | X178: =IF(Table10[[#This Row],[Electricity]]=0,"",Table10[[#This Row],[Electricity]]) | Y178: =IF(Table10[[#This Row],[Water]]=0,"",Table10[[#This Row],[Water]]) | Z178: =IF(Table10[[#This Row],[Washer/Dryer]]=0,"",Table10[[#This Row],[Washer/Dryer]]) | AA178: =IF(Table10[[#This Row],[Stove/Fridge]]=0,"",Table10[[#This Row],[Stove/Fridge]]) | AB178: =IF(Table10[[#This Row],[Dishwasher]]=0,"",Table10[[#This Row],[Dishwasher]]) | AC178: =IF(Table10[[#This Row],[Parking]]=0,"",Table10[[#This Row],[Parking]]) | AD178: =IF(Table10[[#This Row],[Furniture]]=0,"",Table10[[#This Row],[Furniture]]) | AE178: =IF(Table10[[#This Row],[Other]]=0,"",Table10[[#This Row],[Other]])
E181: Total | F181: =SUM(F3:I178) -> 489850 | J181: =SUM(G3:J178) -> 128826
E182: Total Annually | F182: =F181*12 -> 5878200
A186: Number | B186: Type | C186: Avergae SF | D186: Average $/SF | E186: Average Rent
A187: =COUNTIF(Table102[Unit Type],B187) -> 0 | B187: Semi-Private & Ward Beds | C187: =IFERROR(AVERAGEIF(Table102[Unit Type],B187,Table102[Unit Size (sq ft)]),"") | D187: =IFERROR(E187/C187,"") | E187: =IFERROR(AVERAGEIF(Table102[Unit Type],B187,Table102[Rental Rate ($/mth)]),"")
A188: =COUNTIF(Table102[Unit Type],B188) -> 0 | B188: Private Beds | C188: =IFERROR(AVERAGEIF(Table102[Unit Type],B188,Table102[Unit Size (sq ft)]),"") | D188: =IFERROR(E188/C188,"") | E188: =IFERROR(AVERAGEIF(Table102[Unit Type],B188,Table102[Rental Rate ($/mth)]),"")
A189: =COUNTIF(Table102[Unit Type],B189) -> 0 | B189: Shelter Beds (NHCF) | C189: =IFERROR(AVERAGEIF(Table102[Unit Type],B189,Table102[Unit Size (sq ft)]),"") | D189: =IFERROR(E189/C189,"") | E189: =IFERROR(AVERAGEIF(Table102[Unit Type],B189,Table102[Rental Rate ($/mth)]),"")
A190: =COUNTIF(Table102[Unit Type],B190) -> 0 | B190: Bachelor | C190: =IFERROR(AVERAGEIF(Table102[Unit Type],B190,Table102[Unit Size (sq ft)]),"") | D190: =IFERROR(E190/C190,"") | E190: =IFERROR(AVERAGEIF(Table102[Unit Type],B190,Table102[Rental Rate ($/mth)]),"")
A191: =COUNTIF(Table102[Unit Type],B191) -> 0 | B191: 1 Bedrooms | C191: =IFERROR(AVERAGEIF(Table102[Unit Type],B191,Table102[Unit Size (sq ft)]),"") | D191: =IFERROR(E191/C191,"") | E191: =IFERROR(AVERAGEIF(Table102[Unit Type],B191,Table102[Rental Rate ($/mth)]),"")
A192: =COUNTIF(Table102[Unit Type],B192) -> 0 | B192: 2 Bedrooms | C192: =IFERROR(AVERAGEIF(Table102[Unit Type],B192,Table102[Unit Size (sq ft)]),"") | D192: =IFERROR(E192/C192,"") | E192: =IFERROR(AVERAGEIF(Table102[Unit Type],B192,Table102[Rental Rate ($/mth)]),"")
A193: =COUNTIF(Table102[Unit Type],B193) -> 0 | B193: 3 Bedrooms | C193: =IFERROR(AVERAGEIF(Table102[Unit Type],B193,Table102[Unit Size (sq ft)]),"") | D193: =IFERROR(E193/C193,"") | E193: =IFERROR(AVERAGEIF(Table102[Unit Type],B193,Table102[Rental Rate ($/mth)]),"")
A194: =COUNTIF(Table102[Unit Type],B194) -> 0 | B194: 4+ Bedrooms | C194: =IFERROR(AVERAGEIF(Table102[Unit Type],B194,Table102[Unit Size (sq ft)]),"") | D194: =IFERROR(E194/C194,"") | E194: =IFERROR(AVERAGEIF(Table102[Unit Type],B194,Table102[Rental Rate ($/mth)]),"")
A195: =SUM(A187:A194) -> 0 | C195: =J181/A195 -> #DIV/0! | D195: =E195/C195 -> #DIV/0! | E195: =F181/A195 -> #DIV/0!

Sheet Rent Roll CMHC
A1: Unit Details (start with Unit #, Rental Rate or Unit Size) | L1: Unit Designations? | T1: What's included in the unit/rent?
A2: Unit Type | B2: Residential Stream Source | C2: Basement? | D2: Unit # | E2: Vacant? | F2: Rental Rate ($/mth) | G2: Monthly Rev. Accepted | H2: Annual Rev. Submitted | I2: Annual Rev. Accepted | J2: Unit Size (sq ft) | K2: Floor Area Accepted (SF) | L2: Market Unit | M2: Affordable Unit | N2: Subsidized Unit | O2: Care Services | P2: Affordable Care | Q2: Non-Res. Stream Source | R2: Business Type | S2: Lease Type | T2: Bulk Lease Unit | U2: Den Included Unit | V2: Second Bathroom | W2: Heating | X2: Electricity | Y2: Water | Z2: Washer/Dryer | AA2: Stove/Fridge | AB2: Dishwasher | AC2: Parking | AD2: Furniture | AE2: Other
A3: 1 Bedroom | D3: 1 | E3: Yes | F3: 2490 | J3: 624 | L3: Yes | M3: No | AD3: No
A4: 1 Bedroom | D4: 2 | E4: Yes | F4: 2490 | J4: 624 | L4: Yes | M4: No
A5: 1 Bedroom | D5: 3 | E5: Yes | F5: 2490 | J5: 624 | L5: =IF(Table10[[#This Row],[Rental Rate ($/mth)]]<>"",IF(Table10[[#This Row],[Rental Rate ($/mth)]]<='Input CMHC MLI Select'!$C$12,"No","Yes"),"") -> Yes | M5: No
A6: 1 Bedroom | D6: 4 | E6: Yes | F6: 2490 | J6: 624 | L6: =IF(Table10[[#This Row],[Rental Rate ($/mth)]]<>"",IF(Table10[[#This Row],[Rental Rate ($/mth)]]<='Input CMHC MLI Select'!$C$12,"No","Yes"),"") -> Yes | M6: No
A7: 1 Bedroom | D7: 5 | E7: Yes | F7: 2490 | J7: 624 | L7: =IF(Table10[[#This Row],[Rental Rate ($/mth)]]<>"",IF(Table10[[#This Row],[Rental Rate ($/mth)]]<='Input CMHC MLI Select'!$C$12,"No","Yes"),"") -> Yes | M7: No
A8: 1 Bedroom | D8: 6 | F8: 2490 | J8: 624 | L8: =IF(Table10[[#This Row],[Rental Rate ($/mth)]]<>"",IF(Table10[[#This Row],[Rental Rate ($/mth)]]<='Input CMHC MLI Select'!$C$12,"No","Yes"),"") -> Yes | M8: No
A9: 1 Bedroom | D9: 7 | F9: 2490 | J9: 624 | L9: =IF(Table10[[#This Row],[Rental Rate ($/mth)]]<>"",IF(Table10[[#This Row],[Rental Rate ($/mth)]]<='Input CMHC MLI Select'!$C$12,"No","Yes"),"") -> Yes | M9: No
A10: 1 Bedroom | D10: 8 | F10: 2490 | J10: 624 | L10: =IF(Table10[[#This Row],[Rental Rate ($/mth)]]<>"",IF(Table10[[#This Row],[Rental Rate ($/mth)]]<='Input CMHC MLI Select'!$C$12,"No","Yes"),"") -> Yes | M10: No
A11: 1 Bedroom | D11: 9 | F11: 2490 | J11: 624 | L11: =IF(Table10[[#This Row],[Rental Rate ($/mth)]]<>"",IF(Table10[[#This Row],[Rental Rate ($/mth)]]<='Input CMHC MLI Select'!$C$12,"No","Yes"),"") -> Yes | M11: No
A12: 1 Bedroom | D12: 10 | F12: 2490 | J12: 624 | L12: =IF(Table10[[#This Row],[Rental Rate ($/mth)]]<>"",IF(Table10[[#This Row],[Rental Rate ($/mth)]]<='Input CMHC MLI Select'!$C$12,"No","Yes"),"") -> Yes | M12: No
A13: 1 Bedroom | D13: 11 | F13: 2490 | J13: 624 | L13: =IF(Table10[[#This Row],[Rental Rate ($/mth)]]<>"",IF(Table10[[#This Row],[Rental Rate ($/mth)]]<='Input CMHC MLI Select'!$C$12,"No","Yes"),"") -> Yes | M13: No
A14: 1 Bedroom | D14: 12 | F14: 2490 | J14: 624 | L14: =IF(Table10[[#This Row],[Rental Rate ($/mth)]]<>"",IF(Table10[[#This Row],[Rental Rate ($/mth)]]<='Input CMHC MLI Select'!$C$12,"No","Yes"),"") -> Yes | M14: No
A15: 1 Bedroom | D15: 13 | F15: 2490 | J15: 624 | L15: =IF(Table10[[#This Row],[Rental Rate ($/mth)]]<>"",IF(Table10[[#This Row],[Rental Rate ($/mth)]]<='Input CMHC MLI Select'!$C$12,"No","Yes"),"") -> Yes | M15: No
A16: 1 Bedroom | D16: 14 | F16: 2490 | J16: 624 | L16: =IF(Table10[[#This Row],[Rental Rate ($/mth)]]<>"",IF(Table10[[#This Row],[Rental Rate ($/mth)]]<='Input CMHC MLI Select'!$C$12,"No","Yes"),"") -> Yes | M16: No
A17: 1 Bedroom | D17: 15 | F17: 2490 | J17: 624 | L17: =IF(Table10[[#This Row],[Rental Rate ($/mth)]]<>"",IF(Table10[[#This Row],[Rental Rate ($/mth)]]<='Input CMHC MLI Select'!$C$12,"No","Yes"),"") -> Yes | M17: No
A18: 1 Bedroom | D18: 16 | F18: 2490 | J18: 624 | L18: =IF(Table10[[#This Row],[Rental Rate ($/mth)]]<>"",IF(Table10[[#This Row],[Rental Rate ($/mth)]]<='Input CMHC MLI Select'!$C$12,"No","Yes"),"") -> Yes | M18: No
A19: 1 Bedroom | D19: 17 | F19: 2490 | J19: 624 | L19: =IF(Table10[[#This Row],[Rental Rate ($/mth)]]<>"",IF(Table10[[#This Row],[Rental Rate ($/mth)]]<='Input CMHC MLI Select'!$C$12,"No","Yes"),"") -> Yes | M19: No
... A29: 1 Bedroom | D29: 27 | F29: 2490 | J29: 624 | L29: =IF(Table10[[#This Row],[Rental Rate ($/mth)]]<>"",IF(Table10[[#This Row],[Rental Rate ($/mth)]]<='Input CMHC MLI Select'!$C$12,"No","Yes"),"") -> Yes | M29: No
A30: 1 Bedroom | D30: 28 | F30: 2490 | J30: 624 | L30: =IF(Table10[[#This Row],[Rental Rate ($/mth)]]<>"",IF(Table10[[#This Row],[Rental Rate ($/mth)]]<='Input CMHC MLI Select'!$C$12,"No","Yes"),"") -> Yes | M30: =IF(Table10[[#This Row],[Rental Rate ($/mth)]]<>"",IF(Table10[[#This Row],[Rental Rate ($/mth)]]<='Input CMHC MLI Select'!$C$12,"Yes","No"),"") -> No
A31: 1 Bedroom | D31: 29 | F31: 2490 | J31: 624 | L31: =IF(Table10[[#This Row],[Rental Rate ($/mth)]]<>"",IF(Table10[[#This Row],[Rental Rate ($/mth)]]<='Input CMHC MLI Select'!$C$12,"No","Yes"),"") -> Yes | M31: =IF(Table10[[#This Row],[Rental Rate ($/mth)]]<>"",IF(Table10[[#This Row],[Rental Rate ($/mth)]]<='Input CMHC MLI Select'!$C$12,"Yes","No"),"") -> No
A32: 1 Bedroom | D32: 30 | F32: 2490 | J32: 624 | L32: =IF(Table10[[#This Row],[Rental Rate ($/mth)]]<>"",IF(Table10[[#This Row],[Rental Rate ($/mth)]]<='Input CMHC MLI Select'!$C$12,"No","Yes"),"") -> Yes | M32: =IF(Table10[[#This Row],[Rental Rate ($/mth)]]<>"",IF(Table10[[#This Row],[Rental Rate ($/mth)]]<='Input CMHC MLI Select'!$C$12,"Yes","No"),"") -> No
A33: 1 Bedroom | D33: 31 | F33: 2490 | J33: 624 | L33: =IF(Table10[[#This Row],[Rental Rate ($/mth)]]<>"",IF(Table10[[#This Row],[Rental Rate ($/mth)]]<='Input CMHC MLI Select'!$C$12,"No","Yes"),"") -> Yes | M33: =IF(Table10[[#This Row],[Rental Rate ($/mth)]]<>"",IF(Table10[[#This Row],[Rental Rate ($/mth)]]<='Input CMHC MLI Select'!$C$12,"Yes","No"),"") -> No
A34: 1 Bedroom | D34: 32 | F34: 2490 | J34: 624 | L34: =IF(Table10[[#This Row],[Rental Rate ($/mth)]]<>"",IF(Table10[[#This Row],[Rental Rate ($/mth)]]<='Input CMHC MLI Select'!$C$12,"No","Yes"),"") -> Yes | M34: =IF(Table10[[#This Row],[Rental Rate ($/mth)]]<>"",IF(Table10[[#This Row],[Rental Rate ($/mth)]]<='Input CMHC MLI Select'!$C$12,"Yes","No"),"") -> No
A35: 1 Bedroom | D35: 33 | F35: 2490 | J35: 624 | L35: =IF(Table10[[#This Row],[Rental Rate ($/mth)]]<>"",IF(Table10[[#This Row],[Rental Rate ($/mth)]]<='Input CMHC MLI Select'!$C$12,"No","Yes"),"") -> Yes | M35: =IF(Table10[[#This Row],[Rental Rate ($/mth)]]<>"",IF(Table10[[#This Row],[Rental Rate ($/mth)]]<='Input CMHC MLI Select'!$C$12,"Yes","No"),"") -> No
A36: 1 Bedroom | D36: 34 | F36: 2490 | J36: 624 | L36: =IF(Table10[[#This Row],[Rental Rate ($/mth)]]<>"",IF(Table10[[#This Row],[Rental Rate ($/mth)]]<='Input CMHC MLI Select'!$C$12,"No","Yes"),"") -> Yes | M36: =IF(Table10[[#This Row],[Rental Rate ($/mth)]]<>"",IF(Table10[[#This Row],[Rental Rate ($/mth)]]<='Input CMHC MLI Select'!$C$12,"Yes","No"),"") -> No
A37: 1 Bedroom | D37: 35 | F37: 2490 | J37: 624 | L37: =IF(Table10[[#This Row],[Rental Rate ($/mth)]]<>"",IF(Table10[[#This Row],[Rental Rate ($/mth)]]<='Input CMHC MLI Select'!$C$12,"No","Yes"),"") -> Yes | M37: =IF(Table10[[#This Row],[Rental Rate ($/mth)]]<>"",IF(Table10[[#This Row],[Rental Rate ($/mth)]]<='Input CMHC MLI Select'!$C$12,"Yes","No"),"") -> No
A38: 1 Bedroom | D38: 36 | F38: 2490 | J38: 624 | L38: =IF(Table10[[#This Row],[Rental Rate ($/mth)]]<>"",IF(Table10[[#This Row],[Rental Rate ($/mth)]]<='Input CMHC MLI Select'!$C$12,"No","Yes"),"") -> Yes | M38: =IF(Table10[[#This Row],[Rental Rate ($/mth)]]<>"",IF(Table10[[#This Row],[Rental Rate ($/mth)]]<='Input CMHC MLI Select'!$C$12,"Yes","No"),"") -> No
A39: 1 Bedroom | D39: 37 | F39: 2490 | J39: 624 | L39: =IF(Table10[[#This Row],[Rental Rate ($/mth)]]<>"",IF(Table10[[#This Row],[Rental Rate ($/mth)]]<='Input CMHC MLI Select'!$C$12,"No","Yes"),"") -> Yes | M39: =IF(Table10[[#This Row],[Rental Rate ($/mth)]]<>"",IF(Table10[[#This Row],[Rental Rate ($/mth)]]<='Input CMHC MLI Select'!$C$12,"Yes","No"),"") -> No
A40: 1 Bedroom | D40: 38 | F40: 2490 | J40: 624 | L40: =IF(Table10[[#This Row],[Rental Rate ($/mth)]]<>"",IF(Table10[[#This Row],[Rental Rate ($/mth)]]<='Input CMHC MLI Select'!$C$12,"No","Yes"),"") -> Yes | M40: =IF(Table10[[#This Row],[Rental Rate ($/mth)]]<>"",IF(Table10[[#This Row],[Rental Rate ($/mth)]]<='Input CMHC MLI Select'!$C$12,"Yes","No"),"") -> No
A41: 1 Bedroom | D41: 39 | F41: 2490 | J41: 624 | L41: =IF(Table10[[#This Row],[Rental Rate ($/mth)]]<>"",IF(Table10[[#This Row],[Rental Rate ($/mth)]]<='Input CMHC MLI Select'!$C$12,"No","Yes"),"") -> Yes | M41: =IF(Table10[[#This Row],[Rental Rate ($/mth)]]<>"",IF(Table10[[#This Row],[Rental Rate ($/mth)]]<='Input CMHC MLI Select'!$C$12,"Yes","No"),"") -> No
... A172: 3 Bedroom | D172: 170 | F172: 3675 | J172: 1015 | L172: =IF(Table10[[#This Row],[Rental Rate ($/mth)]]<>"",IF(Table10[[#This Row],[Rental Rate ($/mth)]]<='Input CMHC MLI Select'!$C$12,"No","Yes"),"") -> Yes | M172: =IF(Table10[[#This Row],[Rental Rate ($/mth)]]<>"",IF(Table10[[#This Row],[Rental Rate ($/mth)]]<='Input CMHC MLI Select'!$C$12,"Yes","No"),"") -> No
D173: 171 | L173: =IF(Table10[[#This Row],[Rental Rate ($/mth)]]<>"",IF(Table10[[#This Row],[Rental Rate ($/mth)]]<='Input CMHC MLI Select'!$C$12,"No","Yes"),"") | M173: =IF(Table10[[#This Row],[Rental Rate ($/mth)]]<>"",IF(Table10[[#This Row],[Rental Rate ($/mth)]]<='Input CMHC MLI Select'!$C$12,"Yes","No"),"")
D174: 172 | L174: =IF(Table10[[#This Row],[Rental Rate ($/mth)]]<>"",IF(Table10[[#This Row],[Rental Rate ($/mth)]]<='Input CMHC MLI Select'!$C$12,"No","Yes"),"") | M174: =IF(Table10[[#This Row],[Rental Rate ($/mth)]]<>"",IF(Table10[[#This Row],[Rental Rate ($/mth)]]<='Input CMHC MLI Select'!$C$12,"Yes","No"),"")
D175: 173 | L175: =IF(Table10[[#This Row],[Rental Rate ($/mth)]]<>"",IF(Table10[[#This Row],[Rental Rate ($/mth)]]<='Input CMHC MLI Select'!$C$12,"No","Yes"),"") | M175: =IF(Table10[[#This Row],[Rental Rate ($/mth)]]<>"",IF(Table10[[#This Row],[Rental Rate ($/mth)]]<='Input CMHC MLI Select'!$C$12,"Yes","No"),"")
D176: 174 | L176: =IF(Table10[[#This Row],[Rental Rate ($/mth)]]<>"",IF(Table10[[#This Row],[Rental Rate ($/mth)]]<='Input CMHC MLI Select'!$C$12,"No","Yes"),"") | M176: =IF(Table10[[#This Row],[Rental Rate ($/mth)]]<>"",IF(Table10[[#This Row],[Rental Rate ($/mth)]]<='Input CMHC MLI Select'!$C$12,"Yes","No"),"")
D177: 175 | L177: =IF(Table10[[#This Row],[Rental Rate ($/mth)]]<>"",IF(Table10[[#This Row],[Rental Rate ($/mth)]]<='Input CMHC MLI Select'!$C$12,"No","Yes"),"") | M177: =IF(Table10[[#This Row],[Rental Rate ($/mth)]]<>"",IF(Table10[[#This Row],[Rental Rate ($/mth)]]<='Input CMHC MLI Select'!$C$12,"Yes","No"),"")
D178: 176 | L178: =IF(Table10[[#This Row],[Rental Rate ($/mth)]]<>"",IF(Table10[[#This Row],[Rental Rate ($/mth)]]<='Input CMHC MLI Select'!$C$12,"No","Yes"),"") | M178: =IF(Table10[[#This Row],[Rental Rate ($/mth)]]<>"",IF(Table10[[#This Row],[Rental Rate ($/mth)]]<='Input CMHC MLI Select'!$C$12,"Yes","No"),"")
D179: 177 | L179: =IF(Table10[[#This Row],[Rental Rate ($/mth)]]<>"",IF(Table10[[#This Row],[Rental Rate ($/mth)]]<='Input CMHC MLI Select'!$C$12,"No","Yes"),"") | M179: =IF(Table10[[#This Row],[Rental Rate ($/mth)]]<>"",IF(Table10[[#This Row],[Rental Rate ($/mth)]]<='Input CMHC MLI Select'!$C$12,"Yes","No"),"")
D180: 178 | L180: =IF(Table10[[#This Row],[Rental Rate ($/mth)]]<>"",IF(Table10[[#This Row],[Rental Rate ($/mth)]]<='Input CMHC MLI Select'!$C$12,"No","Yes"),"") | M180: =IF(Table10[[#This Row],[Rental Rate ($/mth)]]<>"",IF(Table10[[#This Row],[Rental Rate ($/mth)]]<='Input CMHC MLI Select'!$C$12,"Yes","No"),"")
D181: 179 | L181: =IF(Table10[[#This Row],[Rental Rate ($/mth)]]<>"",IF(Table10[[#This Row],[Rental Rate ($/mth)]]<='Input CMHC MLI Select'!$C$12,"No","Yes"),"") | M181: =IF(Table10[[#This Row],[Rental Rate ($/mth)]]<>"",IF(Table10[[#This Row],[Rental Rate ($/mth)]]<='Input CMHC MLI Select'!$C$12,"Yes","No"),"")
D182: 180 | L182: =IF(Table10[[#This Row],[Rental Rate ($/mth)]]<>"",IF(Table10[[#This Row],[Rental Rate ($/mth)]]<='Input CMHC MLI Select'!$C$12,"No","Yes"),"") | M182: =IF(Table10[[#This Row],[Rental Rate ($/mth)]]<>"",IF(Table10[[#This Row],[Rental Rate ($/mth)]]<='Input CMHC MLI Select'!$C$12,"Yes","No"),"")
D183: 181 | L183: =IF(Table10[[#This Row],[Rental Rate ($/mth)]]<>"",IF(Table10[[#This Row],[Rental Rate ($/mth)]]<='Input CMHC MLI Select'!$C$12,"No","Yes"),"") | M183: =IF(Table10[[#This Row],[Rental Rate ($/mth)]]<>"",IF(Table10[[#This Row],[Rental Rate ($/mth)]]<='Input CMHC MLI Select'!$C$12,"Yes","No"),"")
D184: 182 | L184: =IF(Table10[[#This Row],[Rental Rate ($/mth)]]<>"",IF(Table10[[#This Row],[Rental Rate ($/mth)]]<='Input CMHC MLI Select'!$C$12,"No","Yes"),"") | M184: =IF(Table10[[#This Row],[Rental Rate ($/mth)]]<>"",IF(Table10[[#This Row],[Rental Rate ($/mth)]]<='Input CMHC MLI Select'!$C$12,"Yes","No"),"")
E187: Total | F187: =SUM(F3:I184) -> 489850 | J187: =SUM(G3:J184) -> 128826
E188: Total Annually | F188: =F187*12 -> 5878200
A192: Number | B192: Type | C192: Avergae SF | D192: Average $/SF | E192: Average Rent
A193: =COUNTIF(Table10[Unit Type],B193) -> 0 | B193: Semi-Private & Ward Beds | C193: =IFERROR(AVERAGEIF(Table10[Unit Type],B193,Table10[Unit Size (sq ft)]),"") | D193: =IFERROR(E193/C193,"") | E193: =IFERROR(AVERAGEIF(Table10[Unit Type],B193,Table10[Rental Rate ($/mth)]),"")
A194: =COUNTIF(Table10[Unit Type],B194) -> 0 | B194: Private Beds | C194: =IFERROR(AVERAGEIF(Table10[Unit Type],B194,Table10[Unit Size (sq ft)]),"") | D194: =IFERROR(E194/C194,"") | E194: =IFERROR(AVERAGEIF(Table10[Unit Type],B194,Table10[Rental Rate ($/mth)]),"")
A195: =COUNTIF(Table10[Unit Type],B195) -> 0 | B195: Shelter Beds (NHCF) | C195: =IFERROR(AVERAGEIF(Table10[Unit Type],B195,Table10[Unit Size (sq ft)]),"") | D195: =IFERROR(E195/C195,"") | E195: =IFERROR(AVERAGEIF(Table10[Unit Type],B195,Table10[Rental Rate ($/mth)]),"")
A196: =COUNTIF(Table10[Unit Type],B196) -> 0 | B196: Bachelor | C196: =IFERROR(AVERAGEIF(Table10[Unit Type],B196,Table10[Unit Size (sq ft)]),"") | D196: =IFERROR(E196/C196,"") | E196: =IFERROR(AVERAGEIF(Table10[Unit Type],B196,Table10[Rental Rate ($/mth)]),"")
A197: =COUNTIF(Table10[Unit Type],B197) -> 0 | B197: 1 Bedrooms | C197: =IFERROR(AVERAGEIF(Table10[Unit Type],B197,Table10[Unit Size (sq ft)]),"") | D197: =IFERROR(E197/C197,"") | E197: =IFERROR(AVERAGEIF(Table10[Unit Type],B197,Table10[Rental Rate ($/mth)]),"")
A198: =COUNTIF(Table10[Unit Type],B198) -> 0 | B198: 2 Bedrooms | C198: =IFERROR(AVERAGEIF(Table10[Unit Type],B198,Table10[Unit Size (sq ft)]),"") | D198: =IFERROR(E198/C198,"") | E198: =IFERROR(AVERAGEIF(Table10[Unit Type],B198,Table10[Rental Rate ($/mth)]),"")
A199: =COUNTIF(Table10[Unit Type],B199) -> 0 | B199: 3 Bedrooms | C199: =IFERROR(AVERAGEIF(Table10[Unit Type],B199,Table10[Unit Size (sq ft)]),"") | D199: =IFERROR(E199/C199,"") | E199: =IFERROR(AVERAGEIF(Table10[Unit Type],B199,Table10[Rental Rate ($/mth)]),"")
A200: =COUNTIF(Table10[Unit Type],B200) -> 0 | B200: 4+ Bedrooms | C200: =IFERROR(AVERAGEIF(Table10[Unit Type],B200,Table10[Unit Size (sq ft)]),"") | D200: =IFERROR(E200/C200,"") | E200: =IFERROR(AVERAGEIF(Table10[Unit Type],B200,Table10[Rental Rate ($/mth)]),"")
A201: =SUM(A193:A200) -> 0 | C201: =J187/A201 -> #DIV/0! | D201: =E201/C201 -> #DIV/0! | E201: =F187/A201 -> #DIV/0!

Sheet Proforma Construction
B2: =IF(AND('Input CMHC MLI Select'!D24<=0,'Input CMHC MLI Select'!D37<=0,'Input CMHC MLI Select'!D48<=0),"Proforma CMHC Standard","Proforma - MLI Select "&'Input CMHC MLI Select'!E52&" pts ("&_xlfn.TEXTJOIN(", ",TRUE,IF('Input CMHC MLI Select'!D24>0,"Affordability",""),IF('Input CMHC MLI Select'!D37>0,"Accessibility",""),IF('Input CMHC MLI Select'!D48>0,"Energy efficiency",""))&")") -> Proforma - MLI Select 50 pts (Energy efficiency)
B3: 2240 Birchmount Rd Scarborough
B4: Suite Type | C4: # of Units | E4: Avg. Rent | F4: Area (SF) | G4: Rent/SF | H4: Monthly | I4: Annual
B5: Market Rental Units
B6: ='Rent Roll'!C9 -> Bachelor | C6: ='Rent Roll'!D9 -> 0 | E6: ='Rent Roll'!H9 -> 0 | F6: ='Rent Roll'!F9 -> 0 | G6: =IFERROR(E6/F6,"-") -> - | H6: =E6*C6 -> 0 | I6: =C6*E6*12 -> 0
B7: ='Rent Roll'!C10 -> 1 Bedroom | C7: ='Rent Roll'!D10 -> 84 | E7: ='Rent Roll'!H10 -> 2490 | F7: ='Rent Roll'!F10 -> 624 | G7: =IFERROR(E7/F7,"-") -> 3.9903846 | H7: =E7*C7 -> 209160 | I7: =C7*E7*12 -> 2509920
B8: ='Rent Roll'!C11 -> 2 Bedroom | C8: ='Rent Roll'!D11 -> 68 | E8: ='Rent Roll'!H11 -> 3155 | F8: ='Rent Roll'!F11 -> 855 | G8: =IFERROR(E8/F8,"-") -> 3.6900585 | H8: =E8*C8 -> 214540 | I8: =C8*E8*12 -> 2574480
B9: ='Rent Roll'!C12 -> 3 Bedroom | C9: ='Rent Roll'!D12 -> 18 | E9: ='Rent Roll'!H12 -> 3675 | F9: ='Rent Roll'!F12 -> 1015 | G9: =IFERROR(E9/F9,"-") -> 3.6206897 | H9: =E9*C9 -> 66150 | I9: =C9*E9*12 -> 793800
B10: ='Rent Roll'!C13 -> 4 Bedroom + | C10: ='Rent Roll'!D13 -> 0 | E10: ='Rent Roll'!H13 -> 0 | F10: ='Rent Roll'!F13 -> 0 | G10: =IFERROR(E10/F10,"-") -> - | H10: =E10*C10 -> 0 | I10: =C10*E10*12 -> 0
B11: Affordable Rental Units
B12: ='Rent Roll'!C15 -> 2 Bedrooms (Affordable) | C12: ='Rent Roll'!D15 -> 0 | E12: ='Rent Roll'!H15 -> 0 | F12: ='Rent Roll'!F15 -> 0 | G12: =IFERROR(E12/F12,"-") -> - | H12: =E12*C12 -> 0 | I12: =C12*E12*12 -> 0
B13: ='Rent Roll'!C16 -> 1 Bedroom (Affordable) | C13: ='Rent Roll'!D16 -> 0 | E13: ='Rent Roll'!H16 -> 0 | F13: ='Rent Roll'!F16 -> 0 | G13: =IFERROR(E13/F13,"-") -> - | H13: =E13*C13 -> 0 | I13: =C13*E13*12 -> 0
B14: Total | C14: =SUM(C6:C13) -> 170 | E14: =SUMPRODUCT(C6:C13,E6:E13) -> 489850 | F14: =SUMPRODUCT(C6:C13,F6:F13) -> 128826 | H14: =SUM(H6:H13) -> 489850 | I14: =SUM(I6:I13) -> 5878200
B15: AVERAGE | E15: =E14/C14 -> 2881.4706 | F15: =F14/C14 -> 757.8 | G15: =E15/F15 -> 3.8024157
B17: Add: | E17: Per Stalls | F17: # | H17: Monthly
B18: Garage Parking Stalls | E18: 200 | F18: 162 | G18: Garage Parking Stalls | H18: =E18*F18 -> 32400 | I18: =H18*12 -> 388800
B19: Surface Parking Stalls | E19: 0 | F19: 30 | G19: Surface Parking Stalls | H19: =E19*F19 -> 0 | I19: =H19*12 -> 0
B20: Storage Income | E20: 40 | F20: 100 | G20: Storage Income | H20: =E20*F20 -> 4000 | I20: =H20*12 -> 48000
B21: Submeter | E21: 20 | F21: 170 | G21: Laundry Income | H21: =E21*F21 -> 3400 | I21: =H21*12 -> 40800
B22: Misc. Income | E22: 40 | F22: =4370/12 -> 364.16667 | G22: Misc. Income | H22: =E22*F22 -> 14566.667 | I22: =H22*12 -> 174800
B24: Total Ancillary Income | I24: =SUM(I18:I23) -> 652400
B26: Gross Potential Revenue | I26: =I14+I24 -> 6530600
B28: Less: Vacancy | E28: 0.03 | F28: of Gross Potential Revenue | I28: =-E28*(I26-I22)-K28*I22 -> -197666 | J28: commercial vacancy | K28: 0.04
B29: 2025 CMHC Vacancy Toronto North York ON | E29: 0.032
B30: CMHC 4 Year Average Vacancy, Toronto North York ON | E30: =(0.7%+0.5%+2.1%+3.2%)/4 -> 0.01625
B31: Appraisal | E31: 0.03
B32: Effective Gross Revenue | I32: =I26+I28 -> 6332934
B34: Operating Expenses
B35: Less: | E35: Basis | F35: % of EGI | G35: PUPA
B36: Property Taxes | E36: Appraisal | F36: =IFERROR(I36/I32,"-") -> 0.091091586 | G36: =IFERROR(I36/C14,"-") -> 3393.3941 | I36: 576877
B37: Insurance | E37: Appraisal | F37: =IFERROR(I37/I32,"-") -> 0.012079709 | G37: =IFERROR(I37/C14,"-") -> 450 | I37: 76500
B38: Utilities | E38: Common Area | F38: =IFERROR(I38/I32,"-") -> 0.030333492 | G38: =IFERROR(I38/C14,"-") -> 1130 | I38: 192100
B39: Management Fee | E39: CMHC Bench | F39: ='Input CMHC MLI Select'!D78 -> 0.0425 | G39: =IFERROR(I39/+C56,"-") -> 1583.2335 | I39: =F39*I32 -> 269149.7
B40: Maintenance | E40: CMHC Bench | F40: =IFERROR(I40/I32,"-") -> 0.022280352 | G40: ='Input CMHC MLI Select'!E79 -> 830 | I40: =G40*C14 -> 141100
B41: Wages & Salaries | E41: CMHC Bench | F41: =IFERROR(I41/I32,"-") -> 0.014898308 | G41: ='Input CMHC MLI Select'!E80 -> 555 | I41: =G41*C14 -> 94350
B42: General & Admin | E42: CMHC Bench | F42: ='Input CMHC MLI Select'!D81 -> 0.01 | G42: =IFERROR(I42/C56,"-") -> 372.52553 | I42: =F42*I32 -> 63329.34
B43: Replacement Reserve | E43: CMHC Bench | F43: =IFERROR(I43/+I32,"-") -> 0.0080531394 | G43: 300 | I43: =G43*C14 -> 51000
B44: Replacement Reserve(Garden suite heat pump) | E44: CMHC Bench | F44: =IFERROR(I44/I32,"-") -> 0 | G44: 0 | I44: =G44*C14 -> 0
B45: Total Operating Expenses | F45: =SUM(F36:F44) -> 0.23123659 | G45: 6863 | I45: =SUM(I36:I44) -> 1464406
B47: Net Operating Income | I47: =I32-I45 -> 4868528
B48: Residential Mortgage
C49: Loan to Cost | D49: Loan to Value | E49: Loan Amount | F49: Test Rate | G49: Amortization | H49: DSC | I49: Payments
B50: First Mortgage | C50: =E50/G79 -> 0.96735242 | D50: =E50/C61 -> 0.75998331 | E50: 92500000 | F50: 0.037 | G50: 40 | H50: =I47/I50 -> 1.1026864 | I50: =IF(G50="IO",F50*E50,PMT((F50/2+1)^(1/6)-1,G50*12,-(E50))*12) -> 4415151.7
B51: Cash Flow After Debt Service | I51: =I47-I50 -> 453376.25
B52: Underwriting & Analysis
B53: Residential Mortgage | F53: Loan Analysis
B54: Net Leasable Square Footage | C54: =F14 -> 128826 | F54: Construction Loan Amount | I54: =C71 -> 92500000
B55: Average Unit Size | C55: =IFERROR(C54/C14,"-") -> 757.8 | F55: Estimated Value | I55: =C61 -> 1.217132e+08
B56: Number of Units | C56: =C14 -> 170 | F56: Loan to Value | I56: =D50 -> 0.75998331
B57: Average Monthly Rent | C57: =H14 -> 489850 | F57: Loan to Cost | I57: =C50 -> 0.96735242
B58: Net Operating Income | C58: =I47 -> 4868528 | F58: Loan per Net SF | I58: =IFERROR(I54/C54,"-") -> 718.02276
B59: Operating Costs per Unit | C59: =IFERROR(C58/C56,"-") -> 28638.4 | F59: Loan per Suite | I59: =IFERROR(I54/C56,"-") -> 544117.65
B60: Capitalization Rate | C60: 0.04 | F60: CMHC Fees
B61: Estimated Residential Value | C61: =C58/C60 -> 1.217132e+08 | F61: Net Loan Amount | I61: =I54 -> 92500000
B62: Value per Residential Unit | C62: =IFERROR(C61/C56,"-") -> 715959.99 | F62: Residential Application Fee | I62: =MIN(IF(C56<=100,'Input CMHC MLI Select'!C74*C56,100*'Input CMHC MLI Select'!C74+(C56-100)*100),IF('Input CMHC MLI Select'!C63="NEW CONSTRUCTION",55000,IF('Input CMHC MLI Select'!C63="PURCHASE - REFINANCE",50000,""))) -> 55000
F63: Total LTV Premium | I63: =I61*'Input CMHC MLI Select'!C73 -> 4786875
F64: Total CMHC Fees | I64: =SUM(I62:I63) -> 4841875
F65: Gross CMHC Loan | I65: =I61+I64 -> 97341875
B69: Capital Stack
B70: Sources | C70: Amount | D70: % | E70: Uses | G70: Amount | H70: Per Unit | I70: %
B71: First Mortgage | C71: =E50 -> 92500000 | D71: =C71/$C$79 -> 0.96735242 | E71: =Budget!F77 -> Land | G71: =Budget!H77 -> 10902956 | H71: =IFERROR(G71/$C$56,"-") -> 64135.035 | I71: =G71/$G$79 -> 0.11402163
B72: Borrower's Equity | C72: =C79-C71 -> 3121820.6 | D72: =C72/$C$79 -> 0.032647575 | E72: =Budget!F78 -> Hard Costs | G72: =Budget!H78 -> 65683716 | H72: =IFERROR(G72/$C$56,"-") -> 386374.8 | I72: =G72/$G$79 -> 0.68691137
E73: =Budget!F79 -> Soft Costs | G73: =Budget!H79 -> 10816785 | H73: =IFERROR(G73/$C$56,"-") -> 63628.147 | I73: =G73/$G$79 -> 0.11312047
E74: =Budget!F80 -> Contingency | G74: =Budget!H80 -> 1854513.6 | H74: =IFERROR(G74/$C$56,"-") -> 10908.903 | I74: =G74/$G$79 -> 0.019394251
E75: =Budget!F81 -> Interest Reserve | G75: =Budget!H81 -> 3300000 | H75: =IFERROR(G75/$C$56,"-") -> 19411.765 | I75: =G75/$G$79 -> 0.034510951
E76: =Budget!F82 -> Financing Fees | G76: =Budget!H82 -> 1387500 | H76: =IFERROR(G76/$C$56,"-") -> 8161.7647 | I76: =G76/$G$79 -> 0.014510286
E77: =Budget!F83 -> GST | G77: =Budget!H83 -> 0 | H77: =IFERROR(G77/$C$56,"-") -> 0 | I77: =G77/$G$79 -> 0
E78: =Budget!F84 -> Marketing | G78: =Budget!H84 -> 1676350 | H78: =IFERROR(G78/$C$56,"-") -> 9860.8824 | I78: =G78/$G$79 -> 0.01753104
B79: Total Source | C79: =G79 -> 95621821 | D79: =SUM(D71:D78) -> 1 | E79: Total Uses | G79: =SUM(G71:G78) -> 95621821 | H79: =IFERROR(G79/$C$56,"-") -> 562481.3 | I79: =G79/$G$79 -> 1

Sheet Rent Roll
C5: Portfolio Statistics
C7: Unit Type | D7: # of Unit | E7: GFA | F7: Avg. GFA | G7: Total Rent | H7: Avg. Rent | I7: Avg. Rent PSF
C8: Market rental Units
C9: Bachelor | D9: {=+SUMPRODUCT(($E$22:$E$191=$C9)*1)} -> 0 | E9: {=+SUMPRODUCT(($E$22:$E$191=$C9)*1,$F$22:$F$191)} -> 0 | F9: =+IFERROR(E9/D9,0) -> 0 | G9: {=+SUMPRODUCT(($E$22:$E$191=$C9)*1,$G$22:$G$191)} -> 0 | H9: =+IFERROR(G9/$D9,0) -> 0 | I9: =+IFERROR(G9/$E9,0) -> 0
C10: 1 Bedroom | D10: {=+SUMPRODUCT(($E$22:$E$191=$C10)*1)} -> 84 | E10: {=+SUMPRODUCT(($E$22:$E$191=$C10)*1,$F$22:$F$191)} -> 52416 | F10: =+IFERROR(E10/D10,0) -> 624 | G10: {=+SUMPRODUCT(($E$22:$E$191=$C10)*1,$G$22:$G$191)} -> 209160 | H10: =+IFERROR(G10/$D10,0) -> 2490 | I10: =+IFERROR(G10/$E10,0) -> 3.9903846
C11: 2 Bedroom | D11: {=+SUMPRODUCT(($E$22:$E$191=$C11)*1)} -> 68 | E11: {=+SUMPRODUCT(($E$22:$E$191=$C11)*1,$F$22:$F$191)} -> 58140 | F11: =+IFERROR(E11/D11,0) -> 855 | G11: {=+SUMPRODUCT(($E$22:$E$191=$C11)*1,$G$22:$G$191)} -> 214540 | H11: =+IFERROR(G11/$D11,0) -> 3155 | I11: =+IFERROR(G11/$E11,0) -> 3.6900585
C12: 3 Bedroom | D12: {=+SUMPRODUCT(($E$22:$E$191=$C12)*1)} -> 18 | E12: {=+SUMPRODUCT(($E$22:$E$191=$C12)*1,$F$22:$F$191)} -> 18270 | F12: =+IFERROR(E12/D12,0) -> 1015 | G12: {=+SUMPRODUCT(($E$22:$E$191=$C12)*1,$G$22:$G$191)} -> 66150 | H12: =+IFERROR(G12/$D12,0) -> 3675 | I12: =+IFERROR(G12/$E12,0) -> 3.6206897
C13: 4 Bedroom + | D13: {=+SUMPRODUCT(($E$22:$E$191=$C13)*1)} -> 0 | E13: {=+SUMPRODUCT(($E$22:$E$191=$C13)*1,$F$22:$F$191)} -> 0 | F13: =+IFERROR(E13/D13,0) -> 0 | G13: {=+SUMPRODUCT(($E$22:$E$191=$C13)*1,$G$22:$G$191)} -> 0 | H13: =+IFERROR(G13/$D13,0) -> 0 | I13: =+IFERROR(G13/$E13,0) -> 0
C14: Affordable Rental Units
C15: 2 Bedrooms (Affordable) | D15: {=+SUMPRODUCT(($E$22:$E$191=$C15)*1)} -> 0 | E15: {=+SUMPRODUCT(($E$22:$E$191=$C15)*1,$F$22:$F$191)} -> 0 | F15: =+IFERROR(E15/D15,0) -> 0 | G15: {=+SUMPRODUCT(($E$22:$E$191=$C15)*1,$G$22:$G$191)} -> 0 | H15: =+IFERROR(G15/$D15,0) -> 0 | I15: =+IFERROR(G15/$E15,0) -> 0
C16: 1 Bedroom (Affordable) | D16: {=+SUMPRODUCT(($E$22:$E$191=$C16)*1)} -> 0 | E16: {=+SUMPRODUCT(($E$22:$E$191=$C16)*1,$F$22:$F$191)} -> 0 | F16: =+IFERROR(E16/D16,0) -> 0 | G16: {=+SUMPRODUCT(($E$22:$E$191=$C16)*1,$G$22:$G$191)} -> 0 | H16: =+IFERROR(G16/$D16,0) -> 0 | I16: =+IFERROR(G16/$E16,0) -> 0
C17: Total | D17: =SUM(D9:D16) -> 170 | E17: =SUM(E9:E16) -> 128826 | F17: =+IFERROR(E17/D17,0) -> 757.8 | G17: =SUM(G9:G16) -> 489850 | H17: =+IFERROR(G17/$D17,0) -> 2881.4706 | I17: =+IFERROR(G17/$E17,0) -> 3.8024157
C19: Rent Roll (Excl. Utilities)
C21: # | D21: Unit | E21: Bedrooms | F21: Unit Size | G21: Rent | H21: Rent PSF | I21: Note
D22: ='Rent Roll CMHC'!D3 -> 1 | E22: =IF('Rent Roll CMHC'!M3="Yes",'Rent Roll CMHC'!A3&" (Affordable)",'Rent Roll CMHC'!A3) -> 1 Bedroom | F22: ='Rent Roll CMHC'!J3 -> 624 | G22: ='Rent Roll CMHC'!F3 -> 2490 | H22: =IFERROR(+G22/F22,"-") -> 3.9903846
D23: ='Rent Roll CMHC'!D4 -> 2 | E23: =IF('Rent Roll CMHC'!M4="Yes",'Rent Roll CMHC'!A4&" (Affordable)",'Rent Roll CMHC'!A4) -> 1 Bedroom | F23: ='Rent Roll CMHC'!J4 -> 624 | G23: ='Rent Roll CMHC'!F4 -> 2490 | H23: =IFERROR(+G23/F23,"-") -> 3.9903846
D24: ='Rent Roll CMHC'!D5 -> 3 | E24: =IF('Rent Roll CMHC'!M5="Yes",'Rent Roll CMHC'!A5&" (Affordable)",'Rent Roll CMHC'!A5) -> 1 Bedroom | F24: ='Rent Roll CMHC'!J5 -> 624 | G24: ='Rent Roll CMHC'!F5 -> 2490 | H24: =IFERROR(+G24/F24,"-") -> 3.9903846
D25: ='Rent Roll CMHC'!D6 -> 4 | E25: =IF('Rent Roll CMHC'!M6="Yes",'Rent Roll CMHC'!A6&" (Affordable)",'Rent Roll CMHC'!A6) -> 1 Bedroom | F25: ='Rent Roll CMHC'!J6 -> 624 | G25: ='Rent Roll CMHC'!F6 -> 2490 | H25: =IFERROR(+G25/F25,"-") -> 3.9903846
D26: ='Rent Roll CMHC'!D7 -> 5 | E26: =IF('Rent Roll CMHC'!M7="Yes",'Rent Roll CMHC'!A7&" (Affordable)",'Rent Roll CMHC'!A7) -> 1 Bedroom | F26: ='Rent Roll CMHC'!J7 -> 624 | G26: ='Rent Roll CMHC'!F7 -> 2490 | H26: =IFERROR(+G26/F26,"-") -> 3.9903846
D27: ='Rent Roll CMHC'!D8 -> 6 | E27: =IF('Rent Roll CMHC'!M8="Yes",'Rent Roll CMHC'!A8&" (Affordable)",'Rent Roll CMHC'!A8) -> 1 Bedroom | F27: ='Rent Roll CMHC'!J8 -> 624 | G27: ='Rent Roll CMHC'!F8 -> 2490 | H27: =IFERROR(+G27/F27,"-") -> 3.9903846
D28: ='Rent Roll CMHC'!D9 -> 7 | E28: =IF('Rent Roll CMHC'!M9="Yes",'Rent Roll CMHC'!A9&" (Affordable)",'Rent Roll CMHC'!A9) -> 1 Bedroom | F28: ='Rent Roll CMHC'!J9 -> 624 | G28: ='Rent Roll CMHC'!F9 -> 2490 | H28: =IFERROR(+G28/F28,"-") -> 3.9903846
D29: ='Rent Roll CMHC'!D10 -> 8 | E29: =IF('Rent Roll CMHC'!M10="Yes",'Rent Roll CMHC'!A10&" (Affordable)",'Rent Roll CMHC'!A10) -> 1 Bedroom | F29: ='Rent Roll CMHC'!J10 -> 624 | G29: ='Rent Roll CMHC'!F10 -> 2490 | H29: =IFERROR(+G29/F29,"-") -> 3.9903846
D30: ='Rent Roll CMHC'!D11 -> 9 | E30: =IF('Rent Roll CMHC'!M11="Yes",'Rent Roll CMHC'!A11&" (Affordable)",'Rent Roll CMHC'!A11) -> 1 Bedroom | F30: ='Rent Roll CMHC'!J11 -> 624 | G30: ='Rent Roll CMHC'!F11 -> 2490 | H30: =IFERROR(+G30/F30,"-") -> 3.9903846
D31: ='Rent Roll CMHC'!D12 -> 10 | E31: =IF('Rent Roll CMHC'!M12="Yes",'Rent Roll CMHC'!A12&" (Affordable)",'Rent Roll CMHC'!A12) -> 1 Bedroom | F31: ='Rent Roll CMHC'!J12 -> 624 | G31: ='Rent Roll CMHC'!F12 -> 2490 | H31: =IFERROR(+G31/F31,"-") -> 3.9903846
D32: ='Rent Roll CMHC'!D13 -> 11 | E32: =IF('Rent Roll CMHC'!M13="Yes",'Rent Roll CMHC'!A13&" (Affordable)",'Rent Roll CMHC'!A13) -> 1 Bedroom | F32: ='Rent Roll CMHC'!J13 -> 624 | G32: ='Rent Roll CMHC'!F13 -> 2490 | H32: =IFERROR(+G32/F32,"-") -> 3.9903846
D33: ='Rent Roll CMHC'!D14 -> 12 | E33: =IF('Rent Roll CMHC'!M14="Yes",'Rent Roll CMHC'!A14&" (Affordable)",'Rent Roll CMHC'!A14) -> 1 Bedroom | F33: ='Rent Roll CMHC'!J14 -> 624 | G33: ='Rent Roll CMHC'!F14 -> 2490 | H33: =IFERROR(+G33/F33,"-") -> 3.9903846
... D191: ='Rent Roll CMHC'!D172 -> 170 | E191: =IF('Rent Roll CMHC'!M172="Yes",'Rent Roll CMHC'!A172&" (Affordable)",'Rent Roll CMHC'!A172) -> 3 Bedroom | F191: ='Rent Roll CMHC'!J172 -> 1015 | G191: ='Rent Roll CMHC'!F172 -> 3675 | H191: =IFERROR(+G191/F191,"-") -> 3.6206897

Sheet Proforma Purchase Refi
B2: =IF(AND('Input CMHC MLI Select'!D24<=0,'Input CMHC MLI Select'!D37<=0,'Input CMHC MLI Select'!D48<=0),"Proforma CMHC Standard","Proforma - MLI Select "&'Input CMHC MLI Select'!E52&" pts ("&_xlfn.TEXTJOIN(", ",TRUE,IF('Input CMHC MLI Select'!D24>0,"Affordability",""),IF('Input CMHC MLI Select'!D37>0,"Accessibility",""),IF('Input CMHC MLI Select'!D48>0,"Energy efficiency",""))&")") -> Proforma - MLI Select 50 pts (Energy efficiency)
B3: ='Proforma Construction'!B3 -> 2240 Birchmount Rd Scarborough
B4: Suite Type | C4: # of Units | E4: Avg. Rent | F4: Area (SF) | G4: Rent/SF | H4: Monthly | I4: Annual
B5: Market Rental Units
B6: ='Rent Roll'!C9 -> Bachelor | C6: ='Rent Roll'!D9 -> 0 | E6: ='Rent Roll'!H9 -> 0 | F6: ='Rent Roll'!F9 -> 0 | G6: =IFERROR(E6/F6,"-") -> - | H6: =E6*C6 -> 0 | I6: =C6*E6*12 -> 0
B7: ='Rent Roll'!C10 -> 1 Bedroom | C7: ='Rent Roll'!D10 -> 84 | E7: ='Rent Roll'!H10 -> 2490 | F7: ='Rent Roll'!F10 -> 624 | G7: =IFERROR(E7/F7,"-") -> 3.9903846 | H7: =E7*C7 -> 209160 | I7: =C7*E7*12 -> 2509920
B8: ='Rent Roll'!C11 -> 2 Bedroom | C8: ='Rent Roll'!D11 -> 68 | E8: ='Rent Roll'!H11 -> 3155 | F8: ='Rent Roll'!F11 -> 855 | G8: =IFERROR(E8/F8,"-") -> 3.6900585 | H8: =E8*C8 -> 214540 | I8: =C8*E8*12 -> 2574480
B9: ='Rent Roll'!C12 -> 3 Bedroom | C9: ='Rent Roll'!D12 -> 18 | E9: ='Rent Roll'!H12 -> 3675 | F9: ='Rent Roll'!F12 -> 1015 | G9: =IFERROR(E9/F9,"-") -> 3.6206897 | H9: =E9*C9 -> 66150 | I9: =C9*E9*12 -> 793800
B10: ='Rent Roll'!C13 -> 4 Bedroom + | C10: ='Rent Roll'!D13 -> 0 | E10: ='Rent Roll'!H13 -> 0 | F10: ='Rent Roll'!F13 -> 0 | G10: =IFERROR(E10/F10,"-") -> - | H10: =E10*C10 -> 0 | I10: =C10*E10*12 -> 0
B11: Affordable Rental Units
B12: ='Rent Roll'!C15 -> 2 Bedrooms (Affordable) | C12: ='Rent Roll'!D15 -> 0 | E12: ='Rent Roll'!H15 -> 0 | F12: ='Rent Roll'!F15 -> 0 | G12: =IFERROR(E12/F12,"-") -> - | H12: =E12*C12 -> 0 | I12: =C12*E12*12 -> 0
B13: ='Rent Roll'!C16 -> 1 Bedroom (Affordable) | C13: ='Rent Roll'!D16 -> 0 | E13: ='Rent Roll'!H16 -> 0 | F13: ='Rent Roll'!F16 -> 0 | G13: =IFERROR(E13/F13,"-") -> - | H13: =E13*C13 -> 0 | I13: =C13*E13*12 -> 0
B14: Total | C14: =SUM(C6:C13) -> 170 | E14: =SUMPRODUCT(C6:C13,E6:E13) -> 489850 | F14: =SUMPRODUCT(C6:C13,F6:F13) -> 128826 | H14: =SUM(H6:H13) -> 489850 | I14: =SUM(I6:I13) -> 5878200
B15: AVERAGE | E15: =IFERROR(E14/C14,"-") -> 2881.4706 | F15: =IFERROR(F14/C14,"-") -> 757.8 | G15: =IFERROR(E15/F15,"-") -> 3.8024157
B17: Add: | E17: Per Stalls | F17: # | H17: Monthly
B18: Garage Parking Stalls | E18: ='Proforma Construction'!E18 -> 200 | F18: ='Proforma Construction'!F18 -> 162 | G18: Garage Parking Stalls | H18: =E18*F18 -> 32400 | I18: =H18*12 -> 388800
B19: Surface Parking Stalls | E19: ='Proforma Construction'!E19 -> 0 | F19: ='Proforma Construction'!F19 -> 30 | G19: Surface Parking Stalls | H19: =E19*F19 -> 0 | I19: =H19*12 -> 0
B20: Storage Income | E20: ='Proforma Construction'!E20 -> 40 | F20: ='Proforma Construction'!F20 -> 100 | G20: Storage Income | H20: =E20*F20 -> 4000 | I20: =H20*12 -> 48000
B21: Laundry Income | E21: ='Proforma Construction'!E21 -> 20 | F21: ='Proforma Construction'!F21 -> 170 | G21: Laundry Income | H21: =E21*F21 -> 3400 | I21: =H21*12 -> 40800
B22: Misc. Income | E22: ='Proforma Construction'!E22 -> 40 | F22: ='Proforma Construction'!F22 -> 364.16667 | G22: Misc. Income | H22: =E22*F22 -> 14566.667 | I22: =H22*12 -> 174800
B24: Total Ancillary Income | I24: =SUM(I18:I23) -> 652400
B26: Gross Potential Revenue | I26: =I14+I24 -> 6530600
B28: Less: Vacancy | E28: ='Proforma Construction'!E28 -> 0.03 | F28: of Gross Potential Revenue | I28: ='Proforma Construction'!I28 -> -197666
B29: ='Proforma Construction'!B29 -> 2025 CMHC Vacancy Toronto North York ON | E29: ='Proforma Construction'!E29 -> 0.032
B30: ='Proforma Construction'!B30 -> CMHC 4 Year Average Vacancy, Toronto North York ON | E30: ='Proforma Construction'!E30 -> 0.01625
B31: ='Proforma Construction'!B31 -> Appraisal | E31: ='Proforma Construction'!E31 -> 0.03
B32: Effective Gross Revenue | I32: =I26+I28 -> 6332934
B34: Operating Expenses
B35: Less: | E35: Basis | F35: % of EGI | G35: PUPA
B36: Property Taxes | E36: ='Proforma Construction'!E36 -> Appraisal | F36: =IFERROR(I36/I32,"-") -> 0.091091586 | G36: =IFERROR(I36/C14,"-") -> 3393.3941 | I36: ='Proforma Construction'!I36 -> 576877
B37: Insurance | E37: ='Proforma Construction'!E37 -> Appraisal | F37: =IFERROR(I37/I32,"-") -> 0.012079709 | G37: =IFERROR(I37/C14,"-") -> 450 | I37: ='Proforma Construction'!I37 -> 76500
B38: Utilities | E38: ='Proforma Construction'!E38 -> Common Area | F38: =IFERROR(I38/I32,"-") -> 0.030333492 | G38: =IFERROR(I38/C14,"-") -> 1130 | I38: ='Proforma Construction'!I38 -> 192100
B39: Management Fee | E39: CMHC Bench | F39: ='Input CMHC MLI Select'!D78 -> 0.0425 | G39: =IFERROR(I39/+C56,"-") -> 1583.2335 | I39: =F39*I32 -> 269149.7
B40: Maintenance | E40: CMHC Bench | F40: =IFERROR(I40/I32,"-") -> 0.022280352 | G40: ='Input CMHC MLI Select'!E79 -> 830 | I40: =G40*C14 -> 141100
B41: Wages & Salaries | E41: CMHC Bench | F41: =IFERROR(I41/I32,"-") -> 0.014898308 | G41: ='Input CMHC MLI Select'!E80 -> 555 | I41: =G41*C14 -> 94350
B42: General & Admin | E42: CMHC Bench | F42: ='Input CMHC MLI Select'!D81 -> 0.01 | G42: =IFERROR(I42/C56,"-") -> 372.52553 | I42: =F42*I32 -> 63329.34
B43: Replacement Reserve | E43: CMHC Bench | F43: =IFERROR(I43/+I32,"-") -> 0.0080531394 | G43: ='Proforma Construction'!G43 -> 300 | I43: ='Proforma Construction'!I43 -> 51000
B44: Replacement Reserve(Garden suite heat pump) | E44: CMHC Bench | F44: =IFERROR(I44/I32,"-") -> 0 | G44: ='Proforma Construction'!G44 -> 0 | I44: ='Proforma Construction'!I44 -> 0
B45: Total Operating Expenses | F45: =SUM(F36:F44) -> 0.23123659 | G45: 6863 | I45: =SUM(I36:I44) -> 1464406
B47: Net Operating Income | I47: =I32-I45 -> 4868528
B48: Residential Mortgage
C49: Term | D49: Loan to Value | E49: Loan Amount | F49: Test Rate | G49: Amortization | H49: DSC | I49: Payments
B50: First Mortgage | D50: =E50/C61 -> 0.75998331 | E50: ='Proforma Construction'!E50 -> 92500000 | F50: ='Proforma Construction'!F50 -> 0.037 | G50: ='Proforma Construction'!G50 -> 40 | H50: =I47/I50 -> 1.1026864 | I50: =IF(G50="IO",F50*E50,PMT((F50/2+1)^(1/6)-1,G50*12,-(E50))*12) -> 4415151.7
B51: Cash Flow After Debt Service | I51: =I47-I50 -> 453376.25
B52: Underwriting & Analysis
B53: Residential Mortgage | F53: Loan Analysis
B54: Net Leasable Square Footage | C54: =F14 -> 128826 | F54: Construction Loan Amount | I54: =C71 -> 92500000
B55: Average Unit Size | C55: =IFERROR(C54/C14,"-") -> 757.8 | F55: Estimated Value | I55: =C61 -> 1.217132e+08
B56: Number of Units | C56: =C14 -> 170 | F56: Loan to Value | I56: =D50 -> 0.75998331
B57: Average Monthly Rent | C57: =H14 -> 489850 | F57: Loan to Cost | I57: =C50 -> 0
B58: Net Operating Income | C58: =I47 -> 4868528 | F58: Loan per Net SF | I58: =IFERROR(I54/C54,"-") -> 718.02276
B59: Operating Costs per Unit | C59: =IFERROR(C58/C56,"-") -> 28638.4 | F59: Loan per Suite | I59: =IFERROR(I54/C56,"-") -> 544117.65
B60: Capitalization Rate | C60: ='Proforma Construction'!C60 -> 0.04 | F60: CMHC Fees
B61: Estimated Residential Value | C61: =C58/C60 -> 1.217132e+08 | F61: Net Loan Amount | I61: =I54 -> 92500000
B62: Value per Residential Unit | C62: =IFERROR(C61/C56,"-") -> 715959.99 | F62: Residential Application Fee | I62: =MIN(IF(C56<=100,'Input CMHC MLI Select'!C74*C56,100*'Input CMHC MLI Select'!C74+(C56-100)*100),IF('Input CMHC MLI Select'!C63="NEW CONSTRUCTION",55000,IF('Input CMHC MLI Select'!C63="PURCHASE - REFINANCE",50000,""))) -> 55000
F63: Total LTV Premium | I63: =I61*'Input CMHC MLI Select'!C73 -> 4786875
F64: Total CMHC Fees | I64: =SUM(I62:I63) -> 4841875
F65: Gross CMHC Loan | I65: =I61+I64 -> 97341875
B69: Capital Stack
B70: Sources | C70: Amount | D70: % | E70: Uses | G70: Amount | H70: Per Unit | I70: %
B71: Net Loan Amount | C71: =E50 -> 92500000 | D71: =C71/$C$75 -> 0.95025907 | E71: Exiting Debt | G71: 0 | H71: =IFERROR(G71/$C$56,"-") -> 0 | I71: =G71/$G$75 -> 0
B72: Application Fee | C72: =I62 -> 55000 | D72: =C72/$C$75 -> 0.00056501891 | E72: Application Fee | G72: =I62 -> 55000 | H72: =IFERROR(G72/$C$56,"-") -> 323.52941 | I72: =G72/$G$75 -> 0.00056501891
B73: Insurance Premium | C73: =I63 -> 4786875 | D73: =C73/$C$75 -> 0.049175907 | E73: Insurance Premium | G73: =I63 -> 4786875 | H73: =IFERROR(G73/$C$56,"-") -> 28158.088 | I73: =G73/$G$75 -> 0.049175907
E74: Equity Takeout | G74: =G75-SUM(G71:G73) -> 92500000 | H74: =IFERROR(G74/$C$56,"-") -> 544117.65 | I74: =G74/$G$75 -> 0.95025907
B75: Total Source | C75: =SUM(C71:C74) -> 97341875 | D75: =SUM(D71:D74) -> 1 | E75: Total Uses | G75: =C75 -> 97341875 | H75: =IFERROR(G75/$C$56,"-") -> 572599.26 | I75: =G75/$G$75 -> 1

Sheet Budget
C4: ='Proforma Construction'!B3 -> 2240 Birchmount Rd Scarborough
C6: Construction Budget
C8: Line Item | G8: Total | H8: Per Unit | I8: % of Total | J8: PSF
C10: Land Purchase Price | G10: 10407367 | I10: =IFERROR(G10/$G$71,"0%") -> 0.10883883 | J10: =IFERROR(G10/$D$85,"0") -> 80.786231
C11: Land Transfer Tax | G11: 0 | I11: =IFERROR(G11/$G$71,"0%") -> 0 | J11: =IFERROR(G11/$D$85,"0") -> 0
C12: Land Closing Cost | G12: 0 | I12: =IFERROR(G12/$G$71,"0%") -> 0 | J12: =IFERROR(G12/$D$85,"0") -> 0
C13: Land Carrying Cost | G13: 495589 | I13: =IFERROR(G13/$G$71,"0%") -> 0.0051828024 | J13: =IFERROR(G13/$D$85,"0") -> 3.8469641
C14: Total LAND COSTS | G14: =SUM(G10:G13) -> 10902956 | H14: =G14/$D$77 -> 64135.035 | I14: =IFERROR(G14/$G$71,"0%") -> 0.11402163 | J14: =IFERROR(G14/$D$85,"0") -> 84.633195
C15: Grading Plan | G15: 64395800 | I15: =IFERROR(G15/$G$71,"0%") -> 0.67344252 | J15: =IFERROR(G15/$D$85,"0") -> 499.86649
C16: EPCOR | I16: =IFERROR(G16/$G$71,"0%") -> 0 | J16: =IFERROR(G16/$D$85,"0") -> 0
C17: Basement Digging | I17: =IFERROR(G17/$G$71,"0%") -> 0 | J17: =IFERROR(G17/$D$85,"0") -> 0
C18: Manhole | I18: =IFERROR(G18/$G$71,"0%") -> 0 | J18: =IFERROR(G18/$D$85,"0") -> 0
C19: Foundation | I19: =IFERROR(G19/$G$71,"0%") -> 0 | J19: =IFERROR(G19/$D$85,"0") -> 0
C20: Weeping Tile | I20: =IFERROR(G20/$G$71,"0%") -> 0 | J20: =IFERROR(G20/$D$85,"0") -> 0
C21: Backfill | I21: =IFERROR(G21/$G$71,"0%") -> 0 | J21: =IFERROR(G21/$D$85,"0") -> 0
C22: Framing | I22: =IFERROR(G22/$G$71,"0%") -> 0 | J22: =IFERROR(G22/$D$85,"0") -> 0
C23: Basement Pour | I23: =IFERROR(G23/$G$71,"0%") -> 0 | J23: =IFERROR(G23/$D$85,"0") -> 0
C24: Stairs | I24: =IFERROR(G24/$G$71,"0%") -> 0 | J24: =IFERROR(G24/$D$85,"0") -> 0
C25: Windows & Doors | I25: =IFERROR(G25/$G$71,"0%") -> 0 | J25: =IFERROR(G25/$D$85,"0") -> 0
C26: Roofing | I26: =IFERROR(G26/$G$71,"0%") -> 0 | J26: =IFERROR(G26/$D$85,"0") -> 0
C27: Plumbing | I27: =IFERROR(G27/$G$71,"0%") -> 0 | J27: =IFERROR(G27/$D$85,"0") -> 0
... C47: Security System/Intercom/Speaker System | I47: =IFERROR(G47/$G$71,"0%") -> 0 | J47: =IFERROR(G47/$D$85,"0") -> 0
C48: Contingency | E48: =IFERROR(G48/SUM(G15:G47),"") -> 0.02 | F48: of hard costs | G48: 1287916 | I48: =IFERROR(G48/$G$71,"0%") -> 0.01346885 | J48: =IFERROR(G48/$D$85,"0") -> 9.9973297
C49: TOTAL HARD COSTS | G49: =SUM(G15:G48) -> 65683716 | H49: =G49/$D$77 -> 386374.8 | I49: =IFERROR(G49/$G$71,"0%") -> 0.68691137 | J49: =IFERROR(G49/$D$85,"0") -> 509.86382
C50: Professional Fees | I50: =IFERROR(G50/$G$71,"0%") -> 0 | J50: =IFERROR(G50/$D$85,"0") -> 0
C51: Engineer | G51: 1931874 | I51: =IFERROR(G51/$G$71,"0%") -> 0.020203276 | J51: =IFERROR(G51/$D$85,"0") -> 14.995995
C52: Architect | I52: =IFERROR(G52/$G$71,"0%") -> 0 | J52: =IFERROR(G52/$D$85,"0") -> 0
C53: Environmental Assessment | I53: =IFERROR(G53/$G$71,"0%") -> 0 | J53: =IFERROR(G53/$D$85,"0") -> 0
C54: Lawyer | I54: =IFERROR(G54/$G$71,"0%") -> 0 | J54: =IFERROR(G54/$D$85,"0") -> 0
C55: Soil Reports | I55: =IFERROR(G55/$G$71,"0%") -> 0 | J55: =IFERROR(G55/$D$85,"0") -> 0
C56: Appraiser | I56: =IFERROR(G56/$G$71,"0%") -> 0 | J56: =IFERROR(G56/$D$85,"0") -> 0
C57: Project Monitor - QS | I57: =IFERROR(G57/$G$71,"0%") -> 0 | J57: =IFERROR(G57/$D$85,"0") -> 0
C58: Permit application | G58: 7192106 | I58: =IFERROR(G58/$G$71,"0%") -> 0.075214067 | J58: =IFERROR(G58/$D$85,"0") -> 55.828063
C59: Insurance | I59: =IFERROR(G59/$G$71,"0%") -> 0 | J59: =IFERROR(G59/$D$85,"0") -> 0
C60: New home Warranty | I60: =IFERROR(G60/$G$71,"0%") -> 0 | J60: =IFERROR(G60/$D$85,"0") -> 0
C61: Property Taxes | I61: =IFERROR(G61/$G$71,"0%") -> 0 | J61: =IFERROR(G61/$D$85,"0") -> 0
C62: Development Management Fee | G62: 1692805 | I62: =IFERROR(G62/$G$71,"0%") -> 0.017703125 | J62: =IFERROR(G62/$D$85,"0") -> 13.140243
C63: TOTAL SOFT COSTS | G63: =SUM(G50:G62) -> 10816785 | H63: =G63/$D$77 -> 63628.147 | I63: =IFERROR(G63/$G$71,"0%") -> 0.11312047 | J63: =IFERROR(G63/$D$85,"0") -> 83.964301
C65: Total Contingency | E65: =IFERROR(G65/SUM(G49,G50:G62),"") -> 0.024241849 | F65: of hard and soft costs | G65: =G49*2%+G63*5% -> 1854513.6 | I65: =IFERROR(G65/$G$71,"0%") -> 0.019394251 | J65: =IFERROR(G65/$D$85,"0") -> 14.395491
C66: Interest Reserve | G66: =J93 -> 3300000 | I66: =IFERROR(G66/$G$71,"0%") -> 0.034510951 | J66: =IFERROR(G66/$D$85,"0") -> 25.615947
C67: Financing Fees | G67: ='Proforma Construction'!E50*1.5% -> 1387500 | I67: =IFERROR(G67/$G$71,"0%") -> 0.014510286 | J67: =IFERROR(G67/$D$85,"0") -> 10.770341
C68: GST | G68: 0 | I68: =IFERROR(G68/$G$71,"0%") -> 0 | J68: =IFERROR(G68/$D$85,"0") -> 0
C69: Marketing | G69: 1676350 | I69: =IFERROR(G69/$G$71,"0%") -> 0.01753104 | J69: =IFERROR(G69/$D$85,"0") -> 13.012513
D70: 275000
C71: TOTAL COSTS | G71: =SUM(G14,G49,G63,G65,G66,G67,G69,G68) -> 95621821 | H71: =G71/$D$77 -> 562481.3 | I71: =IFERROR(G71/$G$71,"0%") -> 1 | J71: =IFERROR(G71/$D$85,"0") -> 742.25561
C73: Underwriting & Analysis
C75: PROJECT DETAILS | F75: BUDGET SUMMARY:
H76: Total | I76: % of Total | J76: PSF
C77: # of Units | D77: ='Proforma Construction'!C14 -> 170 | F77: Land | H77: =G14 -> 10902956 | I77: =H77/$G$71 -> 0.11402163 | J77: =H77/$D$85 -> 84.633195
C78: ='Proforma Construction'!B6 -> Bachelor | D78: ='Proforma Construction'!F6*'Proforma Construction'!C6 -> 0 | F78: Hard Costs | H78: =G49 -> 65683716 | I78: =H78/$G$71 -> 0.68691137 | J78: =H78/$D$85 -> 509.86382
C79: ='Proforma Construction'!B7 -> 1 Bedroom | D79: ='Proforma Construction'!F7*'Proforma Construction'!C7 -> 52416 | F79: Soft Costs | H79: =G63 -> 10816785 | I79: =H79/$G$71 -> 0.11312047 | J79: =H79/$D$85 -> 83.964301
C80: ='Proforma Construction'!B8 -> 2 Bedroom | D80: ='Proforma Construction'!F8*'Proforma Construction'!C8 -> 58140 | F80: Contingency | H80: =G65 -> 1854513.6 | I80: =H80/$G$71 -> 0.019394251 | J80: =H80/$D$85 -> 14.395491
C81: ='Proforma Construction'!B9 -> 3 Bedroom | D81: ='Proforma Construction'!F9*'Proforma Construction'!C9 -> 18270 | F81: =C66 -> Interest Reserve | H81: =G66 -> 3300000 | I81: =H81/$G$71 -> 0.034510951 | J81: =H81/$D$85 -> 25.615947
C82: ='Proforma Construction'!B11 -> Affordable Rental Units | F82: =C67 -> Financing Fees | H82: =G67 -> 1387500 | I82: =H82/$G$71 -> 0.014510286 | J82: =H82/$D$85 -> 10.770341
C83: ='Proforma Construction'!B12 -> 2 Bedrooms (Affordable) | D83: ='Proforma Construction'!F11*'Proforma Construction'!C11 -> 0 | F83: =C68 -> GST | H83: =G68 -> 0 | I83: =H83/$G$71 -> 0 | J83: =H83/$D$85 -> 0
C84: ='Proforma Construction'!B13 -> 1 Bedroom (Affordable) | D84: ='Proforma Construction'!F12*'Proforma Construction'!C12 -> 0 | F84: =C69 -> Marketing | H84: =G69 -> 1676350 | I84: =H84/$G$71 -> 0.01753104 | J84: =H84/$D$85 -> 13.012513
C85: Total Sq Ft. | D85: =SUM(D78:D84) -> 128826 | F85: Total | H85: =SUM(H77:H84) -> 95621821 | I85: =H85/$G$71 -> 1 | J85: =H85/$D$85 -> 742.25561
C86: LOAN DETAILS
C87: LOAN DETAILS: | F87: Interest Reserve
C88: Total Loan Amount | D88: ='Proforma Construction'!E50 -> 92500000
C89: Loan PSF (NSA) | D89: =IFERROR(D88/D85,"") -> 718.02276 | F89: Loan Amount | H89: PRIME | I89: SPREAD | J89: =D88 -> 92500000
C90: Loan Per Unit | D90: =IFERROR(D88/D77,"") -> 544117.65 | F90: Interest Rate (estimated) | H90: 0.0445 | I90: 0.015 | J90: =H90+I90 -> 0.0595
C91: Loan to Cost | D91: =IFERROR(D88/G71,"") -> 0.96735242 | F91: Term (years) | J91: 1
C92: Loan to Value | D92: ='Proforma Construction'!D50 -> 0.75998331 | F92: Utilization | J92: 0.6
F93: Estimated Interest Reserve (rounded) | J93: =ROUND(J89*J90*J91*J92,-4) -> 3300000

Sheet Corporate Guarantor PNW 1
A12: PERSONAL NETWORTH
A15: General Information
A16: Full Name with Initial | D16: Home Address | I16: Date of Birth | K16: SIN | M16: Phone Number | O16: Marital Status
A18: Employer | D18: Address | J18: Position | L18: Annual Income | N18: Years Employed
A20: Spouse Name with Initial | D20: Spouse Date of Birth | F20: Spouse SIN | H20: Spouse Phone Number | K20: Number of Dependants
A22: Spouse Employer | D22: Address | J22: Position | L22: Annual Income | N22: Years Employed
A24: Principal Financial Institution | D24: Address | J24: Account Manager | M24: Phone Number
D25: x
A26: Principal Solicitor | D26: Address | J26: Solicitor | M26: Phone Number
A29: Have you ever had an asset repossessed? | E29: NO | F29: (If YES, please provide additional detailed explanation in a separate page)
A30: Are you involved in any claims or lawsuits? | E30: NO | F30: (If YES, please provide additional detailed explanationin a separate page)
A31: Have you ever declared bankruptcy? | E31: NO | F31: (If YES, please provide additional detailed explanation in a separate page)
A32: Do you owe any back taxes? | E32: NO | F32: (If YES, please provide additional detailed explanationin a separate page)
A33: Section A: Cash / Bank Accounts | H33: Section B: Marketable Securities and Other Assets
A34: Institution | D34: Name on Account | F34: Amount | H34: Insitution | K34: Name on Account | N34: Type | O34: Market Value
A39: Total (Automatically Calculated) | F39: =SUM(F35:G38) -> 0 | H39: Total (Automatically Calculated) | O39: =SUM(O35:P38) -> 0
A40: Section C: Account and Loan Receivables | H40: Section D: Automobiles
A41: Name of Debtor | D41: Payment Amount | E41: Maturity | F41: Total Amount | H41: Make | J41: Model | L41: Year | M41: Loan Outstanding | O41: Market Value
M42: 0
M43: 0
M44: 0
O45: =L45-M45 -> 0
A46: Total (Automatically Calculated) | F46: =SUM(F42:G45) -> 0 | H46: Total (Automatically Calculated) | L46: =SUM(L42:L45) -> 0 | M46: =SUM(M42:M45) -> 0 | N46: =SUM(N42:N45) -> 0 | O46: =SUM(O42:P45) -> 0
A47: Section E: Business Holdings | H47: Section F: Other Credit or Liabilities (Excluding mortgages)
A48: Name | D48: Value | E48: % Owned | F48: Total Amount | H48: Name of Lender | K48: Type | L48: Maturity | M48: Payment Amount | O48: Amount
A54: Total (Automatically Calculated) | F54: =SUM(F49:G53) -> 0 | H54: Total (Automatically Calculated) | O54: =SUM(O49:P53) -> 0
A55: PERSONAL NETWORTH
A58: Section G: Real Estate Holdings
A59: Property Name and Address | D59: Lender | E59: Registered Owner | F59: Type | G59: % Owned | H59: Cost | J59: Market Value | K59: Mortgage / Liability | M59: Total Equity (Automatically Calculated) | O59: Ownership Equity (Automatically Calculated) | Q59: LTV
M60: =J60-L60 -> 0 | O60: =M60*G60 -> 0 | Q60: =IF(L60>0,L60/J60,0) -> 0
M61: =J61-L61 -> 0 | O61: =M61*G61 -> 0 | Q61: =IF(L61>0,L61/J61,0) -> 0
M62: =J62-L62 -> 0 | O62: =M62*G62 -> 0 | Q62: =IF(L62>0,L62/J62,0) -> 0
M63: =J63-L63 -> 0 | O63: =M63*G62 -> 0 | Q63: =IF(L63>0,L63/J63,0) -> 0
M64: =J64-L64 -> 0 | O64: =M64*G64 -> 0 | Q64: =IF(L64>0,L64/J64,0) -> 0
M65: =J65-L65 -> 0 | O65: =M65*G65 -> 0 | Q65: =IF(L65>0,L65/J65,0) -> 0
M66: =J66-L66 -> 0 | O66: =M66*G66 -> 0 | Q66: =IF(L66>0,L66/J66,0) -> 0
M67: =J67-L67 -> 0 | O67: =M67*G67 -> 0 | Q67: =IF(L68>0,L68/J68,0) -> 0
M68: =J68-L68 -> 0 | O68: =M68*G68 -> 0 | Q68: =IF(L69>0,L69/J69,0) -> 0
M69: =J69-L69 -> 0 | O69: =M69*G69 -> 0 | Q69: =IF(L70>0,L70/J70,0) -> 0
M70: =J70-L70 -> 0 | O70: =M70*G70 -> 0 | Q70: =IF(L71>0,L71/J71,0) -> 0
M71: =J71-L71 -> 0 | O71: =M71*G71 -> 0 | Q71: =IF(L72>0,L72/J72,0) -> 0
M72: =J72-L72 -> 0 | O72: =M72*G72 -> 0 | Q72: =IF(L73>0,L73/J73,0) -> 0
M73: =J73-L73 -> 0 | O73: =M73*G73 -> 0 | Q73: =IF(L74>0,L74/J74,0) -> 0
M74: =J74-L74 -> 0 | O74: =M74*G74 -> 0 | Q74: =IF(L75>0,L75/J75,0) -> 0
M75: =J75-L75 -> 0 | O75: =M75*G75 -> 0
A76: Total Assets (% Owned) | O76: =SUMPRODUCT(G60:G75,J60:J75) -> 0
A77: Total Liabilities (% Owned) | O77: =SUMPRODUCT(G60:G75,L60:L75) -> 0
A78: Total (% of Owned Portion, Automatically Calculated) | O78: =O76-O77 -> 0
A79: Section H: Life Insurance
A80: Policy Owner | D80: Institution | F80: Policy Number | I80: Beneficiary | M80: Face Value | O80: Cash Value
A85: Total (Automatically Calculated) | O85: =SUM(O81:P84) -> 0
A86: PERSONAL NETWORTH
A89: Financial Profile (All Numbers in This Section Is Automatically Calculated)
A90: Assets | F90: Total | H90: Liabilities | O90: Total
A91: Section A: Cash / Bank Accounts | F91: =F39 -> 0 | H91: Section D: Automobile Loans | O91: =SUM(M42:N45) -> 0
A92: Section B: Marketable Securities | F92: =O39 -> 0 | H92: Section F: Other Credit or Liabilities | O92: =O54 -> 0
A93: Section C: Receivables | F93: =F46 -> 0 | H93: Section G: Real Estate Liabilities | O93: =O77 -> 0
A94: Section D: Automobiles | F94: =O46 -> 0
A95: Section E: Business Holdings | F95: =F54 -> 0
A96: Section G: Real Estate Assets | F96: =O76 -> 0
A97: Section H: Life Insurance | F97: =O85 -> 0
A98: Total Assets | F98: =SUM(F91:G97) -> 0 | H98: Total Liabilities | O98: =SUM(O91:P93) -> 0
H99: Total Personal Net Worth | O99: =F98-O98 -> 0
A100: Declaration
A101: The undersigned hereby declares that all the information provided herein and on the accompanying statements is to the best of my knowledge true, complete and correct and understand it will be used by TMG The Mortgage Group Inc. and other Lenders to determine credit worthiness. The undersigned further consent(s) to TMG The Mortgage Group Inc. and other Lenders making any enquiries it deems necessary to reach a decision on this application, and consent(s) to the disclosure at any time of any credit information about me/us to any credit reporting agency or to any one with whom I/we have financial relations.
A109: Per: | H109: Date:
A111: Identification Verification
A112: Click here to attach a photocopy, scan, or picture of a piece of Government or Province of Canada issued photo identification. Identification could include, but is not limited to, driver's licences, passports, certificate of indian status cards, permanent resident cards, and firearms licences. | H112: Click here to attached a photocopy, scan, or picture of a secondary piece of identification. Indentification could include, but it not limited to birth certificates, provincial or territorial health cards, bank or debit cards, or credit cards.

Sheet PNW 1
A12: PERSONAL NETWORTH
A15: General Information
A16: Full Name with Initial | D16: Home Address | I16: Date of Birth | K16: SIN | M16: Phone Number | O16: Marital Status
A18: Employer | D18: Address | J18: Position | L18: Annual Income | N18: Years Employed
A20: Spouse Name with Initial | D20: Spouse Date of Birth | F20: Spouse SIN | H20: Spouse Phone Number | K20: Number of Dependants
A22: Spouse Employer | D22: Address | J22: Position | L22: Annual Income | N22: Years Employed
L23: 23550
A24: Principal Financial Institution | D24: Address | J24: Account Manager | M24: Phone Number
A25: BMO | D25: x
A26: Principal Solicitor | D26: Address | J26: Solicitor | M26: Phone Number
A29: Have you ever had an asset repossessed? | E29: NO | F29: (If YES, please provide additional detailed explanation in a separate page)
A30: Are you involved in any claims or lawsuits? | E30: NO | F30: (If YES, please provide additional detailed explanationin a separate page)
A31: Have you ever declared bankruptcy? | E31: NO | F31: (If YES, please provide additional detailed explanation in a separate page)
A32: Do you owe any back taxes? | E32: NO | F32: (If YES, please provide additional detailed explanationin a separate page)
A33: Section A: Cash / Bank Accounts | H33: Section B: Marketable Securities and Other Assets
A34: Institution | D34: Name on Account | F34: Amount | H34: Insitution | K34: Name on Account | N34: Type | O34: Market Value
A39: Total (Automatically Calculated) | F39: =SUM(F35:G38) -> 0 | H39: Total (Automatically Calculated) | O39: =SUM(O35:P38) -> 0
A40: Section C: Account and Loan Receivables | H40: Section D: Automobiles
A41: Name of Debtor | D41: Payment Amount | E41: Maturity | F41: Total Amount | H41: Make | J41: Model | L41: Year | M41: Loan Outstanding | O41: Market Value
M42: 0
M43: 0
M44: 0
O45: =L45-M45 -> 0
A46: Total (Automatically Calculated) | F46: =SUM(F42:G45) -> 0 | H46: Total (Automatically Calculated) | L46: =SUM(L42:L45) -> 0 | M46: =SUM(M42:M45) -> 0 | N46: =SUM(N42:N45) -> 0 | O46: =SUM(O42:P45) -> 0
A47: Section E: Business Holdings | H47: Section F: Other Credit or Liabilities (Excluding mortgages)
A48: Name | D48: Value | E48: % Owned | F48: Total Amount | H48: Name of Lender | K48: Type | L48: Maturity | M48: Payment Amount | O48: Amount
A54: Total (Automatically Calculated) | F54: =SUM(F49:G53) -> 0 | H54: Total (Automatically Calculated) | O54: =SUM(O49:P53) -> 0
A55: PERSONAL NETWORTH
A58: Section G: Real Estate Holdings
A59: Property Name and Address | D59: Lender | E59: Registered Owner | F59: Type | G59: % Owned | H59: Cost | J59: Market Value | K59: Mortgage / Liability | M59: Total Equity (Automatically Calculated) | O59: Ownership Equity (Automatically Calculated) | Q59: LTV
M60: =J60-L60 -> 0 | O60: =M60*G60 -> 0 | Q60: =IF(L60>0,L60/J60,0) -> 0
M61: =J61-L61 -> 0 | O61: =M61*G61 -> 0 | Q61: =IF(L61>0,L61/J61,0) -> 0
M62: =J62-L62 -> 0 | O62: =M62*G62 -> 0 | Q62: =IF(L62>0,L62/J62,0) -> 0
M63: =J63-L63 -> 0 | O63: =M63*G62 -> 0 | Q63: =IF(L63>0,L63/J63,0) -> 0
M64: =J64-L64 -> 0 | O64: =M64*G64 -> 0 | Q64: =IF(L64>0,L64/J64,0) -> 0
M65: =J65-L65 -> 0 | O65: =M65*G65 -> 0 | Q65: =IF(L65>0,L65/J65,0) -> 0
M66: =J66-L66 -> 0 | O66: =M66*G66 -> 0 | Q66: =IF(L66>0,L66/J66,0) -> 0
M67: =J67-L67 -> 0 | O67: =M67*G67 -> 0 | Q67: =IF(L68>0,L68/J68,0) -> 0
M68: =J68-L68 -> 0 | O68: =M68*G68 -> 0 | Q68: =IF(L69>0,L69/J69,0) -> 0
M69: =J69-L69 -> 0 | O69: =M69*G69 -> 0 | Q69: =IF(L70>0,L70/J70,0) -> 0
M70: =J70-L70 -> 0 | O70: =M70*G70 -> 0 | Q70: =IF(L71>0,L71/J71,0) -> 0
M71: =J71-L71 -> 0 | O71: =M71*G71 -> 0 | Q71: =IF(L72>0,L72/J72,0) -> 0
M72: =J72-L72 -> 0 | O72: =M72*G72 -> 0 | Q72: =IF(L73>0,L73/J73,0) -> 0
M73: =J73-L73 -> 0 | O73: =M73*G73 -> 0 | Q73: =IF(L74>0,L74/J74,0) -> 0
M74: =J74-L74 -> 0 | O74: =M74*G74 -> 0 | Q74: =IF(L75>0,L75/J75,0) -> 0
M75: =J75-L75 -> 0 | O75: =M75*G75 -> 0
A76: Total Assets (% Owned) | O76: =SUMPRODUCT(G60:G75,J60:J75) -> 0
A77: Total Liabilities (% Owned) | O77: =SUMPRODUCT(G60:G75,L60:L75) -> 0
A78: Total (% of Owned Portion, Automatically Calculated) | O78: =O76-O77 -> 0
A79: Section H: Life Insurance
A80: Policy Owner | D80: Institution | F80: Policy Number | I80: Beneficiary | M80: Face Value | O80: Cash Value
A85: Total (Automatically Calculated) | O85: =SUM(O81:P84) -> 0
A86: PERSONAL NETWORTH
A89: Financial Profile (All Numbers in This Section Is Automatically Calculated)
A90: Assets | F90: Total | H90: Liabilities | O90: Total
A91: Section A: Cash / Bank Accounts | F91: =F39 -> 0 | H91: Section D: Automobile Loans | O91: =SUM(M42:N45) -> 0
A92: Section B: Marketable Securities | F92: =O39 -> 0 | H92: Section F: Other Credit or Liabilities | O92: =O54 -> 0
A93: Section C: Receivables | F93: =F46 -> 0 | H93: Section G: Real Estate Liabilities | O93: =O77 -> 0
A94: Section D: Automobiles | F94: =O46 -> 0
A95: Section E: Business Holdings | F95: =F54 -> 0
A96: Section G: Real Estate Assets | F96: =O76 -> 0
A97: Section H: Life Insurance | F97: =O85 -> 0
A98: Total Assets | F98: =SUM(F91:G97) -> 0 | H98: Total Liabilities | O98: =SUM(O91:P93) -> 0
H99: Total Personal Net Worth | O99: =F98-O98 -> 0
A100: Declaration
A101: The undersigned hereby declares that all the information provided herein and on the accompanying statements is to the best of my knowledge true, complete and correct and understand it will be used by TMG The Mortgage Group Inc. and other Lenders to determine credit worthiness. The undersigned further consent(s) to TMG The Mortgage Group Inc. and other Lenders making any enquiries it deems necessary to reach a decision on this application, and consent(s) to the disclosure at any time of any credit information about me/us to any credit reporting agency or to any one with whom I/we have financial relations.
A109: Per: | H109: Date:
A111: Identification Verification
A112: Click here to attach a photocopy, scan, or picture of a piece of Government or Province of Canada issued photo identification. Identification could include, but is not limited to, driver's licences, passports, certificate of indian status cards, permanent resident cards, and firearms licences. | H112: Click here to attached a photocopy, scan, or picture of a secondary piece of identification. Indentification could include, but it not limited to birth certificates, provincial or territorial health cards, bank or debit cards, or credit cards.

Sheet PNW 2
A12: PERSONAL NETWORTH
A15: General Information
A16: Full Name with Initial | D16: Home Address | I16: Date of Birth | K16: SIN | M16: Phone Number | O16: Marital Status
A17: Li Yang LY | D17: 2128 36th Ave, Vancouver, BC, V6M1L2 | I17: 27206 | K17: 761-290-584 | O17: Married
A18: Employer | D18: Address | J18: Position | L18: Annual Income | N18: Years Employed
A19: self employed | D19: 2128 36th Ave, Vancouver, BC, V6M1L2 | J19: Business owner | L19: 37027 | N19: 3
A20: Spouse Name with Initial | D20: Spouse Date of Birth | F20: Spouse SIN | H20: Spouse Phone Number | K20: Number of Dependants
A21: Dongxiang Qi DQ
A22: Spouse Employer | D22: Address | J22: Position | L22: Annual Income | N22: Years Employed
L23: 23550
A24: Principal Financial Institution | D24: Address | J24: Account Manager | M24: Phone Number
A25: BMO | D25: x
A26: Principal Solicitor | D26: Address | J26: Solicitor | M26: Phone Number
A29: Have you ever had an asset repossessed? | E29: NO | F29: (If YES, please provide additional detailed explanation in a separate page)
A30: Are you involved in any claims or lawsuits? | E30: NO | F30: (If YES, please provide additional detailed explanationin a separate page)
A31: Have you ever declared bankruptcy? | E31: NO | F31: (If YES, please provide additional detailed explanation in a separate page)
A32: Do you owe any back taxes? | E32: NO | F32: (If YES, please provide additional detailed explanationin a separate page)
A33: Section A: Cash / Bank Accounts | H33: Section B: Marketable Securities and Other Assets
A34: Institution | D34: Name on Account | F34: Amount | H34: Insitution | K34: Name on Account | N34: Type | O34: Market Value
A35: BMO #8925 | F35: 251316 | N35: Stocks
N36: Stocks
N37: Stocks
N38: Stocks
A39: Total (Automatically Calculated) | F39: =SUM(F35:G38) -> 251316 | H39: Total (Automatically Calculated) | O39: =SUM(O35:P38) -> 0
A40: Section C: Account and Loan Receivables | H40: Section D: Automobiles
A41: Name of Debtor | D41: Payment Amount | E41: Maturity | F41: Total Amount | H41: Make | J41: Model | L41: Year | M41: Loan Outstanding | O41: Market Value
M42: 0
M43: 0
M44: 0
O45: =L45-M45 -> 0
A46: Total (Automatically Calculated) | F46: =SUM(F42:G45) -> 0 | H46: Total (Automatically Calculated) | L46: =SUM(L42:L45) -> 0 | M46: =SUM(M42:M45) -> 0 | N46: =SUM(N42:N45) -> 0 | O46: =SUM(O42:P45) -> 0
A47: Section E: Business Holdings | H47: Section F: Other Credit or Liabilities (Excluding mortgages)
A48: Name | D48: Value | E48: % Owned | F48: Total Amount | H48: Name of Lender | K48: Type | L48: Maturity | M48: Payment Amount | O48: Amount
A54: Total (Automatically Calculated) | F54: =SUM(F49:G53) -> 0 | H54: Total (Automatically Calculated) | O54: =SUM(O49:P53) -> 0
A55: PERSONAL NETWORTH
A58: Section G: Real Estate Holdings
A59: Property Name and Address | D59: Lender | E59: Registered Owner | F59: Type | G59: % Owned | H59: Cost | J59: Market Value | K59: Mortgage / Liability | M59: Total Equity (Automatically Calculated) | O59: Ownership Equity (Automatically Calculated) | Q59: LTV
M60: =J60-L60 -> 0 | O60: =M60*G60 -> 0 | Q60: =IF(L60>0,L60/J60,0) -> 0
M61: =J61-L61 -> 0 | O61: =M61*G61 -> 0 | Q61: =IF(L61>0,L61/J61,0) -> 0
M62: =J62-L62 -> 0 | O62: =M62*G62 -> 0 | Q62: =IF(L62>0,L62/J62,0) -> 0
M63: =J63-L63 -> 0 | O63: =M63*G62 -> 0 | Q63: =IF(L63>0,L63/J63,0) -> 0
M64: =J64-L64 -> 0 | O64: =M64*G64 -> 0 | Q64: =IF(L64>0,L64/J64,0) -> 0
M65: =J65-L65 -> 0 | O65: =M65*G65 -> 0 | Q65: =IF(L65>0,L65/J65,0) -> 0
M66: =J66-L66 -> 0 | O66: =M66*G66 -> 0 | Q66: =IF(L66>0,L66/J66,0) -> 0
M67: =J67-L67 -> 0 | O67: =M67*G67 -> 0 | Q67: =IF(L68>0,L68/J68,0) -> 0
M68: =J68-L68 -> 0 | O68: =M68*G68 -> 0 | Q68: =IF(L69>0,L69/J69,0) -> 0
M69: =J69-L69 -> 0 | O69: =M69*G69 -> 0 | Q69: =IF(L70>0,L70/J70,0) -> 0
M70: =J70-L70 -> 0 | O70: =M70*G70 -> 0 | Q70: =IF(L71>0,L71/J71,0) -> 0
M71: =J71-L71 -> 0 | O71: =M71*G71 -> 0 | Q71: =IF(L72>0,L72/J72,0) -> 0
M72: =J72-L72 -> 0 | O72: =M72*G72 -> 0 | Q72: =IF(L73>0,L73/J73,0) -> 0
M73: =J73-L73 -> 0 | O73: =M73*G73 -> 0 | Q73: =IF(L74>0,L74/J74,0) -> 0
M74: =J74-L74 -> 0 | O74: =M74*G74 -> 0 | Q74: =IF(L75>0,L75/J75,0) -> 0
M75: =J75-L75 -> 0 | O75: =M75*G75 -> 0
A76: Total Assets (% Owned) | O76: =SUMPRODUCT(G60:G75,J60:J75) -> 0
A77: Total Liabilities (% Owned) | O77: =SUMPRODUCT(G60:G75,L60:L75) -> 0
A78: Total (% of Owned Portion, Automatically Calculated) | O78: =O76-O77 -> 0
A79: Section H: Life Insurance
A80: Policy Owner | D80: Institution | F80: Policy Number | I80: Beneficiary | M80: Face Value | O80: Cash Value
A85: Total (Automatically Calculated) | O85: =SUM(O81:P84) -> 0
A86: PERSONAL NETWORTH
A89: Financial Profile (All Numbers in This Section Is Automatically Calculated)
A90: Assets | F90: Total | H90: Liabilities | O90: Total
A91: Section A: Cash / Bank Accounts | F91: =F39 -> 251316 | H91: Section D: Automobile Loans | O91: =SUM(M42:N45) -> 0
A92: Section B: Marketable Securities | F92: =O39 -> 0 | H92: Section F: Other Credit or Liabilities | O92: =O54 -> 0
A93: Section C: Receivables | F93: =F46 -> 0 | H93: Section G: Real Estate Liabilities | O93: =O77 -> 0
A94: Section D: Automobiles | F94: =O46 -> 0
A95: Section E: Business Holdings | F95: =F54 -> 0
A96: Section G: Real Estate Assets | F96: =O76 -> 0
A97: Section H: Life Insurance | F97: =O85 -> 0
A98: Total Assets | F98: =SUM(F91:G97) -> 251316 | H98: Total Liabilities | O98: =SUM(O91:P93) -> 0
H99: Total Personal Net Worth | O99: =F98-O98 -> 251316
A100: Declaration
A101: The undersigned hereby declares that all the information provided herein and on the accompanying statements is to the best of my knowledge true, complete and correct and understand it will be used by TMG The Mortgage Group Inc. and other Lenders to determine credit worthiness. The undersigned further consent(s) to TMG The Mortgage Group Inc. and other Lenders making any enquiries it deems necessary to reach a decision on this application, and consent(s) to the disclosure at any time of any credit information about me/us to any credit reporting agency or to any one with whom I/we have financial relations.
A109: Per: | H109: Date:
A111: Identification Verification
A112: Click here to attach a photocopy, scan, or picture of a piece of Government or Province of Canada issued photo identification. Identification could include, but is not limited to, driver's licences, passports, certificate of indian status cards, permanent resident cards, and firearms licences. | H112: Click here to attached a photocopy, scan, or picture of a secondary piece of identification. Indentification could include, but it not limited to birth certificates, provincial or territorial health cards, bank or debit cards, or credit cards.

Sheet Executive Summary
B2: Property Highlight | E2: Financial Highlight
B3: Address | C3: ='Proforma Construction'!B3 -> 2240 Birchmount Rd Scarborough | E3: NOI | F3: ='Proforma Construction'!I47 -> 4868528
B4: Number of Storeys | C4: 3 Storeys | E4: Project Cost | F4: ='Proforma Construction'!G79 -> 95621821
B5: Number of Units | C5: ='Proforma Construction'!C56 -> 170 | E5: Cost per Unit | F5: ='Proforma Construction'!H79 -> 562481.3
B6: Number of Parking | C6: ='Proforma Construction'!F18+'Proforma Construction'!F19 -> 192 | E6: CMHC Value | F6: ='Proforma Construction'!C61 -> 1.217132e+08
B7: Construction | C7: Wood Frame | E7: Value/Unit | F7: ='Proforma Construction'!C62 -> 715959.99
B8: Net Rentable Area(SF) | C8: ='Proforma Construction'!F14 -> 128826 | E8: Net Loan Amount | F8: ='Proforma Construction'!E50 -> 92500000
B9: Average Unit Size(SF) | C9: ='Proforma Construction'!F15 -> 757.8 | E9: Loan/Unit | F9: ='Proforma Construction'!I59 -> 544117.65
B10: Rent/SF | C10: ='Proforma Construction'!G15 -> 3.8024157 | E10: LTC | F10: ='Proforma Construction'!C50 -> 0.96735242
E11: DSCR | F11: ='Proforma Construction'!H50 -> 1.1026864
E12: LTV | F12: ='Proforma Construction'!D50 -> 0.75998331

Sheet Mortgage Details
B2: Type of Loan | E2: Loan Details
B3: CMHC MLI Select – Construction Financing | E3: Loan Amount | F3: ='Proforma Construction'!E50 -> 92500000
B4: Borrower | E4: Loan to Cost | F4: ='Proforma Construction'!C50 -> 0.96735242
B5: =Sponsorship!B4 -> 0 | E5: Loan to Value | F5: ='Proforma Construction'!D50 -> 0.75998331
B6: Guarantors | E6: Test Rate | F6: ='Proforma Construction'!F50 -> 0.037
B7: 100% Full Joint and Several | E7: Amortization | F7: ='Proforma Construction'!G50 -> 40
B8: personal guarantees as outlined below: | E8: DSCR | F8: ='Proforma Construction'!H50 -> 1.1026864
B9: =Sponsorship!B11 -> 0 | E9: Payment | F9: ='Proforma Construction'!I50 -> 4415151.7
B10: =Sponsorship!B12 -> 0 | E10: Application Fee | F10: ='Proforma Construction'!I62 -> 55000
E11: Premium | F11: ='Proforma Construction'!I63 -> 4786875
B12: We are requesting the guarantee to reduce to 40% limited recourse once the property has reached twelve months of stabilization. | E12: Gross CMHC Loan | F12: ='Proforma Construction'!I65 -> 97341875
B14: Sources | E14: Uses
B15: Subject Mortgage (Net) | C15: ='Proforma Construction'!C71 -> 92500000 | D15: ='Proforma Construction'!D71 -> 0.96735242 | E15: ='Proforma Construction'!E71 -> Land | F15: ='Proforma Construction'!G71 -> 10902956 | G15: ='Proforma Construction'!I71 -> 0.11402163
B16: Borrower’s Equity | C16: ='Proforma Construction'!C72 -> 3121820.6 | D16: ='Proforma Construction'!D72 -> 0.032647575 | E16: ='Proforma Construction'!E72 -> Hard Costs | F16: ='Proforma Construction'!G72 -> 65683716 | G16: ='Proforma Construction'!I72 -> 0.68691137
E17: ='Proforma Construction'!E73 -> Soft Costs | F17: ='Proforma Construction'!G73 -> 10816785 | G17: ='Proforma Construction'!I73 -> 0.11312047
E18: ='Proforma Construction'!E74 -> Contingency | F18: ='Proforma Construction'!G74 -> 1854513.6 | G18: ='Proforma Construction'!I74 -> 0.019394251
E19: ='Proforma Construction'!E75 -> Interest Reserve | F19: ='Proforma Construction'!G75 -> 3300000 | G19: ='Proforma Construction'!I75 -> 0.034510951
E20: ='Proforma Construction'!E76 -> Financing Fees | F20: ='Proforma Construction'!G76 -> 1387500 | G20: ='Proforma Construction'!I76 -> 0.014510286
E21: ='Proforma Construction'!E77 -> GST | F21: ='Proforma Construction'!G77 -> 0 | G21: ='Proforma Construction'!I78 -> 0.01753104
B22: Total | C22: ='Proforma Construction'!C79 -> 95621821 | D22: =SUM(D15:D20) -> 1 | E22: Total | F22: =SUM(F15:F20) -> 93945471 | G22: =SUM(G15:G21) -> 1
B24: Loan Summary Commentary
B26: New CMHC-insured MLI Selec loan application that will be used for the construction of the subject building.
B27: Under the MLI Select Program, the project qualifies for a total of 100 points as follows:
B28: 1. the Subject development will operate at 42% better than the NECB – 50 points

Sheet Sponsorship
A1: SPONSORSHIP
A2: Corporate Borrower(s)
B3: Name | C3: Financials Date | D3: Assets | E3: Liabilities | F3: Equity
A4: 1 | C4: N/A | D4: 985000 | E4: 735000 | F4: =D4-E4 -> 250000
A5: Corporate Guarantor(s)
B6: Name | C6: Financials Date | D6: Assets | E6: Liabilities | F6: Equity
A7: 1 | C7: N/A | D7: =B48 -> 0 | E7: =D48 -> 0 | F7: =D7-E7 -> 0
A8: Individual Guarantor(s)
A9: Recourse Type | B9: Joint and Several | C9: For | D9: 1
B10: Name | C10: Net Worth | D10: Beacon | E10: Experience | F10: Recourse %
A11: 1 | C11: ='PNW 1'!O99 -> 0 | D11: 782 | E11: 10 years | F11: 1
A12: 2 | C12: ='PNW 2'!O99 -> 251316 | D12: 769 | E12: 10 years | F12: 1
A38: Corporate Guarantor 1 | B38: {='Corporate Guarantor PNW 1'!A17:C17} -> 0 | C38: 0 | D38: 0
A39: Credit Score | B39: N/A | C39: PNW Date | D39: 45748
A40: Assets | B40: Total | C40: Liabilities | D40: Total
A41: Cash / Bank Accounts | B41: ='Corporate Guarantor PNW 1'!F91 -> 0 | C41: Automobile Loans | D41: ='Corporate Guarantor PNW 1'!O91 -> 0
A42: Marketable Securities | B42: ='Corporate Guarantor PNW 1'!F92 -> 0 | C42: Other Credit or Liabilities | D42: ='Corporate Guarantor PNW 1'!O92 -> 0
A43: Receivables | B43: ='Corporate Guarantor PNW 1'!F93 -> 0 | C43: Real Estate Liabilities | D43: ='Corporate Guarantor PNW 1'!O93 -> 0
A44: Automobiles | B44: ='Corporate Guarantor PNW 1'!F94 -> 0
A45: Business Holdings | B45: ='Corporate Guarantor PNW 1'!F95 -> 0
A46: Real Estate Assets | B46: ='Corporate Guarantor PNW 1'!F96 -> 0
A47: Life Insurance | B47: ='Corporate Guarantor PNW 1'!F97 -> 0
A48: Total Assets | B48: =SUM(B41:B47) -> 0 | C48: Total Liabilities | D48: =SUM(D41:D47) -> 0
C49: Total Personal Net Worth | D49: =B48-D48 -> 0
A52: Personal Guarantor 1 | B52: =B11 -> 0
A53: Credit Score | B53: =D11 -> 782 | C53: PNW Date | D53: 45748
A54: Assets | B54: Total | C54: Liabilities | D54: Total
A55: Cash / Bank Accounts | B55: ='PNW 1'!F91 -> 0 | C55: Automobile Loans | D55: ='PNW 1'!O91 -> 0
A56: Marketable Securities | B56: ='PNW 1'!F92 -> 0 | C56: Other Credit or Liabilities | D56: ='PNW 1'!O92 -> 0
A57: Receivables | B57: ='PNW 1'!F93 -> 0 | C57: Real Estate Liabilities | D57: ='PNW 1'!O93 -> 0
A58: Automobiles | B58: ='PNW 1'!F94 -> 0
A59: Business Holdings | B59: ='PNW 1'!F95 -> 0
A60: Real Estate Assets | B60: ='PNW 1'!F96 -> 0
A61: Life Insurance | B61: ='PNW 1'!F97 -> 0
A62: Total Assets | B62: =SUM(B55:B61) -> 0 | C62: Total Liabilities | D62: =SUM(D55:D61) -> 0
C63: Total Personal Net Worth | D63: =B62-D62 -> 0
A66: Personal Guarantor 2 | B66: =B12 -> 0
A67: Credit Score | B67: =D12 -> 769 | C67: PNW Date | D67: 45748
A68: Assets | B68: Total | C68: Liabilities | D68: Total
A69: Cash / Bank Accounts | B69: ='PNW 2'!F91 -> 251316 | C69: Automobile Loans | D69: ='PNW 2'!O91 -> 0
A70: Marketable Securities | B70: ='PNW 2'!F92 -> 0 | C70: Other Credit or Liabilities | D70: ='PNW 2'!O92 -> 0
A71: Receivables | B71: ='PNW 2'!F93 -> 0 | C71: Real Estate Liabilities | D71: ='PNW 2'!O93 -> 0
A72: Automobiles | B72: ='PNW 2'!F94 -> 0
A73: Business Holdings | B73: ='PNW 2'!F95 -> 0
A74: Real Estate Assets | B74: ='PNW 2'!F96 -> 0
A75: Life Insurance | B75: ='PNW 2'!F97 -> 0
A76: Total Assets | B76: =SUM(B69:B75) -> 251316 | C76: Total Liabilities | D76: =SUM(D69:D75) -> 0
C77: Total Personal Net Worth | D77: =B76-D76 -> 251316
A80: Total Networth | B80: =D77+D63+D49 -> 251316 | C80: =B80/'Proforma Construction'!E50 -> 0.0027169297
A81: Real estate equity | B81: =B74-D71+B60-D57+B46-D43 -> 0
A82: Liquid asset | B82: =B69+B56+B55+B70+B41+B42 -> 251316 | C82: =B82/'Proforma Construction'!E50 -> 0.0027169297

Sheet Proforma summary
B2: ='Proforma Construction'!B2 -> Proforma - MLI Select 50 pts (Energy efficiency)
B3: ='Proforma Construction'!B3 -> 2240 Birchmount Rd Scarborough
B4: Suite Type | C4: # of Units | E4: Avg. Rent | F4: Area (SF) | G4: Rent/SF | H4: Monthly | I4: Annual
B5: Market Rental Units
B6: ='Rent Roll'!C9 -> Bachelor | C6: ='Rent Roll'!D9 -> 0 | E6: ='Rent Roll'!H9 -> 0 | F6: ='Rent Roll'!F9 -> 0 | G6: =E6/F6 -> #DIV/0! | H6: =E6*C6 -> 0 | I6: =C6*E6*12 -> 0
B7: ='Rent Roll'!C10 -> 1 Bedroom | C7: ='Rent Roll'!D10 -> 84 | E7: ='Rent Roll'!H10 -> 2490 | F7: ='Rent Roll'!F10 -> 624 | G7: =E7/F7 -> 3.9903846 | H7: =E7*C7 -> 209160 | I7: =C7*E7*12 -> 2509920
B9: Affordable Rental Units
B12: Total | C12: =SUM(C6:C10) -> 84 | E12: =SUMPRODUCT(C6:C11,E6:E11) -> 209160 | F12: =SUMPRODUCT(C6:C11,F6:F11) -> 52416 | H12: =SUM(H6:H11) -> 209160 | I12: =SUM(I6:I11) -> 2509920
B13: AVERAGE | E13: =E12/C12 -> 2490 | F13: =F12/C12 -> 624 | G13: =E13/F13 -> 3.9903846
B15: Add: | E15: Per Stalls | H15: Monthly
B16: Parking Income | F16: 0 | G16: Garage Parking Stalls | H16: =E16*F16 -> 0 | I16: =H16*12 -> 0
F17: 0 | G17: Surface Parking Stalls
B18: Storage Income
B19: Laudry Incoem
B20: Misc. Income
B22: Total Ancillary Income | I22: =SUM(I16:I21) -> 0
B24: Gross Potential Revenue | I24: =I12+I22 -> 2509920
B26: Less: Vacancy | E26: ='Proforma Construction'!E28 -> 0.03 | F26: of Gross Potential Revenue | I26: =-E26*I24 -> -75297.6
B27: ='Proforma Construction'!B29 -> 2025 CMHC Vacancy Toronto North York ON | E27: ='Proforma Construction'!E29 -> 0.032
B28: ='Proforma Construction'!B30 -> CMHC 4 Year Average Vacancy, Toronto North York ON | E28: ='Proforma Construction'!E30 -> 0.01625
B30: Effective Gross Revenue | I30: =I24+I26 -> 2434622.4
B32: Operating Expenses
B33: Less: | E33: Basis | F33: % of EGI | G33: PUPA
B34: ='Proforma Construction'!B36 -> Property Taxes | E34: ='Proforma Construction'!E36 -> Appraisal | F34: ='Proforma Construction'!F36 -> 0.091091586 | G34: ='Proforma Construction'!G36 -> 3393.3941 | I34: ='Proforma Construction'!I36 -> 576877
B35: ='Proforma Construction'!B37 -> Insurance | E35: ='Proforma Construction'!E37 -> Appraisal | F35: ='Proforma Construction'!F37 -> 0.012079709 | G35: ='Proforma Construction'!G37 -> 450 | I35: ='Proforma Construction'!I37 -> 76500
B36: ='Proforma Construction'!B38 -> Utilities | E36: ='Proforma Construction'!E38 -> Common Area | F36: ='Proforma Construction'!F38 -> 0.030333492 | G36: ='Proforma Construction'!G38 -> 1130 | I36: ='Proforma Construction'!I38 -> 192100
B37: ='Proforma Construction'!B39 -> Management Fee | E37: ='Proforma Construction'!E39 -> CMHC Bench | F37: ='Proforma Construction'!F39 -> 0.0425 | G37: ='Proforma Construction'!G39 -> 1583.2335 | I37: ='Proforma Construction'!I39 -> 269149.7
B38: ='Proforma Construction'!B40 -> Maintenance | E38: ='Proforma Construction'!E40 -> CMHC Bench | F38: ='Proforma Construction'!F40 -> 0.022280352 | G38: ='Proforma Construction'!G40 -> 830 | I38: ='Proforma Construction'!I40 -> 141100
B39: ='Proforma Construction'!B41 -> Wages & Salaries | E39: ='Proforma Construction'!E41 -> CMHC Bench | F39: ='Proforma Construction'!F41 -> 0.014898308 | G39: ='Proforma Construction'!G41 -> 555 | I39: ='Proforma Construction'!I41 -> 94350
B40: ='Proforma Construction'!B42 -> General & Admin | E40: ='Proforma Construction'!E42 -> CMHC Bench | F40: ='Proforma Construction'!F42 -> 0.01 | G40: ='Proforma Construction'!G42 -> 372.52553 | I40: ='Proforma Construction'!I42 -> 63329.34
B41: ='Proforma Construction'!B43 -> Replacement Reserve | E41: ='Proforma Construction'!E43 -> CMHC Bench | F41: ='Proforma Construction'!F43 -> 0.0080531394 | G41: ='Proforma Construction'!G43 -> 300 | I41: ='Proforma Construction'!I43 -> 51000
B42: ='Proforma Construction'!B44 -> Replacement Reserve(Garden suite heat pump) | E42: ='Proforma Construction'!E44 -> CMHC Bench | F42: ='Proforma Construction'!F44 -> 0 | G42: ='Proforma Construction'!G44 -> 0 | I42: ='Proforma Construction'!I44 -> 0
B43: Total Operating Expenses | F43: =SUM(F34:F42) -> 0.23123659 | G43: 6863 | I43: =SUM(I34:I42) -> 1464406
B45: Net Operating Income | I45: =I30-I43 -> 970216.36
B46: Residential Mortgage
C47: Loan to Cost | D47: Loan to Value | E47: Loan Amount | F47: Test Rate | G47: Amortization | H47: DSC | I47: Payments
B48: First Mortgage | C48: =E48/G77 -> 0.96735242 | D48: =E48/C59 -> 3.8135823 | E48: ='Proforma Construction'!E50 -> 92500000 | F48: ='Proforma Construction'!F50 -> 0.037 | G48: ='Proforma Construction'!G50 -> 40 | H48: =I45/I48 -> 0.219747 | I48: =IF(G48="IO",F48*E48,PMT((F48/2+1)^(1/6)-1,G48*12,-(E48))*12) -> 4415151.7
B49: Cash Flow After Debt Service | I49: =I45-I48 -> -3444935.3
B50: Underwriting & Analysis
B51: Residential Mortgage | F51: Loan Analysis
B52: Net Leasable Square Footage | C52: =F12 -> 52416 | F52: Construction Loan Amount | I52: =E48 -> 92500000
B53: Average Unit Size | C53: =C52/C12 -> 624 | F53: Estimated Value | I53: =C59 -> 24255409
B54: Number of Units | C54: =C12 -> 84 | F54: Loan to Value | I54: =D48 -> 3.8135823
B55: Average Monthly Rent | C55: =H12 -> 209160 | F55: Loan to Cost | I55: =C48 -> 0.96735242
B56: Net Operating Income | C56: =I45 -> 970216.36 | F56: Loan per Net SF | I56: =I52/C52 -> 1764.7283
B57: Operating Costs per Unit | C57: =C56/C54 -> 11550.195 | F57: Loan per Suite | I57: =I52/C54 -> 1101190.5
B58: Capitalization Rate | C58: ='Proforma Construction'!C60 -> 0.04 | F58: CMHC Fees
B59: Estimated Residential Value | C59: =C56/C58 -> 24255409 | F59: Net Loan Amount | I59: =I52 -> 92500000
B60: Value per Residential Unit | C60: =C59/C54 -> 288754.87 | F60: Residential Application Fee | I60: ='Proforma Construction'!I62 -> 55000
F61: Total LTV Premium | I61: ='Proforma Construction'!I63 -> 4786875
F62: Total CMHC Fees | I62: =SUM(I60:I61) -> 4841875
F63: Gross CMHC Loan | I63: =I59+I62 -> 97341875
B67: ='Proforma Construction'!B69 -> Capital Stack
B68: ='Proforma Construction'!B70 -> Sources | C68: ='Proforma Construction'!C70 -> Amount | D68: ='Proforma Construction'!D70 -> % | E68: ='Proforma Construction'!E70 -> Uses | G68: ='Proforma Construction'!G70 -> Amount | H68: ='Proforma Construction'!H70 -> Per Unit | I68: ='Proforma Construction'!I70 -> %
B69: ='Proforma Construction'!B71 -> First Mortgage | C69: ='Proforma Construction'!C71 -> 92500000 | D69: ='Proforma Construction'!D71 -> 0.96735242 | E69: ='Proforma Construction'!E71 -> Land | G69: ='Proforma Construction'!G71 -> 10902956 | H69: ='Proforma Construction'!H71 -> 64135.035 | I69: ='Proforma Construction'!I71 -> 0.11402163
B70: ='Proforma Construction'!B72 -> Borrower's Equity | C70: ='Proforma Construction'!C72 -> 3121820.6 | D70: ='Proforma Construction'!D72 -> 0.032647575 | E70: ='Proforma Construction'!E72 -> Hard Costs | G70: ='Proforma Construction'!G72 -> 65683716 | H70: ='Proforma Construction'!H72 -> 386374.8 | I70: ='Proforma Construction'!I72 -> 0.68691137
E71: ='Proforma Construction'!E73 -> Soft Costs | G71: ='Proforma Construction'!G73 -> 10816785 | H71: ='Proforma Construction'!H73 -> 63628.147 | I71: ='Proforma Construction'!I73 -> 0.11312047
E72: ='Proforma Construction'!E74 -> Contingency | G72: ='Proforma Construction'!G74 -> 1854513.6 | H72: ='Proforma Construction'!H74 -> 10908.903 | I72: ='Proforma Construction'!I74 -> 0.019394251
E73: ='Proforma Construction'!E75 -> Interest Reserve | G73: ='Proforma Construction'!G75 -> 3300000 | H73: ='Proforma Construction'!H75 -> 19411.765 | I73: ='Proforma Construction'!I75 -> 0.034510951
E74: ='Proforma Construction'!E76 -> Financing Fees | G74: ='Proforma Construction'!G76 -> 1387500 | H74: ='Proforma Construction'!H76 -> 8161.7647 | I74: ='Proforma Construction'!I76 -> 0.014510286
E75: ='Proforma Construction'!E77 -> GST
E76: ='Proforma Construction'!E78 -> Marketing
B77: ='Proforma Construction'!B79 -> Total Source | C77: ='Proforma Construction'!C79 -> 95621821 | D77: ='Proforma Construction'!D79 -> 1 | E77: ='Proforma Construction'!E79 -> Total Uses | G77: ='Proforma Construction'!G79 -> 95621821 | H77: ='Proforma Construction'!H79 -> 562481.3 | I77: ='Proforma Construction'!I79 -> 1

Sheet Project economics
B1: CMHC Vacancy Rate | I1: SALES COMPARABLES
B2: Vacancy Rate | C2: # Unit | D2: %Mix | E2: CMHC Market | F2: Subject | G2: Variance | I2: Index | J2: Address | K2: Sale Date | L2: Value | M2: Units | N2: Price Per Unit | O2: Cap Rate
B3: 3-Bedroom + | C3: 4 | D3: =C3/C5 -> 0.8 | E3: 0.026 | F3: 0.026 | G3: 0 | I3: Subject | J3: =C16 -> 119 Belgravia | L3: 3551457.8 | M3: 5 | N3: =L3/M3 -> 710291.56 | O3: 0.05
B4: 1-Bedroom | C4: 1 | D4: =C4/C5 -> 0.2 | E4: 0.025 | F4: 0.026 | G4: =F4/E4-1 -> 0.04 | I4: 1 | J4: 332 High Park Ave, Toronto | K4: Sep 2023 | L4: 7180000 | M4: 10 | N4: =L4/M4 -> 718000 | O4: 0.033
B5: Total | C5: =SUM(C3:C4) -> 5 | D5: =SUM(D3) -> 0.8 | E5: =E3 -> 0.026 | F5: 0.026 | G5: =(G3*C3+G4*C4)/C5 -> 0.008 | I5: 2 | J5: 353 Oakwood Ave, Toronto | K5: Sep 2023 | L5: 5575000 | M5: 9 | N5: =L5/M5 -> 619444.44 | O5: 0.039
B6: CMHC Average Rate | I6: 3 | J6: 2000-2012 Sheppard Ave W, North York | K6: Apr 2024 | L6: 101000000 | M6: 319 | N6: =L6/M6 -> 316614.42 | O6: 0.042
B7: Average Rents | C7: #Units | D7: %Mix | E7: CMHC Market | F7: Subject | G7: Variance | I7: 4 | J7: 9 Highbourne Road, Toronto | K7: May 2024 | L7: 2600000 | M7: 3 | N7: =L7/M7 -> 866666.67 | O7: 0.0386
B8: 3-Storey Suite (3 BD) | C8: 4 | D8: =C8/C10 -> 0.8 | E8: 2706 | F8: 3513 | G8: =F8/E8-1 -> 0.29822616 | I8: 5 | J8: 134 Carlton Street, Toronto | K8: Jun 2024 | L8: 7480000 | M8: 35 | N8: =L8/M8 -> 213714.29 | O8: 0.0359
B9: Basement (1 BD) | C9: 1 | D9: =C9/C10 -> 0.2 | E9: 1665 | F9: 2750 | G9: =F9/E9-1 -> 0.65165165 | I9: 6 | J9: 1640 Lawrence Ave W, North York | K9: Jun 2024 | L9: 25880000 | M9: 94 | N9: =L9/M9 -> 275319.15 | O9: 0.037
C10: =SUM(C8:C9) -> 5 | D10: =SUM(D8:D9) -> 1 | E10: =(E8*C8+E9*C9)/C10 -> 2497.8 | F10: =(F8*C8+F9*C9)/C10 -> 3360.4 | G10: =(G8*C8+G9*C9)/C10 -> 0.36891126 | I10: 7 | J10: 210 Cosburn Avenue, East York | K10: Jun 2024 | L10: 8228000 | M10: 33 | N10: =L10/M10 -> 249333.33 | O10: 0.0273
I11: 8 | J11: 142 Vaughan Road, York | K11: Oct 2024 | L11: 7175000 | M11: 27 | N11: =L11/M11 -> 265740.74 | O11: 0.0375
I12: 9 | J12: 19 Hatfield Crescent Etobicoke | K12: Dec 2024 | L12: 2864900 | M12: 5 | N12: =L12/M12 -> 572980 | O12: 0.0462
K13: Average | L13: =AVERAGE(L4:L12) -> 18664767 | M13: =AVERAGE(M4:M12) -> 59.444444 | N13: =AVERAGE(N4:N12) -> 455312.56 | O13: =AVERAGE(O4:O12) -> 0.037388889
B14: Rental Comparable | K14: Min | L14: =MIN(L4:L12) -> 2600000 | M14: =MIN(M4:M12) -> 3 | N14: =MIN(N4:N12) -> 213714.29 | O14: =MIN(O4:O12) -> 0.0273
B15: Index | C15: Address | D15: Suit Type | E15: Rental Rate Pu/Pm | K15: Max | L15: =MAX(L4:L12) -> 101000000 | M15: =MAX(M4:M12) -> 319 | N15: =MAX(N4:N12) -> 866666.67 | O15: =MAX(O4:O12) -> 0.0462
B16: Subject | C16: 119 Belgravia | D16: 3-Storey Suits(3 BD) | E16: 3513
B17: Subject | C17: 119 Belgravia | D17: Basement Suits(1 BD) | E17: 2750
B18: 1 | C18: 182 Cameron Avenue Unit 1 (1st floor) | D18: 3 bdrm; 1 bathroom new unit; 1,259 sqft | E18: 3600
B19: 2 | C19: 71 Livingstone Avenue Main Floor | D19: 3 bdrm+den; 2 bathroom new unit | E19: 3750
B20: 3 | C20: 71 Livingstone Avenue Upper Unit (2nd floor) | D20: 3 bdrm; 2 bathroom new unit | E20: 3650
B21: 4 | C21: 15 Ennerdale Road Unit 101 | D21: 3 bdrm; 2 bathroom new unit | E21: 3400
B22: 5 | C22: 48 Lanark Avenue 2 level Laneway Suite | D22: 3 bdrm; 2 bathroom new unit, 1,055 sqft | E22: 3745
B23: 6 | C23: 53 Eversfield Road 2 level Laneway Suite | D23: 3 bdrm; 3 bathroom new unit, 1,055 sqft | E23: 3750
B24: 7 | C24: 16 Little Boulevard 2 level Garden Suite | D24: 3 bdrm; 2 bathroom new unit | E24: 3400
B25: 8 | C25: Confidential, York 2 level Garden Suite | D25: 1 bdrm + den; 1 bath new unit, 620 sqft | E25: 2800
B26: 9 | C26: 504 Beresford Avenue 2 level Garden Suite | D26: 1 bdrm; 1 bathroom new unit, 500-600 sqft | E26: 2700
B27: Average | D27: 3BD Suits | E27: =AVERAGE(E18:E24) -> 3613.5714
D28: Basement Suites | E28: =AVERAGE(E25:E26) -> 2750
D29: Total | E29: =AVERAGE(E18:E26) -> 3421.6667

Sheet DATA
A1: Canada | B1: Canada | C1: 46900 | L1: Taxes | M1: Insurance | N1: Utilities | O1: Maintenance and Repair | P1: Management | Q1: Salaries | R1: Reserve - Appliance | S1: Reserve - Heat pump | T1: Reserve - Elevator | U1: Others Cost
A2: Alberta | B2: =_xlfn.CONCAT("Province - ",A2) -> Province - Alberta | C2: 61500 | F2: NEW CONSTRUCTION | I2: Atlantic | J2: Wood Frame 11 units and less | K2: =_xlfn.CONCAT(I2," - ",J2) -> Atlantic - Wood Frame 11 units and less | L2: Actual | M2: Actual | N2: Actual | O2: 610 | P2: 0.0425 | Q2: 420 | R2: 60 | S2: 190 | T2: 300 | U2: 0.01
A3: Colombie-Britannique | B3: =_xlfn.CONCAT("Province - ",A3) -> Province - Colombie-Britannique | C3: 57600 | F3: PURCHASE - REFINANCE | I3: Atlantic | J3: Wood Frame 12 units and more | K3: =_xlfn.CONCAT(I3," - ",J3) -> Atlantic - Wood Frame 12 units and more | L3: Actual | M3: Actual | N3: Actual | O3: 610 | P3: 0.0425 | Q3: 420 | R3: 60 | S3: 190 | T3: 300 | U3: 0.01
A4: Ile-du-Prince-Édouard | B4: =_xlfn.CONCAT("Province - ",A4) -> Province - Ile-du-Prince-Édouard | C4: 47400 | I4: Atlantic | J4: Concrete | K4: =_xlfn.CONCAT(I4," - ",J4) -> Atlantic - Concrete | L4: Actual | M4: Actual | N4: Actual | O4: 825 | P4: 0.0425 | Q4: 610 | R4: 60 | S4: 190 | T4: 0 | U4: 0.013
A5: Manitoba | B5: =_xlfn.CONCAT("Province - ",A5) -> Province - Manitoba | C5: 41700 | I5: Quebec | J5: Wood Frame 11 units and less | K5: =_xlfn.CONCAT(I5," - ",J5) -> Quebec - Wood Frame 11 units and less | L5: Actual | M5: Actual | N5: Actual | O5: 610 | P5: 0.0425 | Q5: 215 | R5: 60 | S5: 190 | T5: 300 | U5: 0
A6: Nouveau-Brunswick | B6: =_xlfn.CONCAT("Province - ",A6) -> Province - Nouveau-Brunswick | C6: 43200 | F6: 10 YEARS | I6: Quebec | J6: Wood Frame 12 units and more | K6: =_xlfn.CONCAT(I6," - ",J6) -> Quebec - Wood Frame 12 units and more | L6: Actual | M6: Actual | N6: Actual | O6: 610 | P6: 0.05 | Q6: 365 | R6: 60 | S6: 190 | T6: 300 | U6: 0
A7: Nouvelle-Écosse | B7: =_xlfn.CONCAT("Province - ",A7) -> Province - Nouvelle-Écosse | C7: 45000 | F7: 20 YEARS | I7: Quebec | J7: Concrete | K7: =_xlfn.CONCAT(I7," - ",J7) -> Quebec - Concrete | L7: Actual | M7: Actual | N7: Actual | O7: 925 | P7: 0.05 | Q7: 610 | R7: 60 | S7: 190 | T7: 0 | U7: 0
A8: Nunavut | B8: =_xlfn.CONCAT("Province - ",A8) -> Province - Nunavut | C8: 93900 | I8: Ontario | J8: Wood Frame 11 units and less | K8: =_xlfn.CONCAT(I8," - ",J8) -> Ontario - Wood Frame 11 units and less | L8: Actual | M8: Actual | N8: Actual | O8: 830 | P8: 0.0425 | Q8: 555 | R8: 60 | S8: 190 | T8: 300 | U8: 0.01
A9: Ontario | B9: =_xlfn.CONCAT("Province - ",A9) -> Province - Ontario | C9: 48600 | F9: NONE | I9: Ontario | J9: Wood Frame 12 units and more | K9: =_xlfn.CONCAT(I9," - ",J9) -> Ontario - Wood Frame 12 units and more | L9: Actual | M9: Actual | N9: Actual | O9: 830 | P9: 0.0425 | Q9: 555 | R9: 60 | S9: 190 | T9: 300 | U9: 0.01
A10: Québec | B10: =_xlfn.CONCAT("Province - ",A10) -> Province - Québec | C10: 40900 | F10: LEVEL 1 | I10: Ontario | J10: Concrete | K10: =_xlfn.CONCAT(I10," - ",J10) -> Ontario - Concrete | L10: Actual | M10: Actual | N10: Actual | O10: 975 | P10: 0.0425 | Q10: 700 | R10: 60 | S10: 190 | T10: 0 | U10: 0.01
A11: Saskatchewan | B11: =_xlfn.CONCAT("Province - ",A11) -> Province - Saskatchewan | C11: 43600 | F11: LEVEL 2 | I11: Prairies | J11: Wood Frame 11 units and less | K11: =_xlfn.CONCAT(I11," - ",J11) -> Prairies - Wood Frame 11 units and less | L11: Actual | M11: Actual | N11: Actual | O11: 830 | P11: 0.0425 | Q11: 500 | R11: 60 | S11: 190 | T11: 300 | U11: 0.02
A12: Terre-Neuve-et-Labrador | B12: =_xlfn.CONCAT("Province - ",A12) -> Province - Terre-Neuve-et-Labrador | C12: 44800 | F12: LEVEL 3 | I12: Prairies | J12: Wood Frame 12 units and more | K12: =_xlfn.CONCAT(I12," - ",J12) -> Prairies - Wood Frame 12 units and more | L12: Actual | M12: Actual | N12: Actual | O12: 830 | P12: 0.0425 | Q12: 500 | R12: 60 | S12: 190 | T12: 300 | U12: 0.02
A13: Territoires du Nord-Ouest | B13: =_xlfn.CONCAT("Province - ",A13) -> Province - Territoires du Nord-Ouest | C13: 76000 | I13: Prairies | J13: Concrete | K13: =_xlfn.CONCAT(I13," - ",J13) -> Prairies - Concrete | L13: Actual | M13: Actual | N13: Actual | O13: 975 | P13: 0.0425 | Q13: 665 | R13: 60 | S13: 190 | T13: 0 | U13: 0.02
A14: Yukon | B14: =_xlfn.CONCAT("Province - ",A14) -> Province - Yukon | C14: 67400 | I14: British Columbia | J14: Wood Frame 11 units and less | K14: =_xlfn.CONCAT(I14," - ",J14) -> British Columbia - Wood Frame 11 units and less | L14: Actual | M14: Actual | N14: Actual | O14: 830 | P14: 0.0425 | Q14: 635 | R14: 60 | S14: 190 | T14: 300 | U14: 0.017
A15: Alberta | B15: =_xlfn.CONCAT("Rural Center - ",A15) -> Rural Center - Alberta | C15: 45300 | F15: Type | I15: British Columbia | J15: Wood Frame 12 units and more | K15: =_xlfn.CONCAT(I15," - ",J15) -> British Columbia - Wood Frame 12 units and more | L15: Actual | M15: Actual | N15: Actual | O15: 830 | P15: 0.0425 | Q15: 635 | R15: 60 | S15: 190 | T15: 300 | U15: 0.017
A16: Colombie-Britannique | B16: =_xlfn.CONCAT("Rural Center - ",A16) -> Rural Center - Colombie-Britannique | C16: 46000 | F16: Bachelor | I16: British Columbia | J16: Concrete | K16: =_xlfn.CONCAT(I16," - ",J16) -> British Columbia - Concrete | L16: Actual | M16: Actual | N16: Actual | O16: 975 | P16: 0.0425 | Q16: 700 | R16: 60 | S16: 190 | T16: 0 | U16: 0.018
A17: Ile-du-Prince-Édouard | B17: =_xlfn.CONCAT("Rural Center - ",A17) -> Rural Center - Ile-du-Prince-Édouard | C17: 47400 | F17: 1 Bedroom
A18: Manitoba | B18: =_xlfn.CONCAT("Rural Center - ",A18) -> Rural Center - Manitoba | C18: 36900 | F18: 2 Bedroom
A19: Nouveau-Brunswick | B19: =_xlfn.CONCAT("Rural Center - ",A19) -> Rural Center - Nouveau-Brunswick | C19: 39300 | F19: 3 Bedroom
A20: Nouvelle-Écosse | B20: =_xlfn.CONCAT("Rural Center - ",A20) -> Rural Center - Nouvelle-Écosse | C20: 38800 | F20: 4 Bedroom + | I20: LOAN AMOUNT FROM | J20: LOAN AMOUNT TO | K20: 5 YR SPREAD* - PTC | L20: BROKER SPREAD** | M20: 10 YR SPREAD* - PTC | N20: BROKER SPREAD**
A21: Ontario | B21: =_xlfn.CONCAT("Rural Center - ",A21) -> Rural Center - Ontario | C21: 41500 | I21: 0 | J21: 500000 | K21: 260 | L21: 25 | M21: 200 | N21: 15 | O21: ONLY UPDATED THIS TABLE THAT NEED TO BE UPDATED
A22: Québec | B22: =_xlfn.CONCAT("Rural Center - ",A22) -> Rural Center - Québec | C22: 36000 | I22: 500001 | J22: 750000 | K22: 150 | L22: 25 | M22: 125 | N22: 15
A23: Saskatchewan | B23: =_xlfn.CONCAT("Rural Center - ",A23) -> Rural Center - Saskatchewan | C23: 42600 | F23: Utilities | I23: =J22+1 -> 750001 | J23: 1000000 | K23: 115 | L23: 25 | M23: 110 | N23: 15
A24: Terre-Neuve-et-Labrador | B24: =_xlfn.CONCAT("Rural Center - ",A24) -> Rural Center - Terre-Neuve-et-Labrador | C24: 38800 | F24: Owner | I24: =J23+1 -> 1000001 | J24: 1500000 | K24: 105 | L24: 25 | M24: 100 | N24: 15
A25: Abbotsford | B25: =_xlfn.CONCAT("Urban Center - ",A25) -> Urban Center - Abbotsford | C25: 64200 | F25: Tenant | I25: =J24+1 -> 1500001 | J25: 2000000 | K25: 100 | L25: 25 | M25: 95 | N25: 15
A26: Barrie | B26: =_xlfn.CONCAT("Urban Center - ",A26) -> Urban Center - Barrie | C26: 58900 | F26: NA | I26: =J25+1 -> 2000001 | J26: 3000000 | K26: 80 | L26: 25 | M26: 65 | N26: 15
A27: Brampton | B27: =_xlfn.CONCAT("Urban Center - ",A27) -> Urban Center - Brampton | C27: 67700 | I27: =J26+1 -> 3000001 | J27: 5000000 | K27: 70 | L27: 23 | M27: 55 | N27: 15
A28: Brantford | B28: =_xlfn.CONCAT("Urban Center - ",A28) -> Urban Center - Brantford | C28: 40300 | I28: =J27+1 -> 5000001 | J28: 7000000 | K28: 55 | L28: 17 | M28: 50 | N28: 15
A29: Burnaby | B29: =_xlfn.CONCAT("Urban Center - ",A29) -> Urban Center - Burnaby | C29: 60200 | F29: Appliances | I29: =J28+1 -> 7000001 | J29: 10000000 | K29: 50 | L29: 12 | M29: 49 | N29: 10
A30: Calgary | B30: =_xlfn.CONCAT("Urban Center - ",A30) -> Urban Center - Calgary | C30: 69500 | F30: Fridge | I30: =J29+1 -> 10000001 | J30: 1e+22 | K30: 45 | L30: 8 | M30: 48 | N30: 5
A31: Cape Breton | B31: =_xlfn.CONCAT("Urban Center - ",A31) -> Urban Center - Cape Breton | C31: 39400 | F31: Stove
A32: Charlottetown | B32: =_xlfn.CONCAT("Urban Center - ",A32) -> Urban Center - Charlottetown | C32: 49300 | F32: Washer | I32: LOAN AMOUNT FROM | J32: LOAN AMOUNT TO | K32: 5 YR SPREAD* - PTC | L32: BROKER SPREAD** | M32: 10 YR SPREAD* - PTC | N32: BROKER SPREAD**
A33: Chilliwack | B33: =_xlfn.CONCAT("Urban Center - ",A33) -> Urban Center - Chilliwack | C33: 83200 | F33: Dryer | I33: 0 | J33: 500000 | K33: =K21/10000 -> 0.026 | L33: =L21/10000 -> 0.0025 | M33: =M21/10000 -> 0.02 | N33: =N21/10000 -> 0.0015
A34: Cornwall | B34: =_xlfn.CONCAT("Urban Center - ",A34) -> Urban Center - Cornwall | C34: 24700 | F34: Dishwasher | I34: 500001 | J34: 750000 | K34: =K22/10000 -> 0.015 | L34: =L22/10000 -> 0.0025 | M34: =M22/10000 -> 0.0125 | N34: =N22/10000 -> 0.0015
A35: Edmonton | B35: =_xlfn.CONCAT("Urban Center - ",A35) -> Urban Center - Edmonton | C35: 66600 | F35: Microwave | I35: =J34+1 -> 750001 | J35: 1000000 | K35: =K23/10000 -> 0.0115 | L35: =L23/10000 -> 0.0025 | M35: =M23/10000 -> 0.011 | N35: =N23/10000 -> 0.0015
A36: Fredericton | B36: =_xlfn.CONCAT("Urban Center - ",A36) -> Urban Center - Fredericton | C36: 49800 | I36: =J35+1 -> 1000001 | J36: 1500000 | K36: =K24/10000 -> 0.0105 | L36: =L24/10000 -> 0.0025 | M36: =M24/10000 -> 0.01 | N36: =N24/10000 -> 0.0015
A37: Greater Sudbury | B37: =_xlfn.CONCAT("Urban Center - ",A37) -> Urban Center - Greater Sudbury | C37: 46500 | I37: =J36+1 -> 1500001 | J37: 2000000 | K37: =K25/10000 -> 0.01 | L37: =L25/10000 -> 0.0025 | M37: =M25/10000 -> 0.0095 | N37: =N25/10000 -> 0.0015
A38: Guelph | B38: =_xlfn.CONCAT("Urban Center - ",A38) -> Urban Center - Guelph | C38: 57400 | F38: Furniture | I38: =J37+1 -> 2000001 | J38: 3000000 | K38: =K26/10000 -> 0.008 | L38: =L26/10000 -> 0.0025 | M38: =M26/10000 -> 0.0065 | N38: =N26/10000 -> 0.0015
A39: Halifax | B39: =_xlfn.CONCAT("Urban Center - ",A39) -> Urban Center - Halifax | C39: 49900 | F39: Bed | I39: =J38+1 -> 3000001 | J39: 5000000 | K39: =K27/10000 -> 0.007 | L39: =L27/10000 -> 0.0023 | M39: =M27/10000 -> 0.0055 | N39: =N27/10000 -> 0.0015
A40: Hamilton | B40: =_xlfn.CONCAT("Urban Center - ",A40) -> Urban Center - Hamilton | C40: 44400 | F40: Couch | I40: =J39+1 -> 5000001 | J40: 7000000 | K40: =K28/10000 -> 0.0055 | L40: =L28/10000 -> 0.0017 | M40: =M28/10000 -> 0.005 | N40: =N28/10000 -> 0.0015
A41: Kamloops | B41: =_xlfn.CONCAT("Urban Center - ",A41) -> Urban Center - Kamloops | C41: 40900 | F41: Desk | I41: =J40+1 -> 7000001 | J41: 10000000 | K41: =K29/10000 -> 0.005 | L41: =L29/10000 -> 0.0012 | M41: =M29/10000 -> 0.0049 | N41: =N29/10000 -> 0.001
A42: Kelowna | B42: =_xlfn.CONCAT("Urban Center - ",A42) -> Urban Center - Kelowna | C42: 47500 | F42: Table | I42: =J41+1 -> 10000001 | J42: 1e+22 | K42: =K30/10000 -> 0.0045 | L42: =L30/10000 -> 0.0008 | M42: =M30/10000 -> 0.0048 | N42: =N30/10000 -> 0.0005
A43: Kingston | B43: =_xlfn.CONCAT("Urban Center - ",A43) -> Urban Center - Kingston | C43: 52500 | F43: Chairs | I43: For open pool the PTC spread is 10bps higher du to cost structure
A44: Kitchener | B44: =_xlfn.CONCAT("Urban Center - ",A44) -> Urban Center - Kitchener | C44: 57000 | F44: Side Tables | I44: Minimum loan amount is current 2M$ for PTC
A45: Laval | B45: =_xlfn.CONCAT("Urban Center - ",A45) -> Urban Center - Laval | C45: 48800 | F45: TV | I45: Hedge cost are not included in the PTC spread
A46: Lethbridge | B46: =_xlfn.CONCAT("Urban Center - ",A46) -> Urban Center - Lethbridge | C46: 43000 | F46: Matress
A47: London | B47: =_xlfn.CONCAT("Urban Center - ",A47) -> Urban Center - London | C47: 39600
A48: Mississauga | B48: =_xlfn.CONCAT("Urban Center - ",A48) -> Urban Center - Mississauga | C48: 49000 | F48: Semi-Private & Ward Beds | I48: Standard Rental Housing
A49: Moncton | B49: =_xlfn.CONCAT("Urban Center - ",A49) -> Urban Center - Moncton | C49: 45700 | F49: Private Beds | I49: Product | J49: LTV | K49: Construction Financing | L49: All other loan purpose
A50: Montréal | B50: =_xlfn.CONCAT("Urban Center - ",A50) -> Urban Center - Montréal | C50: 43600 | F50: Shelter Beds (NHCF) | I50: Market rental and MLI Select | J50: 0.65 | K50: 0.0325 | L50: 0.026
A51: Nanaimo | B51: =_xlfn.CONCAT("Urban Center - ",A51) -> Urban Center - Nanaimo | C51: 40900 | F51: Bachelor | J51: 0.7 | K51: 0.0375 | L51: 0.0285
A52: Oshawa | B52: =_xlfn.CONCAT("Urban Center - ",A52) -> Urban Center - Oshawa | C52: 54000 | F52: 1 Bedrooms | J52: 0.75 | K52: 0.0425 | L52: 0.0335
A53: Ottawa - Gatineau (Ontario) | B53: =_xlfn.CONCAT("Urban Center - ",A53) -> Urban Center - Ottawa - Gatineau (Ontario) | C53: 61400 | F53: 2 Bedrooms | J53: 0.8 | K53: 0.05 | L53: 0.0435
A54: Ottawa - Gatineau (Québec) | B54: =_xlfn.CONCAT("Urban Center - ",A54) -> Urban Center - Ottawa - Gatineau (Québec) | C54: 48800 | F54: 3 Bedrooms | J54: 0.85 | K54: 0.06 | L54: 0.0535
A55: Prince George | B55: =_xlfn.CONCAT("Urban Center - ",A55) -> Urban Center - Prince George | C55: 34700 | F55: 4+ Bedrooms | I55: MLI Select | J55: 0.9 | K55: 0.0675 | L55: 0.059
A56: Red Deer | B56: =_xlfn.CONCAT("Urban Center - ",A56) -> Urban Center - Red Deer | C56: 35900 | J56: >90% | K56: 0.07 | L56: 0.0615
A57: Regina | B57: =_xlfn.CONCAT("Urban Center - ",A57) -> Urban Center - Regina | C57: 42400 | F57: Shelter Type
A58: RMR Québec | B58: =_xlfn.CONCAT("Urban Center - ",A58) -> Urban Center - RMR Québec | C58: 41100 | F58: Standard Rental Housing | I58: All other Shelter Models
A59: Rouyn-Noranda | B59: =_xlfn.CONCAT("Urban Center - ",A59) -> Urban Center - Rouyn-Noranda | C59: 39000 | F59: Single Room Occupancy | I59: Product | J59: LTV | K59: Construction Financing | L59: All other loan purpose
A60: Saguenay | B60: =_xlfn.CONCAT("Urban Center - ",A60) -> Urban Center - Saguenay | C60: 39200 | F60: Student Housing | I60: Market rental and MLI Select | J60: 0.65 | K60: 0.0655 | L60: 0.063
A61: Saint John | B61: =_xlfn.CONCAT("Urban Center - ",A61) -> Urban Center - Saint John | C61: 48000 | F61: Retirement Homes | J61: 0.7 | K61: 0.0685 | L61: 0.066
A62: Saint-Georges | B62: =_xlfn.CONCAT("Urban Center - ",A62) -> Urban Center - Saint-Georges | C62: 43700 | F62: Suppotive Housing | J62: 0.75 | K62: 0.0715 | L62: 0.069
A63: Saint-Hyacinthe | B63: =_xlfn.CONCAT("Urban Center - ",A63) -> Urban Center - Saint-Hyacinthe | C63: 26900 | J63: 0.8 | K63: 0.073 | L63: 0.0705
A64: Saint-Jean-Iberville | B64: =_xlfn.CONCAT("Urban Center - ",A64) -> Urban Center - Saint-Jean-Iberville | C64: 44500 | J64: 0.85 | K64: 0.08 | L64: 0.0775
A65: Sarnia | B65: =_xlfn.CONCAT("Urban Center - ",A65) -> Urban Center - Sarnia | C65: 25800 | I65: MLI Select | J65: 0.9 | K65: 0.0825 | L65: 0.08
A66: Saskatoon | B66: =_xlfn.CONCAT("Urban Center - ",A66) -> Urban Center - Saskatoon | C66: 43600 | J66: >90% | K66: 0.09 | L66: 0.0875
A67: Sault Ste. Marie | B67: =_xlfn.CONCAT("Urban Center - ",A67) -> Urban Center - Sault Ste. Marie | C67: 22100
A68: Sherbrooke | B68: =_xlfn.CONCAT("Urban Center - ",A68) -> Urban Center - Sherbrooke | C68: 32600 | I68: Surcharge
A69: St John's | B69: =_xlfn.CONCAT("Urban Center - ",A69) -> Urban Center - St John's | C69: 52400 | I69: Extended Amortization | J69: A 0.25% surcharge applies on the net loan amount for every five years, beyond the 25-year standard amortization period.
A70: St. Catharines-Niagara | B70: =_xlfn.CONCAT("Urban Center - ",A70) -> Urban Center - St. Catharines-Niagara | C70: 41900 | I70: Non Resident Space | J70: A 1.00% surcharge applies on the portion of the loan applicable to the non residential space.
A71: Summerside | B71: =_xlfn.CONCAT("Urban Center - ",A71) -> Urban Center - Summerside | C71: 34600 | I71: Second mortgage | J71: A 0.50% surcharge applies to the outstanding balance of the first mortgage loan only.
A72: Surrey | B72: =_xlfn.CONCAT("Urban Center - ",A72) -> Urban Center - Surrey | C72: 51000 | I72: EGI Not Met | J72: A 0.25% surcharge applies on the net loan amount where effective gross income is not met at the time of the first advance. This surcharge does not apply to construction financing.
A73: Thompson | B73: =_xlfn.CONCAT("Urban Center - ",A73) -> Urban Center - Thompson | C73: 68300
A74: Thunder Bay | B74: =_xlfn.CONCAT("Urban Center - ",A74) -> Urban Center - Thunder Bay | C74: 42800 | I74: Discount
A75: Toronto | B75: =_xlfn.CONCAT("Urban Center - ",A75) -> Urban Center - Toronto | C75: 53900 | I75: 50 | J75: 0.1
A76: Trois-Rivières | B76: =_xlfn.CONCAT("Urban Center - ",A76) -> Urban Center - Trois-Rivières | C76: 30700 | I76: 70 | J76: 0.2
A77: Val-d’Or | B77: =_xlfn.CONCAT("Urban Center - ",A77) -> Urban Center - Val-d’Or | C77: 49300 | I77: 90 | J77: 0.3
A78: Vancouver | B78: =_xlfn.CONCAT("Urban Center - ",A78) -> Urban Center - Vancouver | C78: 66900
A79: Victoria | B79: =_xlfn.CONCAT("Urban Center - ",A79) -> Urban Center - Victoria | C79: 48900
A80: Windsor | B80: =_xlfn.CONCAT("Urban Center - ",A80) -> Urban Center - Windsor | C80: 34000
A81: Winnipeg | B81: =_xlfn.CONCAT("Urban Center - ",A81) -> Urban Center - Winnipeg | C81: 44000
A82: Wood Buffalo | B82: =_xlfn.CONCAT("Urban Center - ",A82) -> Urban Center - Wood Buffalo | C82: 72400
A89: MORTAGE CALCULATION - Proforma (CMHC) | E89: MORTAGE CALCULATION - Proforma (CMHC MLI SELECT) | I89: MORTAGE CALCULATION - Proforma (CONVENTIONAL)
A90: INPUTS | B90: Monthly Interest Payment | C90: =((1+('Proforma Construction'!F50/2))^2)^(1/12)-1 -> 0.0030598312 | E90: INPUTS | F90: Monthly Interest Payment | G90: =((1+('Proforma Construction'!F50/2))^2)^(1/12)-1 -> 0.0030598312 | I90: INPUTS | J90: Monthly Interest Payment | K90: =((1+('Proforma Construction'!F50/2))^2)^(1/12)-1 -> 0.0030598312
B91: Monthly Mortgage Payment | C91: ='Proforma Construction'!I50/12 -> 367929.31 | F91: Monthly Mortgage Payment | G91: ='Proforma Construction'!I50/12 -> 367929.31 | J91: Monthly Mortgage Payment | K91: ='Proforma Construction'!I50/12 -> 367929.31
A93: OUTPUT | B93: Sum Interest Payment 1 Years | C93: =SUM(B112:B123) -> 1561556.5 | E93: OUTPUT | F93: Sum Interest Payment 1 Years | G93: =SUM(F112:F123) -> 1816415.1 | I93: OUTPUT | J93: Sum Interest Payment 1 Years | K93: =SUM(J112:J123) -> 1199078.8
B94: Sum Interest Payment 2 Years | C94: =SUM(B124:B135) -> 1454996.8 | F94: Sum Interest Payment 2 Years | G94: =SUM(F124:F135) -> 1719372.5 | J94: Sum Interest Payment 2 Years | K94: =SUM(J124:J135) -> 1078983.4
B95: Sum Interest Payment 3 Years | C95: =SUM(B136:B147) -> 1344458 | F95: Sum Interest Payment 3 Years | G95: =SUM(F136:F147) -> 1618706 | J95: Sum Interest Payment 3 Years | K95: =SUM(J136:J147) -> 954403.39
B96: Sum Interest Payment 4 Years | C96: =SUM(B148:B159) -> 1229791.4 | F96: Sum Interest Payment 4 Years | G96: =SUM(F148:F159) -> 1514280.4 | J96: Sum Interest Payment 4 Years | K96: =SUM(J148:J159) -> 825171.26
B97: Sum Interest Payment 4 Years | C97: =SUM(B160:B171) -> 1110842.9 | F97: Sum Interest Payment 4 Years | G97: =SUM(F160:F171) -> 1405955.4 | J97: Sum Interest Payment 4 Years | K97: =SUM(J160:J171) -> 691113.31
B99: Capital 1 years | C99: =($C$91*12)-C93 -> 2853595.2 | F99: Capital 1 years | G99: =($G$91*12)-G93 -> 2598736.6 | J99: Capital 1 years | K99: =($K$91*12)-K93 -> 3216072.9
B100: Capital 2 years | C100: =($C$91*12)-C94 -> 2960154.9 | F100: Capital 2 years | G100: =($G$91*12)-G94 -> 2695779.2 | J100: Capital 2 years | K100: =($K$91*12)-K94 -> 3336168.3
B101: Capital 3 years | C101: =($C$91*12)-C95 -> 3070693.7 | F101: Capital 3 years | G101: =($G$91*12)-G95 -> 2796445.7 | J101: Capital 3 years | K101: =($K$91*12)-K95 -> 3460748.3
B102: Capital 4 years | C102: =($C$91*12)-C96 -> 3185360.3 | F102: Capital 4 years | G102: =($G$91*12)-G96 -> 2900871.3 | J102: Capital 4 years | K102: =($K$91*12)-K96 -> 3589980.5
B103: Capital 5 years | C103: =($C$91*12)-C97 -> 3304308.9 | F103: Capital 5 years | G103: =($G$91*12)-G97 -> 3009196.3 | J103: Capital 5 years | K103: =($K$91*12)-K97 -> 3724038.4
A105: Validation | B105: Mortage Payment 5 years | C105: =C91*60 -> 22075759 | E105: Validation | F105: Mortage Payment 5 years | G105: =G91*60 -> 22075759 | I105: Validation | J105: Mortage Payment 5 years | K105: =K91*60 -> 22075759
B106: Sum Interest 5 years | C106: =SUM(C93:C97) -> 6701645.5 | F106: Sum Interest 5 years | G106: =SUM(G93:G97) -> 8074729.4 | J106: Sum Interest 5 years | K106: =SUM(K93:K97) -> 4748750.2
B107: Sum Capital 5 years | C107: =SUM(C99:C103) -> 15374113 | F107: Sum Capital 5 years | G107: =SUM(G99:G103) -> 14001029 | J107: Sum Capital 5 years | K107: =SUM(K99:K103) -> 17327008
B108: Calcul Diff - Need to be 0 | C108: =C105-C106-C107 -> 0 | F108: Calcul Diff - Need to be 0 | G108: =G105-G106-G107 -> 0 | J108: Calcul Diff - Need to be 0 | K108: =K105-K106-K107 -> 0
B110: Interest | C110: Balance | F110: Interest | G110: Balance | J110: Interest | K110: Balance
...
