Workbook
Name AltusCC: #REF!
Name AltusParking: #REF!
Name Amenities: '[1]Amenities DDM'!$B$2:$C$11
Name CMHCActualAverage: '[1]CMHC vs Actual Rents'!$B$3:$G$73
Name CMHCGap: '[1]CMHC Gap'!$B$3:$F$73
Name CMHCRentDensity: '[1]CMHC - Rental Density'!$A$5:$F$75
Name CMHCRents: '[1]CMHC - Rental Rates'!$A$5:$G$74
Name CMHCSecondary: '[1]CMHC - Secondary Universe'!$A$4:$E$74
Name CMHCUniverse: '[1]CMHC - Universe'!$A$5:$J$76
Name CMHCVac: '[1]CMHC - Vacancy'!$A$5:$G$74
Name PrizmGroups: '[1]PRIZM Profiles'!$B$5:$E$72
Name PrizmNameRange: '[1]PRIZM Profiles'!$B$6:$B$72
Name PrizmPicLookup1: INDEX(PrizmNameRange,MATCH('[1]7 - Prizm'!A1,PrizmNameRange,0))
Name Proforma: #REF!
Name RentalDensity: '[1]CMHC - Rental Density'!$A$6:$F$75
Name SecondaryU: '[1]CMHC - Secondary Universe'!$A$5:$E$74

Sheet 1. 1A Proforma
F2: Estimated Stabilized Value - Today
F3: 2240 Birchmount Road, Scarborough, ON
D5: RECOMMENDED RENTAL RATES | G5: Unit Mix
D6: Unit Type | E6: Unit Size (SF) | F6: Unit Count | H6: Total SF | I6: Monthly Per Unit | J6: $/SF | K6: Monthly | L6: Total Annual
D7: 1 Bed | E7: 624 | F7: 84 | G7: =F7/$F$10 -> 0.49411765 | H7: =F7*E7 -> 52416 | I7: 2490 | J7: =I7/E7 -> 3.9903846 | K7: =I7*F7 -> 209160 | L7: =K7*12 -> 2509920
D8: 2 Bed | E8: 855.4 | F8: 68 | G8: =F8/$F$10 -> 0.4 | H8: =F8*E8 -> 58167.2 | I8: 3155 | J8: =I8/E8 -> 3.6883329 | K8: =I8*F8 -> 214540 | L8: =K8*12 -> 2574480
D9: 3 Bed | E9: 1015 | F9: 18 | G9: =F9/$F$10 -> 0.10588235 | H9: =F9*E9 -> 18270 | I9: 3675 | J9: =I9/E9 -> 3.6206897 | K9: =I9*F9 -> 66150 | L9: =K9*12 -> 793800
D10: TOTAL/AVG.: | E10: =SUMPRODUCT(E7:E9,F7:F9)/F10 -> 757.96 | F10: =SUM(F7:F9) -> 170 | G10: =SUM(G7:G9) -> 1 | H10: =SUM(H7:H9) -> 128853.2 | I10: =K10/F10 -> 2881.4706 | J10: =K10/H10 -> 3.801613 | K10: =SUM(K7:K9) -> 489850 | L10: =SUM(L7:L9) -> 5878200
C12: =SUM(C7:C7) -> 0
E13: Total Residential Units: | F13: =F10 -> 170 | I13: Net Rentable SF (Residential Units): | J13: =H10 -> 128853.2
I14: Total Monthly Rent Revenue: | J14: =K10 -> 489850
E16: ESTIMATED OPERATING REVENUES | F16: #Spaces | G16: Monthly Fee | H16: Annual Per Unit | I16: Monthly Per Unit | J16: Monthly | K16: Total Annual
E17: Rent | H17: =K17/$F$13 -> 34577.647 | I17: =I10 -> 2881.4706 | J17: =K10 -> 489850 | K17: =L10 -> 5878200
E18: Underground Parking | F18: 162 | G18: 200 | H18: =K18/$F$13 -> 2287.0588 | I18: =J18/$F$13 -> 190.58824 | J18: =F18*G18 -> 32400 | K18: =J18*12 -> 388800
E19: Visitor Parking | F19: 15 | G19: 0
E20: Retail Parking | F20: 15 | G20: 0
E21: Storage Lockers | F21: 100 | G21: 40 | H21: =K21/$F$13 -> 282.35294 | I21: =J21/$F$13 -> 23.529412 | J21: =F21*G21 -> 4000 | K21: =J21*12 -> 48000
E22: Submetering Reimbursement | F22: =F13 -> 170 | G22: =+'[2]Typical Conv.Operating Expenses'!BU96 -> 20 | H22: =K22/F13 -> 240 | I22: =G22 -> 20 | J22: =I22*F13 -> 3400 | K22: =J22*12 -> 40800
E23: SUB-TOTAL: | H23: =SUM(H17:H22) -> 37387.059 | I23: =SUM(I17:I22) -> 3115.5882 | J23: =SUM(J17:J22) -> 529650 | K23: =SUM(K17:K22) -> 6355800
E24: Vacancies (Rent & Parking) | F24: 0.03 | H24: =-H23*$F$24 -> -1121.6118 | I24: =-I23*$F$24 -> -93.467647 | J24: =+K24/12 -> -15889.5 | K24: =-+K23*F24 -> -190674
E25: Other Income | G25: Rate
E26: Net Commercial Retail $/SF | F26: 4370 | G26: 40 | J26: =K26/12 -> 14566.667 | K26: =+F26*G26 -> 174800
E27: Vacancies (Commercial) | F27: 0.04 | J27: =K27/12 -> -582.66667 | K27: =-K26*$F$27 -> -6992
E28: TOTAL: | H28: =SUM(H23:H26) -> 36265.447 | I28: =SUM(I23:I26) -> 3022.1206 | J28: =SUM(J23:J27) -> 527744.5 | K28: =SUM(K23:K27) -> 6332934
E30: ESTIMATED OPERATING EXPENSES (INDUSTRY STANDARD) | H30: Annual Per Unit | I30: Monthly Per Unit | J30: Monthly | K30: Total Annual | L30: % of Revenue
E31: Utilities (Common Area Only) | F31: =$F$13 -> 170 | G31: units @ | H31: =+H80 -> 1130 | I31: =H31/12 -> 94.166667 | J31: =K31/12 -> 16008.333 | K31: =H31*F31 -> 192100 | L31: =+K31/$K$28 -> 0.030333492
E32: Repairs & Maintenance | F32: =$F$13 -> 170 | G32: units @ | H32: =+I93 -> 1050 | I32: =H32/12 -> 87.5 | J32: =K32/12 -> 14875 | K32: =H32*F32 -> 178500 | L32: =+K32/$K$28 -> 0.028185988
E33: Staffing | F33: =$F$13 -> 170 | G33: units @ | H33: =+I109 -> 1200 | I33: =J33/F13 -> 100 | J33: =K33/12 -> 17000 | K33: =+H33*F13 -> 204000 | L33: =+K33/$K$28 -> 0.032212557
E34: Insurance | F34: =$F$13 -> 170 | G34: units @ | H34: =+F117 -> 450 | I34: =H34/12 -> 37.5 | J34: =K34/12 -> 6375 | K34: =H34*F34 -> 76500 | L34: =+K34/$K$28 -> 0.012079709
E35: Marketing | F35: =$F$13 -> 170 | G35: units @ | H35: =+F122 -> 300 | I35: =H35/12 -> 25 | J35: =K35/12 -> 4250 | K35: =H35*F35 -> 51000 | L35: =+K35/$K$28 -> 0.0080531394
E36: General & Admin | F36: =$F$13 -> 170 | G36: units @ | H36: =+F127 -> 250 | I36: =H36/12 -> 20.833333 | J36: =K36/12 -> 3541.6667 | K36: =H36*F36 -> 42500 | L36: =+K36/$K$28 -> 0.0067109495
E37: Management Fee | F37: % of Gross Revenue | G37: 0.0425 | H37: =ROUND(K37/F13,-1) -> 1580 | I37: =J37/F13 -> 131.93613 | J37: =K37/12 -> 22429.141 | K37: =K28*G37 -> 269149.7 | L37: =+K37/$K$28 -> 0.0425
E38: Property Taxes (Per Municipal Rate)* | F38: 0.00754087 | G38: 450000 | H38: =ROUND(K38/F13,-1) -> 3390 | I38: =J38/F13 -> 282.78262 | J38: =K38/12 -> 48073.046 | K38: =F13*G38*F38 -> 576876.55 | L38: =+K38/$K$28 -> 0.091091515
E39: Reserve for Asset Replacement | F39: % of Gross Revenue | G39: =+I137 -> 0.02 | H39: =ROUND(K39/F13,-1) -> 750 | I39: =J39/F13 -> 62.087588 | J39: =K39/12 -> 10554.89 | K39: =K28*G39 -> 126658.68 | L39: =+K39/$K$28 -> 0.02
E40: TOTAL: | F40: =K40/K28 -> 0.27116735 | H40: =SUM(H31:H39) -> 10100 | I40: =SUM(I31:I39) -> 841.80634 | J40: =SUM(J31:J39) -> 143107.08 | K40: =SUM(K31:K39) -> 1717284.9 | L40: =+K40/$K$28 -> 0.27116735
E42: ESTIMATED NET OPERATING INCOME | H42: =H28-H40 -> 26165.447 | I42: =I28-I40 -> 2180.3143 | J42: =J28-J40 -> 384637.42 | K42: =K28-K40 -> 4615649.1
G45: ESTIMATED VALUATION | H45: Residential CAP Rate | I45: Est. Market Value Per Unit | J45: Est. Market Value Per SF | K45: Est. Market Value
G46: Market Value @ | H46: 0.0425 | I46: =ROUND(K46/$F$13,-2) -> 638800 | J46: =K46/$J$13 -> 842.85062 | K46: =ROUND($K$42/H46,-3) -> 108604000
G47: Market Value @ | H47: 0.045 | I47: =ROUND(K47/$F$13,-2) -> 603400 | J47: =K47/$J$13 -> 796.02214 | K47: =ROUND($K$42/H47,-3) -> 102570000
G48: Market Value @ | H48: 0.0475 | I48: =ROUND(K48/$F$13,-2) -> 571600 | J48: =K48/$J$13 -> 754.12951 | K48: =ROUND($K$42/H48,-3) -> 97172000
E51: The New Multi-Residential Tax Rate for Totoronto in 2025 is 0.754087%
E52: Appropriate property tax rate should be confirmed by a specialist. SVN's property tax calculations are estimates only.
E58: FOR INTERNAL USE
E60: PROFORMA ASSUMPTIONS
D61: 1 | E61: Utilities
E62: Building GFA | F62: 146346 | H62: Avg Unit Size | K62: Retail Space | L62: 4370.15
E63: Less Residential GFA | F63: =+H10 -> 128853.2 | G63: =+F63/F62 -> 0.88046957 | H63: =+E10 -> 757.96
E64: Amenity Space | F64: 3703 | G64: =+F64/F62 -> 0.025303049
E65: Common Area GFA | F65: =+F62-F63 -> 17492.8 | G65: =+F65/F62 -> 0.11953043
E68: Total Annual Utilities | F68: Total Common Area $ PSF | H68: Total GFA $ PSF | J68: Rentable $ PSF
F69: MIN | G69: MAX | H69: MIN | I69: MAX | J69: MIN | K69: MAX
E70: Hydro | F70: =+'[2]Typical Conv.Operating Expenses'!BW85 -> 1.1269682 | G70: =+'[2]Typical Conv.Operating Expenses'!BX85 -> 3.1454606 | H70: =+'[2]Typical Conv.Operating Expenses'!BZ85 -> 0.16904523 | I70: =+'[2]Typical Conv.Operating Expenses'!CA85 -> 0.47181908 | J70: =+'[2]Typical Conv.Operating Expenses'!CC85 -> 0.19887674 | K70: =+'[2]Typical Conv.Operating Expenses'!CD85 -> 3.0043212
E71: Gas | F71: =+'[2]Typical Conv.Operating Expenses'!BW86 -> 0.64609058 | G71: =+'[2]Typical Conv.Operating Expenses'!BX86 -> 6.9060051 | H71: =+'[2]Typical Conv.Operating Expenses'!BZ86 -> 0.096913587 | I71: =+'[2]Typical Conv.Operating Expenses'!CA86 -> 1.0359008 | J71: =+'[2]Typical Conv.Operating Expenses'!CC86 -> 0.11401599 | K71: =+'[2]Typical Conv.Operating Expenses'!CD86 -> 6.9060051
E72: =+'[2]Typical Conv.Operating Expenses'!B87 -> Water & Sewer | F72: =+'[2]Typical Conv.Operating Expenses'!BW87 -> 0.54094474 | G72: =+'[2]Typical Conv.Operating Expenses'!BX87 -> 4.755253 | H72: =+'[2]Typical Conv.Operating Expenses'!BZ87 -> 0.081141712 | I72: =+'[2]Typical Conv.Operating Expenses'!CA87 -> 0.71328795 | J72: =+'[2]Typical Conv.Operating Expenses'!CC87 -> 0.095460837 | K72: =+'[2]Typical Conv.Operating Expenses'!CD87 -> 4.755253
F73: =SUM(F70:F72) -> 2.3140035 | G73: =SUM(G70:G72) -> 14.806719 | H73: =+'[2]Typical Conv.Operating Expenses'!BZ88 -> 0.43681288 | I73: =+'[2]Typical Conv.Operating Expenses'!CA88 -> 4.9121525 | J73: =+'[2]Typical Conv.Operating Expenses'!CC88 -> 0.51389751 | K73: =+'[2]Typical Conv.Operating Expenses'!CD88 -> 5.7427339
E74: AVG PSF | F74: =+'[2]Typical Conv.Operating Expenses'!BU93 -> 8.4224722 | H74: =+'[2]Typical Conv.Operating Expenses'!BU94 -> 1.2258459 | J74: =+'[2]Typical Conv.Operating Expenses'!BU92 -> 1.4346518
E75: Peter Wyse (March 18, 2025) | H75: 1.5
E76: Gemini AI Estimate for 200 unit apartment in Ontario | F76: 1620 | G76: per unit | H76: Lowest | I76: Highest
E77: AVG PER UNIT | F77: =+'[2]Typical Conv.Operating Expenses'!BU91 -> 1202.8067 | H77: =+'[2]Typical Conv.Operating Expenses'!BX91 -> 426.08696 | I77: =+'[2]Typical Conv.Operating Expenses'!BX92 -> 2195.3577
E80: Input Estimate $ PSF Common Area | F80: 11 | G80: Subject PSF Common Area | H80: =ROUND(+F81/F13,-1) -> 1130 | I80: Subject Per Unit (Rounded) Input for Proforma
F81: =+F80*F65 -> 192420.8 | G81: Subject Total Utilities | H81: =+H80*F13 -> 192100
F82: =+F81/F62 -> 1.3148347 | G82: Subject $ Gross SF
F83: =+F81/F63 -> 1.4933335 | G83: Subject $ Rentable SF
D85: 2 | E85: REPAIRS & MAINTENANCE COSTS
F86: Per Unit Per Month | H86: Annual Cost
E87: Trash & Recycling | F87: 25 | G87: 50 | H87: =+F87*$F$13*12 -> 51000 | I87: =+G87*$F$13*12 -> 102000
E88: Pest Control | F88: 5 | G88: 20 | H88: =+F88*$F$13*12 -> 10200 | I88: =+G88*$F$13*12 -> 40800
E89: Cleaning and Maintenance | F89: 20 | G89: 35 | H89: =+F89*$F$13*12 -> 40800 | I89: =+G89*$F$13*12 -> 71400
D90: =5*52*8 -> 2080 | F90: =SUM(F87:F89) -> 50 | G90: =SUM(G87:G89) -> 105 | H90: =SUM(H87:H89) -> 102000 | I90: =SUM(I87:I89) -> 214200 | K90: R&M
E91: Per Unit Cost | H91: =+H90/$F$13 -> 600 | I91: =+I90/$F$13 -> 1260 | K91: Low | L91: High
I92: =AVERAGE(H91:I91) -> 930 | J92: AVG Per Unit | K92: =+'[2]Typical Conv.Operating Expenses'!BW101 -> 500 | L92: =+'[2]Typical Conv.Operating Expenses'!BX101 -> 1498.2846
H93: ROUNDED | I93: 1050
G94: CMHC R&M Benchmarks
E95: ADJUST BASED ON TYPE/LOCATION | G95: =+'[2]CMHC '!K10 -> Ontario - Concrete | I95: =ROUND(+'[2]CMHC '!O10*1.025*1.025*1.025,-1) -> 1050 | J95: CMHC Benchmark (inflated to 2025)
G96: =+'[2]CMHC '!K9 -> Ontario - Wood Frame 12 units and more | I96: =ROUND(+'[2]CMHC '!O9*1.025*1.025*1.025,-1) -> 890 | J96: CMHC Benchmark (inflated to 2025)
I97: =+'[2]Expense Comparison'!H11 -> 975 | J97: CMHC Update (Concrete)
D98: 3 | E98: STAFFING
F99: # Positions | G99: Rate/Hr | H99: Annual Hrs | I99: Total
E100: Security | F100: 0.5 | G100: 30 | H100: 2000 | I100: =+F100*G100*H100 -> 30000 | J100: Includes 25% benefits
E101: Maintenance | F101: 1 | G101: 30 | H101: 2000 | I101: =+F101*G101*H101 -> 60000
E102: Cleaning | F102: 1 | G102: 30 | H102: 2000 | I102: =+F102*G102*H102 -> 60000
E103: Concierge/Programming | F103: 0 | G103: 32 | H103: 2000 | I103: =+F103*G103*H103 -> 0
E104: Building Mgr | F104: 1 | G104: 70000 | I104: =+F104*G104 -> 70000
E105: Leasing | F105: 0 | G105: 50000 | I105: =+F105*G105 -> 0 | K105: Staffing
E106: TOTAL PAYROLL | F106: =SUM(F100:F105) -> 3.5 | I106: =SUM(I100:I105) -> 220000 | J106: SVN | K106: Low | L106: High
I107: =+I106/F10 -> 1294.1176 | J107: Per Unit | K107: =+'[2]Typical Conv.Operating Expenses'!BW105 -> 600 | L107: =+'[2]Typical Conv.Operating Expenses'!BX105 -> 1138
I108: =+'[2]Typical Conv.Operating Expenses'!BS105 -> 800.02223 | J108: AVG Per Unit
I109: 1200 | J109: Staffing Cost Per Unit
G110: CMHC Staffing Benchmarks | J110: Use SVN - may include Mgmt staff
E111: ADJUST BASED ON TYPE/LOCATION | G111: =+G95 -> Ontario - Concrete | I111: =ROUND(+'[2]CMHC '!Q10*1.025*1.025*1.025,-1) -> 750 | J111: CMHC Benchmark (inflated to 2025)
G112: =+G96 -> Ontario - Wood Frame 12 units and more | I112: =ROUND(+'[2]CMHC '!Q9*1.025*1.025*1.025,-1) -> 600 | J112: CMHC Benchmark (inflated to 2025)
I113: =+'[2]Expense Comparison'!H15 -> 700 | J113: CMHC Update (Concrete)
D114: 4 | E114: INSURANCE
E115: Per Unit | F115: =+'[2]Typical Conv.Operating Expenses'!BW99 -> 300 | G115: =+'[2]Typical Conv.Operating Expenses'!BX99 -> 600
E116: Total Cost | F116: =+F115*$F$13 -> 51000 | G116: =+G115*$F$13 -> 102000
E117: AVG Cost | F117: 450
J118: Compare Marketing and Other Misc Costs to:
D119: 5 | E119: MARKETING | J119: OTHER COSTS (CMHC Benchmark) | L119: =+'[2]CMHC '!U9 -> 0.01
E120: Per Unit | F120: 100 | G120: =+'[2]Typical Conv.Operating Expenses'!BX106 -> 203 | L120: =+K28*L119 -> 63329.34 | M120: CMHC
E121: Total Cost | F121: =+F120*$F$13 -> 17000 | G121: =+G120*$F$13 -> 34510
...

Sheet 2. Rev 1B Exec Summary
J1: ="Currently running: "&CHOOSE('12. Sensitivity'!$E$8,'12. Sensitivity'!$B$11,'12. Sensitivity'!$B$12,'12. Sensitivity'!$B$13) -> Currently running: Base Case
B3: ='3. Headline #s'!A10 -> Apartment Development Model Reverse 1B
B4: ='3. Headline #s'!A12 -> 2240 Birchmount Road, Scarborough, ON
B5: Executive Summary
A8: OVERVIEW | G8: Worst | H8: Base | I8: Best
B9: Net Operating Income @ Stabilization at Completion | G9: =H9 -> 4899902.8 | H9: ='7. Op Rev and Exp'!H57 -> 4899902.8 | I9: =H9 -> 4899902.8
B10: Capitalization Rate | G10: ='12. Sensitivity'!H13 -> 0.0475 | H10: ='12. Sensitivity'!H10 -> 0.045 | I10: ='12. Sensitivity'!H12 -> 0.0425
B11: Valuation @ | D11: ='7. Op Rev and Exp'!D57 -> 4.4820546 | E11: per sqft average revenue | G11: =G9/G10 -> 1.0315585e+08 | H11: =H9/H10 -> 1.0888673e+08 | I11: =I9/I10 -> 1.1529183e+08
B12: Selling costs @ | D12: ='11. 10-Yr Cash Flow IRR'!E11 -> 0.01 | G12: =-'11. 10-Yr Cash Flow IRR'!$E$11*'2. Rev 1B Exec Summary'!G11 -> -1031558.5 | H12: =-'11. 10-Yr Cash Flow IRR'!$E$11*'2. Rev 1B Exec Summary'!H11 -> -1088867.3 | I12: =-'11. 10-Yr Cash Flow IRR'!$E$11*'2. Rev 1B Exec Summary'!I11 -> -1152918.3
B13: Sales Proceeds | G13: =SUM(G11:G12) -> 1.0212429e+08 | H13: =SUM(H11:H12) -> 1.0779786e+08 | I13: =SUM(I11:I12) -> 1.1413891e+08
B14: Total Costs | G14: =H14 -> -94440551 | H14: =-G48 -> -94440551 | I14: =H14 -> -94440551
B15: Profit before taxes if sold | G15: =SUM(G13:G14) -> 7683738.6 | H15: =SUM(H13:H14) -> 13357310 | I15: =SUM(I13:I14) -> 19698361
B17: Merchant Builder Return on Cost | G17: =-G15/G14 -> 0.081360586 | H17: =-H15/H14 -> 0.14143617 | I17: =-I15/I14 -> 0.20857948
B18: Merchant Builder IRR if sold upon stabilization | H18: ='10. Development Cash Flow'!G105 -> 0.27897087
B19: ="IRR "&'11. 10-Yr Cash Flow IRR'!A66&"-Year" -> IRR 10-Year | H19: ='11. 10-Yr Cash Flow IRR'!B67 -> 0.20617253
A21: SCHEDULE
G22: From | H22: To | I22: Months
B23: Land Purchase | G23: ='8. Schedule'!D13 -> 46069 | H23: ='8. Schedule'!E13 -> 46069 | I23: ='8. Schedule'!C13 -> 0
B24: Pre-Development | G24: ='8. Schedule'!D15 -> 46097 | H24: ='8. Schedule'!E15 -> 46462 | I24: ='8. Schedule'!C15 -> 12
B25: Construction period | G25: ='8. Schedule'!D17 -> 46493 | H25: ='8. Schedule'!E17 -> 47042 | I25: ='8. Schedule'!C17 -> 18
B26: Lease-up | G26: ='8. Schedule'!D19 -> 46981 | H26: ='8. Schedule'!E19 -> 47315 | I26: ='8. Schedule'!C19 -> 11.333333
B27: Stabilized | G27: ='8. Schedule'!D21 -> 47346 | H27: ='8. Schedule'!E21 -> 47346 | I27: ='8. Schedule'!C21 -> 0
A29: UNIT MIX
B30: Unit Type | E30: Sq. Ft. | F30: No. Units | G30: % of Total | H30: Rent | I30: $/SF
B31: ='7. Op Rev and Exp'!B16 -> 1 Bed | E31: ='7. Op Rev and Exp'!D16 -> 52416 | F31: ='7. Op Rev and Exp'!E16 -> 84 | G31: ='7. Op Rev and Exp'!F16 -> 0.49411765 | H31: ='7. Op Rev and Exp'!G16 -> 2490 | I31: ='7. Op Rev and Exp'!I16 -> 3.9903846
B32: ='7. Op Rev and Exp'!B17 -> 2 Bed | E32: ='7. Op Rev and Exp'!D17 -> 58167.2 | F32: ='7. Op Rev and Exp'!E17 -> 68 | G32: ='7. Op Rev and Exp'!F17 -> 0.4 | H32: ='7. Op Rev and Exp'!G17 -> 3155 | I32: ='7. Op Rev and Exp'!I17 -> 3.6883329
B33: Res 2B part | E33: ='7. Op Rev and Exp'!D19 -> 0 | F33: =+'7. Op Rev and Exp'!E19 -> 0 | G33: ='7. Op Rev and Exp'!F19 -> 0 | H33: ='7. Op Rev and Exp'!G19 -> 0 | I33: ='7. Op Rev and Exp'!I19 -> 0
B34: Total Res Units | E34: ='7. Op Rev and Exp'!D20 -> 128853.2 | F34: ='7. Op Rev and Exp'!E20 -> 170 | G34: ='7. Op Rev and Exp'!F20 -> 1 | H34: ='7. Op Rev and Exp'!G20 -> 2881.4706 | I34: =+H34/E35 -> 3.801613
B35: Average Res | E35: ='7. Op Rev and Exp'!D21 -> 757.96 | H35: ='7. Op Rev and Exp'!G21 -> 2881.4706 | I35: ='7. Op Rev and Exp'!I21 -> 3.801613
A37: DEVELOPMENT COSTS
G38: Total | H38: Per Res unit | I38: Per Sqft | J38: %
B39: Land | G39: ='9. Development Costs'!H16 -> 10407367 | H39: ='9. Development Costs'!I16 -> 61219.804 | I39: ='9. Development Costs'!J16 -> 80.769176 | J39: =G39/$G$48 -> 0.11020019
B40: Construction | G40: ='9. Development Costs'!H22 -> 65683716 | H40: ='9. Development Costs'!I22 -> 508814.41 | I40: ='9. Development Costs'!J22 -> 509.75619 | J40: =G40/$G$48 -> 0.69550331
B41: Professional Fees | G41: ='9. Development Costs'!H41 -> 2028467.7 | H41: ='9. Development Costs'!I41 -> 11932.163 | I41: ='9. Development Costs'!J41 -> 15.742471 | J41: =G41/$G$48 -> 0.021478779
B42: Development Management | G42: ='9. Development Costs'!H46 -> 1692804.6 | H42: ='9. Development Costs'!I46 -> 9957.6741 | I42: ='9. Development Costs'!J46 -> 13.137466 | J42: =G42/$G$48 -> 0.017924552
B43: Permits and Approvals | G43: ='9. Development Costs'!H59 -> 7449711.3 | H43: ='9. Development Costs'!I59 -> 43821.831 | I43: ='9. Development Costs'!J59 -> 57.815493 | J43: =G43/$G$48 -> 0.078882548
B44: Marketing and Leasing | G44: ='9. Development Costs'!H66 -> 1676350 | H44: ='9. Development Costs'!I66 -> 9860.8824 | I44: ='9. Development Costs'!J66 -> 13.009766 | J44: =G44/$G$48 -> 0.01775032
B45: Financing and Interest | G45: ='9. Development Costs'!H80-'9. Development Costs'!H77 -> 8970071.7 | H45: ='9. Development Costs'!I80 -> 52765.128 | I45: ='9. Development Costs'!J80 -> 69.61466 | J45: =G45/$G$48 -> 0.094981146
B46: Taxes, HST, VAT | G46: ='9. Development Costs'!H77 -> 0 | H46: ='9. Development Costs'!I77 -> 0 | I46: ='9. Development Costs'!J77 -> 0 | J46: =G46/$G$48 -> 0
B47: Operating income during lease-up incl Sec Deposit | G47: ='9. Development Costs'!H87 -> -3467937.3 | H47: ='9. Development Costs'!I87 -> -20399.631 | I47: ='9. Development Costs'!J87 -> -26.913862 | J47: =G47/$G$48 -> -0.03672085
B48: Total Development Costs | G48: ='9. Development Costs'!H89 -> 94440551 | H48: ='9. Development Costs'!I89 -> 555532.65 | I48: ='9. Development Costs'!J89 -> 732.93136 | J48: =SUM(J39:J47) -> 1
A51: CONSTRUCTION FINANCING
B52: Construction Loan | G52: =-'10. Development Cash Flow'!C107 -> 85000761 | H52: =G52/G54 -> 0.90004516
B53: Equity | G53: =+G48-G52 -> 9439789.8 | H53: =G53/G54 -> 0.099954836 | I53: (Total slightly diff from DCF)
B54: Total | G54: =SUM(G52:G53) -> 94440551 | H54: =SUM(H52:H53) -> 1
A56: PERMANENT FINANCING
B57: LTV ratio | G57: ='11. 10-Yr Cash Flow IRR'!L15 -> 0.84714676
B58: NOI Coverage | G58: ='11. 10-Yr Cash Flow IRR'!L16 -> 1.1081061
B59: Princpal Loan Value | G59: ='11. 10-Yr Cash Flow IRR'!K14 -> 92243039
B60: Annual Debt Service (including Principal) | G60: ='11. 10-Yr Cash Flow IRR'!K16 -> 4421871.7

Sheet 3. Headline #s
A5: =TODAY() -> 46069
A10: Apartment Development Model Reverse 1B
A12: ='1. 1A Proforma'!F3 -> 2240 Birchmount Road, Scarborough, ON
A14: ='2. Rev 1B Exec Summary'!F34&" Units" -> 170 Units
A17: Apartment Pro-forma
A20: Prepared by:
A22: SVN Rock Advisors Inc.
C26: HEADLINE NUMBERS
C28: NOI at stabilization after completion | G28: ='2. Rev 1B Exec Summary'!H9 -> 4899902.8
C29: Capitalization Rate | G29: ='2. Rev 1B Exec Summary'!H10 -> 0.045
C30: Valuation | D30: @ | E30: ='2. Rev 1B Exec Summary'!D11 -> 4.4820546 | F30: per sqft avg revenue | G30: ='2. Rev 1B Exec Summary'!H11 -> 1.0888673e+08
C31: Less: Selling costs | G31: ='2. Rev 1B Exec Summary'!H12 -> -1088867.3
C32: Sales Proceeds | G32: ='2. Rev 1B Exec Summary'!H13 -> 1.0779786e+08
C33: Total Cost | G33: ='2. Rev 1B Exec Summary'!H14 -> -94440551
C34: Profit before taxes if sold at stabilization | G34: ='2. Rev 1B Exec Summary'!H15 -> 13357310
C36: Return on cost | G36: ='2. Rev 1B Exec Summary'!H17 -> 0.14143617
C37: Development Yield | G37: =G28/(-G33) -> 0.051883462
A39: Merchant Builder | C39: Equity IRR, if sold upon stabilization | G39: ='2. Rev 1B Exec Summary'!H18 -> 0.27897087
A40: Investment Hold | C40: ="Equity IRR "&'11. 10-Yr Cash Flow IRR'!A66&"-Year" -> Equity IRR 10-Year | G40: ='2. Rev 1B Exec Summary'!H19 -> 0.20617253
C42: Construction Costs per unit | G42: ='9. Development Costs'!I89 -> 555532.65
C43: Construction Costs per sqft | G43: ='9. Development Costs'!J89 -> 732.93136
C44: Value per unit at stabilization | G44: =G30/'7. Op Rev and Exp'!E20 -> 640510.17
C45: Value per sqft at stabilization | G45: =G30/'9. Development Costs'!I10 -> 845.04481
A48: Disclaimer: RE: Use of the New Apartment Construction Financial Model
A49: SVN Rock Advisors Inc. Brokerage, Derek A. Lobo & Associates (DALA) and/or SVN Canada Inc. (herein described as "the Consultant") has developed the New Apartment Construction Financial Model (herein described as "the model") as a general guide to help a user understand the high level profitability of rental apartment construction development on a given site. The Model is developed in Microsoft Excel, and it is expected by the consultant, that the user of the model is proficient in Excel. Any accidental deletion of a cell may corrupt the entire file and/or show inaccurate results that the Consultant is not responsible for. The model is intended to provide a high level understanding of the profitability, and does not assure and/or guarantee success of a project in any way.
A50: Confidentiality Policy
A51: Intellecutal rights on this file remain with the Consultant
A52: Disclaimers:
A53: We make no guarantees and do not undertake to confirm independently that the information, result and or data provided is accurate or comprehensive. We recommend the client independently review data sources and periodically update and confirm the data used in the excel file.
A54: The consultant's principals, management, staff, contractors and associates are real estate consultants only.
A55: The Consultant makes no guarantees, written or otherwise, that if the client adopts or acts on the excel model's observations, findings, analysis or recommendations in the report that the client's project will be successful, nor do we, as real estate consultants, accept any legal or financial responsibility or liability for failure, under-performance, or termination of the client's project.
A56: Limitation of Liability:
A57: To the fullest extent permitted by applicable law, in no event shall the consultant be liable to the client or any other user for any direct, indirect, incidental, special, punitive, or consequential damages whatsoever resulting from any (i) use of the excel file, (ii) errors, mistakes, or inaccuracies of content, (iii) any bugs, viruses, or like, which may be transmitted to or through the excel file to or by any party, (iv) any loss of your data or content, (v) any errors or omissions in any content or for any loss or damage of any kind incurred as a result of your use of the file, whether based on warranty, contract, tort, or any other legal theory, and whether or not the client/users are advised of the possibility of such damanges, and/or (vi) the disclosure of information pursuant to these terms of use or a privacy policy.
A58: Despite the above, our total liability to you for any cause of action you take against us will at all times be limited to no more than $100/ - (one hundred dollars)

Sheet 4. Area Schedule
A1: AREA SCHEDULE
A2: 2240 Birchmount Road, Scarborough, Ontario
A4: # | B4: Description | C4: Quantity | D4: Unit Area (SF) | E4: Total Area (SF) | F4: Notes
A5: 1 | B5: RESIDENTIAL AREAS
A6: 1.1 | B6: Residential Units
B7: 1 Bedroom Units | C7: 84 | D7: 624 | E7: =C7*D7 -> 52416 | F7: 49% of total units
B8: 2 Bedroom Units | C8: 68 | D8: 855 | E8: =C8*D8 -> 58140 | F8: 40% of total units
B9: 3 Bedroom Units | C9: 18 | D9: 1015 | E9: =C9*D9 -> 18270 | F9: 11% of total units
B10: Total Residential Units | C10: =SUM(C7:C9) -> 170 | D10: =SUMPRODUCT(C7:C9,D7:D9)/C10 -> 757.8 | E10: =SUM(E7:E9) -> 128826 | F10: Net Rentable Area
A12: 2 | B12: AMENITY & COMMON AREAS
A13: 2.1 | B13: Resident Amenities
B14: Fitness Centre | C14: 1 | D14: 1200 | E14: 1200 | F14: Cardio & weights
B15: Multi-Purpose/Party Room | C15: 1 | D15: 1000 | E15: 1000 | F15: Events & gatherings
B16: Co-Working Space | C16: 1 | D16: 600 | E16: 600 | F16: Work from home area
B17: Games/Lounge Area | C17: 1 | D17: 500 | E17: 500 | F17: Recreation space
B18: Outdoor Terrace/BBQ Area | C18: 1 | D18: 403 | E18: 403 | F18: Rooftop or ground level
B19: Total Amenity Space | E19: =SUM(E14:E18) -> 3703 | F19: As per proforma
A21: 2.2 | B21: Building Common Areas
B22: Main Lobby | C22: 1 | D22: 600 | E22: 800 | F22: With concierge desk
B23: Corridors & Hallways | C23: 170 | D23: 25 | E23: =C23*D23 -> 4250 | F23: Per unit average
B24: Elevator Lobbies | C24: 6 | D24: 60 | E24: =C24*D24 -> 360 | F24: Per floor (15 floors)
B25: Stairwells (2) | C25: 2 | D25: 600 | E25: =C25*D25 -> 1200 | F25: Exit stairs
B26: Elevators (3) | C26: 3 | D26: 60 | E26: =C26*D26 -> 180 | F26: Passenger elevators
B27: Mail/Parcel Room | C27: 3 | D27: 150 | E27: 300 | F27: Package lockers
B28: Garbage/Recycling Rooms | C28: 4 | D28: 200 | E28: =C28*D28 -> 800 | F28: Per floor grouping
B29: Electrical/Mechanical Rooms | C29: 2 | D29: 200 | E29: =C29*D29 -> 400 | F29: Service rooms
B30: Storage Lockers | C30: 85 | D30: 25 | E30: =C30*D30 -> 2125 | F30: Resident storage
B31: Janitor/Housekeeping Closets | C31: 3 | D31: 40 | E31: =C31*D31 -> 120 | F31: Per floor grouping
B32: Total Common Areas | E32: =SUM(E22:E31) -> 10535
A34: 3 | B34: COMMERCIAL AREAS
B35: Ground Floor Retail | C35: 1 | D35: 4370 | E35: 4370 | F35: Net leasable area
A37: 4 | B37: PARKING & BACK OF HOUSE
A38: 4.1 | B38: Parking
B39: Underground Parking | C39: 162 | D39: 350 | E39: =C39*D39 -> 56700 | F39: Resident parking
B40: Visitor Parking | C40: 15 | D40: 350 | E40: =C40*D40 -> 5250 | F40: Surface/underground
B41: Retail Parking | C41: 15 | D41: 350 | E41: =C41*D41 -> 5250 | F41: Dedicated retail
B42: Total Parking Area | C42: =SUM(C39:C41) -> 192 | E42: =SUM(E39:E41) -> 67200
A44: 4.2 | B44: Back of House
B45: Loading Dock | C45: 1 | D45: 300 | E45: 500 | F45: Service area
B46: Building Management Office | C46: 1 | D46: 150 | E46: 200 | F46: Admin space
B47: Security Office | C47: 1 | D47: 100 | E47: 150 | F47: Monitoring station
B48: Maintenance Workshop | C48: 1 | D48: 200 | E48: 300 | F48: Tools & supplies
B49: Mechanical Penthouse | C49: 1 | D49: 400 | E49: 2000 | F49: HVAC equipment
B50: Total Back of House | E50: =SUM(E45:E49) -> 3150
B53: BUILDING SUMMARY
B54: Net Residential Area | E54: =E10 -> 128826 | F54: From proforma
B55: Total Amenity Space | E55: =E19 -> 3703 | F55: From proforma
B56: Total Common Areas | E56: =E32 -> 10535 | F56: Calculated to match GFA
B57: Commercial/Retail Area | E57: =E35 -> 4370 | F57: From proforma
B58: Parking Area (below grade) | E58: =E42 -> 67200 | F58: Not included in GFA
B59: Back of House Area | E59: =E50 -> 3150 | F59: Calculated to match GFA
B60: TOTAL GROSS FLOOR AREA (GFA) | E60: =E54+E55+E56+E57+E59 -> 150584 | F60: Calculated total
B63: VERIFICATION
B64: Target GFA (from proforma) | E64: 146346 | F64: Reference
B65: Calculated GFA | E65: =E60 -> 150584 | F65: From schedule above
B66: Variance | E66: =E65-E64 -> 4238 | F66: Should be minimal

Sheet 5. Key Assumptions
B3: =+'3. Headline #s'!$A$10 -> Apartment Development Model Reverse 1B
B4: =+'3. Headline #s'!A12 -> 2240 Birchmount Road, Scarborough, ON
B6: KEY ASSUMPTIONS
B8: 1. Development Schedule
C10: Project Start Date: | G10: =TODAY() -> 46069
E11: Duration | F11: Offset
C12: Land Purchase | E12: 0
C13: Pre-Development | E13: 12
C14: Construction | E14: 18
C15: Lease-up | E15: ='7. Op Rev and Exp'!E20/15 -> 11.333333 | F15: -3
C16: Stabilized | E16: 0
B18: 2. Building Area Schedule Summary
C20: Net Residential Area | F20: ='4. Area Schedule'!E54 -> 128826 | H20: ='4. Area Schedule'!F54 -> From proforma
C21: Total Amenity Space | F21: ='4. Area Schedule'!E55 -> 3703 | H21: ='4. Area Schedule'!F55 -> From proforma
C22: Total Common Areas | F22: ='4. Area Schedule'!E56 -> 10535 | H22: ='4. Area Schedule'!F56 -> Calculated to match GFA
C23: Commercial/Retail Area | F23: ='4. Area Schedule'!E57 -> 4370 | H23: ='4. Area Schedule'!F57 -> From proforma
C24: Parking Area (below grade) | F24: ='4. Area Schedule'!E58 -> 67200 | H24: ='4. Area Schedule'!F58 -> Not included in GFA
C25: Back of House Area | F25: ='4. Area Schedule'!E59 -> 3150 | H25: ='4. Area Schedule'!F59 -> Calculated to match GFA
C26: TOTAL GROSS FLOOR AREA (GFA) | F26: =SUM(F20:F25)-F24 -> 150584 | H26: ='4. Area Schedule'!F60 -> Calculated total
C28: Res No. of Units | F28: ='7. Op Rev and Exp'!E20 -> 170
C29: Building Number of Floors | F29: ='13. Altus Cost Guide 25'!A7 -> 13-39 Storeys | H29: TBC
B32: 2. Development Cost
D34: Cap Rate | E34: % of Value | F34: Numbers | G34: Rentable/SF | H34: Numbers on | I34: % of Value | J34: Rentable/SF
D35: Running | E35: Today | F35: Today | G35: ='7. Op Rev and Exp'!D20 -> 128853.2 | H35: Completion | I35: on Compl | J35: =+G35 -> 128853.2
C36: Value | D36: ='7. Op Rev and Exp'!D56 -> 0.045 | E36: 1 | F36: =+'7. Op Rev and Exp'!H56 -> 1.026064e+08 | G36: =+F36/$G$35 -> 796.3046 | H36: =+'3. Headline #s'!G30 -> 1.0888673e+08 | I36: 1 | J36: =+H36/$J$35 -> 845.04481
C37: Profit (bef commission) | E37: 0.08 | F37: =+F36*E37 -> 8208511.7 | G37: =+F37/$G$35 -> 63.704368 | H37: =+'3. Headline #s'!G34-'3. Headline #s'!G31 -> 14446177 | I37: =+H37/H36 -> 0.13267161 | J37: =+H37/$J$35 -> 112.11346
C38: Total Development Cost | E38: =+E36-E37 -> 0.92 | F38: =+F36*E38 -> 94397884 | G38: =+F38/$G$35 -> 732.60023 | H38: =-'3. Headline #s'!G33 -> 94440551 | I38: =+H38/H36 -> 0.86732839 | J38: =+H38/$J$35 -> 732.93136
G39: * | J39: *
C40: * Net Res Rentable PSF
E41: % of Total | G41: PSF of
E42: Devpt Cost | F42: Amount | G42: Res Rentable
B43: A | C43: Land
C44: Land Purchase | E44: =+E37+0.025 -> 0.105 | F44: =+F38*E44 -> 9911777.9 | G44: =+F44/$G$35 -> 76.923024
C45: Closing & Contingency (% of Land) | D45: 0.05 | F45: =F44*D45 -> 495588.89 | G45: =+F45/$G$35 -> 3.8461512 | M45: Hard Cost Calc
O46: Altus Cost/SF | Q46: Total Cost
B47: B | C47: Construction | N47: SF | O47: Low | P47: High | Q47: Low | R47: High | S47: Average
C48: Hard Cost | E48: =F48/F38 -> 0.68217419 | F48: =S50 -> 64395800 | G48: =+F48/$G$35 -> 499.76097 | M48: GFA | N48: =F26 -> 150584 | O48: ='13. Altus Cost Guide 25'!H7 -> $310 | P48: ='13. Altus Cost Guide 25'!I7 -> $340 | Q48: =O48*N48 -> 46681040 | R48: =P48*N48 -> 51198560 | S48: =(Q48+R48)/2 -> 48939800
C49: Contingency (% of HC) | D49: 0.02 | F49: =F48*D49 -> 1287916 | G49: =+F49/$G$35 -> 9.9952194 | M49: Parking (below grade) | N49: =F24 -> 67200 | O49: ='13. Altus Cost Guide 25'!F38 -> $175 | P49: ='13. Altus Cost Guide 25'!G38 -> $285 | Q49: =O49*N49 -> 11760000 | R49: =P49*N49 -> 19152000 | S49: =(Q49+R49)/2 -> 15456000
M50: Total | Q50: =Q48+Q49 -> 58441040 | R50: =R48+R49 -> 70350560 | S50: =(Q50+R50)/2 -> 64395800
B51: C | C51: Professional Fees (% of HC) | D51: 0.03 | E51: =F51/F38 -> 0.020465226 | F51: =F48*D51 -> 1931874 | G51: =+F51/$G$35 -> 14.992829 | M51: Hard Cost - Proforma | S51: =F48 -> 64395800
C52: Prof Fees Contingency (% of Prof Fees) | D52: 0.05 | F52: =F51*D52 -> 96593.7 | G52: =+F52/$G$35 -> 0.74964145 | M52: Difference | S52: =S51-S50 -> 0
S53: =S52/S50 -> 0
B54: D | C54: Development Management (% of HC/PF) | D54: 0.025 | E54: =F54/F38 -> 0.017932654 | F54: =SUM(F48:F52)*D54 -> 1692804.6 | G54: =+F54/$G$35 -> 13.137466
M55: Development Charges Calc**
B56: E | C56: Permits and Approvals | E56: =F56/F38 -> 0.076189271 | F56: =S60 -> 7192106 | G56: =+F56/$G$35 -> 55.816278 | Q56: # of units | R56: DC/Unit | S56: Cost
C57: Permits and Approvals Contingency | D57: 0.05 | F57: =F56*D57 -> 359605.3 | G57: =+F57/$G$35 -> 2.7908139 | M57: ='7. Op Rev and Exp'!B16 -> 1 Bed | Q57: ='7. Op Rev and Exp'!E16 -> 84 | R57: 34849 | S57: =Q57*R57 -> 2927316
C58: Sub Meter Installation Fee Credit | D58: 600 | E58: per unit | F58: =-D58*F28 -> -102000 | M58: ='7. Op Rev and Exp'!B17 -> 2 Bed | Q58: ='7. Op Rev and Exp'!E17 -> 68 | R58: 50248 | S58: =Q58*R58 -> 3416864
M59: ='7. Op Rev and Exp'!B18 -> 3 Bed | Q59: ='7. Op Rev and Exp'!E18 -> 18 | R59: 47107 | S59: =Q59*R59 -> 847926
B60: F | C60: Marketing and Leasing | M60: Total | Q60: =SUM(Q57:Q59) -> 170 | S60: =SUM(S57:S59) -> 7192106
C61: Comission & Incentive | D61: 1.5 | E61: months of | F61: =('7. Op Rev and Exp'!H32+'7. Op Rev and Exp'!H29)/12*D61 -> 838175 | G61: =+F61/$G$35 -> 6.5048831 | M61: Permits Cost - Proforma | S61: =F56 -> 7192106
C62: Marketing | D62: 1.5 | E62: revenue | F62: =F61 -> 838175 | G62: =+F62/$G$35 -> 6.5048831 | M62: Difference | S62: =S61-S60 -> 0
C63: Total | E63: =+F63/F38 -> 0.017758343 | F63: =+F61+F62 -> 1676350 | G63: =+F63/$G$35 -> 13.009766 | S63: =S62/S60 -> 0
M64: ** Note: since model is mainly merchant builder the DCs are assumed paid in full
M65: on completion. If the builder wants to hold then the DCs are payable in 6 installments,
C66: Development Financing Assumptions | F66: Financing | M66: with exception of some component of the charges.
C67: Equity | E67: =1-E70-E69 -> 0.1 | F67: =+$F$38*E67 -> 9439788.4
G68: Base Int Rate | I68: Prime Rate | J68: Plus Margin
C69: Mezanine Debt | E69: 0.15 | F69: =+$F$38*E69 -> 14159683 | G69: =I69+J69 -> 0.0795 | I69: 0.0445 | J69: 0.035
C70: Regular Debt | E70: 0.75 | F70: =+$F$38*E70 -> 70798413 | G70: =I70+J70 -> 0.0545 | I70: 0.0445 | J70: 0.01
C71: Total Debt | E71: =+E69+E70 -> 0.9 | F71: =+F69+F70 -> 84958096 | G71: =+'6. Debt Stack & Financing'!D20 -> 0.058666667
B73: G | C73: Interest Cost & Fees | F73: =+'9. Development Costs'!H78 -> 7695700.3
C74: Financing Fees | D74: 0.01 | E74: of Debt | F74: =+F71*D74 -> 849580.96
C75: Financing Contingency | D75: 0.005 | E75: of Debt | F75: =+F71*D75 -> 424790.48
C76: Total Financing Cost | E76: =+F76/$F$38 -> 0.095024076 | F76: =SUM(F73:F75) -> 8970071.7 | G76: =+F76/$G$35 -> 69.61466
C77: HST | E77: =+F77/$F$38 -> 0 | F77: =+'9. Development Costs'!H77 -> 0 | G77: =+F77/$G$35 -> 0 | H77: No HST payable under self supply rule, except in Quebec
C78: Total Financing & HST | E78: =+F78/$F$38 -> 0.095024076 | F78: =+F76+F77 -> 8970071.7 | G78: =+F78/$G$35 -> 69.61466
C81: Total Development Cost | F81: =SUM(F44:F58)+F63+F78 -> 97908488 | G81: =+F81/$G$35 -> 759.84522
B82: H | C82: Operating Income During Lease up | F82: =+'9. Development Costs'!H87 -> -3467937.3 | G82: =+F82/$G$35 -> -26.913862
B83: I | C83: Net Development Cost Model | F83: =+F81+F82 -> 94440551 | G83: =+F83/$G$35 -> 732.93136
C84: Dev Cost High Level | F84: =F38 -> 94397884
C85: Difference | F85: =F83-F84 -> 42666.477
D86: Ok if below 1% | F86: =F85/F83 -> 0.00045178132
B88: 3. Land Assumption / KPIs Check
B89: 1 | C89: If the land is not already purchased, then in this model Land cost is determined as a resdidual value based
C90: on the desired profit based on today's project value at the cap rate input into the model.
B92: 2 | C92: Land Cost in the model is based on, as : | D92: =E44 -> 0.105 | E92: of Development Cost assuming the land is not purchased.
D93: ….................. | E93: Actual Purchase Cost of Land on hand
C95: Merchant Builder
B96: 3 | C96: Project's Equity IRR if Sold on Completion | F96: ='3. Headline #s'!G39 -> 0.27897087 | H96: Acceptable (good if 20%~)
B97: 4 | C97: Project's Return on Cost if sold on completion | F97: ='3. Headline #s'!G36 -> 0.14143617 | H97: Acceptable
C99: Investment Hold
B100: 5 | C100: Project's Development Yield | F100: ='3. Headline #s'!G37 -> 0.051883462
B101: 5.1 | C101: Cap Rate running | F101: ='3. Headline #s'!G29 -> 0.045
C102: Spread | F102: =(F100-F101)*100 -> 0.68834625 | H102: Over 1% is better
B104: 6 | C104: Project's 10 Year Equity IRR | F104: ='3. Headline #s'!G40 -> 0.20617253

Sheet 6. Debt Stack & Financing
I1: ='2. Rev 1B Exec Summary'!J1 -> Currently running: Base Case
B4: ='2. Rev 1B Exec Summary'!B3:I3 -> Apartment Development Model Reverse 1B
B5: ='2. Rev 1B Exec Summary'!B4:I4 -> 2240 Birchmount Road, Scarborough, ON
B8: DEBT STACK & FINANCING ASSUMPTIONS
B11: Blended Construction Interest Rate Calucator
E12: Int Rate | F12: Component Int
B13: Total Equity | D13: =+'10. Development Cash Flow'!D108 -> 0.099954838
B14: Total Debt | D14: =1-D13 -> 0.90004516
B16: Total Debt | D16: =+'5. Key Assumptions'!E71 -> 0.9
B17: Mezannine Debt | D17: =+'5. Key Assumptions'!E69 -> 0.15 | E17: ='5. Key Assumptions'!G69 -> 0.0795 | F17: =+D17*E17 -> 0.011925
B18: Regular Bank Debt | D18: =+D16-D17 -> 0.75 | E18: ='5. Key Assumptions'!G70 -> 0.0545 | F18: =+D18*E18 -> 0.040875
B19: Total Debt | D19: =D17+D18 -> 0.9 | F19: =+F17+F18 -> 0.0528
B20: Blended Construction Interest Rate | D20: =+F19/D19 -> 0.058666667
B23: Note 1: Double check the Total Debt Ratio from DCF page.
B24: 2: Client to confirm if Mezannine Debt, otherwise take 0%
B27: CMHC Permanent Take-Out Loan Assumptions
B29: CMHC - MLI Select Program :
B31: Loan to Value Ratio | D31: 0.95
B32: DSCR | D32: 1.1
B33: Amortization | D33: 40 | E33: Years, can go higher
B34: Interest Rate | D34: 0.037
B35: CMHC Premium Cost | D35: 0.0518
B37: Value @ Cap Rate Running | C37: ='11. 10-Yr Cash Flow IRR'!K10 -> 0.045 | D37: ='11. 10-Yr Cash Flow IRR'!K11 -> 1.0888673e+08
B38: Loan Amount | D38: ='11. 10-Yr Cash Flow IRR'!K14 -> 92243039
B39: LTV Ratio | D39: =D38/D37 -> 0.84714676
B40: CMHC Premium Amount | D40: =D38*D35 -> 4778189.4
B42: Stabilized NOI | D42: ='11. 10-Yr Cash Flow IRR'!K9 -> 4899902.8
B43: Annual Debt Service | D43: ='11. 10-Yr Cash Flow IRR'!K16 -> 4421871.7
B44: DSCR | D44: =D42/D43 -> 1.1081061

Sheet 7. Op Rev and Exp
I1: ="Currently running: "&CHOOSE('12. Sensitivity'!$E$8,'12. Sensitivity'!$B$11,'12. Sensitivity'!$B$12,'12. Sensitivity'!$B$13) -> Currently running: Base Case
B3: ='3. Headline #s'!A10 -> Apartment Development Model Reverse 1B
B4: ='3. Headline #s'!A12 -> 2240 Birchmount Road, Scarborough, ON
B5: Operating Revenue and Expenses
B8: Parking
B9: Residential Stalls | D9: =C24 -> 162
B10: Visitor Stalls | D10: =C25 -> 15
B11: Extra Stalls | D11: =C26 -> 15
B12: Total | D12: =SUM(D9:D11) -> 192 | F12: Ratio | G12: =(D9+D10)/E20 -> 1.0411765 | H12: stall per Res unit
B14: Revenue
B15: Residential | C15: Avg Sq Ft | D15: Total Area | E15: No. Units | F15: % Total | G15: Monthly $ | H15: Annual $ | I15: $/Sqft
B16: ='1. 1A Proforma'!D7 -> 1 Bed | C16: ='1. 1A Proforma'!E7 -> 624 | D16: =+C16*E16 -> 52416 | E16: ='1. 1A Proforma'!F7 -> 84 | F16: =E16/$E$20 -> 0.49411765 | G16: ='1. 1A Proforma'!I7 -> 2490 | H16: =+G16*E16*12 -> 2509920 | I16: =H16/D16/12 -> 3.9903846
B17: ='1. 1A Proforma'!D8 -> 2 Bed | C17: ='1. 1A Proforma'!E8 -> 855.4 | D17: =+C17*E17 -> 58167.2 | E17: ='1. 1A Proforma'!F8 -> 68 | F17: =E17/$E$20 -> 0.4 | G17: ='1. 1A Proforma'!I8 -> 3155 | H17: =+G17*E17*12 -> 2574480 | I17: =H17/D17/12 -> 3.6883329
B18: ='1. 1A Proforma'!D9 -> 3 Bed | C18: ='1. 1A Proforma'!E9 -> 1015 | D18: =+C18*E18 -> 18270 | E18: ='1. 1A Proforma'!F9 -> 18 | F18: =E18/$E$20 -> 0.10588235 | G18: ='1. 1A Proforma'!I9 -> 3675 | H18: =+G18*E18*12 -> 793800 | I18: =H18/D18/12 -> 3.6206897
L19: Sensitize Rent - S2 | M19: ='14. Sensitivity 2'!D6 -> 1
B20: Total | C20: =+D20/E20 -> 757.96 | D20: =SUM(D16:D19) -> 128853.2 | E20: =SUM(E16:E19) -> 170 | F20: =SUM(F16:F19) -> 1 | G20: =+H20/12/E20 -> 2881.4706 | H20: =SUM(H16:H19)*M19 -> 5878200 | I20: =H20/D20/12 -> 3.801613 | L20: =H20 -> 5878200
B21: Average Res | D21: =(D16+D17+D19+D18)/E20 -> 757.96 | G21: =(H16+H17+H18+H19)/(E16+E17+E18+E19)/12 -> 2881.4706 | I21: =G21/D21 -> 3.801613 | L21: =H20-L20 -> 0
B23: Other Income | C23: # Spaces | D23: Monthly Fee | E23: Annual/Res Unit | F23: Monthly/Res Unit | G23: Monthly | H23: Annual $
B24: Underground Parking | C24: ='1. 1A Proforma'!F18 -> 162 | D24: ='1. 1A Proforma'!G18 -> 200 | E24: =H24/$E$20 -> 2287.0588 | F24: =G24/$E$20 -> 190.58824 | G24: =D24*C24 -> 32400 | H24: =G24*12 -> 388800
B25: Visitor Parking | C25: ='1. 1A Proforma'!F19 -> 15 | D25: ='1. 1A Proforma'!G19 -> 0 | E25: =H25/$E$20 -> 0 | F25: =G25/$E$20 -> 0 | G25: =D25*C25 -> 0 | H25: =G25*12 -> 0
B26: Retail Parking | C26: ='1. 1A Proforma'!F20 -> 15 | D26: ='1. 1A Proforma'!G20 -> 0 | E26: =H26/$E$20 -> 0 | F26: =G26/$E$20 -> 0 | G26: =D26*C26 -> 0 | H26: =G26*12 -> 0
B27: Storage Lockers | C27: ='1. 1A Proforma'!F21 -> 100 | D27: ='1. 1A Proforma'!G21 -> 40 | E27: =H27/$E$20 -> 282.35294 | F27: =G27/$E$20 -> 23.529412 | G27: =D27*C27 -> 4000 | H27: =G27*12 -> 48000
B28: Submetering Reimbursement | C28: ='1. 1A Proforma'!F22 -> 170 | D28: ='1. 1A Proforma'!G22 -> 20 | E28: =H28/$E$20 -> 240 | F28: =G28/$E$20 -> 20 | G28: =D28*C28 -> 3400 | H28: =G28*12 -> 40800
B29: Commercial / Retail | C29: ='1. 1A Proforma'!F26 -> 4370 | D29: ='1. 1A Proforma'!G26 -> 40 | G29: =H29/12 -> 14566.667 | H29: =C29*D29 -> 174800
B30: Total Other Income | G30: =SUM(G24:G29) -> 54366.667 | H30: =SUM(H24:H29) -> 652400
B32: Total Potential Gross Revenue (including parking & storage) | G32: =H32/12 -> 544216.67 | H32: =H30+H20 -> 6530600
B33: Vacancies (Rent & Others) | C33: ='1. 1A Proforma'!F24 -> 0.03 | G33: =H33/12 -> 16326.5 | H33: =H32*C33 -> 195918
B34: Effective Gross Income | G34: =G32-G33 -> 527890.17 | H34: =H32-H33 -> 6334682
B37: Operating Expenses
E38: Annual/Unit | F38: Monthly Per Unit | G38: Monthly | H38: Total Annual | I38: %
B39: Utilities (Common Area Only) | C39: ='1. 1A Proforma'!F31 -> 170 | D39: ='1. 1A Proforma'!G31 -> units @ | E39: ='1. 1A Proforma'!H31 -> 1130 | F39: =G39/C39 -> 94.166667 | G39: =H39/12 -> 16008.333 | H39: =E39*C39*M39 -> 192100 | I39: =H39/$H$34 -> 0.030325121 | L39: Sensitize Op Cost - S2 | M39: =+'14. Sensitivity 2'!$D$8 -> 1
B40: Repairs & Maintenance | C40: ='1. 1A Proforma'!F32 -> 170 | D40: ='1. 1A Proforma'!G32 -> units @ | E40: ='1. 1A Proforma'!H32 -> 1050 | F40: =G40/C40 -> 87.5 | G40: =H40/12 -> 14875 | H40: =E40*C40*M40 -> 178500 | I40: =H40/$H$34 -> 0.02817821 | L40: Sensitize Op Cost - S2 | M40: =+M39 -> 1
B41: Staffing | C41: ='1. 1A Proforma'!F33 -> 170 | D41: ='1. 1A Proforma'!G33 -> units @ | E41: ='1. 1A Proforma'!H33 -> 1200 | F41: =G41/C41 -> 100 | G41: =H41/12 -> 17000 | H41: =E41*C41*M41 -> 204000 | I41: =H41/$H$34 -> 0.032203669 | L41: Sensitize Op Cost - S2 | M41: =+M40 -> 1
B42: Insurance | C42: ='1. 1A Proforma'!F34 -> 170 | D42: ='1. 1A Proforma'!G34 -> units @ | E42: ='1. 1A Proforma'!H34 -> 450 | F42: =G42/C42 -> 37.5 | G42: =H42/12 -> 6375 | H42: =E42*C42*M42 -> 76500 | I42: =H42/$H$34 -> 0.012076376 | L42: Sensitize Op Cost - S2 | M42: =+M41 -> 1
B43: Marketing | C43: ='1. 1A Proforma'!F35 -> 170 | D43: ='1. 1A Proforma'!G35 -> units @ | E43: ='1. 1A Proforma'!H35 -> 300 | F43: =G43/C43 -> 25 | G43: =H43/12 -> 4250 | H43: =E43*C43*M43 -> 51000 | I43: =H43/$H$34 -> 0.0080509172 | L43: Sensitize Op Cost - S2 | M43: =+M42 -> 1
B44: General & Admin | C44: ='1. 1A Proforma'!F36 -> 170 | D44: ='1. 1A Proforma'!G36 -> units @ | E44: ='1. 1A Proforma'!H36 -> 250 | F44: =G44/C44 -> 20.833333 | G44: =H44/12 -> 3541.6667 | H44: =E44*C44*M44 -> 42500 | I44: =H44/$H$34 -> 0.0067090976 | L44: Sensitize Op Cost - S2 | M44: =+M43 -> 1
B45: Management Fee | C45: ='1. 1A Proforma'!F37 -> % of Gross Revenue | D45: ='1. 1A Proforma'!G37 -> 0.0425 | E45: =H45/C44 -> 1583.6705 | F45: =G45/C44 -> 131.97254 | G45: =H45/12 -> 22435.332 | H45: =H34*D45*M45 -> 269223.99 | I45: =H45/$H$34 -> 0.0425 | L45: Sensitize Op Cost - S2 | M45: =+M44 -> 1
B46: Property Taxes (Municipal Rate)* | C46: ='1. 1A Proforma'!F38 -> 0.00754087 | D46: ='1. 1A Proforma'!G38 -> 450000 | E46: =H46/$E$20 -> 3393.3915 | F46: =G46/$E$20 -> 282.78262 | G46: =H46/12 -> 48073.046 | H46: =C46*D46*E20*M46 -> 576876.55 | I46: =H46/$H$34 -> 0.091066379 | L46: Sensitize Op Cost - S2 | M46: =+M45 -> 1
B47: Reserve for Asset Replacement | C47: ='1. 1A Proforma'!F39 -> % of Gross Revenue | D47: ='1. 1A Proforma'!G39 -> 0.02 | E47: =H47/$E$20 -> 745.25671 | F47: =G47/$E$20 -> 62.104725 | G47: =H47/12 -> 10557.803 | H47: =D47*H34*M47 -> 126693.64 | I47: =H47/$H$34 -> 0.02 | L47: Sensitize Op Cost - S2 | M47: =+M46 -> 1
B48: Total Expenses | E48: =SUM(E39:E47) -> 10102.319 | F48: =SUM(F39:F47) -> 841.85989 | G48: =H48/12 -> 143116.18 | H48: =SUM(H39:H47) -> 1717394.2 | I48: =H48/$H$34 -> 0.27110977
B49: Operating Expenses Varience | H49: ='12. Sensitivity'!H30 -> 0 | L49: 1717394.2
B50: Operating Expenses | H50: =(1+H49)*H48 -> 1717394.2 | L50: =H48-L49 -> 0
B51: Operating Expenses/Revenue | H51: =H50/H34 -> 0.27110977
B53: Net Operating Income and Valuation
B55: NOI Today | C55: @ | D55: =I20 -> 3.801613 | E55: per sqft average res revenue | H55: =H34-H50 -> 4617287.8
B56: Valuation today | C56: @ | D56: ='12. Sensitivity'!H10 -> 0.045 | E56: Cap rate | F56: =H56/E20 -> 603567.04 | G56: Total | H56: =H55/D56 -> 1.026064e+08
B57: NOI at Stabilization | C57: @ | D57: =(MAX('10. Development Cash Flow'!I23:CZ23)*12)/D20/12 -> 4.4820546 | E57: per sqft average revenue | H57: =MAX('10. Development Cash Flow'!I26:CZ26)*12 -> 4899902.8
B58: Valuation @ Stabilization | C58: @ | D58: ='12. Sensitivity'!H10 -> 0.045 | E58: Cap rate | F58: =H58/E20 -> 640510.17 | G58: Total | H58: =H57/D58 -> 1.0888673e+08

Sheet 8. Schedule
BP1: ="Currently running: "&CHOOSE('12. Sensitivity'!$E$8,'12. Sensitivity'!$B$11,'12. Sensitivity'!$B$12,'12. Sensitivity'!$B$13) -> Currently running: Base Case
B3: ='3. Headline #s'!A10 -> Apartment Development Model Reverse 1B
B4: ='3. Headline #s'!A12 -> 2240 Birchmount Road, Scarborough, ON
B5: Schedule
B8: Project Start Date | D8: ='5. Key Assumptions'!G10 -> 46069
I10: =D8 -> 46069 | J10: =EDATE(I10,1) -> 46097 | K10: =EDATE(J10,1) -> 46128 | L10: =EDATE(K10,1) -> 46158 | M10: =EDATE(L10,1) -> 46189 | N10: =EDATE(M10,1) -> 46219 | O10: =EDATE(N10,1) -> 46250 | P10: =EDATE(O10,1) -> 46281 | Q10: =EDATE(P10,1) -> 46311 | ... BP10: =EDATE(BO10,1) -> 47864
C11: Duration | D11: Start Date | E11: End Date | F11: Anchored to | G11: Offset | I11: ="Q"&ROUNDUP(MONTH(I10)/3,0)&" "&YEAR(I10) -> Q1 2026 | L11: ="Q"&ROUNDUP(MONTH(L10)/3,0)&" "&YEAR(L10) -> Q2 2026 | O11: ="Q"&ROUNDUP(MONTH(O10)/3,0)&" "&YEAR(O10) -> Q3 2026 | R11: ="Q"&ROUNDUP(MONTH(R10)/3,0)&" "&YEAR(R10) -> Q4 2026 | U11: ="Q"&ROUNDUP(MONTH(U10)/3,0)&" "&YEAR(U10) -> Q1 2027 | X11: ="Q"&ROUNDUP(MONTH(X10)/3,0)&" "&YEAR(X10) -> Q2 2027 | AA11: ="Q"&ROUNDUP(MONTH(AA10)/3,0)&" "&YEAR(AA10) -> Q3 2027 | AD11: ="Q"&ROUNDUP(MONTH(AD10)/3,0)&" "&YEAR(AD10) -> Q4 2027 | AG11: ="Q"&ROUNDUP(MONTH(AG10)/3,0)&" "&YEAR(AG10) -> Q1 2028 | AJ11: ="Q"&ROUNDUP(MONTH(AJ10)/3,0)&" "&YEAR(AJ10) -> Q2 2028 | AM11: ="Q"&ROUNDUP(MONTH(AM10)/3,0)&" "&YEAR(AM10) -> Q3 2028 | AP11: ="Q"&ROUNDUP(MONTH(AP10)/3,0)&" "&YEAR(AP10) -> Q4 2028 | AS11: ="Q"&ROUNDUP(MONTH(AS10)/3,0)&" "&YEAR(AS10) -> Q1 2029 | AV11: ="Q"&ROUNDUP(MONTH(AV10)/3,0)&" "&YEAR(AV10) -> Q2 2029 | AY11: ="Q"&ROUNDUP(MONTH(AY10)/3,0)&" "&YEAR(AY10) -> Q3 2029 | BB11: ="Q"&ROUNDUP(MONTH(BB10)/3,0)&" "&YEAR(BB10) -> Q4 2029 | BE11: ="Q"&ROUNDUP(MONTH(BE10)/3,0)&" "&YEAR(BE10) -> Q1 2030 | BH11: ="Q"&ROUNDUP(MONTH(BH10)/3,0)&" "&YEAR(BH10) -> Q2 2030 | BK11: ="Q"&ROUNDUP(MONTH(BK10)/3,0)&" "&YEAR(BK10) -> Q3 2030 | BN11: ="Q"&ROUNDUP(MONTH(BN10)/3,0)&" "&YEAR(BN10) -> Q4 2030
B13: Land Purchase | C13: =+'5. Key Assumptions'!E12 -> 0 | D13: =D8 -> 46069 | E13: =EDATE(D13,C13) -> 46069 | F13: =B8 -> Project Start Date | G13: =+'5. Key Assumptions'!F12 -> 0 | I13: =IF(AND(I$10>=$D13,I$10<=$E13),1,"") -> 1 | J13: =IF(AND(J$10>=$D13,J$10<=$E13),1,"") | K13: =IF(AND(K$10>=$D13,K$10<=$E13),1,"") | L13: =IF(AND(L$10>=$D13,L$10<=$E13),1,"") | M13: =IF(AND(M$10>=$D13,M$10<=$E13),1,"") | N13: =IF(AND(N$10>=$D13,N$10<=$E13),1,"") | O13: =IF(AND(O$10>=$D13,O$10<=$E13),1,"") | P13: =IF(AND(P$10>=$D13,P$10<=$E13),1,"") | ... BP13: =IF(AND(BP$10>=$D13,BP$10<=$E13),1,"")
B15: Pre-Development | C15: =+'5. Key Assumptions'!E13 -> 12 | D15: =EDATE(E13,G15+1) -> 46097 | E15: =EDATE(D15,C15) -> 46462 | F15: =B13 -> Land Purchase | G15: =+'5. Key Assumptions'!F13 -> 0 | I15: =IF(AND(I$10>=$D15,I$10<=$E15),1,"") | J15: =IF(AND(J$10>=$D15,J$10<=$E15),1,"") -> 1 | K15: =IF(AND(K$10>=$D15,K$10<=$E15),1,"") -> 1 | L15: =IF(AND(L$10>=$D15,L$10<=$E15),1,"") -> 1 | M15: =IF(AND(M$10>=$D15,M$10<=$E15),1,"") -> 1 | N15: =IF(AND(N$10>=$D15,N$10<=$E15),1,"") -> 1 | O15: =IF(AND(O$10>=$D15,O$10<=$E15),1,"") -> 1 | P15: =IF(AND(P$10>=$D15,P$10<=$E15),1,"") -> 1 | ... BP15: =IF(AND(BP$10>=$D15,BP$10<=$E15),1,"")
B17: Construction | C17: =+'12. Sensitivity'!H20 -> 18 | D17: =EDATE(E15,G17+1) -> 46493 | E17: =EDATE(D17,C17) -> 47042 | F17: =B15 -> Pre-Development | G17: =+'5. Key Assumptions'!F14 -> 0 | I17: =IF(AND(I$10>=$D17,I$10<=$E17),1,"") | J17: =IF(AND(J$10>=$D17,J$10<=$E17),1,"") | K17: =IF(AND(K$10>=$D17,K$10<=$E17),1,"") | L17: =IF(AND(L$10>=$D17,L$10<=$E17),1,"") | M17: =IF(AND(M$10>=$D17,M$10<=$E17),1,"") | N17: =IF(AND(N$10>=$D17,N$10<=$E17),1,"") | O17: =IF(AND(O$10>=$D17,O$10<=$E17),1,"") | P17: =IF(AND(P$10>=$D17,P$10<=$E17),1,"") | ... BP17: =IF(AND(BP$10>=$D17,BP$10<=$E17),1,"")
B19: Lease-up | C19: =+'12. Sensitivity'!H25 -> 11.333333 | D19: =EDATE(E17,G19+1) -> 46981 | E19: =EDATE(D19,C19) -> 47315 | F19: =B17 -> Construction | G19: =+'5. Key Assumptions'!F15 -> -3 | I19: =IF(AND(I$10>=$D19,I$10<=$E19),1,"") | J19: =IF(AND(J$10>=$D19,J$10<=$E19),1,"") | K19: =IF(AND(K$10>=$D19,K$10<=$E19),1,"") | L19: =IF(AND(L$10>=$D19,L$10<=$E19),1,"") | M19: =IF(AND(M$10>=$D19,M$10<=$E19),1,"") | N19: =IF(AND(N$10>=$D19,N$10<=$E19),1,"") | O19: =IF(AND(O$10>=$D19,O$10<=$E19),1,"") | P19: =IF(AND(P$10>=$D19,P$10<=$E19),1,"") | ... BP19: =IF(AND(BP$10>=$D19,BP$10<=$E19),1,"")
I20: =IF(AND(I$10>=$D20,I$10<=$E20),1,"") | J20: =IF(AND(J$10>=$D20,J$10<=$E20),1,"") | K20: =IF(AND(K$10>=$D20,K$10<=$E20),1,"") | L20: =IF(AND(L$10>=$D20,L$10<=$E20),1,"") | M20: =IF(AND(M$10>=$D20,M$10<=$E20),1,"") | N20: =IF(AND(N$10>=$D20,N$10<=$E20),1,"") | O20: =IF(AND(O$10>=$D20,O$10<=$E20),1,"") | P20: =IF(AND(P$10>=$D20,P$10<=$E20),1,"") | ... BP20: =IF(AND(BP$10>=$D20,BP$10<=$E20),1,"")
B21: Stabilized | C21: =+'5. Key Assumptions'!E16 -> 0 | D21: =EDATE(E19,G21+1) -> 47346 | E21: =EDATE(D21,C21) -> 47346 | F21: =B19 -> Lease-up | G21: =+'5. Key Assumptions'!F16 -> 0 | I21: =IF(AND(I$10>=$D21,I$10<=$E21),1,"") | J21: =IF(AND(J$10>=$D21,J$10<=$E21),1,"") | K21: =IF(AND(K$10>=$D21,K$10<=$E21),1,"") | L21: =IF(AND(L$10>=$D21,L$10<=$E21),1,"") | M21: =IF(AND(M$10>=$D21,M$10<=$E21),1,"") | N21: =IF(AND(N$10>=$D21,N$10<=$E21),1,"") | O21: =IF(AND(O$10>=$D21,O$10<=$E21),1,"") | P21: =IF(AND(P$10>=$D21,P$10<=$E21),1,"") | ... BP21: =IF(AND(BP$10>=$D21,BP$10<=$E21),1,"")

Sheet 9. Development Costs
J1: ="Currently running: "&CHOOSE('12. Sensitivity'!$E$8,'12. Sensitivity'!$B$11,'12. Sensitivity'!$B$12,'12. Sensitivity'!$B$13) -> Currently running: Base Case
B3: ='3. Headline #s'!A10 -> Apartment Development Model Reverse 1B
B4: ='3. Headline #s'!A12 -> 2240 Birchmount Road, Scarborough, ON
B5: Development Costs
B9: Number of Units: | I9: ='7. Op Rev and Exp'!E20 -> 170 | J9: Res only
B10: Net Rentable Area: | I10: ='7. Op Rev and Exp'!D20 -> 128853.2 | J10: Res
H12: Total | I12: Per unit | J12: Per Sqft
B13: LAND | M13: Contingency Prov
B14: Land | H14: =+'5. Key Assumptions'!F44 -> 9911777.9 | I14: =H14/$I$9 -> 58304.576 | J14: =H14/$I$10 -> 76.923024
B15: Closing / Other Cost | G15: =+H15/H14 -> 0.05 | H15: =+'5. Key Assumptions'!F45 -> 495588.89 | I15: =H15/$I$9 -> 2915.2288 | J15: =H15/$I$10 -> 3.8461512
B16: Total Land Costs | G16: =H16/$H$89 -> 0.11020019 | H16: =SUM(H14:H15) -> 10407367 | I16: =SUM(I14:I15) -> 61219.804 | J16: =SUM(J14:J15) -> 80.769176
B18: CONSTRUCTION
B19: Construction hard cost | H19: =+'5. Key Assumptions'!F48*M19 -> 64395800 | I19: =H19/$I$9 -> 378798.82 | J19: =H19/$I$10 -> 499.76097 | L19: Sensitize | M19: =+'14. Sensitivity 2'!D10 -> 1
B20: Offsite/Sitework Costs | H20: 0 | I20: =H20/$I$9 -> 0 | J20: =H20/$I$10 -> 0
B21: Construction contingency | G21: =+H21/H19 -> 0.02 | H21: =+'5. Key Assumptions'!F49 -> 1287916 | I21: =H21/$I$9 -> 7575.9765 | J21: =H21/$I$10 -> 9.9952194 | K21: =+H21/H19 -> 0.02 | L21: =+H19 -> 64395800 | M21: =+H21 -> 1287916 | N21: =+M21/L21 -> 0.02
B22: Total Construction Costs | G22: =H22/$H$89 -> 0.69550331 | H22: =SUM(H19:H21) -> 65683716 | I22: =SUM(I14:I21) -> 508814.41 | J22: =SUM(J19:J21) -> 509.75619
B24: PROFESSIONAL FEES
B25: Architect | H25: =+'5. Key Assumptions'!F51 -> 1931874 | I25: =H25/$I$9 -> 11363.965 | J25: =H25/$I$10 -> 14.992829
B26: Landscape architect | I26: =H26/$I$9 -> 0 | J26: =H26/$I$10 -> 0
B27: Structural engineer | I27: =H27/$I$9 -> 0 | J27: =H27/$I$10 -> 0
B28: Civil engineer | I28: =H28/$I$9 -> 0 | J28: =H28/$I$10 -> 0
B29: Mechanical & Electrical engineer | I29: =H29/$I$9 -> 0 | J29: =H29/$I$10 -> 0
B30: Geotechnical engineer | I30: =H30/$I$9 -> 0 | J30: =H30/$I$10 -> 0
B31: Site Servicing Engineer | I31: =H31/$I$9 -> 0 | J31: =H31/$I$10 -> 0
B32: Survey | I32: =H32/$I$9 -> 0 | J32: =H32/$I$10 -> 0
I33: =H33/$I$9 -> 0 | J33: =H33/$I$10 -> 0
I34: =H34/$I$9 -> 0 | J34: =H34/$I$10 -> 0
B35: Others | I35: =H35/$I$9 -> 0 | J35: =H35/$I$10 -> 0
B36: Environmental consultant | H36: 0 | I36: =H36/$I$9 -> 0 | J36: =H36/$I$10 -> 0
B37: Interior design | H37: 0 | I37: =H37/$I$9 -> 0 | J37: =H37/$I$10 -> 0
B38: Traffic consultant | H38: 0 | I38: =H38/$I$9 -> 0 | J38: =H38/$I$10 -> 0
B39: Disbursements | H39: 0 | I39: =H39/$I$9 -> 0 | J39: =H39/$I$10 -> 0
B40: Professional fee contingency | G40: 0.1 | H40: =+'5. Key Assumptions'!F52 -> 96593.7 | I40: =H40/$I$9 -> 568.19824 | J40: =H40/$I$10 -> 0.74964145
B41: Total Professional Fees | G41: =H41/$H$89 -> 0.021478779 | H41: =SUM(H25:H40) -> 2028467.7 | I41: =SUM(I25:I40) -> 11932.163 | J41: =SUM(J25:J40) -> 15.742471 | K41: =+H41/H22 -> 0.030882353 | L41: =+H41-H40 -> 1931874 | M41: =+H40 -> 96593.7 | N41: =+M41/L41 -> 0.05
B43: DEVELOPMENT MANAGEMENT
B45: Development Management Fee | H45: =+'5. Key Assumptions'!F54 -> 1692804.6 | I45: =H45/$I$9 -> 9957.6741 | J45: =H45/$I$10 -> 13.137466
B46: Total Development Management Fee | G46: =H46/$H$89 -> 0.017924552 | H46: =SUM(H44:H45) -> 1692804.6 | I46: =SUM(I44:I45) -> 9957.6741 | J46: =SUM(J44:J45) -> 13.137466
B48: PERMITS AND APPROVALS
B49: Development Permit | H49: 0 | I49: =H49/$I$9 -> 0 | J49: =H49/$I$10 -> 0
B50: Rezoning | H50: 0 | I50: =H50/$I$9 -> 0 | J50: =H50/$I$10 -> 0
B51: Building permit | I51: =H51/$I$9 -> 0 | J51: =H51/$I$10 -> 0
B52: City Development charges | I52: =H52/$I$9 -> 0 | J52: =H52/$I$10 -> 0
B53: Park Dedication Fee | H53: 0 | I53: =H53/$I$9 -> 0 | J53: =H53/$I$10 -> 0
B54: Other Development Charges | H54: =+'5. Key Assumptions'!F56 -> 7192106 | I54: =H54/$I$9 -> 42306.506 | J54: =H54/$I$10 -> 55.816278
B55: Sub-Meter Installation Fee Credit | F55: =+'5. Key Assumptions'!D58 -> 600 | H55: =-F55*I9 -> -102000 | I55: =H55/$I$9 -> -600 | J55: =H55/$I$10 -> -0.7915985
B56: Utilities Connection | H56: 0 | I56: =H56/$I$9 -> 0 | J56: =H56/$I$10 -> 0
B57: Land titles | H57: 0 | I57: =H57/$I$9 -> 0 | J57: =H57/$I$10 -> 0
B58: Permit and approval contingency | G58: 0.1 | H58: =+'5. Key Assumptions'!F57 -> 359605.3 | I58: =H58/$I$9 -> 2115.3253 | J58: =H58/$I$10 -> 2.7908139
B59: Total Permit and Approvals | G59: =H59/$H$89 -> 0.078882548 | H59: =SUM(H49:H58) -> 7449711.3 | I59: =SUM(I49:I58) -> 43821.831 | J59: =SUM(J49:J58) -> 57.815493 | L59: =+H59-H58 -> 7090106 | M59: =+H58 -> 359605.3 | N59: =+M59/L59 -> 0.050719312
B61: MARKETINGAND LEASING
B62: Tenant Inducement | H62: 0 | I62: =H62/I9 -> 0 | J62: =H62/I10 -> 0
B63: Commissions & Incentive | H63: =+'5. Key Assumptions'!F61 -> 838175 | I63: =H63/I9 -> 4930.4412 | J63: =H63/I10 -> 6.5048831
B64: Sales Staff | H64: 0 | I64: =H64/I9 -> 0 | J64: =H64/I10 -> 0
B65: Marketing | H65: =+'5. Key Assumptions'!F62 -> 838175 | I65: =H65/$I$9 -> 4930.4412 | J65: =H65/$I$10 -> 6.5048831
B66: Total Marketing and Leasing | G66: =H66/$H$89 -> 0.01775032 | H66: =SUM(H62:H65) -> 1676350 | I66: =SUM(I62:I65) -> 9860.8824 | J66: =SUM(J62:J65) -> 13.009766
B68: FINANCING AND INTEREST
B69: Appraisal | I69: =H69/$I$9 -> 0 | J69: =H69/$I$10 -> 0
B70: Legal fees | I70: =H70/$I$9 -> 0 | J70: =H70/$I$10 -> 0
B71: Property Taxes During Construction | F71: Tax rate | H71: 0 | I71: =H71/$I$9 -> 0 | J71: =H71/$I$10 -> 0
B72: Quantity Surveyor | H72: 0 | I72: =H72/$I$9 -> 0 | J72: =H72/$I$10 -> 0
B73: Insurance | H73: 0 | I73: =H73/$I$9 -> 0 | J73: =H73/$I$10 -> 0
B74: LC and Bonding | H74: 0 | I74: =H74/$I$9 -> 0 | J74: =H74/$I$10 -> 0
B75: Loan fees | H75: =+'5. Key Assumptions'!F74 -> 849580.96 | I75: =H75/$I$9 -> 4997.5351 | J75: =H75/$I$10 -> 6.5934021
B76: Bank's Legal / Other charges | H76: 0 | I76: =H76/$I$9 -> 0 | J76: =H76/$I$10 -> 0
B77: HST | H77: 0 | I77: =H77/$I$9 -> 0 | J77: =H77/$I$10 -> 0 | L77: No HST under Self Supply except for Quebec where QST applies
B78: Construction Loan Interest | F78: @ | G78: ='12. Sensitivity'!H15 -> 0.058666667 | H78: =-'10. Development Cash Flow'!E93 -> 7695700.3 | I78: =H78/$I$9 -> 45268.825 | J78: =H78/$I$10 -> 59.724557
B79: Financing contingency | G79: =+H79/(H80-H79) -> 0.049710532 | H79: =+'5. Key Assumptions'!F75 -> 424790.48 | I79: =H79/$I$9 -> 2498.7675 | J79: =H79/$I$10 -> 3.296701
B80: Total Financing and Interest Costs | G80: =H80/$H$89 -> 0.094981146 | H80: =SUM(H69:H79) -> 8970071.7 | I80: =SUM(I69:I79) -> 52765.128 | J80: =SUM(J69:J79) -> 69.61466 | L80: =+H80-H79 -> 8545281.3 | M80: =+H79 -> 424790.48 | N80: =+M80/L80 -> 0.049710532
B82: OPERATING INCOME DURING LEASE-UP
B83: Security Deposit | H83: =-'10. Development Cash Flow'!E22 -> -515585.74 | I83: =H83/$I$9 -> -3032.8573 | J83: =H83/$I$10 -> -4.0013421
B84: Revenue | H84: =-'10. Development Cash Flow'!E23 -> -4175747.3 | I84: =H84/$I$9 -> -24563.219 | J84: =H84/$I$10 -> -32.407013
B85: Vacancy Provision | H85: =-'10. Development Cash Flow'!E24 -> 125272.42 | I85: =H85/$I$9 -> 736.89658 | J85: =H85/$I$10 -> 0.97221038
B86: Operating Expenses | H86: =-'10. Development Cash Flow'!E25 -> 1098123.3 | I86: =H86/$I$9 -> 6459.5489 | J86: =H86/$I$10 -> 8.522282
B87: Total Income During Lease-up incl Sec Deposit | G87: =+H87/H89 -> -0.03672085 | H87: =SUM(H83:H86) -> -3467937.3 | I87: =SUM(I83:I86) -> -20399.631 | J87: =SUM(J83:J86) -> -26.913862
B89: TOTAL DEVELOPMENT COSTS | H89: =SUM(H16,H22,H41,H59,H46,H66,H80,H87) -> 94440551 | I89: =H89/I9 -> 555532.65 | J89: =H89/I10 -> 732.93136 | L89: =+H89-H16 -> 84033184 | M89: =SUM(M21:M87) -> 2168905.5 | N89: =+M89/L89 -> 0.025810107

Sheet 10. Development Cash Flow
B2: ='3. Headline #s'!A10 -> Apartment Development Model Reverse 1B
B3: ='3. Headline #s'!A12 -> 2240 Birchmount Road, Scarborough, ON
B5: Cash Flow | I5: =YEAR(I7) -> 2026 | J5: =YEAR(J7) -> 2026 | K5: =YEAR(K7) -> 2026 | L5: =YEAR(L7) -> 2026 | M5: =YEAR(M7) -> 2026 | N5: =YEAR(N7) -> 2026 | O5: =YEAR(O7) -> 2026 | P5: =YEAR(P7) -> 2026 | ... CZ5: =YEAR(CZ7) -> 2034
I6: 1 | J6: 2 | K6: 3 | L6: 4 | M6: 5 | N6: 6 | O6: 7 | P6: 8 | Q6: 9 | R6: 10 | S6: 11 | T6: 12 | U6: 13 | V6: 14 | W6: 15 | X6: 16 | Y6: 17 | Z6: 18 | AA6: 19 | AB6: 20 | AC6: 21 | AD6: 22 | AE6: 23 | AF6: 24 | AG6: 25 | AH6: 26 | AI6: 27 | AJ6: 28 | AK6: 29 | AL6: 30 | AM6: 31 | AN6: 32 | AO6: 33 | AP6: 34 | AQ6: 35 | AR6: 36 | AS6: 37 | AT6: 38 | AU6: 39 | AV6: 40 | AW6: 41 | AX6: 42 | AY6: 43 | AZ6: 44 | BA6: 45 | BB6: 46 | BC6: 47 | BD6: 48 | BE6: 49 | BF6: 50 | BG6: 51 | BH6: 52 | BI6: 53 | BJ6: 54 | BK6: 55 | BL6: 56 | BM6: 57 | BN6: 58 | BO6: 59 | BP6: 60 | BQ6: 61 | BR6: 62 | BS6: 63 | BT6: 64 | BU6: 65 | BV6: 66 | BW6: 67 | BX6: 68 | BY6: 69 | BZ6: 70 | CA6: 71 | CB6: 72 | CC6: 73 | CD6: 74 | CE6: 75 | CF6: 76 | CG6: 77 | CH6: 78 | CI6: 79 | CJ6: 80 | CK6: 81 | CL6: 82 | CM6: 83 | CN6: 84 | CO6: 85 | CP6: 86 | CQ6: 87 | CR6: 88 | CS6: 89 | CT6: 90 | CU6: 91 | CV6: 92 | CW6: 93 | CX6: 94 | CY6: 95 | CZ6: 96
B7: Items | C7: Budget | D7: Variance | E7: Total Cashflow | F7: Start | G7: End | H7: Months | I7: ='8. Schedule'!D8 -> 46069 | J7: =EDATE(I7,1) -> 46097 | K7: =EDATE(J7,1) -> 46128 | L7: =EDATE(K7,1) -> 46158 | M7: =EDATE(L7,1) -> 46189 | N7: =EDATE(M7,1) -> 46219 | O7: =EDATE(N7,1) -> 46250 | P7: =EDATE(O7,1) -> 46281 | Q7: =EDATE(P7,1) -> 46311 | ... CZ7: =EDATE(CY7,1) -> 48960
B8: LEASE-UP SCHEDULE
B9: Number of Units Completed | C9: ='9. Development Costs'!$I$9 -> 170 | D9: =ROUND(C9-E9,0) -> 0 | E9: =SUM(I9:CZ9) -> 170 | I9: =IF(I7='8. Schedule'!$E$17,'10. Development Cash Flow'!$C$9,0) -> 0 | J9: =IF(J7='8. Schedule'!$E$17,'10. Development Cash Flow'!$C$9,0) -> 0 | K9: =IF(K7='8. Schedule'!$E$17,'10. Development Cash Flow'!$C$9,0) -> 0 | L9: =IF(L7='8. Schedule'!$E$17,'10. Development Cash Flow'!$C$9,0) -> 0 | M9: =IF(M7='8. Schedule'!$E$17,'10. Development Cash Flow'!$C$9,0) -> 0 | N9: =IF(N7='8. Schedule'!$E$17,'10. Development Cash Flow'!$C$9,0) -> 0 | O9: =IF(O7='8. Schedule'!$E$17,'10. Development Cash Flow'!$C$9,0) -> 0 | P9: =IF(P7='8. Schedule'!$E$17,'10. Development Cash Flow'!$C$9,0) -> 0 | ... CZ9: =IF(CZ7='8. Schedule'!$E$17,'10. Development Cash Flow'!$C$9,0) -> 0
B10: Cumulative Units Complete | C10: ='9. Development Costs'!$I$9 -> 170 | D10: =ROUND(C10-E10,0) -> 0 | E10: =MAX(I10:CZ10) -> 170 | I10: =I9 -> 0 | J10: =I10+J9 -> 0 | K10: =J10+K9 -> 0 | L10: =K10+L9 -> 0 | M10: =L10+M9 -> 0 | N10: =M10+N9 -> 0 | O10: =N10+O9 -> 0 | P10: =O10+P9 -> 0 | Q10: =P10+Q9 -> 0 | ... CZ10: =CY10+CZ9 -> 170
B11: Percentage Completed | E11: =MAX(I11:CZ11) -> 1 | I11: =I10/'9. Development Costs'!$I$9 -> 0 | J11: =J10/'9. Development Costs'!$I$9 -> 0 | K11: =K10/'9. Development Costs'!$I$9 -> 0 | L11: =L10/'9. Development Costs'!$I$9 -> 0 | M11: =M10/'9. Development Costs'!$I$9 -> 0 | N11: =N10/'9. Development Costs'!$I$9 -> 0 | O11: =O10/'9. Development Costs'!$I$9 -> 0 | P11: =P10/'9. Development Costs'!$I$9 -> 0 | ... CZ11: =CZ10/'9. Development Costs'!$I$9 -> 1
B12: New Units Leased | C12: ='9. Development Costs'!$I$9 -> 170 | D12: =ROUND(C12-E12,0) -> 0 | E12: =SUM(I12:CZ12) -> 170 | F12: ='8. Schedule'!D19 -> 46981 | G12: ='8. Schedule'!E19 -> 47315 | H12: =DATEDIF(F12,G12,"m")+1 -> 12 | I12: =IF(AND(I$7<=$G12,I$7>=$F12,$H12<>0,$H12<>""),$C12/$H12,0) -> 0 | J12: =IF(AND(J$7<=$G12,J$7>=$F12,$H12<>0,$H12<>""),$C12/$H12,0) -> 0 | K12: =IF(AND(K$7<=$G12,K$7>=$F12,$H12<>0,$H12<>""),$C12/$H12,0) -> 0 | L12: =IF(AND(L$7<=$G12,L$7>=$F12,$H12<>0,$H12<>""),$C12/$H12,0) -> 0 | M12: =IF(AND(M$7<=$G12,M$7>=$F12,$H12<>0,$H12<>""),$C12/$H12,0) -> 0 | N12: =IF(AND(N$7<=$G12,N$7>=$F12,$H12<>0,$H12<>""),$C12/$H12,0) -> 0 | O12: =IF(AND(O$7<=$G12,O$7>=$F12,$H12<>0,$H12<>""),$C12/$H12,0) -> 0 | P12: =IF(AND(P$7<=$G12,P$7>=$F12,$H12<>0,$H12<>""),$C12/$H12,0) -> 0 | ... CZ12: =IF(AND(CZ$7<=$G12,CZ$7>=$F12,$H12<>0,$H12<>""),$C12/$H12,0) -> 0
B13: Cumulative Units Leased | C13: ='9. Development Costs'!$I$9 -> 170 | D13: =ROUND(C13-E13,0) -> 0 | E13: =MAX(I13:CZ13) -> 170 | I13: =I12 -> 0 | J13: =I13+J12 -> 0 | K13: =J13+K12 -> 0 | L13: =K13+L12 -> 0 | M13: =L13+M12 -> 0 | N13: =M13+N12 -> 0 | O13: =N13+O12 -> 0 | P13: =O13+P12 -> 0 | Q13: =P13+Q12 -> 0 | ... CZ13: =CY13+CZ12 -> 170
B14: Percentage Leased | E14: =MAX(I14:CZ14) -> 1 | I14: =I13/'9. Development Costs'!$I$9 -> 0 | J14: =J13/'9. Development Costs'!$I$9 -> 0 | K14: =K13/'9. Development Costs'!$I$9 -> 0 | L14: =L13/'9. Development Costs'!$I$9 -> 0 | M14: =M13/'9. Development Costs'!$I$9 -> 0 | N14: =N13/'9. Development Costs'!$I$9 -> 0 | O14: =O13/'9. Development Costs'!$I$9 -> 0 | P14: =P13/'9. Development Costs'!$I$9 -> 0 | ... CZ14: =CZ13/'9. Development Costs'!$I$9 -> 1
B15: Units Occupied | C15: ='9. Development Costs'!$I$9 -> 170 | D15: =ROUND(C15-E15,0) -> 0 | E15: =SUM(I15:CZ15) -> 170 | I15: 0 | J15: =IF(I$7>=$F$9,MIN(J10,J13)-I16,0) -> 0 | K15: =IF(J$7>=$F$9,MIN(K10,K13)-J16,0) -> 0 | L15: =IF(K$7>=$F$9,MIN(L10,L13)-K16,0) -> 0 | M15: =IF(L$7>=$F$9,MIN(M10,M13)-L16,0) -> 0 | N15: =IF(M$7>=$F$9,MIN(N10,N13)-M16,0) -> 0 | O15: =IF(N$7>=$F$9,MIN(O10,O13)-N16,0) -> 0 | P15: =IF(O$7>=$F$9,MIN(P10,P13)-O16,0) -> 0 | Q15: =IF(P$7>=$F$9,MIN(Q10,Q13)-P16,0) -> 0 | ... CZ15: =IF(CY$7>=$F$9,MIN(CZ10,CZ13)-CY16,0) -> 0
B16: Cumulative Units Occupied | C16: ='9. Development Costs'!$I$9 -> 170 | D16: =ROUND(C16-E16,0) -> 0 | E16: =MAX(I16:CZ16) -> 170 | I16: =I15 -> 0 | J16: =I16+J15 -> 0 | K16: =J16+K15 -> 0 | L16: =K16+L15 -> 0 | M16: =L16+M15 -> 0 | N16: =M16+N15 -> 0 | O16: =N16+O15 -> 0 | P16: =O16+P15 -> 0 | Q16: =P16+Q15 -> 0 | ... CZ16: =CY16+CZ15 -> 170
B17: Percentage Occupied | E17: =MAX(I17:CZ17) -> 1 | I17: =I16/'9. Development Costs'!$I$9 -> 0 | J17: =J16/'9. Development Costs'!$I$9 -> 0 | K17: =K16/'9. Development Costs'!$I$9 -> 0 | L17: =L16/'9. Development Costs'!$I$9 -> 0 | M17: =M16/'9. Development Costs'!$I$9 -> 0 | N17: =N16/'9. Development Costs'!$I$9 -> 0 | O17: =O16/'9. Development Costs'!$I$9 -> 0 | P17: =P16/'9. Development Costs'!$I$9 -> 0 | ... CZ17: =CZ16/'9. Development Costs'!$I$9 -> 1
B19: OPERATING INCOME
B20: Revenue Inflation Factor | I20: =(1+'11. 10-Yr Cash Flow IRR'!$E$9)^(YEAR(I7)-YEAR('8. Schedule'!$D$8)) -> 1 | J20: =(1+'11. 10-Yr Cash Flow IRR'!$E$9)^(YEAR(J7)-YEAR('8. Schedule'!$D$8)) -> 1 | K20: =(1+'11. 10-Yr Cash Flow IRR'!$E$9)^(YEAR(K7)-YEAR('8. Schedule'!$D$8)) -> 1 | L20: =(1+'11. 10-Yr Cash Flow IRR'!$E$9)^(YEAR(L7)-YEAR('8. Schedule'!$D$8)) -> 1 | M20: =(1+'11. 10-Yr Cash Flow IRR'!$E$9)^(YEAR(M7)-YEAR('8. Schedule'!$D$8)) -> 1 | N20: =(1+'11. 10-Yr Cash Flow IRR'!$E$9)^(YEAR(N7)-YEAR('8. Schedule'!$D$8)) -> 1 | O20: =(1+'11. 10-Yr Cash Flow IRR'!$E$9)^(YEAR(O7)-YEAR('8. Schedule'!$D$8)) -> 1 | P20: =(1+'11. 10-Yr Cash Flow IRR'!$E$9)^(YEAR(P7)-YEAR('8. Schedule'!$D$8)) -> 1 | ... CZ20: =(1+'11. 10-Yr Cash Flow IRR'!$E$9)^(YEAR(CZ7)-YEAR('8. Schedule'!$D$8)) -> 1.1716594
B21: Cost Inflation Factor | I21: =(1+'11. 10-Yr Cash Flow IRR'!$E$10)^(YEAR(I7)-YEAR('8. Schedule'!$D$8)) -> 1 | J21: =(1+'11. 10-Yr Cash Flow IRR'!$E$9)^(YEAR(J7)-YEAR('8. Schedule'!$D$8)) -> 1 | K21: =(1+'11. 10-Yr Cash Flow IRR'!$E$9)^(YEAR(K7)-YEAR('8. Schedule'!$D$8)) -> 1 | L21: =(1+'11. 10-Yr Cash Flow IRR'!$E$9)^(YEAR(L7)-YEAR('8. Schedule'!$D$8)) -> 1 | M21: =(1+'11. 10-Yr Cash Flow IRR'!$E$9)^(YEAR(M7)-YEAR('8. Schedule'!$D$8)) -> 1 | N21: =(1+'11. 10-Yr Cash Flow IRR'!$E$9)^(YEAR(N7)-YEAR('8. Schedule'!$D$8)) -> 1 | O21: =(1+'11. 10-Yr Cash Flow IRR'!$E$9)^(YEAR(O7)-YEAR('8. Schedule'!$D$8)) -> 1 | P21: =(1+'11. 10-Yr Cash Flow IRR'!$E$9)^(YEAR(P7)-YEAR('8. Schedule'!$D$8)) -> 1 | Q21: =(1+'11. 10-Yr Cash Flow IRR'!$E$9)^(YEAR(Q7)-YEAR('8. Schedule'!$D$8)) -> 1 | ... CZ21: =(1+'11. 10-Yr Cash Flow IRR'!$E$9)^(YEAR(CZ7)-YEAR('8. Schedule'!$D$8)) -> 1.1716594
B22: Security Deposit | C22: =-'9. Development Costs'!H83 -> 515585.74 | E22: =SUM(I22:CZ22) -> 515585.74 | I22: =+'7. Op Rev and Exp'!$H$20/'7. Op Rev and Exp'!$E$20/12*I12*I20 -> 0 | J22: =+'7. Op Rev and Exp'!$H$20/'7. Op Rev and Exp'!$E$20/12*J12*J20 -> 0 | K22: =+'7. Op Rev and Exp'!$H$20/'7. Op Rev and Exp'!$E$20/12*K12*K20 -> 0 | L22: =+'7. Op Rev and Exp'!$H$20/'7. Op Rev and Exp'!$E$20/12*L12*L20 -> 0 | M22: =+'7. Op Rev and Exp'!$H$20/'7. Op Rev and Exp'!$E$20/12*M12*M20 -> 0 | N22: =+'7. Op Rev and Exp'!$H$20/'7. Op Rev and Exp'!$E$20/12*N12*N20 -> 0 | O22: =+'7. Op Rev and Exp'!$H$20/'7. Op Rev and Exp'!$E$20/12*O12*O20 -> 0 | P22: =+'7. Op Rev and Exp'!$H$20/'7. Op Rev and Exp'!$E$20/12*P12*P20 -> 0 | ... CZ22: =+'7. Op Rev and Exp'!$H$20/'7. Op Rev and Exp'!$E$20/12*CZ12*CZ20 -> 0
B23: Revenue | C23: =-'9. Development Costs'!H84 -> 4175747.3 | D23: =ROUND(C23-E23,0) -> 0 | E23: =SUM(I23:CZ23) -> 4175747.3 | I23: =IF(I110="PUD",'7. Op Rev and Exp'!$H$32/12*I$17*I$20,0) -> 0 | J23: =IF(J110="PUD",'7. Op Rev and Exp'!$H$32/12*J$17*J$20,0) -> 0 | K23: =IF(K110="PUD",'7. Op Rev and Exp'!$H$32/12*K$17*K$20,0) -> 0 | L23: =IF(L110="PUD",'7. Op Rev and Exp'!$H$32/12*L$17*L$20,0) -> 0 | M23: =IF(M110="PUD",'7. Op Rev and Exp'!$H$32/12*M$17*M$20,0) -> 0 | N23: =IF(N110="PUD",'7. Op Rev and Exp'!$H$32/12*N$17*N$20,0) -> 0 | O23: =IF(O110="PUD",'7. Op Rev and Exp'!$H$32/12*O$17*O$20,0) -> 0 | P23: =IF(P110="PUD",'7. Op Rev and Exp'!$H$32/12*P$17*P$20,0) -> 0 | ... CZ23: =IF(CZ110="PUD",'7. Op Rev and Exp'!$H$32/12*CZ$17*CZ$20,0) -> 0
B24: Vacancy Provision | C24: =-'9. Development Costs'!H85 -> -125272.42 | D24: =ROUND(C24-E24,0) -> 0 | E24: =SUM(I24:CZ24) -> -125272.42 | I24: =IF(I110="PUD",-'7. Op Rev and Exp'!$H$33/12*I$17*I$20,0) -> 0 | J24: =IF(J110="PUD",-'7. Op Rev and Exp'!$H$33/12*J$17*J$20,0) -> 0 | K24: =IF(K110="PUD",-'7. Op Rev and Exp'!$H$33/12*K$17*K$20,0) -> 0 | L24: =IF(L110="PUD",-'7. Op Rev and Exp'!$H$33/12*L$17*L$20,0) -> 0 | M24: =IF(M110="PUD",-'7. Op Rev and Exp'!$H$33/12*M$17*M$20,0) -> 0 | N24: =IF(N110="PUD",-'7. Op Rev and Exp'!$H$33/12*N$17*N$20,0) -> 0 | O24: =IF(O110="PUD",-'7. Op Rev and Exp'!$H$33/12*O$17*O$20,0) -> 0 | P24: =IF(P110="PUD",-'7. Op Rev and Exp'!$H$33/12*P$17*P$20,0) -> 0 | ... CZ24: =IF(CZ110="PUD",-'7. Op Rev and Exp'!$H$33/12*CZ$17*CZ$20,0) -> 0
B25: Operating Expenses | C25: =-'9. Development Costs'!H86 -> -1098123.3 | D25: =ROUND(C25-E25,0) -> 0 | E25: =SUM(I25:CZ25) -> -1098123.3 | I25: =IF(I110="PUD",-'7. Op Rev and Exp'!$H$50/12*I$17*I$21,0) -> 0 | J25: =IF(J110="PUD",-'7. Op Rev and Exp'!$H$50/12*J$17*J$21,0) -> 0 | K25: =IF(K110="PUD",-'7. Op Rev and Exp'!$H$50/12*K$17*K$21,0) -> 0 | L25: =IF(L110="PUD",-'7. Op Rev and Exp'!$H$50/12*L$17*L$21,0) -> 0 | M25: =IF(M110="PUD",-'7. Op Rev and Exp'!$H$50/12*M$17*M$21,0) -> 0 | N25: =IF(N110="PUD",-'7. Op Rev and Exp'!$H$50/12*N$17*N$21,0) -> 0 | O25: =IF(O110="PUD",-'7. Op Rev and Exp'!$H$50/12*O$17*O$21,0) -> 0 | P25: =IF(P110="PUD",-'7. Op Rev and Exp'!$H$50/12*P$17*P$21,0) -> 0 | ... CZ25: =IF(CZ110="PUD",-'7. Op Rev and Exp'!$H$50/12*CZ$17*CZ$21,0) -> 0
B26: NOI | C26: =SUM(C23:C25) -> 2952351.5 | E26: =SUM(I26:CZ26)+E21 -> 2952351.5 | I26: =SUM(I23:I25) -> 0 | J26: =SUM(J23:J25) -> 0 | K26: =SUM(K23:K25) -> 0 | L26: =SUM(L23:L25) -> 0 | M26: =SUM(M23:M25) -> 0 | N26: =SUM(N23:N25) -> 0 | O26: =SUM(O23:O25) -> 0 | P26: =SUM(P23:P25) -> 0 | ... CZ26: =SUM(CZ23:CZ25) -> 0
B28: LAND
B29: ='9. Development Costs'!B14 -> Land | C29: =-'9. Development Costs'!H14 -> -9911777.9 | D29: =ROUND(C29-E29,0) -> 0 | E29: =SUM(I29:CZ29) -> -9911777.9 | F29: ='8. Schedule'!D13 -> 46069 | G29: ='8. Schedule'!E13 -> 46069 | H29: =DATEDIF(F29,G29,"m")+1 -> 1 | I29: =IF(AND(I$7<=$G29,I$7>=$F29,$H29<>0,$H29<>""),$C29/$H29,0) -> -9911777.9 | J29: =IF(AND(J$7<=$G29,J$7>=$F29,$H29<>0,$H29<>""),$C29/$H29,0) -> 0 | K29: =IF(AND(K$7<=$G29,K$7>=$F29,$H29<>0,$H29<>""),$C29/$H29,0) -> 0 | L29: =IF(AND(L$7<=$G29,L$7>=$F29,$H29<>0,$H29<>""),$C29/$H29,0) -> 0 | M29: =IF(AND(M$7<=$G29,M$7>=$F29,$H29<>0,$H29<>""),$C29/$H29,0) -> 0 | N29: =IF(AND(N$7<=$G29,N$7>=$F29,$H29<>0,$H29<>""),$C29/$H29,0) -> 0 | O29: =IF(AND(O$7<=$G29,O$7>=$F29,$H29<>0,$H29<>""),$C29/$H29,0) -> 0 | P29: =IF(AND(P$7<=$G29,P$7>=$F29,$H29<>0,$H29<>""),$C29/$H29,0) -> 0 | ... CZ29: =IF(AND(CZ$7<=$G29,CZ$7>=$F29,$H29<>0,$H29<>""),$C29/$H29,0) -> 0
B30: ='9. Development Costs'!B15 -> Closing / Other Cost | C30: =-'9. Development Costs'!H15 -> -495588.89 | D30: =ROUND(C30-E30,0) -> 0 | E30: =SUM(I30:CZ30) -> -495588.89 | F30: =F29 -> 46069 | G30: =G29 -> 46069 | H30: =DATEDIF(F30,G30,"m")+1 -> 1 | I30: =IF(AND(I$7<=$G30,I$7>=$F30,$H30<>0,$H30<>""),$C30/$H30,0) -> -495588.89 | J30: =IF(AND(J$7<=$G30,J$7>=$F30,$H30<>0,$H30<>""),$C30/$H30,0) -> 0 | K30: =IF(AND(K$7<=$G30,K$7>=$F30,$H30<>0,$H30<>""),$C30/$H30,0) -> 0 | L30: =IF(AND(L$7<=$G30,L$7>=$F30,$H30<>0,$H30<>""),$C30/$H30,0) -> 0 | M30: =IF(AND(M$7<=$G30,M$7>=$F30,$H30<>0,$H30<>""),$C30/$H30,0) -> 0 | N30: =IF(AND(N$7<=$G30,N$7>=$F30,$H30<>0,$H30<>""),$C30/$H30,0) -> 0 | O30: =IF(AND(O$7<=$G30,O$7>=$F30,$H30<>0,$H30<>""),$C30/$H30,0) -> 0 | P30: =IF(AND(P$7<=$G30,P$7>=$F30,$H30<>0,$H30<>""),$C30/$H30,0) -> 0 | ... CZ30: =IF(AND(CZ$7<=$G30,CZ$7>=$F30,$H30<>0,$H30<>""),$C30/$H30,0) -> 0
B31: ='9. Development Costs'!B16 -> Total Land Costs | C31: =-'9. Development Costs'!H16 -> -10407367 | D31: =C31-E31 -> 0 | E31: =SUM(I31:CZ31) -> -10407367 | I31: =SUM(I29:I30) -> -10407367 | J31: =SUM(J29:J30) -> 0 | K31: =SUM(K29:K30) -> 0 | L31: =SUM(L29:L30) -> 0 | M31: =SUM(M29:M30) -> 0 | N31: =SUM(N29:N30) -> 0 | O31: =SUM(O29:O30) -> 0 | P31: =SUM(P29:P30) -> 0 | ... CZ31: =SUM(CZ29:CZ30) -> 0
B33: CONSTRUCTION
A34: Steep | B34: S Curve Option:
A35: Moderately Steep | B35: 2 | C35: S-curve StDev: | D35: =H36/B35 -> 9.5
A36: Moderate | B36: S Curve Distribution | C36: 1 | D36: =C36-E36 -> 0 | E36: =SUM(I36:CZ36) -> 1 | F36: =F41 -> 46493 | G36: =G41 -> 47042 | H36: =DATEDIF(F36,G36,"m")+1 -> 19 | I36: =IF(AND(I$7>=$F36,I$7<=$G36),(_xlfn.NORM.DIST((YEAR(I$7)-YEAR($F36))*12+MONTH(I$7)-MONTH($F36)+1,$H36/2,$D35,TRUE)-_xlfn.NORM.DIST((YEAR(I$7)-YEAR($F36))*12+MONTH(I$7)-MONTH($F36),$H36/2,$D35,TRUE))/(1-2*_xlfn.NORM.DIST(0,$H36/2,$D35,TRUE))*$C36,0) -> 0 | J36: =IF(AND(J$7>=$F36,J$7<=$G36),(_xlfn.NORM.DIST((YEAR(J$7)-YEAR($F36))*12+MONTH(J$7)-MONTH($F36)+1,$H36/2,$D35,TRUE)-_xlfn.NORM.DIST((YEAR(J$7)-YEAR($F36))*12+MONTH(J$7)-MONTH($F36),$H36/2,$D35,TRUE))/(1-2*_xlfn.NORM.DIST(0,$H36/2,$D35,TRUE))*$C36,0) -> 0 | K36: =IF(AND(K$7>=$F36,K$7<=$G36),(_xlfn.NORM.DIST((YEAR(K$7)-YEAR($F36))*12+MONTH(K$7)-MONTH($F36)+1,$H36/2,$D35,TRUE)-_xlfn.NORM.DIST((YEAR(K$7)-YEAR($F36))*12+MONTH(K$7)-MONTH($F36),$H36/2,$D35,TRUE))/(1-2*_xlfn.NORM.DIST(0,$H36/2,$D35,TRUE))*$C36,0) -> 0 | L36: =IF(AND(L$7>=$F36,L$7<=$G36),(_xlfn.NORM.DIST((YEAR(L$7)-YEAR($F36))*12+MONTH(L$7)-MONTH($F36)+1,$H36/2,$D35,TRUE)-_xlfn.NORM.DIST((YEAR(L$7)-YEAR($F36))*12+MONTH(L$7)-MONTH($F36),$H36/2,$D35,TRUE))/(1-2*_xlfn.NORM.DIST(0,$H36/2,$D35,TRUE))*$C36,0) -> 0 | M36: =IF(AND(M$7>=$F36,M$7<=$G36),(_xlfn.NORM.DIST((YEAR(M$7)-YEAR($F36))*12+MONTH(M$7)-MONTH($F36)+1,$H36/2,$D35,TRUE)-_xlfn.NORM.DIST((YEAR(M$7)-YEAR($F36))*12+MONTH(M$7)-MONTH($F36),$H36/2,$D35,TRUE))/(1-2*_xlfn.NORM.DIST(0,$H36/2,$D35,TRUE))*$C36,0) -> 0 | N36: =IF(AND(N$7>=$F36,N$7<=$G36),(_xlfn.NORM.DIST((YEAR(N$7)-YEAR($F36))*12+MONTH(N$7)-MONTH($F36)+1,$H36/2,$D35,TRUE)-_xlfn.NORM.DIST((YEAR(N$7)-YEAR($F36))*12+MONTH(N$7)-MONTH($F36),$H36/2,$D35,TRUE))/(1-2*_xlfn.NORM.DIST(0,$H36/2,$D35,TRUE))*$C36,0) -> 0 | O36: =IF(AND(O$7>=$F36,O$7<=$G36),(_xlfn.NORM.DIST((YEAR(O$7)-YEAR($F36))*12+MONTH(O$7)-MONTH($F36)+1,$H36/2,$D35,TRUE)-_xlfn.NORM.DIST((YEAR(O$7)-YEAR($F36))*12+MONTH(O$7)-MONTH($F36),$H36/2,$D35,TRUE))/(1-2*_xlfn.NORM.DIST(0,$H36/2,$D35,TRUE))*$C36,0) -> 0 | P36: =IF(AND(P$7>=$F36,P$7<=$G36),(_xlfn.NORM.DIST((YEAR(P$7)-YEAR($F36))*12+MONTH(P$7)-MONTH($F36)+1,$H36/2,$D35,TRUE)-_xlfn.NORM.DIST((YEAR(P$7)-YEAR($F36))*12+MONTH(P$7)-MONTH($F36),$H36/2,$D35,TRUE))/(1-2*_xlfn.NORM.DIST(0,$H36/2,$D35,TRUE))*$C36,0) -> 0 | ... CZ36: =IF(AND(CZ$7>=$F36,CZ$7<=$G36),(_xlfn.NORM.DIST((YEAR(CZ$7)-YEAR($F36))*12+MONTH(CZ$7)-MONTH($F36)+1,$H36/2,$D35,TRUE)-_xlfn.NORM.DIST((YEAR(CZ$7)-YEAR($F36))*12+MONTH(CZ$7)-MONTH($F36),$H36/2,$D35,TRUE))/(1-2*_xlfn.NORM.DIST(0,$H36/2,$D35,TRUE))*$C36,0) -> 0
A37: Moderately Flat | B37: Even Distribution | C37: 1 | D37: =C37-E37 -> 0 | E37: =SUM(I37:CZ37) -> 1 | F37: =F41 -> 46493 | G37: =G41 -> 47042 | H37: =DATEDIF(F37,G37,"m")+1 -> 19 | I37: =IF(AND(I$7<=$G37,I$7>=$F37,$H37<>0,$H37<>""),$C37/$H37,0) -> 0 | J37: =IF(AND(J$7<=$G37,J$7>=$F37,$H37<>0,$H37<>""),$C37/$H37,0) -> 0 | K37: =IF(AND(K$7<=$G37,K$7>=$F37,$H37<>0,$H37<>""),$C37/$H37,0) -> 0 | L37: =IF(AND(L$7<=$G37,L$7>=$F37,$H37<>0,$H37<>""),$C37/$H37,0) -> 0 | M37: =IF(AND(M$7<=$G37,M$7>=$F37,$H37<>0,$H37<>""),$C37/$H37,0) -> 0 | N37: =IF(AND(N$7<=$G37,N$7>=$F37,$H37<>0,$H37<>""),$C37/$H37,0) -> 0 | O37: =IF(AND(O$7<=$G37,O$7>=$F37,$H37<>0,$H37<>""),$C37/$H37,0) -> 0 | P37: =IF(AND(P$7<=$G37,P$7>=$F37,$H37<>0,$H37<>""),$C37/$H37,0) -> 0 | ... CZ37: =IF(AND(CZ$7<=$G37,CZ$7>=$F37,$H37<>0,$H37<>""),$C37/$H37,0) -> 0
B38: Construction Cost Option:
B39: 1
B40: Construction % Completion | I40: =CHOOSE($B$39,I36,I37) -> 0 | J40: =CHOOSE($B$39,J36,J37)+I40 -> 0 | K40: =CHOOSE($B$39,K36,K37)+J40 -> 0 | L40: =CHOOSE($B$39,L36,L37)+K40 -> 0 | M40: =CHOOSE($B$39,M36,M37)+L40 -> 0 | N40: =CHOOSE($B$39,N36,N37)+M40 -> 0 | O40: =CHOOSE($B$39,O36,O37)+N40 -> 0 | P40: =CHOOSE($B$39,P36,P37)+O40 -> 0 | Q40: =CHOOSE($B$39,Q36,Q37)+P40 -> 0 | ... CZ40: =CHOOSE($B$39,CZ36,CZ37)+CY40 -> 1
B41: ='9. Development Costs'!B19 -> Construction hard cost | C41: =-'9. Development Costs'!H19 -> -64395800 | D41: =ROUND(C41-E41,0) -> 0 | E41: =SUM(I41:CZ41) -> -64395800 | F41: ='8. Schedule'!D17 -> 46493 | G41: ='8. Schedule'!E17 -> 47042 | H41: =DATEDIF(F41,G41,"m")+1 -> 19 | I41: =I40*$C$41 -> 0 | J41: =(J40-I40)*$C$41 -> 0 | K41: =(K40-J40)*$C$41 -> 0 | L41: =(L40-K40)*$C$41 -> 0 | M41: =(M40-L40)*$C$41 -> 0 | N41: =(N40-M40)*$C$41 -> 0 | O41: =(O40-N40)*$C$41 -> 0 | P41: =(P40-O40)*$C$41 -> 0 | Q41: =(Q40-P40)*$C$41 -> 0 | ... CZ41: =(CZ40-CY40)*$C$41 -> 0
B42: ='9. Development Costs'!B20 -> Offsite/Sitework Costs | C42: =-'9. Development Costs'!H20 -> 0 | D42: =ROUND(C42-E42,0) -> 0 | E42: =SUM(I42:CZ42) -> 0 | F42: =F41 -> 46493 | G42: =G41 -> 47042 | H42: =DATEDIF(F42,G42,"m")+1 -> 19 | I42: =IF(AND(I$7<=$G42,I$7>=$F42,$H42<>0,$H42<>""),$C42/$H42,0) -> 0 | J42: =IF(AND(J$7<=$G42,J$7>=$F42,$H42<>0,$H42<>""),$C42/$H42,0) -> 0 | K42: =IF(AND(K$7<=$G42,K$7>=$F42,$H42<>0,$H42<>""),$C42/$H42,0) -> 0 | L42: =IF(AND(L$7<=$G42,L$7>=$F42,$H42<>0,$H42<>""),$C42/$H42,0) -> 0 | M42: =IF(AND(M$7<=$G42,M$7>=$F42,$H42<>0,$H42<>""),$C42/$H42,0) -> 0 | N42: =IF(AND(N$7<=$G42,N$7>=$F42,$H42<>0,$H42<>""),$C42/$H42,0) -> 0 | O42: =IF(AND(O$7<=$G42,O$7>=$F42,$H42<>0,$H42<>""),$C42/$H42,0) -> 0 | P42: =IF(AND(P$7<=$G42,P$7>=$F42,$H42<>0,$H42<>""),$C42/$H42,0) -> 0 | ... CZ42: =IF(AND(CZ$7<=$G42,CZ$7>=$F42,$H42<>0,$H42<>""),$C42/$H42,0) -> 0
B43: ='9. Development Costs'!B21 -> Construction contingency | C43: =-'9. Development Costs'!H21 -> -1287916 | D43: =ROUND(C43-E43,0) -> 0 | E43: =SUM(I43:CZ43) -> -1287916 | F43: =F41 -> 46493 | G43: =G41 -> 47042 | H43: =DATEDIF(F43,G43,"m")+1 -> 19 | I43: =IF(AND(I$7<=$G43,I$7>=$F43,$H43<>0,$H43<>""),$C43/$H43,0) -> 0 | J43: =IF(AND(J$7<=$G43,J$7>=$F43,$H43<>0,$H43<>""),$C43/$H43,0) -> 0 | K43: =IF(AND(K$7<=$G43,K$7>=$F43,$H43<>0,$H43<>""),$C43/$H43,0) -> 0 | L43: =IF(AND(L$7<=$G43,L$7>=$F43,$H43<>0,$H43<>""),$C43/$H43,0) -> 0 | M43: =IF(AND(M$7<=$G43,M$7>=$F43,$H43<>0,$H43<>""),$C43/$H43,0) -> 0 | N43: =IF(AND(N$7<=$G43,N$7>=$F43,$H43<>0,$H43<>""),$C43/$H43,0) -> 0 | O43: =IF(AND(O$7<=$G43,O$7>=$F43,$H43<>0,$H43<>""),$C43/$H43,0) -> 0 | P43: =IF(AND(P$7<=$G43,P$7>=$F43,$H43<>0,$H43<>""),$C43/$H43,0) -> 0 | ... CZ43: =IF(AND(CZ$7<=$G43,CZ$7>=$F43,$H43<>0,$H43<>""),$C43/$H43,0) -> 0
B44: ='9. Development Costs'!B22 -> Total Construction Costs | C44: =-'9. Development Costs'!H22 -> -65683716 | D44: =C44-E44 -> 0 | E44: =SUM(I44:CZ44) -> -65683716 | I44: =SUM(I41:I43) -> 0 | J44: =SUM(J41:J43) -> 0 | K44: =SUM(K41:K43) -> 0 | L44: =SUM(L41:L43) -> 0 | M44: =SUM(M41:M43) -> 0 | N44: =SUM(N41:N43) -> 0 | O44: =SUM(O41:O43) -> 0 | P44: =SUM(P41:P43) -> 0 | ... CZ44: =SUM(CZ41:CZ43) -> 0
B46: PROFESSIONAL FEES
B47: ='9. Development Costs'!B25 -> Architect | C47: =-'9. Development Costs'!H25 -> -1931874 | D47: =ROUND(C47-E47,0) -> 0 | E47: =SUM(I47:CZ47) -> -1931874 | F47: ='8. Schedule'!D15 -> 46097 | G47: ='8. Schedule'!E17 -> 47042 | H47: =DATEDIF(F47,G47,"m")+1 -> 32 | I47: =IF(AND(I$7<=$G47,I$7>=$F47,$H47<>0,$H47<>""),$C47/$H47,0) -> 0 | J47: =IF(AND(J$7<=$G47,J$7>=$F47,$H47<>0,$H47<>""),$C47/$H47,0) -> -60371.062 | K47: =IF(AND(K$7<=$G47,K$7>=$F47,$H47<>0,$H47<>""),$C47/$H47,0) -> -60371.062 | L47: =IF(AND(L$7<=$G47,L$7>=$F47,$H47<>0,$H47<>""),$C47/$H47,0) -> -60371.062 | M47: =IF(AND(M$7<=$G47,M$7>=$F47,$H47<>0,$H47<>""),$C47/$H47,0) -> -60371.062 | N47: =IF(AND(N$7<=$G47,N$7>=$F47,$H47<>0,$H47<>""),$C47/$H47,0) -> -60371.062 | O47: =IF(AND(O$7<=$G47,O$7>=$F47,$H47<>0,$H47<>""),$C47/$H47,0) -> -60371.062 | P47: =IF(AND(P$7<=$G47,P$7>=$F47,$H47<>0,$H47<>""),$C47/$H47,0) -> -60371.062 | ... CZ47: =IF(AND(CZ$7<=$G47,CZ$7>=$F47,$H47<>0,$H47<>""),$C47/$H47,0) -> 0
B48: ='9. Development Costs'!B26 -> Landscape architect | C48: =-'9. Development Costs'!H26 -> 0 | D48: =ROUND(C48-E48,0) -> 0 | E48: =SUM(I48:CZ48) -> 0 | F48: =F$47 -> 46097 | G48: =G$47 -> 47042 | H48: =DATEDIF(F48,G48,"m")+1 -> 32 | I48: =IF(AND(I$7<=$G48,I$7>=$F48,$H48<>0,$H48<>""),$C48/$H48,0) -> 0 | J48: =IF(AND(J$7<=$G48,J$7>=$F48,$H48<>0,$H48<>""),$C48/$H48,0) -> 0 | K48: =IF(AND(K$7<=$G48,K$7>=$F48,$H48<>0,$H48<>""),$C48/$H48,0) -> 0 | L48: =IF(AND(L$7<=$G48,L$7>=$F48,$H48<>0,$H48<>""),$C48/$H48,0) -> 0 | M48: =IF(AND(M$7<=$G48,M$7>=$F48,$H48<>0,$H48<>""),$C48/$H48,0) -> 0 | N48: =IF(AND(N$7<=$G48,N$7>=$F48,$H48<>0,$H48<>""),$C48/$H48,0) -> 0 | O48: =IF(AND(O$7<=$G48,O$7>=$F48,$H48<>0,$H48<>""),$C48/$H48,0) -> 0 | P48: =IF(AND(P$7<=$G48,P$7>=$F48,$H48<>0,$H48<>""),$C48/$H48,0) -> 0 | ... CZ48: =IF(AND(CZ$7<=$G48,CZ$7>=$F48,$H48<>0,$H48<>""),$C48/$H48,0) -> 0
B49: ='9. Development Costs'!B27 -> Structural engineer | C49: =-'9. Development Costs'!H27 -> 0 | D49: =ROUND(C49-E49,0) -> 0 | E49: =SUM(I49:CZ49) -> 0 | F49: =F$47 -> 46097 | G49: =G$47 -> 47042 | H49: =DATEDIF(F49,G49,"m")+1 -> 32 | I49: =IF(AND(I$7<=$G49,I$7>=$F49,$H49<>0,$H49<>""),$C49/$H49,0) -> 0 | J49: =IF(AND(J$7<=$G49,J$7>=$F49,$H49<>0,$H49<>""),$C49/$H49,0) -> 0 | K49: =IF(AND(K$7<=$G49,K$7>=$F49,$H49<>0,$H49<>""),$C49/$H49,0) -> 0 | L49: =IF(AND(L$7<=$G49,L$7>=$F49,$H49<>0,$H49<>""),$C49/$H49,0) -> 0 | M49: =IF(AND(M$7<=$G49,M$7>=$F49,$H49<>0,$H49<>""),$C49/$H49,0) -> 0 | N49: =IF(AND(N$7<=$G49,N$7>=$F49,$H49<>0,$H49<>""),$C49/$H49,0) -> 0 | O49: =IF(AND(O$7<=$G49,O$7>=$F49,$H49<>0,$H49<>""),$C49/$H49,0) -> 0 | P49: =IF(AND(P$7<=$G49,P$7>=$F49,$H49<>0,$H49<>""),$C49/$H49,0) -> 0 | ... CZ49: =IF(AND(CZ$7<=$G49,CZ$7>=$F49,$H49<>0,$H49<>""),$C49/$H49,0) -> 0
B50: ='9. Development Costs'!B28 -> Civil engineer | C50: =-'9. Development Costs'!H28 -> 0 | D50: =ROUND(C50-E50,0) -> 0 | E50: =SUM(I50:CZ50) -> 0 | F50: =F$47 -> 46097 | G50: =G$47 -> 47042 | H50: =DATEDIF(F50,G50,"m")+1 -> 32 | I50: =IF(AND(I$7<=$G50,I$7>=$F50,$H50<>0,$H50<>""),$C50/$H50,0) -> 0 | J50: =IF(AND(J$7<=$G50,J$7>=$F50,$H50<>0,$H50<>""),$C50/$H50,0) -> 0 | K50: =IF(AND(K$7<=$G50,K$7>=$F50,$H50<>0,$H50<>""),$C50/$H50,0) -> 0 | L50: =IF(AND(L$7<=$G50,L$7>=$F50,$H50<>0,$H50<>""),$C50/$H50,0) -> 0 | M50: =IF(AND(M$7<=$G50,M$7>=$F50,$H50<>0,$H50<>""),$C50/$H50,0) -> 0 | N50: =IF(AND(N$7<=$G50,N$7>=$F50,$H50<>0,$H50<>""),$C50/$H50,0) -> 0 | O50: =IF(AND(O$7<=$G50,O$7>=$F50,$H50<>0,$H50<>""),$C50/$H50,0) -> 0 | P50: =IF(AND(P$7<=$G50,P$7>=$F50,$H50<>0,$H50<>""),$C50/$H50,0) -> 0 | ... CZ50: =IF(AND(CZ$7<=$G50,CZ$7>=$F50,$H50<>0,$H50<>""),$C50/$H50,0) -> 0
B51: ='9. Development Costs'!B29 -> Mechanical & Electrical engineer | C51: =-'9. Development Costs'!H29 -> 0 | D51: =ROUND(C51-E51,0) -> 0 | E51: =SUM(I51:CZ51) -> 0 | F51: =F$47 -> 46097 | G51: =G$47 -> 47042 | H51: =DATEDIF(F51,G51,"m")+1 -> 32 | I51: =IF(AND(I$7<=$G51,I$7>=$F51,$H51<>0,$H51<>""),$C51/$H51,0) -> 0 | J51: =IF(AND(J$7<=$G51,J$7>=$F51,$H51<>0,$H51<>""),$C51/$H51,0) -> 0 | K51: =IF(AND(K$7<=$G51,K$7>=$F51,$H51<>0,$H51<>""),$C51/$H51,0) -> 0 | L51: =IF(AND(L$7<=$G51,L$7>=$F51,$H51<>0,$H51<>""),$C51/$H51,0) -> 0 | M51: =IF(AND(M$7<=$G51,M$7>=$F51,$H51<>0,$H51<>""),$C51/$H51,0) -> 0 | N51: =IF(AND(N$7<=$G51,N$7>=$F51,$H51<>0,$H51<>""),$C51/$H51,0) -> 0 | O51: =IF(AND(O$7<=$G51,O$7>=$F51,$H51<>0,$H51<>""),$C51/$H51,0) -> 0 | P51: =IF(AND(P$7<=$G51,P$7>=$F51,$H51<>0,$H51<>""),$C51/$H51,0) -> 0 | ... CZ51: =IF(AND(CZ$7<=$G51,CZ$7>=$F51,$H51<>0,$H51<>""),$C51/$H51,0) -> 0
B52: ='9. Development Costs'!B30 -> Geotechnical engineer | C52: =-'9. Development Costs'!H30 -> 0 | D52: =ROUND(C52-E52,0) -> 0 | E52: =SUM(I52:CZ52) -> 0 | F52: =F$47 -> 46097 | G52: =G$47 -> 47042 | H52: =DATEDIF(F52,G52,"m")+1 -> 32 | I52: =IF(AND(I$7<=$G52,I$7>=$F52,$H52<>0,$H52<>""),$C52/$H52,0) -> 0 | J52: =IF(AND(J$7<=$G52,J$7>=$F52,$H52<>0,$H52<>""),$C52/$H52,0) -> 0 | K52: =IF(AND(K$7<=$G52,K$7>=$F52,$H52<>0,$H52<>""),$C52/$H52,0) -> 0 | L52: =IF(AND(L$7<=$G52,L$7>=$F52,$H52<>0,$H52<>""),$C52/$H52,0) -> 0 | M52: =IF(AND(M$7<=$G52,M$7>=$F52,$H52<>0,$H52<>""),$C52/$H52,0) -> 0 | N52: =IF(AND(N$7<=$G52,N$7>=$F52,$H52<>0,$H52<>""),$C52/$H52,0) -> 0 | O52: =IF(AND(O$7<=$G52,O$7>=$F52,$H52<>0,$H52<>""),$C52/$H52,0) -> 0 | P52: =IF(AND(P$7<=$G52,P$7>=$F52,$H52<>0,$H52<>""),$C52/$H52,0) -> 0 | ... CZ52: =IF(AND(CZ$7<=$G52,CZ$7>=$F52,$H52<>0,$H52<>""),$C52/$H52,0) -> 0
B53: ='9. Development Costs'!B31 -> Site Servicing Engineer | C53: =-'9. Development Costs'!H31 -> 0 | D53: =ROUND(C53-E53,0) -> 0 | E53: =SUM(I53:CZ53) -> 0 | F53: =F$47 -> 46097 | G53: =G$47 -> 47042 | H53: =DATEDIF(F53,G53,"m")+1 -> 32 | I53: =IF(AND(I$7<=$G53,I$7>=$F53,$H53<>0,$H53<>""),$C53/$H53,0) -> 0 | J53: =IF(AND(J$7<=$G53,J$7>=$F53,$H53<>0,$H53<>""),$C53/$H53,0) -> 0 | K53: =IF(AND(K$7<=$G53,K$7>=$F53,$H53<>0,$H53<>""),$C53/$H53,0) -> 0 | L53: =IF(AND(L$7<=$G53,L$7>=$F53,$H53<>0,$H53<>""),$C53/$H53,0) -> 0 | M53: =IF(AND(M$7<=$G53,M$7>=$F53,$H53<>0,$H53<>""),$C53/$H53,0) -> 0 | N53: =IF(AND(N$7<=$G53,N$7>=$F53,$H53<>0,$H53<>""),$C53/$H53,0) -> 0 | O53: =IF(AND(O$7<=$G53,O$7>=$F53,$H53<>0,$H53<>""),$C53/$H53,0) -> 0 | P53: =IF(AND(P$7<=$G53,P$7>=$F53,$H53<>0,$H53<>""),$C53/$H53,0) -> 0 | ... CZ53: =IF(AND(CZ$7<=$G53,CZ$7>=$F53,$H53<>0,$H53<>""),$C53/$H53,0) -> 0
B54: ='9. Development Costs'!B32 -> Survey | C54: =-'9. Development Costs'!H32 -> 0 | D54: =ROUND(C54-E54,0) -> 0 | E54: =SUM(I54:CZ54) -> 0 | F54: =F$47 -> 46097 | G54: =G$47 -> 47042 | H54: =DATEDIF(F54,G54,"m")+1 -> 32 | I54: =IF(AND(I$7<=$G54,I$7>=$F54,$H54<>0,$H54<>""),$C54/$H54,0) -> 0 | J54: =IF(AND(J$7<=$G54,J$7>=$F54,$H54<>0,$H54<>""),$C54/$H54,0) -> 0 | K54: =IF(AND(K$7<=$G54,K$7>=$F54,$H54<>0,$H54<>""),$C54/$H54,0) -> 0 | L54: =IF(AND(L$7<=$G54,L$7>=$F54,$H54<>0,$H54<>""),$C54/$H54,0) -> 0 | M54: =IF(AND(M$7<=$G54,M$7>=$F54,$H54<>0,$H54<>""),$C54/$H54,0) -> 0 | N54: =IF(AND(N$7<=$G54,N$7>=$F54,$H54<>0,$H54<>""),$C54/$H54,0) -> 0 | O54: =IF(AND(O$7<=$G54,O$7>=$F54,$H54<>0,$H54<>""),$C54/$H54,0) -> 0 | P54: =IF(AND(P$7<=$G54,P$7>=$F54,$H54<>0,$H54<>""),$C54/$H54,0) -> 0 | ... CZ54: =IF(AND(CZ$7<=$G54,CZ$7>=$F54,$H54<>0,$H54<>""),$C54/$H54,0) -> 0
B55: Other | C55: =-'9. Development Costs'!H35 -> 0 | D55: =ROUND(C55-E55,0) -> 0 | E55: =SUM(I55:CZ55) -> 0 | F55: =F$47 -> 46097 | G55: =G$47 -> 47042 | H55: =DATEDIF(F55,G55,"m")+1 -> 32 | I55: =IF(AND(I$7<=$G55,I$7>=$F55,$H55<>0,$H55<>""),$C55/$H55,0) -> 0 | J55: =IF(AND(J$7<=$G55,J$7>=$F55,$H55<>0,$H55<>""),$C55/$H55,0) -> 0 | K55: =IF(AND(K$7<=$G55,K$7>=$F55,$H55<>0,$H55<>""),$C55/$H55,0) -> 0 | L55: =IF(AND(L$7<=$G55,L$7>=$F55,$H55<>0,$H55<>""),$C55/$H55,0) -> 0 | M55: =IF(AND(M$7<=$G55,M$7>=$F55,$H55<>0,$H55<>""),$C55/$H55,0) -> 0 | N55: =IF(AND(N$7<=$G55,N$7>=$F55,$H55<>0,$H55<>""),$C55/$H55,0) -> 0 | O55: =IF(AND(O$7<=$G55,O$7>=$F55,$H55<>0,$H55<>""),$C55/$H55,0) -> 0 | P55: =IF(AND(P$7<=$G55,P$7>=$F55,$H55<>0,$H55<>""),$C55/$H55,0) -> 0 | ... CZ55: =IF(AND(CZ$7<=$G55,CZ$7>=$F55,$H55<>0,$H55<>""),$C55/$H55,0) -> 0
B56: ='9. Development Costs'!B36 -> Environmental consultant | C56: =-'9. Development Costs'!H36 -> 0 | D56: =ROUND(C56-E56,0) -> 0 | E56: =SUM(I56:CZ56) -> 0 | F56: =F$47 -> 46097 | G56: =G$47 -> 47042 | H56: =DATEDIF(F56,G56,"m")+1 -> 32 | I56: =IF(AND(I$7<=$G56,I$7>=$F56,$H56<>0,$H56<>""),$C56/$H56,0) -> 0 | J56: =IF(AND(J$7<=$G56,J$7>=$F56,$H56<>0,$H56<>""),$C56/$H56,0) -> 0 | K56: =IF(AND(K$7<=$G56,K$7>=$F56,$H56<>0,$H56<>""),$C56/$H56,0) -> 0 | L56: =IF(AND(L$7<=$G56,L$7>=$F56,$H56<>0,$H56<>""),$C56/$H56,0) -> 0 | M56: =IF(AND(M$7<=$G56,M$7>=$F56,$H56<>0,$H56<>""),$C56/$H56,0) -> 0 | N56: =IF(AND(N$7<=$G56,N$7>=$F56,$H56<>0,$H56<>""),$C56/$H56,0) -> 0 | O56: =IF(AND(O$7<=$G56,O$7>=$F56,$H56<>0,$H56<>""),$C56/$H56,0) -> 0 | P56: =IF(AND(P$7<=$G56,P$7>=$F56,$H56<>0,$H56<>""),$C56/$H56,0) -> 0 | ... CZ56: =IF(AND(CZ$7<=$G56,CZ$7>=$F56,$H56<>0,$H56<>""),$C56/$H56,0) -> 0
B57: ='9. Development Costs'!B37 -> Interior design | C57: =-'9. Development Costs'!H37 -> 0 | D57: =ROUND(C57-E57,0) -> 0 | E57: =SUM(I57:CZ57) -> 0 | F57: =F$47 -> 46097 | G57: =G$47 -> 47042 | H57: =DATEDIF(F57,G57,"m")+1 -> 32 | I57: =IF(AND(I$7<=$G57,I$7>=$F57,$H57<>0,$H57<>""),$C57/$H57,0) -> 0 | J57: =IF(AND(J$7<=$G57,J$7>=$F57,$H57<>0,$H57<>""),$C57/$H57,0) -> 0 | K57: =IF(AND(K$7<=$G57,K$7>=$F57,$H57<>0,$H57<>""),$C57/$H57,0) -> 0 | L57: =IF(AND(L$7<=$G57,L$7>=$F57,$H57<>0,$H57<>""),$C57/$H57,0) -> 0 | M57: =IF(AND(M$7<=$G57,M$7>=$F57,$H57<>0,$H57<>""),$C57/$H57,0) -> 0 | N57: =IF(AND(N$7<=$G57,N$7>=$F57,$H57<>0,$H57<>""),$C57/$H57,0) -> 0 | O57: =IF(AND(O$7<=$G57,O$7>=$F57,$H57<>0,$H57<>""),$C57/$H57,0) -> 0 | P57: =IF(AND(P$7<=$G57,P$7>=$F57,$H57<>0,$H57<>""),$C57/$H57,0) -> 0 | ... CZ57: =IF(AND(CZ$7<=$G57,CZ$7>=$F57,$H57<>0,$H57<>""),$C57/$H57,0) -> 0
B58: ='9. Development Costs'!B38 -> Traffic consultant | C58: =-'9. Development Costs'!H38 -> 0 | D58: =ROUND(C58-E58,0) -> 0 | E58: =SUM(I58:CZ58) -> 0 | F58: =F$47 -> 46097 | G58: =G$47 -> 47042 | H58: =DATEDIF(F58,G58,"m")+1 -> 32 | I58: =IF(AND(I$7<=$G58,I$7>=$F58,$H58<>0,$H58<>""),$C58/$H58,0) -> 0 | J58: =IF(AND(J$7<=$G58,J$7>=$F58,$H58<>0,$H58<>""),$C58/$H58,0) -> 0 | K58: =IF(AND(K$7<=$G58,K$7>=$F58,$H58<>0,$H58<>""),$C58/$H58,0) -> 0 | L58: =IF(AND(L$7<=$G58,L$7>=$F58,$H58<>0,$H58<>""),$C58/$H58,0) -> 0 | M58: =IF(AND(M$7<=$G58,M$7>=$F58,$H58<>0,$H58<>""),$C58/$H58,0) -> 0 | N58: =IF(AND(N$7<=$G58,N$7>=$F58,$H58<>0,$H58<>""),$C58/$H58,0) -> 0 | O58: =IF(AND(O$7<=$G58,O$7>=$F58,$H58<>0,$H58<>""),$C58/$H58,0) -> 0 | P58: =IF(AND(P$7<=$G58,P$7>=$F58,$H58<>0,$H58<>""),$C58/$H58,0) -> 0 | ... CZ58: =IF(AND(CZ$7<=$G58,CZ$7>=$F58,$H58<>0,$H58<>""),$C58/$H58,0) -> 0
B59: ='9. Development Costs'!B39 -> Disbursements | C59: =-'9. Development Costs'!H39 -> 0 | D59: =ROUND(C59-E59,0) -> 0 | E59: =SUM(I59:CZ59) -> 0 | F59: =F$47 -> 46097 | G59: =G$47 -> 47042 | H59: =DATEDIF(F59,G59,"m")+1 -> 32 | I59: =IF(AND(I$7<=$G59,I$7>=$F59,$H59<>0,$H59<>""),$C59/$H59,0) -> 0 | J59: =IF(AND(J$7<=$G59,J$7>=$F59,$H59<>0,$H59<>""),$C59/$H59,0) -> 0 | K59: =IF(AND(K$7<=$G59,K$7>=$F59,$H59<>0,$H59<>""),$C59/$H59,0) -> 0 | L59: =IF(AND(L$7<=$G59,L$7>=$F59,$H59<>0,$H59<>""),$C59/$H59,0) -> 0 | M59: =IF(AND(M$7<=$G59,M$7>=$F59,$H59<>0,$H59<>""),$C59/$H59,0) -> 0 | N59: =IF(AND(N$7<=$G59,N$7>=$F59,$H59<>0,$H59<>""),$C59/$H59,0) -> 0 | O59: =IF(AND(O$7<=$G59,O$7>=$F59,$H59<>0,$H59<>""),$C59/$H59,0) -> 0 | P59: =IF(AND(P$7<=$G59,P$7>=$F59,$H59<>0,$H59<>""),$C59/$H59,0) -> 0 | ... CZ59: =IF(AND(CZ$7<=$G59,CZ$7>=$F59,$H59<>0,$H59<>""),$C59/$H59,0) -> 0
B60: ='9. Development Costs'!B40 -> Professional fee contingency | C60: =-'9. Development Costs'!H40 -> -96593.7 | D60: =ROUND(C60-E60,0) -> 0 | E60: =SUM(I60:CZ60) -> -96593.7 | F60: =F$47 -> 46097 | G60: =G$47 -> 47042 | H60: =DATEDIF(F60,G60,"m")+1 -> 32 | I60: =IF(AND(I$7<=$G60,I$7>=$F60,$H60<>0,$H60<>""),$C60/$H60,0) -> 0 | J60: =IF(AND(J$7<=$G60,J$7>=$F60,$H60<>0,$H60<>""),$C60/$H60,0) -> -3018.5531 | K60: =IF(AND(K$7<=$G60,K$7>=$F60,$H60<>0,$H60<>""),$C60/$H60,0) -> -3018.5531 | L60: =IF(AND(L$7<=$G60,L$7>=$F60,$H60<>0,$H60<>""),$C60/$H60,0) -> -3018.5531 | M60: =IF(AND(M$7<=$G60,M$7>=$F60,$H60<>0,$H60<>""),$C60/$H60,0) -> -3018.5531 | N60: =IF(AND(N$7<=$G60,N$7>=$F60,$H60<>0,$H60<>""),$C60/$H60,0) -> -3018.5531 | O60: =IF(AND(O$7<=$G60,O$7>=$F60,$H60<>0,$H60<>""),$C60/$H60,0) -> -3018.5531 | P60: =IF(AND(P$7<=$G60,P$7>=$F60,$H60<>0,$H60<>""),$C60/$H60,0) -> -3018.5531 | ... CZ60: =IF(AND(CZ$7<=$G60,CZ$7>=$F60,$H60<>0,$H60<>""),$C60/$H60,0) -> 0
B61: ='9. Development Costs'!B41 -> Total Professional Fees | C61: =SUM(C47:C60) -> -2028467.7 | D61: =C61-E61 -> 0 | E61: =SUM(I61:CZ61) -> -2028467.7 | I61: =SUM(I47:I60) -> 0 | J61: =SUM(J47:J60) -> -63389.616 | K61: =SUM(K47:K60) -> -63389.616 | L61: =SUM(L47:L60) -> -63389.616 | M61: =SUM(M47:M60) -> -63389.616 | N61: =SUM(N47:N60) -> -63389.616 | O61: =SUM(O47:O60) -> -63389.616 | P61: =SUM(P47:P60) -> -63389.616 | ... CZ61: =SUM(CZ47:CZ60) -> 0
B63: DEVELOPMENT MANAGEMENT
B64: ='9. Development Costs'!B46 -> Total Development Management Fee | C64: =-'9. Development Costs'!H46 -> -1692804.6 | D64: =ROUND(C64-E64,0) -> 0 | E64: =SUM(I64:CZ64) -> -1692804.6 | F64: ='8. Schedule'!D13 -> 46069 | G64: ='8. Schedule'!E17 -> 47042 | H64: =DATEDIF(F64,G64,"m")+1 -> 33 | I64: =IF(AND(I$7<=$G64,I$7>=$F64,$H64<>0,$H64<>""),$C64/$H64,0) -> -51297.109 | J64: =IF(AND(J$7<=$G64,J$7>=$F64,$H64<>0,$H64<>""),$C64/$H64,0) -> -51297.109 | K64: =IF(AND(K$7<=$G64,K$7>=$F64,$H64<>0,$H64<>""),$C64/$H64,0) -> -51297.109 | L64: =IF(AND(L$7<=$G64,L$7>=$F64,$H64<>0,$H64<>""),$C64/$H64,0) -> -51297.109 | M64: =IF(AND(M$7<=$G64,M$7>=$F64,$H64<>0,$H64<>""),$C64/$H64,0) -> -51297.109 | N64: =IF(AND(N$7<=$G64,N$7>=$F64,$H64<>0,$H64<>""),$C64/$H64,0) -> -51297.109 | O64: =IF(AND(O$7<=$G64,O$7>=$F64,$H64<>0,$H64<>""),$C64/$H64,0) -> -51297.109 | P64: =IF(AND(P$7<=$G64,P$7>=$F64,$H64<>0,$H64<>""),$C64/$H64,0) -> -51297.109 | ... CZ64: =IF(AND(CZ$7<=$G64,CZ$7>=$F64,$H64<>0,$H64<>""),$C64/$H64,0) -> 0
B66: PERMIT AND APPROVALS
B67: ='9. Development Costs'!B49 -> Development Permit | C67: =-'9. Development Costs'!H49 -> 0 | D67: =ROUND(C67-E67,0) -> 0 | E67: =SUM(I67:CZ67) -> 0 | F67: ='8. Schedule'!D15 -> 46097 | G67: ='8. Schedule'!E15 -> 46462 | H67: =DATEDIF(F67,G67,"m")+1 -> 13 | I67: =IF(AND(I$7<=$G67,I$7>=$F67,$H67<>0,$H67<>""),$C67/$H67,0) -> 0 | J67: =IF(AND(J$7<=$G67,J$7>=$F67,$H67<>0,$H67<>""),$C67/$H67,0) -> 0 | K67: =IF(AND(K$7<=$G67,K$7>=$F67,$H67<>0,$H67<>""),$C67/$H67,0) -> 0 | L67: =IF(AND(L$7<=$G67,L$7>=$F67,$H67<>0,$H67<>""),$C67/$H67,0) -> 0 | M67: =IF(AND(M$7<=$G67,M$7>=$F67,$H67<>0,$H67<>""),$C67/$H67,0) -> 0 | N67: =IF(AND(N$7<=$G67,N$7>=$F67,$H67<>0,$H67<>""),$C67/$H67,0) -> 0 | O67: =IF(AND(O$7<=$G67,O$7>=$F67,$H67<>0,$H67<>""),$C67/$H67,0) -> 0 | P67: =IF(AND(P$7<=$G67,P$7>=$F67,$H67<>0,$H67<>""),$C67/$H67,0) -> 0 | ... CZ67: =IF(AND(CZ$7<=$G67,CZ$7>=$F67,$H67<>0,$H67<>""),$C67/$H67,0) -> 0
B68: ='9. Development Costs'!B50 -> Rezoning | C68: =-'9. Development Costs'!H50 -> 0 | D68: =ROUND(C68-E68,0) -> 0 | E68: =SUM(I68:CZ68) -> 0 | F68: =F67 -> 46097 | G68: =G67 -> 46462 | H68: =DATEDIF(F68,G68,"m")+1 -> 13 | I68: =IF(AND(I$7<=$G68,I$7>=$F68,$H68<>0,$H68<>""),$C68/$H68,0) -> 0 | J68: =IF(AND(J$7<=$G68,J$7>=$F68,$H68<>0,$H68<>""),$C68/$H68,0) -> 0 | K68: =IF(AND(K$7<=$G68,K$7>=$F68,$H68<>0,$H68<>""),$C68/$H68,0) -> 0 | L68: =IF(AND(L$7<=$G68,L$7>=$F68,$H68<>0,$H68<>""),$C68/$H68,0) -> 0 | M68: =IF(AND(M$7<=$G68,M$7>=$F68,$H68<>0,$H68<>""),$C68/$H68,0) -> 0 | N68: =IF(AND(N$7<=$G68,N$7>=$F68,$H68<>0,$H68<>""),$C68/$H68,0) -> 0 | O68: =IF(AND(O$7<=$G68,O$7>=$F68,$H68<>0,$H68<>""),$C68/$H68,0) -> 0 | P68: =IF(AND(P$7<=$G68,P$7>=$F68,$H68<>0,$H68<>""),$C68/$H68,0) -> 0 | ... CZ68: =IF(AND(CZ$7<=$G68,CZ$7>=$F68,$H68<>0,$H68<>""),$C68/$H68,0) -> 0
B69: ='9. Development Costs'!B51 -> Building permit | C69: =-'9. Development Costs'!H51 -> 0 | D69: =ROUND(C69-E69,0) -> 0 | E69: =SUM(I69:CZ69) -> 0 | F69: =F68 -> 46097 | G69: =G68 -> 46462 | H69: =DATEDIF(F69,G69,"m")+1 -> 13 | I69: =IF(AND(I$7<=$G69,I$7>=$F69,$H69<>0,$H69<>""),$C69/$H69,0) -> 0 | J69: =IF(AND(J$7<=$G69,J$7>=$F69,$H69<>0,$H69<>""),$C69/$H69,0) -> 0 | K69: =IF(AND(K$7<=$G69,K$7>=$F69,$H69<>0,$H69<>""),$C69/$H69,0) -> 0 | L69: =IF(AND(L$7<=$G69,L$7>=$F69,$H69<>0,$H69<>""),$C69/$H69,0) -> 0 | M69: =IF(AND(M$7<=$G69,M$7>=$F69,$H69<>0,$H69<>""),$C69/$H69,0) -> 0 | N69: =IF(AND(N$7<=$G69,N$7>=$F69,$H69<>0,$H69<>""),$C69/$H69,0) -> 0 | O69: =IF(AND(O$7<=$G69,O$7>=$F69,$H69<>0,$H69<>""),$C69/$H69,0) -> 0 | P69: =IF(AND(P$7<=$G69,P$7>=$F69,$H69<>0,$H69<>""),$C69/$H69,0) -> 0 | ... CZ69: =IF(AND(CZ$7<=$G69,CZ$7>=$F69,$H69<>0,$H69<>""),$C69/$H69,0) -> 0
B70: ='9. Development Costs'!B52 -> City Development charges | C70: =-'9. Development Costs'!H52 -> 0 | D70: =ROUND(C70-E70,0) -> 0 | E70: =SUM(I70:CZ70) -> 0 | F70: ='8. Schedule'!E17 -> 47042 | G70: =F70 -> 47042 | H70: =DATEDIF(F70,G70,"m")+1 -> 1 | I70: =IF(AND(I$7<=$G70,I$7>=$F70,$H70<>0,$H70<>""),$C70/$H70,0) -> 0 | J70: =IF(AND(J$7<=$G70,J$7>=$F70,$H70<>0,$H70<>""),$C70/$H70,0) -> 0 | K70: =IF(AND(K$7<=$G70,K$7>=$F70,$H70<>0,$H70<>""),$C70/$H70,0) -> 0 | L70: =IF(AND(L$7<=$G70,L$7>=$F70,$H70<>0,$H70<>""),$C70/$H70,0) -> 0 | M70: =IF(AND(M$7<=$G70,M$7>=$F70,$H70<>0,$H70<>""),$C70/$H70,0) -> 0 | N70: =IF(AND(N$7<=$G70,N$7>=$F70,$H70<>0,$H70<>""),$C70/$H70,0) -> 0 | O70: =IF(AND(O$7<=$G70,O$7>=$F70,$H70<>0,$H70<>""),$C70/$H70,0) -> 0 | P70: =IF(AND(P$7<=$G70,P$7>=$F70,$H70<>0,$H70<>""),$C70/$H70,0) -> 0 | ... CZ70: =IF(AND(CZ$7<=$G70,CZ$7>=$F70,$H70<>0,$H70<>""),$C70/$H70,0) -> 0
B71: ='9. Development Costs'!B53 -> Park Dedication Fee | C71: =-'9. Development Costs'!H53 -> 0 | D71: =ROUND(C71-E71,0) -> 0 | E71: =SUM(I71:CZ71) -> 0 | F71: =F70 -> 47042 | G71: =G70 -> 47042 | H71: =DATEDIF(F71,G71,"m")+1 -> 1 | I71: =IF(AND(I$7<=$G71,I$7>=$F71,$H71<>0,$H71<>""),$C71/$H71,0) -> 0 | J71: =IF(AND(J$7<=$G71,J$7>=$F71,$H71<>0,$H71<>""),$C71/$H71,0) -> 0 | K71: =IF(AND(K$7<=$G71,K$7>=$F71,$H71<>0,$H71<>""),$C71/$H71,0) -> 0 | L71: =IF(AND(L$7<=$G71,L$7>=$F71,$H71<>0,$H71<>""),$C71/$H71,0) -> 0 | M71: =IF(AND(M$7<=$G71,M$7>=$F71,$H71<>0,$H71<>""),$C71/$H71,0) -> 0 | N71: =IF(AND(N$7<=$G71,N$7>=$F71,$H71<>0,$H71<>""),$C71/$H71,0) -> 0 | O71: =IF(AND(O$7<=$G71,O$7>=$F71,$H71<>0,$H71<>""),$C71/$H71,0) -> 0 | P71: =IF(AND(P$7<=$G71,P$7>=$F71,$H71<>0,$H71<>""),$C71/$H71,0) -> 0 | ... CZ71: =IF(AND(CZ$7<=$G71,CZ$7>=$F71,$H71<>0,$H71<>""),$C71/$H71,0) -> 0
B72: ='9. Development Costs'!B54 -> Other Development Charges | C72: =-'9. Development Costs'!H54 -> -7192106 | D72: =ROUND(C72-E72,0) -> 0 | E72: =SUM(I72:CZ72) -> -7192106 | F72: =F71 -> 47042 | G72: =G71 -> 47042 | H72: =DATEDIF(F72,G72,"m")+1 -> 1 | I72: =IF(AND(I$7<=$G72,I$7>=$F72,$H72<>0,$H72<>""),$C72/$H72,0) -> 0 | J72: =IF(AND(J$7<=$G72,J$7>=$F72,$H72<>0,$H72<>""),$C72/$H72,0) -> 0 | K72: =IF(AND(K$7<=$G72,K$7>=$F72,$H72<>0,$H72<>""),$C72/$H72,0) -> 0 | L72: =IF(AND(L$7<=$G72,L$7>=$F72,$H72<>0,$H72<>""),$C72/$H72,0) -> 0 | M72: =IF(AND(M$7<=$G72,M$7>=$F72,$H72<>0,$H72<>""),$C72/$H72,0) -> 0 | N72: =IF(AND(N$7<=$G72,N$7>=$F72,$H72<>0,$H72<>""),$C72/$H72,0) -> 0 | O72: =IF(AND(O$7<=$G72,O$7>=$F72,$H72<>0,$H72<>""),$C72/$H72,0) -> 0 | P72: =IF(AND(P$7<=$G72,P$7>=$F72,$H72<>0,$H72<>""),$C72/$H72,0) -> 0 | ... CZ72: =IF(AND(CZ$7<=$G72,CZ$7>=$F72,$H72<>0,$H72<>""),$C72/$H72,0) -> 0
B73: ='9. Development Costs'!B55 -> Sub-Meter Installation Fee Credit | C73: =-'9. Development Costs'!H55 -> 102000 | E73: =SUM(I73:CZ73) -> 102000 | F73: =+G41 -> 47042 | G73: =+F73 -> 47042 | H73: =DATEDIF(F73,G73,"m")+1 -> 1 | I73: =IF(AND(I$7<=$G73,I$7>=$F73,$H73<>0,$H73<>""),$C73/$H73,0) -> 0 | J73: =IF(AND(J$7<=$G73,J$7>=$F73,$H73<>0,$H73<>""),$C73/$H73,0) -> 0 | K73: =IF(AND(K$7<=$G73,K$7>=$F73,$H73<>0,$H73<>""),$C73/$H73,0) -> 0 | L73: =IF(AND(L$7<=$G73,L$7>=$F73,$H73<>0,$H73<>""),$C73/$H73,0) -> 0 | M73: =IF(AND(M$7<=$G73,M$7>=$F73,$H73<>0,$H73<>""),$C73/$H73,0) -> 0 | N73: =IF(AND(N$7<=$G73,N$7>=$F73,$H73<>0,$H73<>""),$C73/$H73,0) -> 0 | O73: =IF(AND(O$7<=$G73,O$7>=$F73,$H73<>0,$H73<>""),$C73/$H73,0) -> 0 | P73: =IF(AND(P$7<=$G73,P$7>=$F73,$H73<>0,$H73<>""),$C73/$H73,0) -> 0 | ... CZ73: =IF(AND(CZ$7<=$G73,CZ$7>=$F73,$H73<>0,$H73<>""),$C73/$H73,0) -> 0
B74: ='9. Development Costs'!B56 -> Utilities Connection | C74: =-'9. Development Costs'!H56 -> 0 | D74: =ROUND(C74-E74,0) -> 0 | E74: =SUM(I74:CZ74) -> 0 | F74: =F$47 -> 46097 | G74: =G$47 -> 47042 | H74: =DATEDIF(F74,G74,"m")+1 -> 32 | I74: =IF(AND(I$7<=$G74,I$7>=$F74,$H74<>0,$H74<>""),$C74/$H74,0) -> 0 | J74: =IF(AND(J$7<=$G74,J$7>=$F74,$H74<>0,$H74<>""),$C74/$H74,0) -> 0 | K74: =IF(AND(K$7<=$G74,K$7>=$F74,$H74<>0,$H74<>""),$C74/$H74,0) -> 0 | L74: =IF(AND(L$7<=$G74,L$7>=$F74,$H74<>0,$H74<>""),$C74/$H74,0) -> 0 | M74: =IF(AND(M$7<=$G74,M$7>=$F74,$H74<>0,$H74<>""),$C74/$H74,0) -> 0 | N74: =IF(AND(N$7<=$G74,N$7>=$F74,$H74<>0,$H74<>""),$C74/$H74,0) -> 0 | O74: =IF(AND(O$7<=$G74,O$7>=$F74,$H74<>0,$H74<>""),$C74/$H74,0) -> 0 | P74: =IF(AND(P$7<=$G74,P$7>=$F74,$H74<>0,$H74<>""),$C74/$H74,0) -> 0 | ... CZ74: =IF(AND(CZ$7<=$G74,CZ$7>=$F74,$H74<>0,$H74<>""),$C74/$H74,0) -> 0
B75: ='9. Development Costs'!B57 -> Land titles | C75: =-'9. Development Costs'!H57 -> 0 | D75: =ROUND(C75-E75,0) -> 0 | E75: =SUM(I75:CZ75) -> 0 | F75: =F74 -> 46097 | G75: =F75 -> 46097 | H75: =DATEDIF(F75,G75,"m")+1 -> 1 | I75: =IF(AND(I$7<=$G75,I$7>=$F75,$H75<>0,$H75<>""),$C75/$H75,0) -> 0 | J75: =IF(AND(J$7<=$G75,J$7>=$F75,$H75<>0,$H75<>""),$C75/$H75,0) -> 0 | K75: =IF(AND(K$7<=$G75,K$7>=$F75,$H75<>0,$H75<>""),$C75/$H75,0) -> 0 | L75: =IF(AND(L$7<=$G75,L$7>=$F75,$H75<>0,$H75<>""),$C75/$H75,0) -> 0 | M75: =IF(AND(M$7<=$G75,M$7>=$F75,$H75<>0,$H75<>""),$C75/$H75,0) -> 0 | N75: =IF(AND(N$7<=$G75,N$7>=$F75,$H75<>0,$H75<>""),$C75/$H75,0) -> 0 | O75: =IF(AND(O$7<=$G75,O$7>=$F75,$H75<>0,$H75<>""),$C75/$H75,0) -> 0 | P75: =IF(AND(P$7<=$G75,P$7>=$F75,$H75<>0,$H75<>""),$C75/$H75,0) -> 0 | ... CZ75: =IF(AND(CZ$7<=$G75,CZ$7>=$F75,$H75<>0,$H75<>""),$C75/$H75,0) -> 0
B76: ='9. Development Costs'!B58 -> Permit and approval contingency | C76: =-'9. Development Costs'!H58 -> -359605.3 | D76: =ROUND(C76-E76,0) -> 0 | E76: =SUM(I76:CZ76) -> -359605.3 | F76: =F$47 -> 46097 | G76: =G67 -> 46462 | H76: =DATEDIF(F76,G76,"m")+1 -> 13 | I76: =IF(AND(I$7<=$G76,I$7>=$F76,$H76<>0,$H76<>""),$C76/$H76,0) -> 0 | J76: =IF(AND(J$7<=$G76,J$7>=$F76,$H76<>0,$H76<>""),$C76/$H76,0) -> -27661.946 | K76: =IF(AND(K$7<=$G76,K$7>=$F76,$H76<>0,$H76<>""),$C76/$H76,0) -> -27661.946 | L76: =IF(AND(L$7<=$G76,L$7>=$F76,$H76<>0,$H76<>""),$C76/$H76,0) -> -27661.946 | M76: =IF(AND(M$7<=$G76,M$7>=$F76,$H76<>0,$H76<>""),$C76/$H76,0) -> -27661.946 | N76: =IF(AND(N$7<=$G76,N$7>=$F76,$H76<>0,$H76<>""),$C76/$H76,0) -> -27661.946 | O76: =IF(AND(O$7<=$G76,O$7>=$F76,$H76<>0,$H76<>""),$C76/$H76,0) -> -27661.946 | P76: =IF(AND(P$7<=$G76,P$7>=$F76,$H76<>0,$H76<>""),$C76/$H76,0) -> -27661.946 | ... CZ76: =IF(AND(CZ$7<=$G76,CZ$7>=$F76,$H76<>0,$H76<>""),$C76/$H76,0) -> 0
B77: ='9. Development Costs'!B59 -> Total Permit and Approvals | C77: =-'9. Development Costs'!H59 -> -7449711.3 | D77: =C77-E77 -> 0 | E77: =SUM(I77:CZ77) -> -7449711.3 | I77: =SUM(I67:I76) -> 0 | J77: =SUM(J67:J76) -> -27661.946 | K77: =SUM(K67:K76) -> -27661.946 | L77: =SUM(L67:L76) -> -27661.946 | M77: =SUM(M67:M76) -> -27661.946 | N77: =SUM(N67:N76) -> -27661.946 | O77: =SUM(O67:O76) -> -27661.946 | P77: =SUM(P67:P76) -> -27661.946 | ... CZ77: =SUM(CZ67:CZ76) -> 0
B79: MARKETING AND LEASING
B80: ='9. Development Costs'!B65 -> Marketing | C80: =-'9. Development Costs'!H66 -> -1676350 | D80: =ROUND(C80-E80,0) -> 0 | E80: =SUM(I80:CZ80) -> -1676350 | F80: ='8. Schedule'!D19 -> 46981 | G80: ='8. Schedule'!E19 -> 47315 | H80: =DATEDIF(F80,G80,"m")+1 -> 12 | I80: =IF(AND(I$7<=$G80,I$7>=$F80,$H80<>0,$H80<>""),$C80/$H80,0) -> 0 | J80: =IF(AND(J$7<=$G80,J$7>=$F80,$H80<>0,$H80<>""),$C80/$H80,0) -> 0 | K80: =IF(AND(K$7<=$G80,K$7>=$F80,$H80<>0,$H80<>""),$C80/$H80,0) -> 0 | L80: =IF(AND(L$7<=$G80,L$7>=$F80,$H80<>0,$H80<>""),$C80/$H80,0) -> 0 | M80: =IF(AND(M$7<=$G80,M$7>=$F80,$H80<>0,$H80<>""),$C80/$H80,0) -> 0 | N80: =IF(AND(N$7<=$G80,N$7>=$F80,$H80<>0,$H80<>""),$C80/$H80,0) -> 0 | O80: =IF(AND(O$7<=$G80,O$7>=$F80,$H80<>0,$H80<>""),$C80/$H80,0) -> 0 | P80: =IF(AND(P$7<=$G80,P$7>=$F80,$H80<>0,$H80<>""),$C80/$H80,0) -> 0 | ... CZ80: =IF(AND(CZ$7<=$G80,CZ$7>=$F80,$H80<>0,$H80<>""),$C80/$H80,0) -> 0
B81: ='9. Development Costs'!B66 -> Total Marketing and Leasing | C81: =C80 -> -1676350 | D81: =C81-E81 -> 0 | E81: =SUM(I81:CZ81) -> -1676350 | I81: =SUM(I80:I80) -> 0 | J81: =SUM(J80:J80) -> 0 | K81: =SUM(K80:K80) -> 0 | L81: =SUM(L80:L80) -> 0 | M81: =SUM(M80:M80) -> 0 | N81: =SUM(N80:N80) -> 0 | O81: =SUM(O80:O80) -> 0 | P81: =SUM(P80:P80) -> 0 | ... CZ81: =SUM(CZ80:CZ80) -> 0
B83: FINANCING AND INTEREST
B84: ='9. Development Costs'!B69 -> Appraisal | C84: =-'9. Development Costs'!H69 -> 0 | D84: =ROUND(C84-E84,0) -> 0 | E84: =SUM(I84:CZ84) -> 0 | F84: ='8. Schedule'!D13 -> 46069 | G84: ='8. Schedule'!E13 -> 46069 | H84: =DATEDIF(F84,G84,"m")+1 -> 1 | I84: =IF(AND(I$7<=$G84,I$7>=$F84,$H84<>0,$H84<>""),$C84/$H84,0) -> 0 | J84: =IF(AND(J$7<=$G84,J$7>=$F84,$H84<>0,$H84<>""),$C84/$H84,0) -> 0 | K84: =IF(AND(K$7<=$G84,K$7>=$F84,$H84<>0,$H84<>""),$C84/$H84,0) -> 0 | L84: =IF(AND(L$7<=$G84,L$7>=$F84,$H84<>0,$H84<>""),$C84/$H84,0) -> 0 | M84: =IF(AND(M$7<=$G84,M$7>=$F84,$H84<>0,$H84<>""),$C84/$H84,0) -> 0 | N84: =IF(AND(N$7<=$G84,N$7>=$F84,$H84<>0,$H84<>""),$C84/$H84,0) -> 0 | O84: =IF(AND(O$7<=$G84,O$7>=$F84,$H84<>0,$H84<>""),$C84/$H84,0) -> 0 | P84: =IF(AND(P$7<=$G84,P$7>=$F84,$H84<>0,$H84<>""),$C84/$H84,0) -> 0 | ... CZ84: =IF(AND(CZ$7<=$G84,CZ$7>=$F84,$H84<>0,$H84<>""),$C84/$H84,0) -> 0
B85: ='9. Development Costs'!B70 -> Legal fees | C85: =-'9. Development Costs'!H70 -> 0 | D85: =ROUND(C85-E85,0) -> 0 | E85: =SUM(I85:CZ85) -> 0 | F85: =F84 -> 46069 | G85: =G84 -> 46069 | H85: =DATEDIF(F85,G85,"m")+1 -> 1 | I85: =IF(AND(I$7<=$G85,I$7>=$F85,$H85<>0,$H85<>""),$C85/$H85,0) -> 0 | J85: =IF(AND(J$7<=$G85,J$7>=$F85,$H85<>0,$H85<>""),$C85/$H85,0) -> 0 | K85: =IF(AND(K$7<=$G85,K$7>=$F85,$H85<>0,$H85<>""),$C85/$H85,0) -> 0 | L85: =IF(AND(L$7<=$G85,L$7>=$F85,$H85<>0,$H85<>""),$C85/$H85,0) -> 0 | M85: =IF(AND(M$7<=$G85,M$7>=$F85,$H85<>0,$H85<>""),$C85/$H85,0) -> 0 | N85: =IF(AND(N$7<=$G85,N$7>=$F85,$H85<>0,$H85<>""),$C85/$H85,0) -> 0 | O85: =IF(AND(O$7<=$G85,O$7>=$F85,$H85<>0,$H85<>""),$C85/$H85,0) -> 0 | P85: =IF(AND(P$7<=$G85,P$7>=$F85,$H85<>0,$H85<>""),$C85/$H85,0) -> 0 | ... CZ85: =IF(AND(CZ$7<=$G85,CZ$7>=$F85,$H85<>0,$H85<>""),$C85/$H85,0) -> 0
B86: ='9. Development Costs'!B71 -> Property Taxes During Construction | C86: =-'9. Development Costs'!H71 -> 0 | D86: =ROUND(C86-E86,0) -> 0 | E86: =SUM(I86:CZ86) -> 0 | F86: ='8. Schedule'!D15 -> 46097 | G86: ='8. Schedule'!E17 -> 47042 | H86: =DATEDIF(F86,G86,"m")+1 -> 32 | I86: =IF(AND(I$7<=$G86,I$7>=$F86,$H86<>0,$H86<>""),$C86/$H86,0) -> 0 | J86: =IF(AND(J$7<=$G86,J$7>=$F86,$H86<>0,$H86<>""),$C86/$H86,0) -> 0 | K86: =IF(AND(K$7<=$G86,K$7>=$F86,$H86<>0,$H86<>""),$C86/$H86,0) -> 0 | L86: =IF(AND(L$7<=$G86,L$7>=$F86,$H86<>0,$H86<>""),$C86/$H86,0) -> 0 | M86: =IF(AND(M$7<=$G86,M$7>=$F86,$H86<>0,$H86<>""),$C86/$H86,0) -> 0 | N86: =IF(AND(N$7<=$G86,N$7>=$F86,$H86<>0,$H86<>""),$C86/$H86,0) -> 0 | O86: =IF(AND(O$7<=$G86,O$7>=$F86,$H86<>0,$H86<>""),$C86/$H86,0) -> 0 | P86: =IF(AND(P$7<=$G86,P$7>=$F86,$H86<>0,$H86<>""),$C86/$H86,0) -> 0 | ... CZ86: =IF(AND(CZ$7<=$G86,CZ$7>=$F86,$H86<>0,$H86<>""),$C86/$H86,0) -> 0
B87: ='9. Development Costs'!B72 -> Quantity Surveyor | C87: =-'9. Development Costs'!H72 -> 0 | D87: =ROUND(C87-E87,0) -> 0 | E87: =SUM(I87:CZ87) -> 0 | F87: =F86 -> 46097 | G87: =G86 -> 47042 | H87: =DATEDIF(F87,G87,"m")+1 -> 32 | I87: =IF(AND(I$7<=$G87,I$7>=$F87,$H87<>0,$H87<>""),$C87/$H87,0) -> 0 | J87: =IF(AND(J$7<=$G87,J$7>=$F87,$H87<>0,$H87<>""),$C87/$H87,0) -> 0 | K87: =IF(AND(K$7<=$G87,K$7>=$F87,$H87<>0,$H87<>""),$C87/$H87,0) -> 0 | L87: =IF(AND(L$7<=$G87,L$7>=$F87,$H87<>0,$H87<>""),$C87/$H87,0) -> 0 | M87: =IF(AND(M$7<=$G87,M$7>=$F87,$H87<>0,$H87<>""),$C87/$H87,0) -> 0 | N87: =IF(AND(N$7<=$G87,N$7>=$F87,$H87<>0,$H87<>""),$C87/$H87,0) -> 0 | O87: =IF(AND(O$7<=$G87,O$7>=$F87,$H87<>0,$H87<>""),$C87/$H87,0) -> 0 | P87: =IF(AND(P$7<=$G87,P$7>=$F87,$H87<>0,$H87<>""),$C87/$H87,0) -> 0 | ... CZ87: =IF(AND(CZ$7<=$G87,CZ$7>=$F87,$H87<>0,$H87<>""),$C87/$H87,0) -> 0
B88: ='9. Development Costs'!B73 -> Insurance | C88: =-'9. Development Costs'!H73 -> 0 | D88: =ROUND(C88-E88,0) -> 0 | E88: =SUM(I88:CZ88) -> 0 | F88: =F$47 -> 46097 | G88: =G$47 -> 47042 | H88: =DATEDIF(F88,G88,"m")+1 -> 32 | I88: =IF(AND(I$7<=$G88,I$7>=$F88,$H88<>0,$H88<>""),$C88/$H88,0) -> 0 | J88: =IF(AND(J$7<=$G88,J$7>=$F88,$H88<>0,$H88<>""),$C88/$H88,0) -> 0 | K88: =IF(AND(K$7<=$G88,K$7>=$F88,$H88<>0,$H88<>""),$C88/$H88,0) -> 0 | L88: =IF(AND(L$7<=$G88,L$7>=$F88,$H88<>0,$H88<>""),$C88/$H88,0) -> 0 | M88: =IF(AND(M$7<=$G88,M$7>=$F88,$H88<>0,$H88<>""),$C88/$H88,0) -> 0 | N88: =IF(AND(N$7<=$G88,N$7>=$F88,$H88<>0,$H88<>""),$C88/$H88,0) -> 0 | O88: =IF(AND(O$7<=$G88,O$7>=$F88,$H88<>0,$H88<>""),$C88/$H88,0) -> 0 | P88: =IF(AND(P$7<=$G88,P$7>=$F88,$H88<>0,$H88<>""),$C88/$H88,0) -> 0 | ... CZ88: =IF(AND(CZ$7<=$G88,CZ$7>=$F88,$H88<>0,$H88<>""),$C88/$H88,0) -> 0
B89: ='9. Development Costs'!B74 -> LC and Bonding | C89: =-'9. Development Costs'!H74 -> 0 | D89: =ROUND(C89-E89,0) -> 0 | E89: =SUM(I89:CZ89) -> 0 | F89: =F$47 -> 46097 | G89: =G$47 -> 47042 | H89: =DATEDIF(F89,G89,"m")+1 -> 32 | I89: =IF(AND(I$7<=$G89,I$7>=$F89,$H89<>0,$H89<>""),$C89/$H89,0) -> 0 | J89: =IF(AND(J$7<=$G89,J$7>=$F89,$H89<>0,$H89<>""),$C89/$H89,0) -> 0 | K89: =IF(AND(K$7<=$G89,K$7>=$F89,$H89<>0,$H89<>""),$C89/$H89,0) -> 0 | L89: =IF(AND(L$7<=$G89,L$7>=$F89,$H89<>0,$H89<>""),$C89/$H89,0) -> 0 | M89: =IF(AND(M$7<=$G89,M$7>=$F89,$H89<>0,$H89<>""),$C89/$H89,0) -> 0 | N89: =IF(AND(N$7<=$G89,N$7>=$F89,$H89<>0,$H89<>""),$C89/$H89,0) -> 0 | O89: =IF(AND(O$7<=$G89,O$7>=$F89,$H89<>0,$H89<>""),$C89/$H89,0) -> 0 | P89: =IF(AND(P$7<=$G89,P$7>=$F89,$H89<>0,$H89<>""),$C89/$H89,0) -> 0 | ... CZ89: =IF(AND(CZ$7<=$G89,CZ$7>=$F89,$H89<>0,$H89<>""),$C89/$H89,0) -> 0
B90: ='9. Development Costs'!B75 -> Loan fees | C90: =-'9. Development Costs'!H75 -> -849580.96 | D90: =ROUND(C90-E90,0) -> 0 | E90: =SUM(I90:CZ90) -> -849580.96 | F90: =F$47 -> 46097 | G90: =G$47 -> 47042 | H90: =DATEDIF(F90,G90,"m")+1 -> 32 | I90: =IF(AND(I$7<=$G90,I$7>=$F90,$H90<>0,$H90<>""),$C90/$H90,0) -> 0 | J90: =IF(AND(J$7<=$G90,J$7>=$F90,$H90<>0,$H90<>""),$C90/$H90,0) -> -26549.405 | K90: =IF(AND(K$7<=$G90,K$7>=$F90,$H90<>0,$H90<>""),$C90/$H90,0) -> -26549.405 | L90: =IF(AND(L$7<=$G90,L$7>=$F90,$H90<>0,$H90<>""),$C90/$H90,0) -> -26549.405 | M90: =IF(AND(M$7<=$G90,M$7>=$F90,$H90<>0,$H90<>""),$C90/$H90,0) -> -26549.405 | N90: =IF(AND(N$7<=$G90,N$7>=$F90,$H90<>0,$H90<>""),$C90/$H90,0) -> -26549.405 | O90: =IF(AND(O$7<=$G90,O$7>=$F90,$H90<>0,$H90<>""),$C90/$H90,0) -> -26549.405 | P90: =IF(AND(P$7<=$G90,P$7>=$F90,$H90<>0,$H90<>""),$C90/$H90,0) -> -26549.405 | ... CZ90: =IF(AND(CZ$7<=$G90,CZ$7>=$F90,$H90<>0,$H90<>""),$C90/$H90,0) -> 0
B91: ='9. Development Costs'!B76 -> Bank's Legal / Other charges | C91: =-'9. Development Costs'!H76 -> 0 | D91: =ROUND(C91-E91,0) -> 0 | E91: =SUM(I91:CZ91) -> 0 | F91: =F$47 -> 46097 | G91: =G$47 -> 47042 | H91: =DATEDIF(F91,G91,"m")+1 -> 32 | I91: =IF(AND(I$7<=$G91,I$7>=$F91,$H91<>0,$H91<>""),$C91/$H91,0) -> 0 | J91: =IF(AND(J$7<=$G91,J$7>=$F91,$H91<>0,$H91<>""),$C91/$H91,0) -> 0 | K91: =IF(AND(K$7<=$G91,K$7>=$F91,$H91<>0,$H91<>""),$C91/$H91,0) -> 0 | L91: =IF(AND(L$7<=$G91,L$7>=$F91,$H91<>0,$H91<>""),$C91/$H91,0) -> 0 | M91: =IF(AND(M$7<=$G91,M$7>=$F91,$H91<>0,$H91<>""),$C91/$H91,0) -> 0 | N91: =IF(AND(N$7<=$G91,N$7>=$F91,$H91<>0,$H91<>""),$C91/$H91,0) -> 0 | O91: =IF(AND(O$7<=$G91,O$7>=$F91,$H91<>0,$H91<>""),$C91/$H91,0) -> 0 | P91: =IF(AND(P$7<=$G91,P$7>=$F91,$H91<>0,$H91<>""),$C91/$H91,0) -> 0 | ... CZ91: =IF(AND(CZ$7<=$G91,CZ$7>=$F91,$H91<>0,$H91<>""),$C91/$H91,0) -> 0
B92: ='9. Development Costs'!B77 -> HST | C92: =-'9. Development Costs'!H77 -> 0 | D92: =ROUND(C92-E92,0) -> 0 | E92: =SUM(I92:CZ92) -> 0 | F92: =F72 -> 47042 | G92: =G72 -> 47042 | H92: =DATEDIF(F92,G92,"m")+1 -> 1 | I92: =IF(AND(I$7<=$G92,I$7>=$F92,$H92<>0,$H92<>""),$C92/$H92,0) -> 0 | J92: =IF(AND(J$7<=$G92,J$7>=$F92,$H92<>0,$H92<>""),$C92/$H92,0) -> 0 | K92: =IF(AND(K$7<=$G92,K$7>=$F92,$H92<>0,$H92<>""),$C92/$H92,0) -> 0 | L92: =IF(AND(L$7<=$G92,L$7>=$F92,$H92<>0,$H92<>""),$C92/$H92,0) -> 0 | M92: =IF(AND(M$7<=$G92,M$7>=$F92,$H92<>0,$H92<>""),$C92/$H92,0) -> 0 | N92: =IF(AND(N$7<=$G92,N$7>=$F92,$H92<>0,$H92<>""),$C92/$H92,0) -> 0 | O92: =IF(AND(O$7<=$G92,O$7>=$F92,$H92<>0,$H92<>""),$C92/$H92,0) -> 0 | P92: =IF(AND(P$7<=$G92,P$7>=$F92,$H92<>0,$H92<>""),$C92/$H92,0) -> 0 | ... CZ92: =IF(AND(CZ$7<=$G92,CZ$7>=$F92,$H92<>0,$H92<>""),$C92/$H92,0) -> 0
B93: ='9. Development Costs'!B78 -> Construction Loan Interest | C93: =E93 -> -7695700.3 | D93: =ROUND(C93-E93,0) -> 0 | E93: =SUM(I93:CZ93) -> -7695700.3 | I93: 0 | J93: =IF(J110="PUD",-'9. Development Costs'!$G$78/12*I107,0) -> -4981.1687 | K93: =IF(K110="PUD",-'9. Development Costs'!$G$78/12*J107,0) -> -5896.1418 | L93: =IF(L110="PUD",-'9. Development Costs'!$G$78/12*K107,0) -> -6815.5902 | M93: =IF(M110="PUD",-'9. Development Costs'!$G$78/12*L107,0) -> -7739.5316 | N93: =IF(N110="PUD",-'9. Development Costs'!$G$78/12*M107,0) -> -8667.9902 | O93: =IF(O110="PUD",-'9. Development Costs'!$G$78/12*N107,0) -> -9600.9907 | P93: =IF(P110="PUD",-'9. Development Costs'!$G$78/12*O107,0) -> -10538.552 | Q93: =IF(Q110="PUD",-'9. Development Costs'!$G$78/12*P107,0) -> -11480.695 | ... CZ93: =IF(CZ110="PUD",-'9. Development Costs'!$G$78/12*CY107,0) -> 0
B94: ='9. Development Costs'!B79 -> Financing contingency | C94: =-'9. Development Costs'!H79 -> -424790.48 | D94: =ROUND(C94-E94,0) -> 0 | E94: =SUM(I94:CZ94) -> -424790.48 | F94: =F$47 -> 46097 | G94: =G$47 -> 47042 | H94: =DATEDIF(F94,G94,"m")+1 -> 32 | I94: =IF(AND(I$7<=$G94,I$7>=$F94,$H94<>0,$H94<>""),$C94/$H94,0) -> 0 | J94: =IF(AND(J$7<=$G94,J$7>=$F94,$H94<>0,$H94<>""),$C94/$H94,0) -> -13274.702 | K94: =IF(AND(K$7<=$G94,K$7>=$F94,$H94<>0,$H94<>""),$C94/$H94,0) -> -13274.702 | L94: =IF(AND(L$7<=$G94,L$7>=$F94,$H94<>0,$H94<>""),$C94/$H94,0) -> -13274.702 | M94: =IF(AND(M$7<=$G94,M$7>=$F94,$H94<>0,$H94<>""),$C94/$H94,0) -> -13274.702 | N94: =IF(AND(N$7<=$G94,N$7>=$F94,$H94<>0,$H94<>""),$C94/$H94,0) -> -13274.702 | O94: =IF(AND(O$7<=$G94,O$7>=$F94,$H94<>0,$H94<>""),$C94/$H94,0) -> -13274.702 | P94: =IF(AND(P$7<=$G94,P$7>=$F94,$H94<>0,$H94<>""),$C94/$H94,0) -> -13274.702 | ... CZ94: =IF(AND(CZ$7<=$G94,CZ$7>=$F94,$H94<>0,$H94<>""),$C94/$H94,0) -> 0
B95: ='9. Development Costs'!B80 -> Total Financing and Interest Costs | C95: =SUM(C84:C94) -> -8970071.7 | D95: =ROUND(C95-E95,0) -> 0 | E95: =SUM(I95:CZ95) -> -8970071.7 | I95: =SUM(I84:I94) -> 0 | J95: =SUM(J84:J94) -> -44805.276 | K95: =SUM(K84:K94) -> -45720.249 | L95: =SUM(L84:L94) -> -46639.698 | M95: =SUM(M84:M94) -> -47563.639 | N95: =SUM(N84:N94) -> -48492.098 | O95: =SUM(O84:O94) -> -49425.098 | P95: =SUM(P84:P94) -> -50362.66 | ... CZ95: =SUM(CZ84:CZ94) -> 0
B97: CONSTRUCTION LOAN
B98: Cash Flow before loan draws | C98: =SUM(C22,C26,C31,C44,C61,C64,C77,C81,C95) -> -94440551 | D98: =ROUND(C98-E98,0) -> 0 | E98: =SUM(E22,E26,E31,E44,E61,E64,E77,E81,E95) -> -94440551 | I98: =SUM(I22,I26,I31,I44,I61,I64,I77,I81,I95) -> -10458664 | J98: =SUM(J22,J26,J31,J44,J61,J64,J77,J81,J95) -> -187153.95 | K98: =SUM(K22,K26,K31,K44,K61,K64,K77,K81,K95) -> -188068.92 | L98: =SUM(L22,L26,L31,L44,L61,L64,L77,L81,L95) -> -188988.37 | M98: =SUM(M22,M26,M31,M44,M61,M64,M77,M81,M95) -> -189912.31 | N98: =SUM(N22,N26,N31,N44,N61,N64,N77,N81,N95) -> -190840.77 | O98: =SUM(O22,O26,O31,O44,O61,O64,O77,O81,O95) -> -191773.77 | P98: =SUM(P22,P26,P31,P44,P61,P64,P77,P81,P95) -> -192711.33 | ... CZ98: =SUM(CZ22,CZ26,CZ31,CZ44,CZ61,CZ64,CZ77,CZ81,CZ95) -> 0
B99: Construction Loan Draws | E99: =SUM(I99:CZ99) -> 85000762 | I99: =-I114 -> 1018875.4 | J99: =-J114 -> 187153.95 | K99: =-K114 -> 188068.92 | L99: =-L114 -> 188988.37 | M99: =-M114 -> 189912.31 | N99: =-N114 -> 190840.77 | O99: =-O114 -> 191773.77 | P99: =-P114 -> 192711.33 | ... CZ99: =-CZ114 -> 0
B100: Repayment of Construction Loan | E100: =SUM(I100:CZ100) -> -85000761 | I100: 0 | J100: =IF(AND(I93<0,J110="SLD"),-I107,0) -> 0 | K100: =IF(AND(J93<0,K110="SLD"),-J107,0) -> 0 | L100: =IF(AND(K93<0,L110="SLD"),-K107,0) -> 0 | M100: =IF(AND(L93<0,M110="SLD"),-L107,0) -> 0 | N100: =IF(AND(M93<0,N110="SLD"),-M107,0) -> 0 | O100: =IF(AND(N93<0,O110="SLD"),-N107,0) -> 0 | P100: =IF(AND(O93<0,P110="SLD"),-O107,0) -> 0 | Q100: =IF(AND(P93<0,Q110="SLD"),-P107,0) -> 0 | ... CZ100: =IF(AND(CY93<0,CZ110="SLD"),-CY107,0) -> 0
B102: Valuation at stabilization | I102: 0 | J102: =I26*12/'12. Sensitivity'!$H$10*(J110="SLD")*(I93<0) -> 0 | K102: =J26*12/'12. Sensitivity'!$H$10*(K110="SLD")*(J93<0) -> 0 | L102: =K26*12/'12. Sensitivity'!$H$10*(L110="SLD")*(K93<0) -> 0 | M102: =L26*12/'12. Sensitivity'!$H$10*(M110="SLD")*(L93<0) -> 0 | N102: =M26*12/'12. Sensitivity'!$H$10*(N110="SLD")*(M93<0) -> 0 | O102: =N26*12/'12. Sensitivity'!$H$10*(O110="SLD")*(N93<0) -> 0 | P102: =O26*12/'12. Sensitivity'!$H$10*(P110="SLD")*(O93<0) -> 0 | Q102: =P26*12/'12. Sensitivity'!$H$10*(Q110="SLD")*(P93<0) -> 0 | ... CZ102: =CY26*12/'12. Sensitivity'!$H$10*(CZ110="SLD")*(CY93<0) -> 0
B103: Selling Costs | I103: =-'11. 10-Yr Cash Flow IRR'!$E$11*I102 -> 0 | J103: =-'11. 10-Yr Cash Flow IRR'!$E$11*J102 -> 0 | K103: =-'11. 10-Yr Cash Flow IRR'!$E$11*K102 -> 0 | L103: =-'11. 10-Yr Cash Flow IRR'!$E$11*L102 -> 0 | M103: =-'11. 10-Yr Cash Flow IRR'!$E$11*M102 -> 0 | N103: =-'11. 10-Yr Cash Flow IRR'!$E$11*N102 -> 0 | O103: =-'11. 10-Yr Cash Flow IRR'!$E$11*O102 -> 0 | P103: =-'11. 10-Yr Cash Flow IRR'!$E$11*P102 -> 0 | ... CZ103: =-'11. 10-Yr Cash Flow IRR'!$E$11*CZ102 -> 0
B104: Net Cash Flow - Equity | C104: =ROUND(SUM(C98:C103),0) -> -94440551 | D104: =SUM(D98:D99) -> 0 | E104: =ROUND(SUM(I104:CZ104),0) -> 13357312 | H104: =SUM(H98:H99) -> 0 | I104: =SUM(I98:I103) -> -9439788.4 | J104: =SUM(J98:J103) -> 1.4551915e-10 | K104: =SUM(K98:K103) -> -7.5669959e-10 | L104: =SUM(L98:L103) -> -4.9476512e-10 | M104: =SUM(M98:M103) -> -8.1490725e-10 | N104: =SUM(N98:N103) -> -1.1641532e-10 | O104: =SUM(O98:O103) -> -6.693881e-10 | P104: =SUM(P98:P103) -> -4.6566129e-10 | ... CZ104: =SUM(CZ98:CZ103) -> 0
F105: IRR | G105: =+(1+IRR(I104:CZ104,0.02))^12-1 -> 0.27897087
B106: Cumulative | D106: Loan to Cost:
B107: Construction Loan Balance | C107: =-MAX(I107:CZ107) -> -85000761 | D107: =+C107/C104 -> 0.90004516 | I107: =I99 -> 1018875.4 | J107: =ROUND(J99+I107+J100,0) -> 1206029 | K107: =ROUND(K99+J107+K100,0) -> 1394098 | L107: =ROUND(L99+K107+L100,0) -> 1583086 | M107: =ROUND(M99+L107+M100,0) -> 1772998 | N107: =ROUND(N99+M107+N100,0) -> 1963839 | O107: =ROUND(O99+N107+O100,0) -> 2155613 | P107: =ROUND(P99+O107+P100,0) -> 2348324 | Q107: =ROUND(Q99+P107+Q100,0) -> 2541977 | ... CZ107: =ROUND(CZ99+CY107+CZ100,0) -> 0
B108: Equity | C108: =E114 -> -9439788.4 | D108: =1-D107 -> 0.099954838 | I108: =-I104 -> 9439788.4 | J108: =(I110="PUD")*(I108-J104) -> 9439788.4 | K108: =(J110="PUD")*(J108-K104) -> 9439788.4 | L108: =(K110="PUD")*(K108-L104) -> 9439788.4 | M108: =(L110="PUD")*(L108-M104) -> 9439788.4 | N108: =(M110="PUD")*(M108-N104) -> 9439788.4 | O108: =(N110="PUD")*(N108-O104) -> 9439788.4 | P108: =(O110="PUD")*(O108-P104) -> 9439788.4 | Q108: =(P110="PUD")*(P108-Q104) -> 9439788.4 | ... CZ108: =(CY110="PUD")*(CY108-CZ104) -> 0
B110: Development Status | I110: =IF(I7<='8. Schedule'!$E$21,"PUD","SLD") -> PUD | J110: =IF(J7<='8. Schedule'!$E$21,"PUD","SLD") -> PUD | K110: =IF(K7<='8. Schedule'!$E$21,"PUD","SLD") -> PUD | L110: =IF(L7<='8. Schedule'!$E$21,"PUD","SLD") -> PUD | M110: =IF(M7<='8. Schedule'!$E$21,"PUD","SLD") -> PUD | N110: =IF(N7<='8. Schedule'!$E$21,"PUD","SLD") -> PUD | O110: =IF(O7<='8. Schedule'!$E$21,"PUD","SLD") -> PUD | P110: =IF(P7<='8. Schedule'!$E$21,"PUD","SLD") -> PUD | ... CZ110: =IF(CZ7<='8. Schedule'!$E$21,"PUD","SLD") -> SLD
B112: Cost to Date | I112: =IF(I110="PUD",I98,0) -> -10458664 | J112: =IF(J110="PUD",I112+J98,0) -> -10645818 | K112: =IF(K110="PUD",J112+K98,0) -> -10833887 | L112: =IF(L110="PUD",K112+L98,0) -> -11022875 | M112: =IF(M110="PUD",L112+M98,0) -> -11212787 | N112: =IF(N110="PUD",M112+N98,0) -> -11403628 | O112: =IF(O110="PUD",N112+O98,0) -> -11595402 | P112: =IF(P110="PUD",O112+P98,0) -> -11788113 | Q112: =IF(Q110="PUD",P112+Q98,0) -> -11981767 | ... CZ112: =IF(CZ110="PUD",CY112+CZ98,0) -> 0
B114: Cost to Complete Financing | D114: =C104*(1-D107)-E114 -> -1.568 | E114: =-'5. Key Assumptions'!F67 -> -9439788.4 | I114: =IF(AND(I110="PUD",I112<$E$114),I112-$E$114,0) -> -1018875.4 | J114: =IF(AND(J110="PUD",J112<$E$114),J112-$E$114-SUM($I$114:I114),0) -> -187153.95 | K114: =IF(AND(K110="PUD",K112<$E$114),K112-$E$114-SUM($I$114:J114),0) -> -188068.92 | L114: =IF(AND(L110="PUD",L112<$E$114),L112-$E$114-SUM($I$114:K114),0) -> -188988.37 | M114: =IF(AND(M110="PUD",M112<$E$114),M112-$E$114-SUM($I$114:L114),0) -> -189912.31 | N114: =IF(AND(N110="PUD",N112<$E$114),N112-$E$114-SUM($I$114:M114),0) -> -190840.77 | O114: =IF(AND(O110="PUD",O112<$E$114),O112-$E$114-SUM($I$114:N114),0) -> -191773.77 | P114: =IF(AND(P110="PUD",P112<$E$114),P112-$E$114-SUM($I$114:O114),0) -> -192711.33 | Q114: =IF(AND(Q110="PUD",Q112<$E$114),Q112-$E$114-SUM($I$114:P114),0) -> -193653.47 | ... CZ114: =IF(AND(CZ110="PUD",CZ112<$E$114),CZ112-$E$114-SUM($I$114:CY114),0) -> 0
D116: Goal seek to 0 by changing

Sheet 11. 10-Yr Cash Flow IRR
M1: ="Currently running: "&CHOOSE('12. Sensitivity'!$E$8,'12. Sensitivity'!$B$11,'12. Sensitivity'!$B$12,'12. Sensitivity'!$B$13) -> Currently running: Base Case
A2: ='3. Headline #s'!A10 -> Apartment Development Model Reverse 1B
A3: ='3. Headline #s'!A12 -> 2240 Birchmount Road, Scarborough, ON
A4: Stabilized Rental Cash Flow Analysis
B8: OTHER ASSUMPTIONS
B9: Annual Revenue Inflation | E9: 0.02 | H9: Annualized NOI at Stabilization | K9: ='7. Op Rev and Exp'!H57 -> 4899902.8
B10: Annual Cost Inflation | E10: 0.02 | H10: Capitalization Rate | K10: ='7. Op Rev and Exp'!D56 -> 0.045
B11: Selling Costs | E11: 0.01 | H11: Value | K11: =K9/K10 -> 1.0888673e+08
B12: Min. NOI Coverage | E12: ='6. Debt Stack & Financing'!D32 -> 1.1 | H12: Maximum Allowable Permanent Loan Amount | K12: =MIN(E13*K11,-PV(E14,E15,K9/E12)) -> 92243039
B13: Max. LTV @ Stabilization | E13: ='6. Debt Stack & Financing'!D31 -> 0.95 | H13: Choose Loan Option: | K13: 1 | S13: Maximum Allowable Loan
B14: Permanent Loan Interest Rate | E14: ='6. Debt Stack & Financing'!D34 -> 0.037 | H14: Permanent Loan Principal | K14: =IF(K13=1,K12,MIN(K12,'10. Development Cash Flow'!E99)) -> 92243039 | S14: Lesser of Construction Loan and Max Loan
B15: Loan Term (years) | E15: ='6. Debt Stack & Financing'!D33 -> 40 | H15: Equity Requirement | K15: ='9. Development Costs'!H89-'11. 10-Yr Cash Flow IRR'!K14 -> 2197511.8 | L15: =K14/K11 -> 0.84714676 | M15: LTV
B16: Construction Loan Ratio | E16: =+'10. Development Cash Flow'!D107 -> 0.90004516 | H16: Annual Debt Service | K16: =-PMT(E14/12,E15*12,K14)*12 -> 4421871.7 | L16: =K9/K16 -> 1.1081061 | M16: NOI Coverage
B19: YEAR | C19: 1 | D19: 2 | E19: 3 | F19: 4 | G19: 5 | H19: 6 | I19: 7 | J19: 8 | K19: 9 | L19: 10
C20: =YEAR('8. Schedule'!D8) -> 2026 | D20: =C20+1 -> 2027 | E20: =D20+1 -> 2028 | F20: =E20+1 -> 2029 | G20: =F20+1 -> 2030 | H20: =G20+1 -> 2031 | I20: =H20+1 -> 2032 | J20: =I20+1 -> 2033 | K20: =J20+1 -> 2034 | L20: =K20+1 -> 2035
A21: Stabilized Holding Months | C21: =IF(C$20<YEAR('8. Schedule'!$E$21),0,IF(C$20=YEAR('8. Schedule'!$E$21),12-MONTH('8. Schedule'!$E$21),12)) -> 0 | D21: =IF(D$20<YEAR('8. Schedule'!$E$21),0,IF(D$20=YEAR('8. Schedule'!$E$21),12-MONTH('8. Schedule'!$E$21),12)) -> 0 | E21: =IF(E$20<YEAR('8. Schedule'!$E$21),0,IF(E$20=YEAR('8. Schedule'!$E$21),12-MONTH('8. Schedule'!$E$21),12)) -> 0 | F21: =IF(F$20<YEAR('8. Schedule'!$E$21),0,IF(F$20=YEAR('8. Schedule'!$E$21),12-MONTH('8. Schedule'!$E$21),12)) -> 4 | G21: =IF(G$20<YEAR('8. Schedule'!$E$21),0,IF(G$20=YEAR('8. Schedule'!$E$21),12-MONTH('8. Schedule'!$E$21),12)) -> 12 | H21: =IF(H$20<YEAR('8. Schedule'!$E$21),0,IF(H$20=YEAR('8. Schedule'!$E$21),12-MONTH('8. Schedule'!$E$21),12)) -> 12 | I21: =IF(I$20<YEAR('8. Schedule'!$E$21),0,IF(I$20=YEAR('8. Schedule'!$E$21),12-MONTH('8. Schedule'!$E$21),12)) -> 12 | J21: =IF(J$20<YEAR('8. Schedule'!$E$21),0,IF(J$20=YEAR('8. Schedule'!$E$21),12-MONTH('8. Schedule'!$E$21),12)) -> 12 | ... L21: =IF(L$20<YEAR('8. Schedule'!$E$21),0,IF(L$20=YEAR('8. Schedule'!$E$21),12-MONTH('8. Schedule'!$E$21),12)) -> 12
A22: Revenue Inflation Factor | C22: =(1+$E$9)^(C20-YEAR('8. Schedule'!$D$8)) -> 1 | D22: =(1+$E$9)^(D20-YEAR('8. Schedule'!$D$8)) -> 1.02 | E22: =(1+$E$9)^(E20-YEAR('8. Schedule'!$D$8)) -> 1.0404 | F22: =(1+$E$9)^(F20-YEAR('8. Schedule'!$D$8)) -> 1.061208 | G22: =(1+$E$9)^(G20-YEAR('8. Schedule'!$D$8)) -> 1.0824322 | H22: =(1+$E$9)^(H20-YEAR('8. Schedule'!$D$8)) -> 1.1040808 | I22: =(1+$E$9)^(I20-YEAR('8. Schedule'!$D$8)) -> 1.1261624 | J22: =(1+$E$9)^(J20-YEAR('8. Schedule'!$D$8)) -> 1.1486857 | ... L22: =(1+$E$9)^(L20-YEAR('8. Schedule'!$D$8)) -> 1.1950926
A23: Cost Inflation Factor | C23: =(1+$E$10)^(C20-YEAR('8. Schedule'!$D$8)) -> 1 | D23: =(1+$E$10)^(D20-YEAR('8. Schedule'!$D$8)) -> 1.02 | E23: =(1+$E$10)^(E20-YEAR('8. Schedule'!$D$8)) -> 1.0404 | F23: =(1+$E$10)^(F20-YEAR('8. Schedule'!$D$8)) -> 1.061208 | G23: =(1+$E$10)^(G20-YEAR('8. Schedule'!$D$8)) -> 1.0824322 | H23: =(1+$E$10)^(H20-YEAR('8. Schedule'!$D$8)) -> 1.1040808 | I23: =(1+$E$10)^(I20-YEAR('8. Schedule'!$D$8)) -> 1.1261624 | J23: =(1+$E$10)^(J20-YEAR('8. Schedule'!$D$8)) -> 1.1486857 | ... L23: =(1+$E$10)^(L20-YEAR('8. Schedule'!$D$8)) -> 1.1950926
A26: Revenue | C26: =C$21/12*C$22*'7. Op Rev and Exp'!$H$32 -> 0 | D26: =D$21/12*D$22*'7. Op Rev and Exp'!$H$32 -> 0 | E26: =E$21/12*E$22*'7. Op Rev and Exp'!$H$32 -> 0 | F26: =F$21/12*F$22*'7. Op Rev and Exp'!$H$32 -> 2310108.3 | G26: =G$21/12*G$22*'7. Op Rev and Exp'!$H$32 -> 7068931.5 | H26: =H$21/12*H$22*'7. Op Rev and Exp'!$H$32 -> 7210310.1 | I26: =I$21/12*I$22*'7. Op Rev and Exp'!$H$32 -> 7354516.3 | J26: =J$21/12*J$22*'7. Op Rev and Exp'!$H$32 -> 7501606.6 | ... L26: =L$21/12*L$22*'7. Op Rev and Exp'!$H$32 -> 7804671.5
A27: Vacancy Provision | C27: =-C$21/12*C$22*'7. Op Rev and Exp'!$H$33 -> 0 | D27: =-D$21/12*D$22*'7. Op Rev and Exp'!$H$33 -> 0 | E27: =-E$21/12*E$22*'7. Op Rev and Exp'!$H$33 -> 0 | F27: =-F$21/12*F$22*'7. Op Rev and Exp'!$H$33 -> -69303.25 | G27: =-G$21/12*G$22*'7. Op Rev and Exp'!$H$33 -> -212067.94 | H27: =-H$21/12*H$22*'7. Op Rev and Exp'!$H$33 -> -216309.3 | I27: =-I$21/12*I$22*'7. Op Rev and Exp'!$H$33 -> -220635.49 | J27: =-J$21/12*J$22*'7. Op Rev and Exp'!$H$33 -> -225048.2 | ... L27: =-L$21/12*L$22*'7. Op Rev and Exp'!$H$33 -> -234140.15
A28: Operating Expenses | C28: =-C$21/12*C$23*'7. Op Rev and Exp'!$H$50 -> 0 | D28: =-D$21/12*D$23*'7. Op Rev and Exp'!$H$50 -> 0 | E28: =-E$21/12*E$23*'7. Op Rev and Exp'!$H$50 -> 0 | F28: =-F$21/12*F$23*'7. Op Rev and Exp'!$H$50 -> -607504.15 | G28: =-G$21/12*G$23*'7. Op Rev and Exp'!$H$50 -> -1858962.7 | H28: =-H$21/12*H$23*'7. Op Rev and Exp'!$H$50 -> -1896141.9 | I28: =-I$21/12*I$23*'7. Op Rev and Exp'!$H$50 -> -1934064.8 | J28: =-J$21/12*J$23*'7. Op Rev and Exp'!$H$50 -> -1972746.1 | ... L28: =-L$21/12*L$23*'7. Op Rev and Exp'!$H$50 -> -2052445
A29: Stabilized NOI | C29: =SUM(C26:C28) -> 0 | D29: =SUM(D26:D28) -> 0 | E29: =SUM(E26:E28) -> 0 | F29: =SUM(F26:F28) -> 1633300.9 | G29: =SUM(G26:G28) -> 4997900.8 | H29: =SUM(H26:H28) -> 5097858.8 | I29: =SUM(I26:I28) -> 5199816 | J29: =SUM(J26:J28) -> 5303812.3 | ... L29: =SUM(L26:L28) -> 5518086.4
A31: Development Cash Flow | C31: =IF(C20<=YEAR('8. Schedule'!$E$21),SUMIFS('10. Development Cash Flow'!$I98:$CZ98,'10. Development Cash Flow'!$I5:$CZ5,C$20,'10. Development Cash Flow'!$I110:$CZ110,"PUD"),0) -> -12371919 | D31: =IF(D20<=YEAR('8. Schedule'!$E$21),SUMIFS('10. Development Cash Flow'!$I98:$CZ98,'10. Development Cash Flow'!$I5:$CZ5,D$20,'10. Development Cash Flow'!$I110:$CZ110,"PUD"),0) -> -33553029 | E31: =IF(E20<=YEAR('8. Schedule'!$E$21),SUMIFS('10. Development Cash Flow'!$I98:$CZ98,'10. Development Cash Flow'!$I5:$CZ5,E$20,'10. Development Cash Flow'!$I110:$CZ110,"PUD"),0) -> -47091995 | F31: =IF(F20<=YEAR('8. Schedule'!$E$21),SUMIFS('10. Development Cash Flow'!$I98:$CZ98,'10. Development Cash Flow'!$I5:$CZ5,F$20,'10. Development Cash Flow'!$I110:$CZ110,"PUD"),0) -> -1423607.8 | G31: =IF(G20<=YEAR('8. Schedule'!$E$21),SUMIFS('10. Development Cash Flow'!$I98:$CZ98,'10. Development Cash Flow'!$I5:$CZ5,G$20,'10. Development Cash Flow'!$I110:$CZ110,"PUD"),0) -> 0 | H31: =IF(H20<=YEAR('8. Schedule'!$E$21),SUMIFS('10. Development Cash Flow'!$I98:$CZ98,'10. Development Cash Flow'!$I5:$CZ5,H$20,'10. Development Cash Flow'!$I110:$CZ110,"PUD"),0) -> 0 | I31: =IF(I20<=YEAR('8. Schedule'!$E$21),SUMIFS('10. Development Cash Flow'!$I98:$CZ98,'10. Development Cash Flow'!$I5:$CZ5,I$20,'10. Development Cash Flow'!$I110:$CZ110,"PUD"),0) -> 0 | J31: =IF(J20<=YEAR('8. Schedule'!$E$21),SUMIFS('10. Development Cash Flow'!$I98:$CZ98,'10. Development Cash Flow'!$I5:$CZ5,J$20,'10. Development Cash Flow'!$I110:$CZ110,"PUD"),0) -> 0 | ... L31: =IF(L20<=YEAR('8. Schedule'!$E$21),SUMIFS('10. Development Cash Flow'!$I98:$CZ98,'10. Development Cash Flow'!$I5:$CZ5,L$20,'10. Development Cash Flow'!$I110:$CZ110,"PUD"),0) -> 0
A32: Construction Loan Draw | C32: =IF(C34=MAX($C$34:$L$34),C57-C31-C34,C57-C31) -> 2932130.6 | D32: =IF(D34=MAX($C$34:$L$34),D57-D31-D34,D57-D31) -> 33553029 | E32: =IF(E34=MAX($C$34:$L$34),E57-E31-E34,E57-E31) -> 47091995 | F32: =IF(F34=MAX($C$34:$L$34),F57-F31-F34,F57-F31) -> -88355345 | G32: =IF(G34=MAX($C$34:$L$34),G57-G31-G34,G57-G31) -> 0 | H32: =IF(H34=MAX($C$34:$L$34),H57-H31-H34,H57-H31) -> 0 | I32: =IF(I34=MAX($C$34:$L$34),I57-I31-I34,I57-I31) -> 0 | J32: =IF(J34=MAX($C$34:$L$34),J57-J31-J34,J57-J31) -> 0 | ... L32: =IF(L34=MAX($C$34:$L$34),L57-L31-L34,L57-L31) -> 0
A33: Construction Loan Balance | C33: =C32 -> 2932130.6 | D33: =IF(AND(C33+D32<10,C33+D32>-10),0,C33+D32) -> 36485160 | E33: =IF(AND(D33+E32<10,D33+E32>-10),0,D33+E32) -> 83577155 | F33: =IF(AND(E33+F32<10,E33+F32>-10),0,E33+F32) -> -4778189.7 | G33: =IF(AND(F33+G32<10,F33+G32>-10),0,F33+G32) -> -4778189.7 | H33: =IF(AND(G33+H32<10,G33+H32>-10),0,G33+H32) -> -4778189.7 | I33: =IF(AND(H33+I32<10,H33+I32>-10),0,H33+I32) -> -4778189.7 | J33: =IF(AND(I33+J32<10,I33+J32>-10),0,I33+J32) -> -4778189.7 | K33: =IF(AND(J33+K32<10,J33+K32>-10),0,J33+K32) -> -4778189.7 | L33: =IF(AND(K33+L32<10,K33+L32>-10),0,K33+L32) -> -4778189.7
A34: Permanent Loan Balance | C34: 0 | D34: =IF(D20<YEAR('8. Schedule'!$E$21),0,IF(D20=YEAR('8. Schedule'!$E$21),$K$14,'11. 10-Yr Cash Flow IRR'!C34+'11. 10-Yr Cash Flow IRR'!C38)) -> 0 | E34: =IF(E20<YEAR('8. Schedule'!$E$21),0,IF(E20=YEAR('8. Schedule'!$E$21),$K$14,'11. 10-Yr Cash Flow IRR'!D34+'11. 10-Yr Cash Flow IRR'!D38)) -> 0 | F34: =IF(F20<YEAR('8. Schedule'!$E$21),0,IF(F20=YEAR('8. Schedule'!$E$21),$K$14,'11. 10-Yr Cash Flow IRR'!E34+'11. 10-Yr Cash Flow IRR'!E38)) -> 92243039 | G34: =IF(G20<YEAR('8. Schedule'!$E$21),0,IF(G20=YEAR('8. Schedule'!$E$21),$K$14,'11. 10-Yr Cash Flow IRR'!F34+'11. 10-Yr Cash Flow IRR'!F38)) -> 91905187 | H34: =IF(H20<YEAR('8. Schedule'!$E$21),0,IF(H20=YEAR('8. Schedule'!$E$21),$K$14,'11. 10-Yr Cash Flow IRR'!G34+'11. 10-Yr Cash Flow IRR'!G38)) -> 90866307 | I34: =IF(I20<YEAR('8. Schedule'!$E$21),0,IF(I20=YEAR('8. Schedule'!$E$21),$K$14,'11. 10-Yr Cash Flow IRR'!H34+'11. 10-Yr Cash Flow IRR'!H38)) -> 89788330 | J34: =IF(J20<YEAR('8. Schedule'!$E$21),0,IF(J20=YEAR('8. Schedule'!$E$21),$K$14,'11. 10-Yr Cash Flow IRR'!I34+'11. 10-Yr Cash Flow IRR'!I38)) -> 88669785 | K34: =IF(K20<YEAR('8. Schedule'!$E$21),0,IF(K20=YEAR('8. Schedule'!$E$21),$K$14,'11. 10-Yr Cash Flow IRR'!J34+'11. 10-Yr Cash Flow IRR'!J38)) -> 87509144 | L34: =IF(L20<YEAR('8. Schedule'!$E$21),0,IF(L20=YEAR('8. Schedule'!$E$21),$K$14,'11. 10-Yr Cash Flow IRR'!K34+'11. 10-Yr Cash Flow IRR'!K38)) -> 86304824
A36: Stabilized NOI | C36: =C29 -> 0 | D36: =D29 -> 0 | E36: =E29 -> 0 | F36: =F29 -> 1633300.9 | G36: =G29 -> 4997900.8 | H36: =H29 -> 5097858.8 | I36: =I29 -> 5199816 | J36: =J29 -> 5303812.3 | ... L36: =L29 -> 5518086.4
A37: Interest Payment | C37: =SUMIF($C$76:$C$195,C$20,$E76:$E195) -> 0 | D37: =SUMIF($C$76:$C$195,D$20,$E76:$E195) -> 0 | E37: =SUMIF($C$76:$C$195,E$20,$E76:$E195) -> 0 | F37: =SUMIF($C$76:$C$195,F$20,$E76:$E195) -> -1136105.6 | G37: =SUMIF($C$76:$C$195,G$20,$E76:$E195) -> -3382991.8 | H37: =SUMIF($C$76:$C$195,H$20,$E76:$E195) -> -3343894.6 | I37: =SUMIF($C$76:$C$195,I$20,$E76:$E195) -> -3303326.1 | J37: =SUMIF($C$76:$C$195,J$20,$E76:$E195) -> -3261230.8 | ... L37: =SUMIF($C$76:$C$195,L$20,$E76:$E195) -> -3172227.9 | O37: DSCR Check from Year
A38: Prinpical Payment | C38: =SUMIF($C$76:$C$195,C$20,$D76:$D195) -> 0 | D38: =SUMIF($C$76:$C$195,D$20,$D76:$D195) -> 0 | E38: =SUMIF($C$76:$C$195,E$20,$D76:$D195) -> 0 | F38: =SUMIF($C$76:$C$195,F$20,$D76:$D195) -> -337851.64 | G38: =SUMIF($C$76:$C$195,G$20,$D76:$D195) -> -1038879.9 | H38: =SUMIF($C$76:$C$195,H$20,$D76:$D195) -> -1077977.1 | I38: =SUMIF($C$76:$C$195,I$20,$D76:$D195) -> -1118545.6 | J38: =SUMIF($C$76:$C$195,J$20,$D76:$D195) -> -1160640.9 | ... L38: =SUMIF($C$76:$C$195,L$20,$D76:$D195) -> -1249643.7 | O38: =G19 -> 5 | P38: =H19 -> 6 | Q38: =I19 -> 7 | R38: =J19 -> 8 | S38: =K19 -> 9 | T38: =L19 -> 10
A39: Income before Tax | C39: =SUM(C36:C38) -> 0 | D39: =SUM(D36:D38) -> 0 | E39: =SUM(E36:E38) -> 0 | F39: =SUM(F36:F38) -> 159343.7 | G39: =SUM(G36:G38) -> 576029.14 | H39: =SUM(H36:H38) -> 675987.16 | I39: =SUM(I36:I38) -> 777944.34 | J39: =SUM(J36:J38) -> 881940.66 | ... L39: =SUM(L36:L38) -> 1096214.7 | O39: =-G36/(G37+G38) -> 1.1302682 | P39: =-H36/(H37+H38) -> 1.1528735 | Q39: =-I36/(I37+I38) -> 1.175931 | R39: =-J36/(J37+J38) -> 1.1994496 | S39: =-K36/(K37+K38) -> 1.2234386 | T39: =-L36/(L37+L38) -> 1.2479074
A41: ="Valuation @ "&TEXT('12. Sensitivity'!H13,"0.00%")&" Cap rate" -> Valuation @ 4.75% Cap rate | C41: =IF(AND(C21<>0,C20>=YEAR('8. Schedule'!$E$21)),'11. 10-Yr Cash Flow IRR'!C36/'11. 10-Yr Cash Flow IRR'!C21*12/'12. Sensitivity'!$H$13,0) -> 0 | D41: =IF(AND(D21<>0,D20>=YEAR('8. Schedule'!$E$21)),'11. 10-Yr Cash Flow IRR'!D36/'11. 10-Yr Cash Flow IRR'!D21*12/'12. Sensitivity'!$H$13,0) -> 0 | E41: =IF(AND(E21<>0,E20>=YEAR('8. Schedule'!$E$21)),'11. 10-Yr Cash Flow IRR'!E36/'11. 10-Yr Cash Flow IRR'!E21*12/'12. Sensitivity'!$H$13,0) -> 0 | F41: =IF(AND(F21<>0,F20>=YEAR('8. Schedule'!$E$21)),'11. 10-Yr Cash Flow IRR'!F36/'11. 10-Yr Cash Flow IRR'!F21*12/'12. Sensitivity'!$H$13,0) -> 1.0315585e+08 | G41: =IF(AND(G21<>0,G20>=YEAR('8. Schedule'!$E$21)),'11. 10-Yr Cash Flow IRR'!G36/'11. 10-Yr Cash Flow IRR'!G21*12/'12. Sensitivity'!$H$13,0) -> 1.0521896e+08 | H41: =IF(AND(H21<>0,H20>=YEAR('8. Schedule'!$E$21)),'11. 10-Yr Cash Flow IRR'!H36/'11. 10-Yr Cash Flow IRR'!H21*12/'12. Sensitivity'!$H$13,0) -> 1.0732334e+08 | I41: =IF(AND(I21<>0,I20>=YEAR('8. Schedule'!$E$21)),'11. 10-Yr Cash Flow IRR'!I36/'11. 10-Yr Cash Flow IRR'!I21*12/'12. Sensitivity'!$H$13,0) -> 1.0946981e+08 | J41: =IF(AND(J21<>0,J20>=YEAR('8. Schedule'!$E$21)),'11. 10-Yr Cash Flow IRR'!J36/'11. 10-Yr Cash Flow IRR'!J21*12/'12. Sensitivity'!$H$13,0) -> 1.1165921e+08 | ... L41: =IF(AND(L21<>0,L20>=YEAR('8. Schedule'!$E$21)),'11. 10-Yr Cash Flow IRR'!L36/'11. 10-Yr Cash Flow IRR'!L21*12/'12. Sensitivity'!$H$13,0) -> 1.1617024e+08
A42: ="Less: Selling Cost @ "&TEXT($E$11,"0.00%") -> Less: Selling Cost @ 1.00% | C42: =-$E$11*C41 -> 0 | D42: =-$E$11*D41 -> 0 | E42: =-$E$11*E41 -> 0 | F42: =-$E$11*F41 -> -1031558.5 | G42: =-$E$11*G41 -> -1052189.6 | H42: =-$E$11*H41 -> -1073233.4 | I42: =-$E$11*I41 -> -1094698.1 | J42: =-$E$11*J41 -> -1116592.1 | ... L42: =-$E$11*L41 -> -1161702.4
A43: Less: Loan Balance | C43: =-C$34 -> 0 | D43: =-D$34 -> 0 | E43: =-E$34 -> 0 | F43: =-F$34 -> -92243039 | G43: =-G$34 -> -91905187 | H43: =-H$34 -> -90866307 | I43: =-I$34 -> -89788330 | J43: =-J$34 -> -88669785 | ... L43: =-L$34 -> -86304824
A44: Net Proceeds from Sale | C44: =SUM(C41:C43) -> 0 | D44: =SUM(D41:D43) -> 0 | E44: =SUM(E41:E43) -> 0 | F44: =SUM(F41:F43) -> 9881250.3 | G44: =SUM(G41:G43) -> 12261588 | H44: =SUM(H41:H43) -> 15383803 | I44: =SUM(I41:I43) -> 18586782 | J44: =SUM(J41:J43) -> 21872830 | ... L44: =SUM(L41:L43) -> 28703713
A46: ="Valuation @ "&TEXT('12. Sensitivity'!H10,"0.00%")&" Cap rate" -> Valuation @ 4.50% Cap rate | C46: =IF(AND(C21<>0,C20>=YEAR('8. Schedule'!$E$21)),'11. 10-Yr Cash Flow IRR'!C36/'11. 10-Yr Cash Flow IRR'!C21*12/'12. Sensitivity'!$H$10,0) -> 0 | D46: =IF(AND(D21<>0,D20>=YEAR('8. Schedule'!$E$21)),'11. 10-Yr Cash Flow IRR'!D36/'11. 10-Yr Cash Flow IRR'!D21*12/'12. Sensitivity'!$H$10,0) -> 0 | E46: =IF(AND(E21<>0,E20>=YEAR('8. Schedule'!$E$21)),'11. 10-Yr Cash Flow IRR'!E36/'11. 10-Yr Cash Flow IRR'!E21*12/'12. Sensitivity'!$H$10,0) -> 0 | F46: =IF(AND(F21<>0,F20>=YEAR('8. Schedule'!$E$21)),'11. 10-Yr Cash Flow IRR'!F36/'11. 10-Yr Cash Flow IRR'!F21*12/'12. Sensitivity'!$H$10,0) -> 1.0888673e+08 | G46: =IF(AND(G21<>0,G20>=YEAR('8. Schedule'!$E$21)),'11. 10-Yr Cash Flow IRR'!G36/'11. 10-Yr Cash Flow IRR'!G21*12/'12. Sensitivity'!$H$10,0) -> 1.1106446e+08 | H46: =IF(AND(H21<>0,H20>=YEAR('8. Schedule'!$E$21)),'11. 10-Yr Cash Flow IRR'!H36/'11. 10-Yr Cash Flow IRR'!H21*12/'12. Sensitivity'!$H$10,0) -> 1.1328575e+08 | I46: =IF(AND(I21<>0,I20>=YEAR('8. Schedule'!$E$21)),'11. 10-Yr Cash Flow IRR'!I36/'11. 10-Yr Cash Flow IRR'!I21*12/'12. Sensitivity'!$H$10,0) -> 1.1555147e+08 | J46: =IF(AND(J21<>0,J20>=YEAR('8. Schedule'!$E$21)),'11. 10-Yr Cash Flow IRR'!J36/'11. 10-Yr Cash Flow IRR'!J21*12/'12. Sensitivity'!$H$10,0) -> 1.178625e+08 | ... L46: =IF(AND(L21<>0,L20>=YEAR('8. Schedule'!$E$21)),'11. 10-Yr Cash Flow IRR'!L36/'11. 10-Yr Cash Flow IRR'!L21*12/'12. Sensitivity'!$H$10,0) -> 1.2262414e+08
A47: ="Less: Selling Cost @ "&TEXT($E$11,"0.00%") -> Less: Selling Cost @ 1.00% | C47: =-$E$11*C46 -> 0 | D47: =-$E$11*D46 -> 0 | E47: =-$E$11*E46 -> 0 | F47: =-$E$11*F46 -> -1088867.3 | G47: =-$E$11*G46 -> -1110644.6 | H47: =-$E$11*H46 -> -1132857.5 | I47: =-$E$11*I46 -> -1155514.7 | J47: =-$E$11*J46 -> -1178625 | ... L47: =-$E$11*L46 -> -1226241.4
A48: Less: Loan Balance | C48: =-C$34 -> 0 | D48: =-D$34 -> 0 | E48: =-E$34 -> 0 | F48: =-F$34 -> -92243039 | G48: =-G$34 -> -91905187 | H48: =-H$34 -> -90866307 | I48: =-I$34 -> -89788330 | J48: =-J$34 -> -88669785 | ... L48: =-L$34 -> -86304824
A49: Net Proceeds from Sale | C49: =SUM(C46:C48) -> 0 | D49: =SUM(D46:D48) -> 0 | E49: =SUM(E46:E48) -> 0 | F49: =SUM(F46:F48) -> 15554822 | G49: =SUM(G46:G48) -> 18048631 | H49: =SUM(H46:H48) -> 21286587 | I49: =SUM(I46:I48) -> 24607622 | J49: =SUM(J46:J48) -> 28014087 | ... L49: =SUM(L46:L48) -> 35093076
A51: ="Valuation @ "&TEXT('12. Sensitivity'!H12,"0.00%")&" Cap rate" -> Valuation @ 4.25% Cap rate | C51: =IF(AND(C21<>0,C20>=YEAR('8. Schedule'!$E$21)),'11. 10-Yr Cash Flow IRR'!C36/'11. 10-Yr Cash Flow IRR'!C21*12/'12. Sensitivity'!$H$12,0) -> 0 | D51: =IF(AND(D21<>0,D20>=YEAR('8. Schedule'!$E$21)),'11. 10-Yr Cash Flow IRR'!D36/'11. 10-Yr Cash Flow IRR'!D21*12/'12. Sensitivity'!$H$12,0) -> 0 | E51: =IF(AND(E21<>0,E20>=YEAR('8. Schedule'!$E$21)),'11. 10-Yr Cash Flow IRR'!E36/'11. 10-Yr Cash Flow IRR'!E21*12/'12. Sensitivity'!$H$12,0) -> 0 | F51: =IF(AND(F21<>0,F20>=YEAR('8. Schedule'!$E$21)),'11. 10-Yr Cash Flow IRR'!F36/'11. 10-Yr Cash Flow IRR'!F21*12/'12. Sensitivity'!$H$12,0) -> 1.1529183e+08 | G51: =IF(AND(G21<>0,G20>=YEAR('8. Schedule'!$E$21)),'11. 10-Yr Cash Flow IRR'!G36/'11. 10-Yr Cash Flow IRR'!G21*12/'12. Sensitivity'!$H$12,0) -> 1.1759767e+08 | H51: =IF(AND(H21<>0,H20>=YEAR('8. Schedule'!$E$21)),'11. 10-Yr Cash Flow IRR'!H36/'11. 10-Yr Cash Flow IRR'!H21*12/'12. Sensitivity'!$H$12,0) -> 1.1994962e+08 | I51: =IF(AND(I21<>0,I20>=YEAR('8. Schedule'!$E$21)),'11. 10-Yr Cash Flow IRR'!I36/'11. 10-Yr Cash Flow IRR'!I21*12/'12. Sensitivity'!$H$12,0) -> 1.2234861e+08 | J51: =IF(AND(J21<>0,J20>=YEAR('8. Schedule'!$E$21)),'11. 10-Yr Cash Flow IRR'!J36/'11. 10-Yr Cash Flow IRR'!J21*12/'12. Sensitivity'!$H$12,0) -> 1.2479558e+08 | ... L51: =IF(AND(L21<>0,L20>=YEAR('8. Schedule'!$E$21)),'11. 10-Yr Cash Flow IRR'!L36/'11. 10-Yr Cash Flow IRR'!L21*12/'12. Sensitivity'!$H$12,0) -> 1.2983733e+08
A52: ="Less: Selling Cost @ "&TEXT($E$11,"0.00%") -> Less: Selling Cost @ 1.00% | C52: =-$E$11*C51 -> 0 | D52: =-$E$11*D51 -> 0 | E52: =-$E$11*E51 -> 0 | F52: =-$E$11*F51 -> -1152918.3 | G52: =-$E$11*G51 -> -1175976.7 | H52: =-$E$11*H51 -> -1199496.2 | I52: =-$E$11*I51 -> -1223486.1 | J52: =-$E$11*J51 -> -1247955.8 | ... L52: =-$E$11*L51 -> -1298373.3
A53: Less: Loan Balance | C53: =-C$34 -> 0 | D53: =-D$34 -> 0 | E53: =-E$34 -> 0 | F53: =-F$34 -> -92243039 | G53: =-G$34 -> -91905187 | H53: =-H$34 -> -90866307 | I53: =-I$34 -> -89788330 | J53: =-J$34 -> -88669785 | ... L53: =-L$34 -> -86304824
A54: Net Proceeds from Sale | C54: =SUM(C51:C53) -> 0 | D54: =SUM(D51:D53) -> 0 | E54: =SUM(E51:E53) -> 0 | F54: =SUM(F51:F53) -> 21895873 | G54: =SUM(G51:G53) -> 24516502 | H54: =SUM(H51:H53) -> 27883816 | I54: =SUM(I51:I53) -> 31336796 | J54: =SUM(J51:J53) -> 34877844 | ... L54: =SUM(L51:L53) -> 42234129
B56: IRR CALCULATION | D56: ="Based on valuation @ "&TEXT('12. Sensitivity'!H10,"0.00%")&" Cap rate" -> Based on valuation @ 4.50% Cap rate
A57: Equity Investment | C57: =ROUND(SUMIFS('10. Development Cash Flow'!$I104:$CZ104,'10. Development Cash Flow'!$I5:$CZ5,C$20,'10. Development Cash Flow'!$I110:$CZ110,"PUD"),0) -> -9439788 | D57: =ROUND(IF(D34=MAX($C34:$L34),-$K$15-SUM($C$57:C57),0)+SUMIFS('10. Development Cash Flow'!$I104:$CZ104,'10. Development Cash Flow'!$I5:$CZ5,D$20,'10. Development Cash Flow'!$I110:$CZ110,"PUD"),0) -> 0 | E57: =ROUND(IF(E34=MAX($C34:$L34),-$K$15-SUM($C$57:D57),0)+SUMIFS('10. Development Cash Flow'!$I104:$CZ104,'10. Development Cash Flow'!$I5:$CZ5,E$20,'10. Development Cash Flow'!$I110:$CZ110,"PUD"),0) -> 0 | F57: =ROUND(IF(F34=MAX($C34:$L34),-$K$15-SUM($C$57:E57),0)+SUMIFS('10. Development Cash Flow'!$I104:$CZ104,'10. Development Cash Flow'!$I5:$CZ5,F$20,'10. Development Cash Flow'!$I110:$CZ110,"PUD"),0)-'6. Debt Stack & Financing'!D40 -> 2464086.6 | G57: =ROUND(IF(G34=MAX($C34:$L34),-$K$15-SUM($C$57:F57),0)+SUMIFS('10. Development Cash Flow'!$I104:$CZ104,'10. Development Cash Flow'!$I5:$CZ5,G$20,'10. Development Cash Flow'!$I110:$CZ110,"PUD"),0) -> 0 | H57: =ROUND(IF(H34=MAX($C34:$L34),-$K$15-SUM($C$57:G57),0)+SUMIFS('10. Development Cash Flow'!$I104:$CZ104,'10. Development Cash Flow'!$I5:$CZ5,H$20,'10. Development Cash Flow'!$I110:$CZ110,"PUD"),0) -> 0 | I57: =ROUND(IF(I34=MAX($C34:$L34),-$K$15-SUM($C$57:H57),0)+SUMIFS('10. Development Cash Flow'!$I104:$CZ104,'10. Development Cash Flow'!$I5:$CZ5,I$20,'10. Development Cash Flow'!$I110:$CZ110,"PUD"),0) -> 0 | J57: =ROUND(IF(J34=MAX($C34:$L34),-$K$15-SUM($C$57:I57),0)+SUMIFS('10. Development Cash Flow'!$I104:$CZ104,'10. Development Cash Flow'!$I5:$CZ5,J$20,'10. Development Cash Flow'!$I110:$CZ110,"PUD"),0) -> 0 | K57: =ROUND(IF(K34=MAX($C34:$L34),-$K$15-SUM($C$57:J57),0)+SUMIFS('10. Development Cash Flow'!$I104:$CZ104,'10. Development Cash Flow'!$I5:$CZ5,K$20,'10. Development Cash Flow'!$I110:$CZ110,"PUD"),0) -> 0 | L57: =ROUND(IF(L34=MAX($C34:$L34),-$K$15-SUM($C$57:K57),0)+SUMIFS('10. Development Cash Flow'!$I104:$CZ104,'10. Development Cash Flow'!$I5:$CZ5,L$20,'10. Development Cash Flow'!$I110:$CZ110,"PUD"),0) -> 0
A58: Income before Tax | C58: =C39 -> 0 | D58: =D39 -> 0 | E58: =E39 -> 0 | F58: =F39 -> 159343.7 | G58: =G39 -> 576029.14 | H58: =H39 -> 675987.16 | I58: =I39 -> 777944.34 | J58: =J39 -> 881940.66 | ... L58: =L39 -> 1096214.7
A60: 5 | B60: -year cash flow | C60: =IF(C$19<=$A60,SUM(C$57:C$58),0)+IF(C$19=$A60,C$49,0) -> -9439788 | D60: =IF(D$19<=$A60,SUM(D$57:D$58),0)+IF(D$19=$A60,D$49,0) -> 0 | E60: =IF(E$19<=$A60,SUM(E$57:E$58),0)+IF(E$19=$A60,E$49,0) -> 0 | F60: =IF(F$19<=$A60,SUM(F$57:F$58),0)+IF(F$19=$A60,F$49,0) -> 2623430.3 | G60: =IF(G$19<=$A60,SUM(G$57:G$58),0)+IF(G$19=$A60,G$49,0) -> 18624660 | H60: =IF(H$19<=$A60,SUM(H$57:H$58),0)+IF(H$19=$A60,H$49,0) -> 0 | I60: =IF(I$19<=$A60,SUM(I$57:I$58),0)+IF(I$19=$A60,I$49,0) -> 0 | J60: =IF(J$19<=$A60,SUM(J$57:J$58),0)+IF(J$19=$A60,J$49,0) -> 0 | ... L60: =IF(L$19<=$A60,SUM(L$57:L$58),0)+IF(L$19=$A60,L$49,0) -> 0
A61: IRR | B61: =IFERROR(IRR(C60:L60),"-") -> 0.23360651
A63: 7 | B63: -year cash flow | C63: =IF(C$19<=$A63,SUM(C$57:C$58),0)+IF(C$19=$A63,C$49,0) -> -9439788 | D63: =IF(D$19<=$A63,SUM(D$57:D$58),0)+IF(D$19=$A63,D$49,0) -> 0 | E63: =IF(E$19<=$A63,SUM(E$57:E$58),0)+IF(E$19=$A63,E$49,0) -> 0 | F63: =IF(F$19<=$A63,SUM(F$57:F$58),0)+IF(F$19=$A63,F$49,0) -> 2623430.3 | G63: =IF(G$19<=$A63,SUM(G$57:G$58),0)+IF(G$19=$A63,G$49,0) -> 576029.14 | H63: =IF(H$19<=$A63,SUM(H$57:H$58),0)+IF(H$19=$A63,H$49,0) -> 675987.16 | I63: =IF(I$19<=$A63,SUM(I$57:I$58),0)+IF(I$19=$A63,I$49,0) -> 25385566 | J63: =IF(J$19<=$A63,SUM(J$57:J$58),0)+IF(J$19=$A63,J$49,0) -> 0 | ... L63: =IF(L$19<=$A63,SUM(L$57:L$58),0)+IF(L$19=$A63,L$49,0) -> 0
A64: IRR | B64: =IRR(C63:L63) -> 0.22501047
A66: 10 | B66: -year cash flow | C66: =IF(C$19<=$A66,SUM(C$57:C$58),0)+IF(C$19=$A66,C$49,0) -> -9439788 | D66: =IF(D$19<=$A66,SUM(D$57:D$58),0)+IF(D$19=$A66,D$49,0) -> 0 | E66: =IF(E$19<=$A66,SUM(E$57:E$58),0)+IF(E$19=$A66,E$49,0) -> 0 | F66: =IF(F$19<=$A66,SUM(F$57:F$58),0)+IF(F$19=$A66,F$49,0) -> 2623430.3 | G66: =IF(G$19<=$A66,SUM(G$57:G$58),0)+IF(G$19=$A66,G$49,0) -> 576029.14 | H66: =IF(H$19<=$A66,SUM(H$57:H$58),0)+IF(H$19=$A66,H$49,0) -> 675987.16 | I66: =IF(I$19<=$A66,SUM(I$57:I$58),0)+IF(I$19=$A66,I$49,0) -> 777944.34 | J66: =IF(J$19<=$A66,SUM(J$57:J$58),0)+IF(J$19=$A66,J$49,0) -> 881940.66 | ... L66: =IF(L$19<=$A66,SUM(L$57:L$58),0)+IF(L$19=$A66,L$49,0) -> 36189291
A67: IRR | B67: =IRR(C66:L66) -> 0.20617253
A74: Loan Amortization Schedule
A75: Period | B75: Month | C75: Year | D75: Principal | E75: Interest | F75: Beginning Balance | G75: Ending Balance
A76: 1 | B76: =EDATE('8. Schedule'!$E$21,1) -> 47377 | C76: =YEAR(B76) -> 2029 | D76: =PPMT($E$14/12,A76,$E$15*12,$F$76) -> -84073.27 | E76: =IPMT($E$14/12,A76,$E$15*12,$F$76) -> -284416.04 | F76: =K14 -> 92243039 | G76: =F76+D76 -> 92158966
A77: 2 | B77: =EDATE(B76,1) -> 47407 | C77: =YEAR(B77) -> 2029 | D77: =PPMT($E$14/12,A77,$E$15*12,$F$76) -> -84332.496 | E77: =IPMT($E$14/12,A77,$E$15*12,$F$76) -> -284156.81 | F77: =G76 -> 92158966 | G77: =F77+D77 -> 92074633
A78: 3 | B78: =EDATE(B77,1) -> 47438 | C78: =YEAR(B78) -> 2029 | D78: =PPMT($E$14/12,A78,$E$15*12,$F$76) -> -84592.521 | E78: =IPMT($E$14/12,A78,$E$15*12,$F$76) -> -283896.79 | F78: =G77 -> 92074633 | G78: =F78+D78 -> 91990041
A79: 4 | B79: =EDATE(B78,1) -> 47468 | C79: =YEAR(B79) -> 2029 | D79: =PPMT($E$14/12,A79,$E$15*12,$F$76) -> -84853.348 | E79: =IPMT($E$14/12,A79,$E$15*12,$F$76) -> -283635.96 | F79: =G78 -> 91990041 | G79: =F79+D79 -> 91905187
A80: 5 | B80: =EDATE(B79,1) -> 47499 | C80: =YEAR(B80) -> 2030 | D80: =PPMT($E$14/12,A80,$E$15*12,$F$76) -> -85114.979 | E80: =IPMT($E$14/12,A80,$E$15*12,$F$76) -> -283374.33 | F80: =G79 -> 91905187 | G80: =F80+D80 -> 91820072
A81: 6 | B81: =EDATE(B80,1) -> 47530 | C81: =YEAR(B81) -> 2030 | D81: =PPMT($E$14/12,A81,$E$15*12,$F$76) -> -85377.417 | E81: =IPMT($E$14/12,A81,$E$15*12,$F$76) -> -283111.89 | F81: =G80 -> 91820072 | G81: =F81+D81 -> 91734695
A82: 7 | B82: =EDATE(B81,1) -> 47558 | C82: =YEAR(B82) -> 2030 | D82: =PPMT($E$14/12,A82,$E$15*12,$F$76) -> -85640.664 | E82: =IPMT($E$14/12,A82,$E$15*12,$F$76) -> -282848.64 | F82: =G81 -> 91734695 | G82: =F82+D82 -> 91649054
A83: 8 | B83: =EDATE(B82,1) -> 47589 | C83: =YEAR(B83) -> 2030 | D83: =PPMT($E$14/12,A83,$E$15*12,$F$76) -> -85904.723 | E83: =IPMT($E$14/12,A83,$E$15*12,$F$76) -> -282584.58 | F83: =G82 -> 91649054 | G83: =F83+D83 -> 91563150
A84: 9 | B84: =EDATE(B83,1) -> 47619 | C84: =YEAR(B84) -> 2030 | D84: =PPMT($E$14/12,A84,$E$15*12,$F$76) -> -86169.596 | E84: =IPMT($E$14/12,A84,$E$15*12,$F$76) -> -282319.71 | F84: =G83 -> 91563150 | G84: =F84+D84 -> 91476980
A85: 10 | B85: =EDATE(B84,1) -> 47650 | C85: =YEAR(B85) -> 2030 | D85: =PPMT($E$14/12,A85,$E$15*12,$F$76) -> -86435.285 | E85: =IPMT($E$14/12,A85,$E$15*12,$F$76) -> -282054.02 | F85: =G84 -> 91476980 | G85: =F85+D85 -> 91390545
A86: 11 | B86: =EDATE(B85,1) -> 47680 | C86: =YEAR(B86) -> 2030 | D86: =PPMT($E$14/12,A86,$E$15*12,$F$76) -> -86701.794 | E86: =IPMT($E$14/12,A86,$E$15*12,$F$76) -> -281787.51 | F86: =G85 -> 91390545 | G86: =F86+D86 -> 91303843
A87: 12 | B87: =EDATE(B86,1) -> 47711 | C87: =YEAR(B87) -> 2030 | D87: =PPMT($E$14/12,A87,$E$15*12,$F$76) -> -86969.125 | E87: =IPMT($E$14/12,A87,$E$15*12,$F$76) -> -281520.18 | F87: =G86 -> 91303843 | G87: =F87+D87 -> 91216874
A88: 13 | B88: =EDATE(B87,1) -> 47742 | C88: =YEAR(B88) -> 2030 | D88: =PPMT($E$14/12,A88,$E$15*12,$F$76) -> -87237.279 | E88: =IPMT($E$14/12,A88,$E$15*12,$F$76) -> -281252.03 | F88: =G87 -> 91216874 | G88: =F88+D88 -> 91129637
... A195: 120 | B195: =EDATE(B194,1) -> 50998 | C195: =YEAR(B195) -> 2039 | D195: =PPMT($E$14/12,A195,$E$15*12,$F$76) -> -121272.59 | E195: =IPMT($E$14/12,A195,$E$15*12,$F$76) -> -247216.71 | F195: =G194 -> 80178394 | G195: =F195+D195 -> 80057121

Sheet 12. Sensitivity
J1: ="Currently running: "&CHOOSE('12. Sensitivity'!$E$8,'12. Sensitivity'!$B$11,'12. Sensitivity'!$B$12,'12. Sensitivity'!$B$13) -> Currently running: Base Case
B3: ='3. Headline #s'!A10 -> Apartment Development Model Reverse 1B
B4: ='3. Headline #s'!A12 -> 2240 Birchmount Road, Scarborough, ON
B5: Scenarios
D8: Select Scenario: | E8: 1
B9: SENSITIZED ASSUMPTIONS
B10: Capitalization Rate | H10: =CHOOSE($E$8,H11,H12,H13) -> 0.045
B11: Base Case | H11: ='1. 1A Proforma'!H47 -> 0.045
B12: Best Case | H12: ='1. 1A Proforma'!H46 -> 0.0425
B13: Worst Case | H13: ='1. 1A Proforma'!H48 -> 0.0475
B15: Construction Loan Interest Rate | H15: =CHOOSE($E$8,H16,H17,H18) -> 0.058666667
B16: Base Case | H16: =+'6. Debt Stack & Financing'!D20 -> 0.058666667
B17: Best Case | H17: =+H16-0.0025 -> 0.056166667
B18: Worst Case | H18: =+H16+0.0025 -> 0.061166667
B20: Construction Period (Months) | H20: =CHOOSE($E$8,H21,H22,H23) -> 18
B21: Base Case | H21: ='5. Key Assumptions'!E14 -> 18
B22: Best Case | H22: =H21-3 -> 15
B23: Worst Case | H23: =H21+3 -> 21
B25: Lease-up Period (Months) | H25: =CHOOSE($E$8,H26,H27,H28) -> 11.333333
B26: Base Case | H26: ='5. Key Assumptions'!E15 -> 11.333333
B27: Best Case | H27: =H26-2 -> 9.3333333
B28: Worst Case | H28: =H26+2 -> 13.333333
B30: Operating Expense Varience | H30: =CHOOSE($E$8,H31,H32,H33) -> 0
B31: Base Case | H31: 0
B32: Best Case | H32: -0.05
B33: Worst Case | H33: 0.05

Sheet 13. Altus Cost Guide 25
A1: Altus Group - 2025 Canadian Cost Guide
A2: Private Sector Construction Costs (Cost per Square Foot)
A4: Building Type | B4: Vancouver Low | C4: Vancouver High | D4: Calgary Low | E4: Calgary High | F4: GTA Low | G4: GTA High | H4: Ottawa Low | I4: Ottawa High | J4: Montreal Low | K4: Montreal High
A5: RESIDENTIAL - Condominiums/Apartments
A6: Up to 12 Storeys | B6: $330 | C6: $405 | D6: $295 | E6: $350 | F6: $290 | G6: $390 | H6: $270 | I6: $345 | J6: $260 | K6: $320
A7: 13-39 Storeys | B7: $360 | C7: $455 | D7: $305 | E7: $360 | F7: $295 | G7: $385 | H7: $310 | I7: $340 | J7: $300 | K7: $315
A8: 40-60 Storeys | B8: $360 | C8: $480 | D8: $310 | E8: $365 | F8: $330 | G8: $410 | H8: $315 | I8: $365 | J8: $310 | K8: $355
A9: 60+ Storeys | B9: $370 | C9: $485 | D9: N/A | E9: N/A | F9: $365 | G9: $480 | H9: N/A | I9: N/A | J9: N/A | K9: N/A
A10: Premium for High Quality | B10: up to $275 | D10: up to $265 | F10: up to $245 | H10: up to $195 | J10: up to $200
A12: RESIDENTIAL - Wood Framed
A13: Row Townhouse | B13: $205 | C13: $310 | D13: $185 | E13: $245 | F13: $205 | G13: $265 | H13: $130 | I13: $180 | J13: $135 | K13: $185
A14: Single Family | B14: $200 | C14: $320 | D14: $175 | E14: $265 | F14: $200 | G14: $275 | H14: $140 | I14: $225 | J14: $145 | K14: $205
A15: 3 Storey Stacked Townhouse | B15: $225 | C15: $315 | D15: $195 | E15: $255 | F15: $230 | G15: $270 | H15: $170 | I15: $205 | J15: $155 | K15: $205
A16: Up to 6 Storey Wood Framed | B16: $275 | C16: $365 | D16: $235 | E16: $345 | F16: $245 | G16: $330 | H16: $215 | I16: $280 | J16: $210 | K16: $275
A18: COMMERCIAL - Office Buildings
A19: Under 5 Storeys (Class B) | B19: $300 | C19: $380 | D19: $240 | E19: $325 | F19: $260 | G19: $355 | H19: $240 | I19: $310 | J19: $200 | K19: $270
A20: 5-30 Storeys (Class B) | B20: $300 | C20: $375 | D20: $245 | E20: $330 | F20: $270 | G20: $380 | H20: $250 | I20: $340 | J20: $205 | K20: $280
A21: 5-30 Storeys (Class A) | B21: $345 | C21: $425 | D21: $270 | E21: $375 | F21: $305 | G21: $450 | H21: $295 | I21: $385 | J21: $265 | K21: $355
A22: 31-60 Storeys (Class A) | B22: $370 | C22: $460 | D22: $305 | E22: $430 | F22: $355 | G22: $510 | H22: N/A | I22: N/A | J22: $315 | K22: $440
A24: COMMERCIAL - Retail
A25: Strip Plaza | B25: $210 | C25: $300 | D25: $220 | E25: $300 | F25: $235 | G25: $295 | H25: $170 | I25: $245 | J25: $155 | K25: $225
A26: Supermarket | B26: $215 | C26: $270 | D26: $210 | E26: $260 | F26: $175 | G26: $260 | H26: $180 | I26: $260 | J26: $175 | K26: $230
A27: Big Box Store | B27: $205 | C27: $270 | D27: $200 | E27: $255 | F27: $165 | G27: $240 | H27: $175 | I27: $225 | J27: $165 | K27: $220
A28: Enclosed Mall | B28: $350 | C28: $460 | D28: $270 | E28: $420 | F28: $275 | G28: $480 | H28: $245 | I28: $315 | J28: $245 | K28: $330
A30: COMMERCIAL - Hotels
A31: Budget | B31: $240 | C31: $310 | D31: $240 | E31: $325 | F31: $245 | G31: $325 | H31: $220 | I31: $285 | J31: $195 | K31: $265
A32: Suite Hotel | B32: $340 | C32: $425 | D32: $300 | E32: $410 | F32: $345 | G32: $420 | H32: $290 | I32: $385 | J32: $245 | K32: $325
A33: 4-star Full Service | B33: $395 | C33: $560 | D33: $320 | E33: $435 | F33: $390 | G33: $565 | H33: $345 | I33: $520 | J33: $310 | K33: $455
A35: PARKING
A36: Surface Parking | B36: $13 | C36: $25 | D36: $11 | E36: $27 | F36: $15 | G36: $30 | H36: $12 | I36: $24 | J36: $11 | K36: $22
A37: Freestanding (Above Grade) | B37: $130 | C37: $210 | D37: $115 | E37: $175 | F37: $125 | G37: $200 | H37: $115 | I37: $165 | J37: $105 | K37: $155
A38: Underground Parking | B38: $170 | C38: $290 | D38: $160 | E38: $220 | F38: $175 | G38: $285 | H38: $200 | I38: $290 | J38: $145 | K38: $195
A40: INDUSTRIAL
A41: Warehouse | B41: $125 | C41: $210 | D41: $125 | E41: $165 | F41: $80 | G41: $180 | H41: $120 | I41: $170 | J41: $115 | K41: $175
A42: Distribution Facility | B42: $200 | C42: $485 | D42: $150 | E42: $450 | F42: $180 | G42: $480 | H42: $165 | I42: $445 | J42: $160 | K42: $440
A49: Data as of: | B49: January 31, 2025
A51: Key Notes
A52: • All costs are in CAD per square foot
A53: • Costs include above-grade scope only
A54: • Add below-grade parking costs separately
A55: • Excludes GST/HST/QST (includes PST where applicable)
A56: • Does not include soft costs or tariff impacts
A57: • Costs based on mid-quality finishes unless noted

Sheet 14. Sensitivity 2
B2: SENSITIVITY 2 TEST
D4: Sensitize
B6: Res Rent | D6: 1
B8: Operating Cost | D8: 1
B10: Construction Cost | D10: 1
B13: This is mainlyl for Sheet 15 where the headline numbers are compared against current running case
B14: versus when one of the above variables are tested for sensitivity.

Sheet 15. Headline #s
A5: =TODAY() -> 46069
A10: Apartment Development Model
A12: Suburban Highrise Project in Ontario
A14: ='2. Rev 1B Exec Summary'!F34&" Units" -> 170 Units
A17: Apartment Pro-forma
A20: Prepared by:
A22: SVN Rock Advisors Inc.
C24: HEADLINE NUMBERS - SENSITIVITY 2 TEST
G26: Modified Base | I26: Base Case | K26: Variance
C28: NOI at stabilization | G28: ='2. Rev 1B Exec Summary'!H9 -> 4899902.8 | I28: 4899902.8 | K28: =+G28-I28 -> 0
C29: Capitalization Rate | G29: ='2. Rev 1B Exec Summary'!H10 -> 0.045 | I29: 0.045 | K29: =+G29-I29 -> 0
C30: Valuation | D30: @ | E30: ='2. Rev 1B Exec Summary'!D11 -> 4.4820546 | F30: per sqft avg revenue | G30: ='2. Rev 1B Exec Summary'!H11 -> 1.0888673e+08 | I30: 1.0888673e+08 | K30: =+G30-I30 -> 0
C31: Less: Selling costs | G31: ='2. Rev 1B Exec Summary'!H12 -> -1088867.3 | I31: -1088867.3 | K31: =+G31-I31 -> 0
C32: Sales Proceeds | G32: ='2. Rev 1B Exec Summary'!H13 -> 1.0779786e+08 | I32: 1.0779786e+08 | K32: =+G32-I32 -> 0
C33: Total Cost | G33: ='2. Rev 1B Exec Summary'!H14 -> -94440551 | I33: -94440551 | K33: =+G33-I33 -> 0
C34: Profit before taxes if sold at stabilization | G34: ='2. Rev 1B Exec Summary'!H15 -> 13357310 | I34: 13357310 | K34: =+G34-I34 -> 0
C36: Return on cost | G36: ='2. Rev 1B Exec Summary'!H17 -> 0.14143617 | I36: 0.14143617 | K36: =+G36-I36 -> 0
C37: Development Yield | G37: =G28/(-G33) -> 0.051883462 | I37: 0.051883462 | K37: =+G37-I37 -> 0
C39: IRR upon stabilization if sold | G39: ='2. Rev 1B Exec Summary'!H18 -> 0.27897087 | I39: 0.27897087 | K39: =+G39-I39 -> 0
C40: ="IRR "&'11. 10-Yr Cash Flow IRR'!A66&"-Year" -> IRR 10-Year | G40: ='2. Rev 1B Exec Summary'!H19 -> 0.20617253 | I40: 0.20617253 | K40: =+G40-I40 -> 0
C42: Construction Costs per unit | G42: ='9. Development Costs'!I89 -> 555532.65 | I42: 555532.65 | K42: =+G42-I42 -> 0
C43: Construction Costs per sqft | G43: ='9. Development Costs'!J89 -> 732.93136 | I43: 732.93136 | K43: =+G43-I43 -> 0
C44: Value per unit at stabilization | G44: =G30/'7. Op Rev and Exp'!E20 -> 640510.17 | I44: 640510.17 | K44: =+G44-I44 -> 0
C45: Value per sqft at stabilization | G45: =G30/'9. Development Costs'!I10 -> 845.04481 | I45: 845.04481 | K45: =+G45-I45 -> 0
A48: Disclaimer: RE: Use of the New Apartment Construction Financial Model
A49: SVN Rock Advisors Inc. Brokerage, Derek A. Lobo & Associates (DALA) and/or SVN Canada Inc. (herein described as "the Consultant") has developed the New Apartment Construction Financial Model (herein described as "the model") as a general guide to help a user understand the high level profitability of rental apartment construction development on a given site. The Model is developed in Microsoft Excel, and it is expected by the consultant, that the user of the model is proficient in Excel. Any accidental deletion of a cell may corrupt the entire file and/or show inaccurate results that the Consultant is not responsible for. The model is intended to provide a high level understanding of the profitability, and does not assure and/or guarantee success of a project in any way.
A50: Confidentiality Policy
A51: Intellecutal rights on this file remain with the Consultant
A52: Disclaimers:
A53: We make no guarantees and do not undertake to confirm independently that the information, result and or data provided is accurate or comprehensive. We recommend the client independently review data sources and periodically update and confirm the data used in the excel file.
A54: The consultant's principals, management, staff, contractors and associates are real estate consultants only.
A55: The Consultant makes no guarantees, written or otherwise, that if the client adopts or acts on the excel model's observations, findings, analysis or recommendations in the report that the client's project will be successful, nor do we, as real estate consultants, accept any legal or financial responsibility or liability for failure, under-performance, or termination of the client's project.
A56: Limitation of Liability:
A57: To the fullest extent permitted by applicable law, in no event shall the consultant be liable to the client or any other user for any direct, indirect, incidental, special, punitive, or consequential damages whatsoever resulting from any (i) use of the excel file, (ii) errors, mistakes, or inaccuracies of content, (iii) any bugs, viruses, or like, which may be transmitted to or through the excel file to or by any party, (iv) any loss of your data or content, (v) any errors or omissions in any content or for any loss or damage of any kind incurred as a result of your use of the file, whether based on warranty, contract, tort, or any other legal theory, and whether or not the client/users are advised of the possibility of such damanges, and/or (vi) the disclosure of information pursuant to these terms of use or a privacy policy.
A58: Despite the above, our total liability to you for any cause of action you take against us will at all times be limited to no more than $100/ - (one hundred dollars)
