Workbook

Sheet DevCon Pres Tbl
B3: Sensitivity Analysis of a Res Development Project
B4: Development Summary
B6: Scenario | C6: Area Sq Ft | D6: Unit | E6: NOI Now | I6: NOI Stabilized | N6: Sale Proceeds | O6: Development Costs | V6: Profit Before | X6: Return on | Y6: Development | Z6: IRR if | AA6: IRR
E7: Res Rent/SF | F7: Revenue | G7: Op Costs | H7: NOI | I7: Res Rent/SF | J7: Revenue | K7: Op Exp | L7: NOI | N7: (Value-sale costs) | O7: Land | P7: Construction | Q7: Soft Costs | R7: HST | S7: Financing | T7: Ops NOI | U7: Net Dev Costs | V7: Tax | X7: Cost | Y7: Yield | Z7: Sold on Stab | AA7: 10 Year
B9: Running Model | C9: =+'Executive Summary'!E34 -> 85975 | D9: =+'Executive Summary'!F34 -> 100 | E9: =+'Operating Revenue and Expenses'!J19 -> 2.6246002 | F9: =+'Operating Revenue and Expenses'!I29 -> 2834325 | G9: =+'Operating Revenue and Expenses'!I43 -> 765110 | H9: =+F9-G9 -> 2069215 | I9: =+E9/H9*L9 -> 3.8151156 | J9: =MAX('Development Cash Flow'!I23:CZ23)*12*0.975 -> 3007808.4 | K9: ='Development Cash Flow'!BT25*12 -> 0 | L9: =+J9+K9 -> 3007808.4 | N9: =(+L9/0.04)*0.99 -> 74443257 | O9: =+'Executive Summary'!G39 -> 5989000 | P9: =+'Executive Summary'!G40 -> 30000000 | Q9: =SUM('Executive Summary'!G41:G44) -> 6743750 | R9: =+'Executive Summary'!G46 -> 3820151.5 | S9: =+'Executive Summary'!G45 -> 3714932.5 | T9: =+'Executive Summary'!G47 -> -1080051.6 | U9: =SUM(O9:T9) -> 49187782 | V9: =+N9-U9 -> 25255475 | X9: =+V9/U9 -> 0.51345016 | Y9: =L9/U9 -> 0.061149501 | Z9: =+Cover!G39 -> 0.25094511 | AA9: =+Cover!G40 -> 0.13515738
B11: Base | C11: 81675 | D11: 100 | E11: 2.5414141 | F11: 2659644 | G11: 694735.2 | H11: 1964908.8 | I11: 3.6505396 | J11: 2822435.5 | K11: 0 | L11: 2822435.5 | N11: 69855278 | O11: 5700000 | P11: 26500000 | Q11: 5396560 | R11: 2236939.7 | S11: 2217278.5 | T11: -735677.33 | U11: 41315101 | V11: 28540178 | X11: 0.69079288 | Y11: 0.068314864 | Z11: 0.24825976 | AA11: 0.16138068
C12: =+C9-C11 -> 4300 | D12: =+D9-D11 -> 0 | E12: =+E9-E11 -> 0.083186033 | F12: =+F9-F11 -> 174681 | G12: =+G9-G11 -> 70374.8 | H12: =+H9-H11 -> 104306.2 | I12: =+I9-I11 -> 0.16457593 | J12: =+J9-J11 -> 185372.87 | ... L12: =+L9-L11 -> 185372.87 | N12: =+N9-N11 -> 4587978.6 | O12: =+O9-O11 -> 289000 | P12: =+P9-P11 -> 3500000 | Q12: =+Q9-Q11 -> 1347190 | R12: =+R9-R11 -> 1583211.8 | S12: =+S9-S11 -> 1497654.1 | T12: =+T9-T11 -> -344374.3 | U12: =+U9-U11 -> 7872681.6 | V12: =+V9-V11 -> -3284702.9 | X12: =+X9-X11 -> -0.17734272 | Y12: =+Y9-Y11 -> -0.0071653626 | Z12: =+Z9-Z11 -> 0.0026853473 | AA12: =+AA9-AA11 -> -0.026223309
B13: Sensitivity
B14: Revenue + 5% | C14: 81675 | D14: 100 | E14: 2.5414141 | F14: 2659644 | G14: 694735.2 | H14: 1964908.8 | I14: 3.6505396 | J14: 2822435.5 | K14: 0 | L14: 2822435.5 | N14: 69855278 | O14: 5700000 | P14: 26500000 | Q14: 5396560 | R14: 2236939.7 | S14: 2217278.5 | T14: -735677.33 | U14: 41315101 | V14: 28540178 | X14: 0.69079288 | Y14: 0.068314864 | Z14: 0.24825976 | AA14: 0.16138068
B15: Variance | C15: =(+C14-$C$11)/$C$11 -> 0 | D15: =(+D14-$D$11)/$D$11 -> 0 | E15: =(+E14-$E$11)/$E$11 -> 0 | F15: =(+F14-$F$11)/$F$11 -> 0 | G15: =(+G14-$G$11)/$G$11 -> 0 | H15: =(+H14-$H$11)/$H$11 -> 0 | I15: =(+I14-$I$11)/$I$11 -> 0 | J15: =(+J14-$J$11)/$J$11 -> 0 | K15: =(+K14-$K$11)/$K$11 -> #DIV/0! | L15: =(+L14-$L$11)/$L$11 -> 0 | N15: =(+N14-$N$11)/$N$11 -> 0 | O15: =(+O14-$O$11)/$O$11 -> 0 | P15: =(+P14-$P$11)/$P$11 -> 0 | Q15: =(+Q14-$Q$11)/$Q$11 -> 0 | R15: =(+R14-$R$11)/$R$11 -> 0 | S15: =(+S14-$S$11)/$S$11 -> 0 | T15: =(+T14-$T$11)/$T$11 -> 0 | U15: =(+U14-$U$11)/$U$11 -> 0 | V15: =(+V14-$V$11)/$V$11 -> 0 | X15: =+X14-$X$11 -> 0 | Y15: =+Y14-$Y$11 -> 0 | Z15: =+Z14-$Z$11 -> 0 | AA15: =+AA14-$AA$11 -> 0
B16: Dollar Profit Uplift | V16: =+V14-$V$11 -> 0
B18: Operating Cost -5% | C18: 81675 | D18: 100 | E18: 2.5414141 | F18: 2659644 | G18: 694735.2 | H18: 1964908.8 | I18: 3.6505396 | J18: 2822435.5 | K18: 0 | L18: 2822435.5 | N18: 69855278 | O18: 5700000 | P18: 26500000 | Q18: 5396560 | R18: 2236939.7 | S18: 2217278.5 | T18: -735677.33 | U18: 41315101 | V18: 28540178 | X18: 0.69079288 | Y18: 0.068314864 | Z18: 0.24825976 | AA18: 0.16138068
B19: Variance | C19: =(+C18-$C$11)/$C$11 -> 0 | D19: =(+D18-$D$11)/$D$11 -> 0 | E19: =(+E18-$E$11)/$E$11 -> 0 | F19: =(+F18-$F$11)/$F$11 -> 0 | G19: =(+G18-$G$11)/$G$11 -> 0 | H19: =(+H18-$H$11)/$H$11 -> 0 | I19: =(+I18-$I$11)/$I$11 -> 0 | J19: =(+J18-$J$11)/$J$11 -> 0 | K19: =(+K18-$K$11)/$K$11 -> #DIV/0! | L19: =(+L18-$L$11)/$L$11 -> 0 | N19: =(+N18-$N$11)/$N$11 -> 0 | O19: =(+O18-$O$11)/$O$11 -> 0 | P19: =(+P18-$P$11)/$P$11 -> 0 | Q19: =(+Q18-$Q$11)/$Q$11 -> 0 | R19: =(+R18-$R$11)/$R$11 -> 0 | S19: =(+S18-$S$11)/$S$11 -> 0 | T19: =(+T18-$T$11)/$T$11 -> 0 | U19: =(+U18-$U$11)/$U$11 -> 0 | V19: =(+V18-$V$11)/$V$11 -> 0 | X19: =+X18-$X$11 -> 0 | Y19: =+Y18-$Y$11 -> 0 | Z19: =+Z18-$Z$11 -> 0 | AA19: =+AA18-$AA$11 -> 0
B20: Dollar Profit Uplift | V20: =+V18-$V$11 -> 0
B22: Construction Cost - 5% | C22: 81675 | D22: 100 | E22: 2.5414141 | F22: 2659644 | G22: 694735.2 | H22: 1964908.8 | I22: 3.6505396 | J22: 2822435.5 | K22: 0 | L22: 2822435.5 | N22: 69855278 | O22: 5700000 | P22: 26500000 | Q22: 5396560 | R22: 2236939.7 | S22: 2217278.5 | T22: -735677.33 | U22: 41315101 | V22: 28540178 | X22: 0.69079288 | Y22: 0.068314864 | Z22: 0.24825976 | AA22: 0.16138068
B23: Variance | C23: =(+C22-$C$11)/$C$11 -> 0 | D23: =(+D22-$D$11)/$D$11 -> 0 | E23: =(+E22-$E$11)/$E$11 -> 0 | F23: =(+F22-$F$11)/$F$11 -> 0 | G23: =(+G22-$G$11)/$G$11 -> 0 | H23: =(+H22-$H$11)/$H$11 -> 0 | I23: =(+I22-$I$11)/$I$11 -> 0 | J23: =(+J22-$J$11)/$J$11 -> 0 | K23: =(+K22-$K$11)/$K$11 -> #DIV/0! | L23: =(+L22-$L$11)/$L$11 -> 0 | N23: =(+N22-$N$11)/$N$11 -> 0 | O23: =(+O22-$O$11)/$O$11 -> 0 | P23: =(+P22-$P$11)/$P$11 -> 0 | Q23: =(+Q22-$Q$11)/$Q$11 -> 0 | R23: =(+R22-$R$11)/$R$11 -> 0 | S23: =(+S22-$S$11)/$S$11 -> 0 | T23: =(+T22-$T$11)/$T$11 -> 0 | U23: =(+U22-$U$11)/$U$11 -> 0 | V23: =(+V22-$V$11)/$V$11 -> 0 | X23: =+X22-$X$11 -> 0 | Y23: =+Y22-$Y$11 -> 0 | Z23: =+Z22-$Z$11 -> 0 | AA23: =+AA22-$AA$11 -> 0
B24: Dollar Profit Uplift | V24: =+V22-$V$11 -> 0

Sheet Sensitiv2
B4: Sensitize
B6: Res Rent | D6: 1
B8: Operating Cost | D8: 1
B10: Construction Cost | D10: 1

Sheet Cover (2)
A5: =TODAY() -> 44642
A10: Apartment Development Model
A12: Suburban Highrise Project in Ontario
A14: ='Executive Summary'!F34&" Units" -> 100 Units
A17: Apartment Pro-forma
A20: Prepared by:
A22: SVN Rock Advisors Inc.
C24: HEADLINE NUMBERS
G26: Modified Base | I26: Base Case | K26: Variance
C28: NOI at stabilization | G28: ='Executive Summary'!H9 -> 2195867.5 | I28: 2195867.5 | K28: =+G28-I28 -> 0
C29: Capitalization Rate | G29: ='Executive Summary'!H10 -> 0.04 | I29: 0.04 | K29: =+G29-I29 -> 0
C30: Valuation | D30: @ | E30: ='Executive Summary'!D11 -> 2.9901441 | F30: per sqft avg revenue | G30: ='Executive Summary'!H11 -> 54896688 | I30: 54896688 | K30: =+G30-I30 -> 0
C31: Less: Selling costs | G31: ='Executive Summary'!H12 -> -548966.88 | I31: -548966.88 | K31: =+G31-I31 -> 0
C32: Sales Proceeds | G32: ='Executive Summary'!H13 -> 54347721 | I32: 54347721 | K32: =+G32-I32 -> 0
C33: Total Cost | G33: ='Executive Summary'!H14 -> -49187782 | I33: -49187782 | K33: =+G33-I33 -> 0
C34: Profit before taxes if sold at stabilization | G34: ='Executive Summary'!H15 -> 5159938.5 | I34: 5159938.5 | K34: =+G34-I34 -> 0
C36: Return on cost | G36: ='Executive Summary'!H17 -> 0.10490285 | I36: 0.10490285 | K36: =+G36-I36 -> 0
C37: Development Yield | G37: =G28/(-G33) -> 0.044642539 | I37: 0.044642539 | K37: =+G37-I37 -> 0
C39: IRR upon stabilization if sold | G39: ='Executive Summary'!H18 -> 0.25094511 | I39: 0.25094511 | K39: =+G39-I39 -> 0
C40: ="IRR "&'10-Yr Cash Flow IRR'!A66&"-Year" -> IRR 10-Year | G40: ='Executive Summary'!H19 -> 0.13515738 | I40: 0.13515738 | K40: =+G40-I40 -> 0
C42: Construction Costs per unit | G42: ='Development Costs'!I89 -> 491877.82 | I42: 491877.82 | K42: =+G42-I42 -> 0
C43: Construction Costs per sqft | G43: ='Development Costs'!J89 -> 572.11727 | I43: 572.11727 | K43: =+G43-I43 -> 0
C44: Value per unit at stabilization | G44: =G30/'Operating Revenue and Expenses'!F19 -> 548966.88 | I44: 548966.88 | K44: =+G44-I44 -> 0
C45: Value per sqft at stabilization | G45: =G30/'Development Costs'!I10 -> 638.5192 | I45: 638.5192 | K45: =+G45-I45 -> 0
A48: Disclaimer: RE: Use of the New Apartment Construction Financial Model
A49: SVN Rock Advisors Inc. Brokerage, Derek A. Lobo & Associates (DALA) and/or SVN Canada Inc. (herein described as "the Consultant") has developed the New Apartment Construction Financial Model (herein described as "the model") as a general guide to help a user understand the high level profitability of rental apartment construction development on a given site. The Model is developed in Microsoft Excel, and it is expected by the consultant, that the user of the model is proficient in Excel. Any accidental deletion of a cell may corrupt the entire file and/or show inaccurate results that the Consultant is not responsible for. The model is intended to provide a high level understanding of the profitability, and does not assure and/or guarantee success of a project in any way.
A50: Confidentiality Policy
A51: Intellecutal rights on this file remain with the Consultant
A52: Disclaimers:
A53: We make no guarantees and do not undertake to confirm independently that the information, result and or data provided is accurate or comprehensive. We recommend the client independently review data sources and periodically update and confirm the data used in the excel file.
A54: The consultant's principals, management, staff, contractors and associates are real estate consultants only.
A55: The Consultant makes no guarantees, written or otherwise, that if the client adopts or acts on the excel model's observations, findings, analysis or recommendations in the report that the client's project will be successful, nor do we, as real estate consultants, accept any legal or financial responsibility or liability for failure, under-performance, or termination of the client's project.
A56: Limitation of Liability:
A57: To the fullest extent permitted by applicable law, in no event shall the consultant be liable to the client or any other user for any direct, indirect, incidental, special, punitive, or consequential damages whatsoever resulting from any (i) use of the excel file, (ii) errors, mistakes, or inaccuracies of content, (iii) any bugs, viruses, or like, which may be transmitted to or through the excel file to or by any party, (iv) any loss of your data or content, (v) any errors or omissions in any content or for any loss or damage of any kind incurred as a result of your use of the file, whether based on warranty, contract, tort, or any other legal theory, and whether or not the client/users are advised of the possibility of such damanges, and/or (vi) the disclosure of information pursuant to these terms of use or a privacy policy.
A58: Despite the above, our total liability to you for any cause of action you take against us will at all times be limited to no more than $100/ - (one hundred dollars)

Sheet Cover
A5: =TODAY() -> 44642
A10: Apartment Development Model
A12: Suburban / Urban Location
A14: ='Executive Summary'!F34&" Units" -> 100 Units
A17: Apartment Pro-forma
A20: Prepared by:
A22: SVN Rock Advisors Inc.
C26: HEADLINE NUMBERS
C28: NOI at stabilization | G28: ='Executive Summary'!H9 -> 2195867.5
C29: Capitalization Rate | G29: ='Executive Summary'!H10 -> 0.04
C30: Valuation | D30: @ | E30: ='Executive Summary'!D11 -> 2.9901441 | F30: per sqft avg revenue | G30: ='Executive Summary'!H11 -> 54896688
C31: Less: Selling costs | G31: ='Executive Summary'!H12 -> -548966.88
C32: Sales Proceeds | G32: ='Executive Summary'!H13 -> 54347721
C33: Total Cost | G33: ='Executive Summary'!H14 -> -49187782
C34: Profit before taxes if sold at stabilization | G34: ='Executive Summary'!H15 -> 5159938.5
C36: Return on cost | G36: ='Executive Summary'!H17 -> 0.10490285
C37: Development Yield | G37: =G28/(-G33) -> 0.044642539
C39: IRR upon stabilization if sold | G39: ='Executive Summary'!H18 -> 0.25094511
C40: ="IRR "&'10-Yr Cash Flow IRR'!A66&"-Year" -> IRR 10-Year | G40: ='Executive Summary'!H19 -> 0.13515738
C42: Construction Costs per unit | G42: ='Development Costs'!I89 -> 491877.82
C43: Construction Costs per sqft | G43: ='Development Costs'!J89 -> 572.11727
C44: Value per unit at stabilization | G44: =G30/'Operating Revenue and Expenses'!F19 -> 548966.88
C45: Value per sqft at stabilization | G45: =G30/'Development Costs'!I10 -> 638.5192
A48: Disclaimer: RE: Use of the New Apartment Construction Financial Model
A49: SVN Rock Advisors Inc. Brokerage, Derek A. Lobo & Associates (DALA) and/or SVN Canada Inc. (herein described as "the Consultant") has developed the New Apartment Construction Financial Model (herein described as "the model") as a general guide to help a user understand the high level profitability of rental apartment construction development on a given site. The Model is developed in Microsoft Excel, and it is expected by the consultant, that the user of the model is proficient in Excel. Any accidental deletion of a cell may corrupt the entire file and/or show inaccurate results that the Consultant is not responsible for. The model is intended to provide a high level understanding of the profitability, and does not assure and/or guarantee success of a project in any way.
A50: Confidentiality Policy
A51: Intellecutal rights on this file remain with the Consultant
A52: Disclaimers:
A53: We make no guarantees and do not undertake to confirm independently that the information, result and or data provided is accurate or comprehensive. We recommend the client independently review data sources and periodically update and confirm the data used in the excel file.
A54: The consultant's principals, management, staff, contractors and associates are real estate consultants only.
A55: The Consultant makes no guarantees, written or otherwise, that if the client adopts or acts on the excel model's observations, findings, analysis or recommendations in the report that the client's project will be successful, nor do we, as real estate consultants, accept any legal or financial responsibility or liability for failure, under-performance, or termination of the client's project.
A56: Limitation of Liability:
A57: To the fullest extent permitted by applicable law, in no event shall the consultant be liable to the client or any other user for any direct, indirect, incidental, special, punitive, or consequential damages whatsoever resulting from any (i) use of the excel file, (ii) errors, mistakes, or inaccuracies of content, (iii) any bugs, viruses, or like, which may be transmitted to or through the excel file to or by any party, (iv) any loss of your data or content, (v) any errors or omissions in any content or for any loss or damage of any kind incurred as a result of your use of the file, whether based on warranty, contract, tort, or any other legal theory, and whether or not the client/users are advised of the possibility of such damanges, and/or (vi) the disclosure of information pursuant to these terms of use or a privacy policy.
A58: Despite the above, our total liability to you for any cause of action you take against us will at all times be limited to no more than $100/ - (one hundred dollars)

Sheet Executive Summary
J1: ="Currently running: "&CHOOSE(Sensitivity!$E$8,Sensitivity!$B$11,Sensitivity!$B$12,Sensitivity!$B$13) -> Currently running: Base Case
B3: =Cover!A10 -> Apartment Development Model
B4: =Cover!A12 -> Suburban / Urban Location
B5: Executive Summary
A8: OVERVIEW
B9: Net Operating Income @ Stabilization | G9: =H9 -> 2195867.5 | H9: ='Operating Revenue and Expenses'!I52 -> 2195867.5 | I9: =H9 -> 2195867.5
B10: Capitalization Rate | G10: =Sensitivity!H13 -> 0.0425 | H10: =Sensitivity!H10 -> 0.04 | I10: =Sensitivity!H12 -> 0.0375
B11: Valuation @ | D11: ='Operating Revenue and Expenses'!E52 -> 2.9901441 | E11: per sqft average revenue | G11: =G9/G10 -> 51667471 | H11: =H9/H10 -> 54896688 | I11: =I9/I10 -> 58556467
B12: Selling costs @ | D12: ='10-Yr Cash Flow IRR'!E11 -> 0.01 | G12: =-'10-Yr Cash Flow IRR'!$E$11*'Executive Summary'!G11 -> -516674.71 | H12: =-'10-Yr Cash Flow IRR'!$E$11*'Executive Summary'!H11 -> -548966.88 | I12: =-'10-Yr Cash Flow IRR'!$E$11*'Executive Summary'!I11 -> -585564.67
B13: Sales Proceeds | G13: =SUM(G11:G12) -> 51150796 | H13: =SUM(H11:H12) -> 54347721 | I13: =SUM(I11:I12) -> 57970902
B14: Total Costs | G14: =H14 -> -49187782 | H14: =-G48 -> -49187782 | I14: =H14 -> -49187782
B15: Profit before taxes if sold | G15: =SUM(G13:G14) -> 1963013.7 | H15: =SUM(H13:H14) -> 5159938.5 | I15: =SUM(I13:I14) -> 8783119.9
B17: Return on Cost | G17: =-G15/G14 -> 0.039908564 | H17: =-H15/H14 -> 0.10490285 | I17: =-I15/I14 -> 0.17856304
B18: IRR upon stabilization if sold | H18: ='Development Cash Flow'!G106 -> 0.25094511
B19: ="IRR "&'10-Yr Cash Flow IRR'!A66&"-Year" -> IRR 10-Year | H19: ='10-Yr Cash Flow IRR'!B67 -> 0.13515738
A21: SCHEDULE
G22: From | H22: To | I22: Months
B23: Land Purchase | G23: =Schedule!D13 -> 44562 | H23: =Schedule!E13 -> 44562 | I23: =Schedule!C13 -> 0
B24: Pre-Development | G24: =Schedule!D15 -> 44593 | H24: =Schedule!E15 -> 44958 | I24: =Schedule!C15 -> 12
B25: Construction period | G25: =Schedule!D17 -> 44986 | H25: =Schedule!E17 -> 45536 | I25: =Schedule!C17 -> 18
B26: Lease-up | G26: =Schedule!D19 -> 45474 | H26: =Schedule!E19 -> 45658 | I26: =Schedule!C19 -> 6
B27: Stabilized | G27: =Schedule!D21 -> 45689 | H27: =Schedule!E21 -> 45689 | I27: =Schedule!C21 -> 0
A29: UNIT MIX
B30: Unit Type | E30: Sq. Ft. | F30: No. Units | G30: % of Total | H30: Rent | I30: $/SF
B31: ='Operating Revenue and Expenses'!B16 -> 1 Bed | E31: ='Operating Revenue and Expenses'!E16 -> 25200 | F31: ='Operating Revenue and Expenses'!F16 -> 35 | G31: ='Operating Revenue and Expenses'!G16 -> 0.35 | H31: ='Operating Revenue and Expenses'!H16 -> 1990 | I31: ='Operating Revenue and Expenses'!J16 -> 2.7638889
B32: ='Operating Revenue and Expenses'!B17 -> 2 Bed | E32: ='Operating Revenue and Expenses'!E17 -> 60775 | F32: ='Operating Revenue and Expenses'!F17 -> 65 | G32: ='Operating Revenue and Expenses'!G17 -> 0.65 | H32: ='Operating Revenue and Expenses'!H17 -> 2400 | I32: ='Operating Revenue and Expenses'!J17 -> 2.5668449
B33: Res 2B part | E33: ='Operating Revenue and Expenses'!E18 -> 0 | F33: =+'Operating Revenue and Expenses'!F18 -> 0 | G33: ='Operating Revenue and Expenses'!G18 -> 0 | H33: ='Operating Revenue and Expenses'!H18 -> 0 | I33: ='Operating Revenue and Expenses'!J18 -> 0
B34: Total Res Units | E34: ='Operating Revenue and Expenses'!E19 -> 85975 | F34: ='Operating Revenue and Expenses'!F19 -> 100 | G34: ='Operating Revenue and Expenses'!G19 -> 1 | H34: ='Operating Revenue and Expenses'!H19 -> 2256.5 | I34: =+H34/E35 -> 2.6246002
B35: Average Res | E35: ='Operating Revenue and Expenses'!E20 -> 859.75 | H35: ='Operating Revenue and Expenses'!H20 -> 2256.5 | I35: ='Operating Revenue and Expenses'!J20 -> 2.6246002
A37: DEVELOPMENT COSTS
G38: Total | H38: Per Res unit | I38: Per Sqft | J38: %
B39: Land | G39: ='Development Costs'!H16 -> 5989000 | H39: ='Development Costs'!I16 -> 59890 | I39: ='Development Costs'!J16 -> 69.659785 | J39: =G39/$G$48 -> 0.12175788
B40: Construction | G40: ='Development Costs'!H22 -> 30000000 | H40: ='Development Costs'!I22 -> 419780 | I40: ='Development Costs'!J22 -> 348.93864 | J40: =G40/$G$48 -> 0.60990755
B41: Professional Fees | G41: ='Development Costs'!H41 -> 1419000 | H41: ='Development Costs'!I41 -> 14190 | I41: ='Development Costs'!J41 -> 16.504798 | J41: =G41/$G$48 -> 0.028848627
B42: Development Management | G42: ='Development Costs'!H46 -> 1254000 | H42: ='Development Costs'!I46 -> 12540 | I42: ='Development Costs'!J46 -> 14.585635 | J42: =G42/$G$48 -> 0.025494136
B43: Permits and Approvals | G43: ='Development Costs'!H59 -> 3344000 | H43: ='Development Costs'!I59 -> 33440 | I43: ='Development Costs'!J59 -> 38.895028 | J43: =G43/$G$48 -> 0.067984362
B44: Marketing and Leasing | G44: ='Development Costs'!H66 -> 726750 | H44: ='Development Costs'!I66 -> 7267.5 | I44: ='Development Costs'!J66 -> 8.4530387 | J44: =G44/$G$48 -> 0.01477501
B45: Financing and Interest | G45: ='Development Costs'!H80-'Development Costs'!H77 -> 3714932.5 | H45: ='Development Costs'!I80 -> 75350.84 | I45: ='Development Costs'!J80 -> 87.642734 | J45: =G45/$G$48 -> 0.075525513
B46: Taxes, HST, VAT | G46: ='Development Costs'!H77 -> 3820151.5 | H46: ='Development Costs'!I77 -> 38201.515 | I46: ='Development Costs'!J77 -> 44.433283 | J46: =G46/$G$48 -> 0.077664642
B47: Operating income during lease-up incl Sec Deposit | G47: ='Development Costs'!H87 -> -1080051.6 | H47: ='Development Costs'!I87 -> -10800.516 | I47: ='Development Costs'!J87 -> -12.562392 | J47: =G47/$G$48 -> -0.021957722
B48: Total Development Costs | G48: ='Development Costs'!H89 -> 49187782 | H48: ='Development Costs'!I89 -> 491877.82 | I48: ='Development Costs'!J89 -> 572.11727 | J48: =SUM(J39:J47) -> 1
A51: CONSTRUCTION FINANCING
B52: Construction Loan | G52: =-'Development Cash Flow'!C108 -> 44198885 | H52: =G52/G54 -> 0.89857446
B53: Equity | G53: =+G48-G52 -> 4988897.4 | H53: =G53/G54 -> 0.10142554 | I53: (Total slightly diff from DCF)
B54: Total | G54: =SUM(G52:G53) -> 49187782 | H54: =SUM(H52:H53) -> 1
A56: PERMANENT FINANCING
B57: LTV ratio | G57: ='10-Yr Cash Flow IRR'!L15 -> 0.63320537
B58: NOI Coverage | G58: ='10-Yr Cash Flow IRR'!L16 -> 1.1101004
B59: Princpal Loan Value | G59: ='10-Yr Cash Flow IRR'!K14 -> 34760878
B60: Annual Debt Service (including Principal) | G60: ='10-Yr Cash Flow IRR'!K16 -> 1978080.2

Sheet Schedule
BP1: ="Currently running: "&CHOOSE(Sensitivity!$E$8,Sensitivity!$B$11,Sensitivity!$B$12,Sensitivity!$B$13) -> Currently running: Base Case
B3: =Cover!A10 -> Apartment Development Model
B4: =Cover!A12 -> Suburban / Urban Location
B5: Schedule
B8: Project Start Date | D8: 44562
I10: =D8 -> 44562 | J10: =EDATE(I10,1) -> 44593 | K10: =EDATE(J10,1) -> 44621 | L10: =EDATE(K10,1) -> 44652 | M10: =EDATE(L10,1) -> 44682 | N10: =EDATE(M10,1) -> 44713 | O10: =EDATE(N10,1) -> 44743 | P10: =EDATE(O10,1) -> 44774 | Q10: =EDATE(P10,1) -> 44805 | ... BP10: =EDATE(BO10,1) -> 46357
C11: Duration | D11: Start Date | E11: End Date | F11: Anchored to | G11: Offset | I11: ="Q"&ROUNDUP(MONTH(I10)/3,0)&" "&YEAR(I10) -> Q1 2022 | L11: ="Q"&ROUNDUP(MONTH(L10)/3,0)&" "&YEAR(L10) -> Q2 2022 | O11: ="Q"&ROUNDUP(MONTH(O10)/3,0)&" "&YEAR(O10) -> Q3 2022 | R11: ="Q"&ROUNDUP(MONTH(R10)/3,0)&" "&YEAR(R10) -> Q4 2022 | U11: ="Q"&ROUNDUP(MONTH(U10)/3,0)&" "&YEAR(U10) -> Q1 2023 | X11: ="Q"&ROUNDUP(MONTH(X10)/3,0)&" "&YEAR(X10) -> Q2 2023 | AA11: ="Q"&ROUNDUP(MONTH(AA10)/3,0)&" "&YEAR(AA10) -> Q3 2023 | AD11: ="Q"&ROUNDUP(MONTH(AD10)/3,0)&" "&YEAR(AD10) -> Q4 2023 | AG11: ="Q"&ROUNDUP(MONTH(AG10)/3,0)&" "&YEAR(AG10) -> Q1 2024 | AJ11: ="Q"&ROUNDUP(MONTH(AJ10)/3,0)&" "&YEAR(AJ10) -> Q2 2024 | AM11: ="Q"&ROUNDUP(MONTH(AM10)/3,0)&" "&YEAR(AM10) -> Q3 2024 | AP11: ="Q"&ROUNDUP(MONTH(AP10)/3,0)&" "&YEAR(AP10) -> Q4 2024 | AS11: ="Q"&ROUNDUP(MONTH(AS10)/3,0)&" "&YEAR(AS10) -> Q1 2025 | AV11: ="Q"&ROUNDUP(MONTH(AV10)/3,0)&" "&YEAR(AV10) -> Q2 2025 | AY11: ="Q"&ROUNDUP(MONTH(AY10)/3,0)&" "&YEAR(AY10) -> Q3 2025 | BB11: ="Q"&ROUNDUP(MONTH(BB10)/3,0)&" "&YEAR(BB10) -> Q4 2025 | BE11: ="Q"&ROUNDUP(MONTH(BE10)/3,0)&" "&YEAR(BE10) -> Q1 2026 | BH11: ="Q"&ROUNDUP(MONTH(BH10)/3,0)&" "&YEAR(BH10) -> Q2 2026 | BK11: ="Q"&ROUNDUP(MONTH(BK10)/3,0)&" "&YEAR(BK10) -> Q3 2026 | BN11: ="Q"&ROUNDUP(MONTH(BN10)/3,0)&" "&YEAR(BN10) -> Q4 2026
B13: Land Purchase | C13: 0 | D13: =D8 -> 44562 | E13: =EDATE(D13,C13) -> 44562 | F13: =B8 -> Project Start Date | G13: 0 | I13: =IF(AND(I$10>=$D13,I$10<=$E13),1,"") -> 1 | J13: =IF(AND(J$10>=$D13,J$10<=$E13),1,"") | K13: =IF(AND(K$10>=$D13,K$10<=$E13),1,"") | L13: =IF(AND(L$10>=$D13,L$10<=$E13),1,"") | M13: =IF(AND(M$10>=$D13,M$10<=$E13),1,"") | N13: =IF(AND(N$10>=$D13,N$10<=$E13),1,"") | O13: =IF(AND(O$10>=$D13,O$10<=$E13),1,"") | P13: =IF(AND(P$10>=$D13,P$10<=$E13),1,"") | ... BP13: =IF(AND(BP$10>=$D13,BP$10<=$E13),1,"")
B15: Pre-Development | C15: 12 | D15: =EDATE(E13,G15+1) -> 44593 | E15: =EDATE(D15,C15) -> 44958 | F15: =B13 -> Land Purchase | G15: 0 | I15: =IF(AND(I$10>=$D15,I$10<=$E15),1,"") | J15: =IF(AND(J$10>=$D15,J$10<=$E15),1,"") -> 1 | K15: =IF(AND(K$10>=$D15,K$10<=$E15),1,"") -> 1 | L15: =IF(AND(L$10>=$D15,L$10<=$E15),1,"") -> 1 | M15: =IF(AND(M$10>=$D15,M$10<=$E15),1,"") -> 1 | N15: =IF(AND(N$10>=$D15,N$10<=$E15),1,"") -> 1 | O15: =IF(AND(O$10>=$D15,O$10<=$E15),1,"") -> 1 | P15: =IF(AND(P$10>=$D15,P$10<=$E15),1,"") -> 1 | ... BP15: =IF(AND(BP$10>=$D15,BP$10<=$E15),1,"")
B17: Construction | C17: =Sensitivity!H20 -> 18 | D17: =EDATE(E15,G17+1) -> 44986 | E17: =EDATE(D17,C17) -> 45536 | F17: =B15 -> Pre-Development | G17: 0 | I17: =IF(AND(I$10>=$D17,I$10<=$E17),1,"") | J17: =IF(AND(J$10>=$D17,J$10<=$E17),1,"") | K17: =IF(AND(K$10>=$D17,K$10<=$E17),1,"") | L17: =IF(AND(L$10>=$D17,L$10<=$E17),1,"") | M17: =IF(AND(M$10>=$D17,M$10<=$E17),1,"") | N17: =IF(AND(N$10>=$D17,N$10<=$E17),1,"") | O17: =IF(AND(O$10>=$D17,O$10<=$E17),1,"") | P17: =IF(AND(P$10>=$D17,P$10<=$E17),1,"") | ... BP17: =IF(AND(BP$10>=$D17,BP$10<=$E17),1,"")
B19: Lease-up | C19: =Sensitivity!H25 -> 6 | D19: =EDATE(E17,G19+1) -> 45474 | E19: =EDATE(D19,C19) -> 45658 | F19: =B17 -> Construction | G19: -3 | I19: =IF(AND(I$10>=$D19,I$10<=$E19),1,"") | J19: =IF(AND(J$10>=$D19,J$10<=$E19),1,"") | K19: =IF(AND(K$10>=$D19,K$10<=$E19),1,"") | L19: =IF(AND(L$10>=$D19,L$10<=$E19),1,"") | M19: =IF(AND(M$10>=$D19,M$10<=$E19),1,"") | N19: =IF(AND(N$10>=$D19,N$10<=$E19),1,"") | O19: =IF(AND(O$10>=$D19,O$10<=$E19),1,"") | P19: =IF(AND(P$10>=$D19,P$10<=$E19),1,"") | ... BP19: =IF(AND(BP$10>=$D19,BP$10<=$E19),1,"")
I20: =IF(AND(I$10>=$D20,I$10<=$E20),1,"") | J20: =IF(AND(J$10>=$D20,J$10<=$E20),1,"") | K20: =IF(AND(K$10>=$D20,K$10<=$E20),1,"") | L20: =IF(AND(L$10>=$D20,L$10<=$E20),1,"") | M20: =IF(AND(M$10>=$D20,M$10<=$E20),1,"") | N20: =IF(AND(N$10>=$D20,N$10<=$E20),1,"") | O20: =IF(AND(O$10>=$D20,O$10<=$E20),1,"") | P20: =IF(AND(P$10>=$D20,P$10<=$E20),1,"") | ... BP20: =IF(AND(BP$10>=$D20,BP$10<=$E20),1,"")
B21: Stabilized | C21: 0 | D21: =EDATE(E19,G21+1) -> 45689 | E21: =EDATE(D21,C21) -> 45689 | F21: =B19 -> Lease-up | G21: 0 | I21: =IF(AND(I$10>=$D21,I$10<=$E21),1,"") | J21: =IF(AND(J$10>=$D21,J$10<=$E21),1,"") | K21: =IF(AND(K$10>=$D21,K$10<=$E21),1,"") | L21: =IF(AND(L$10>=$D21,L$10<=$E21),1,"") | M21: =IF(AND(M$10>=$D21,M$10<=$E21),1,"") | N21: =IF(AND(N$10>=$D21,N$10<=$E21),1,"") | O21: =IF(AND(O$10>=$D21,O$10<=$E21),1,"") | P21: =IF(AND(P$10>=$D21,P$10<=$E21),1,"") | ... BP21: =IF(AND(BP$10>=$D21,BP$10<=$E21),1,"")

Sheet Operating Revenue and Expenses
J1: ="Currently running: "&CHOOSE(Sensitivity!$E$8,Sensitivity!$B$11,Sensitivity!$B$12,Sensitivity!$B$13) -> Currently running: Base Case
B3: =Cover!A10 -> Apartment Development Model
B4: =Cover!A12 -> Suburban / Urban Location
B5: Operating Revenue and Expenses
B8: Parking
B9: Residential Stalls | E9: 105
B10: Visitor Stalls | E10: 10
B11: Extra Stalls | E11: 0
B12: Total | E12: =SUM(E9:E11) -> 115 | G12: Ratio | H12: =E12/F19 -> 1.15 | I12: stall per unit
B14: Revenue
B15: Residential | D15: Avg Sq Ft | E15: Total Area | F15: No. Units | G15: % Total | H15: Monthly $ | I15: Annual $ | J15: $/Sqft
B16: 1 Bed | D16: 720 | E16: =+D16*F16 -> 25200 | F16: =100*0.35 -> 35 | G16: =F16/$F$19 -> 0.35 | H16: 1990 | I16: =+H16*F16*12 -> 835800 | J16: =I16/E16/12 -> 2.7638889
B17: 2 Bed | D17: 935 | E17: =+D17*F17 -> 60775 | F17: =100*0.65 -> 65 | G17: =F17/$F$19 -> 0.65 | H17: 2400 | I17: =+H17*F17*12 -> 1872000 | J17: =I17/E17/12 -> 2.5668449
M18: Sensitize Rent | N18: =Sensitiv2!D6 -> 1
B19: Total | D19: =+E19/F19 -> 859.75 | E19: =SUM(E16:E18) -> 85975 | F19: =SUM(F16:F18) -> 100 | G19: =SUM(G16:G18) -> 1 | H19: =+I19/12/F19 -> 2256.5 | I19: =SUM(I16:I18)*N18 -> 2707800 | J19: =I19/E19/12 -> 2.6246002
B20: Average Res | E20: =(E16+E17+E18)/F19 -> 859.75 | H20: =(I16+I17)/(F16+F17)/12 -> 2256.5 | J20: =H20/E20 -> 2.6246002
B22: Other Income
B23: Storage Lockers | E23: 100 | G23: 40 | H23: =G23*E23 -> 4000 | I23: =H23*12 -> 48000
B24: Parking Revenue | E24: =E9 -> 105 | F24: x | G24: 120 | H24: =E24*G24 -> 12600 | I24: =H24*12 -> 151200
B25: Total Other Income | I25: =SUM(I23:I24) -> 199200
B27: Total Potential Gross Revenue (including parking & storage) | H27: =+I27/F19/12 -> 2422.5 | I27: =SUM(I19,I25) -> 2907000 | J27: =+I27/E19/12 -> 2.8176796
B28: Less: Vacancy and collection loss | F28: @ | G28: 0.025 | H28: =G28*H27 -> 60.5625 | I28: =G28*I27 -> 72675
B29: Effective Gross Income | H29: =+H27-H28 -> 2361.9375 | I29: =+I27-I28 -> 2834325
B31: Operating Expenses
G32: Per Unit | H32: % | I32: Annual $
B33: Property Taxes | G33: 3200 | H33: =G33/$G$43 -> 0.41824051 | I33: =G33*$F$19 -> 320000
B34: Insurance | G34: 225 | H34: =G34/$G$43 -> 0.029407536 | I34: =G34*$F$19*N34 -> 22500 | M34: Sensitize Op Cost | N34: =+Sensitiv2!D8 -> 1
B35: Repair & Maintenance | G35: 900 | H35: =G35/$G$43 -> 0.11763014 | I35: =G35*$F$19*N35 -> 90000 | M35: Sensitize Op Cost | N35: =+N34 -> 1
B36: Utilities | G36: 1500 | H36: =G36/$G$43 -> 0.19605024 | I36: =G36*$F$19*N36 -> 150000 | M36: Sensitize Op Cost | N36: =+N35 -> 1
B37: Hydro | G37: 0 | H37: =G37/$G$43 -> 0 | I37: =G37*$F$19 -> 0 | M37: Sensitize Op Cost | N37: =+N36 -> 1
B38: Sub-Metering Revenue Share | G38: =-8*12 -> -96 | H38: =G38/$G$43 -> -0.012547215 | I38: =G38*$F$19 -> -9600 | K38: $ 8/unit/month
B39: Staff (Ops & Maint) | G39: 800 | H39: =G39/$G$43 -> 0.10456013 | I39: =G39*$F$19*N39 -> 80000 | M39: Sensitize Op Cost | N39: =+N36 -> 1
B40: Marketing | G40: 250 | H40: =G40/$G$43 -> 0.03267504 | I40: =G40*$F$19*N40 -> 25000 | M40: Sensitize Op Cost | N40: =+N39 -> 1
B41: Internet | G41: 0 | H41: =G41/$G$43 -> 0 | I41: =G41*$F$19 -> 0
B42: Management Fee | D42: 0.03 | G42: =I42/F19 -> 872.1 | H42: =G42/$G$43 -> 0.11398361 | I42: =D42*I27 -> 87210
B43: Total Expenses | G43: =I43/F19 -> 7651.1 | H43: =SUM(H33:H42) -> 1 | I43: =SUM(I33:I42) -> 765110
B44: Operating Expenses Varience | I44: =Sensitivity!H30 -> 0
B45: Operating Expenses | I45: =(1+I44)*I43 -> 765110
B46: Operating Expenses/Revenue | I46: =I45/I29 -> 0.26994434
B48: Net Operating Income and Valuation
B50: NOI Today | D50: @ | E50: =+I27/E19/12 -> 2.8176796 | F50: per sqft average revenue | I50: =I29-I45 -> 2069215
B51: Valuation today | D51: @ | E51: =Sensitivity!H10 -> 0.04 | F51: Cap rate | G51: =I51/F19 -> 517303.75 | H51: Total | I51: =I50/E51 -> 51730375
B52: NOI at Stabilization | D52: @ | E52: =(MAX('Development Cash Flow'!I23:CZ23)*12)/E19/12 -> 2.9901441 | F52: per sqft average revenue | I52: =MAX('Development Cash Flow'!I26:CZ26)*12 -> 2195867.5
B53: Valuation @ Stabilization | D53: @ | E53: =Sensitivity!H10 -> 0.04 | F53: Cap rate | G53: =I53/F19 -> 548966.88 | H53: Total | I53: =I52/E53 -> 54896688

Sheet Development Costs
J1: ="Currently running: "&CHOOSE(Sensitivity!$E$8,Sensitivity!$B$11,Sensitivity!$B$12,Sensitivity!$B$13) -> Currently running: Base Case
B3: =Cover!A10 -> Apartment Development Model
B4: =Cover!A12 -> Suburban / Urban Location
B5: Development Costs
B9: Number of Units: | I9: ='Operating Revenue and Expenses'!F19 -> 100 | J9: Res only
B10: Net Rentable Area: | I10: ='Operating Revenue and Expenses'!E19 -> 85975 | J10: Res
H12: Total | I12: Per unit | J12: Per Sqft
B13: LAND | M13: Contingency Prov
B14: Land | H14: =5350000+300000 -> 5650000 | I14: =H14/$I$9 -> 56500 | J14: =H14/$I$10 -> 65.716778
B15: Closing / Other Cost | G15: 0.06 | H15: =G15*H14 -> 339000 | I15: =H15/$I$9 -> 3390 | J15: =H15/$I$10 -> 3.9430067
B16: Total Land Costs | G16: =H16/$H$89 -> 0.12175788 | H16: =SUM(H14:H15) -> 5989000 | I16: =SUM(I14:I15) -> 59890 | J16: =SUM(J14:J15) -> 69.659785
B18: CONSTRUCTION
B19: Construction hard cost | H19: =28500000*M19 -> 28500000 | I19: =H19/$I$9 -> 285000 | J19: =H19/$I$10 -> 331.49171 | L19: Sensitize | M19: =+Sensitiv2!D10 -> 1
B20: Offsite/Sitework Costs | H20: 0 | I20: =H20/$I$9 -> 0 | J20: =H20/$I$10 -> 0
B21: Construction contingency | G21: =+H21/H19 -> 0.052631579 | H21: =25000000*0.06 -> 1500000 | I21: =H21/$I$9 -> 15000 | J21: =H21/$I$10 -> 17.446932 | K21: =+H21/H19 -> 0.052631579 | L21: =+H19 -> 28500000 | M21: =+H21 -> 1500000 | N21: =+M21/L21 -> 0.052631579
B22: Total Construction Costs | G22: =H22/$H$89 -> 0.60990755 | H22: =SUM(H19:H21) -> 30000000 | I22: =SUM(I14:I21) -> 419780 | J22: =SUM(J19:J21) -> 348.93864
B24: PROFESSIONAL FEES
B25: Architect | H25: =1200000*0.4 -> 480000 | I25: =H25/$I$9 -> 4800 | J25: =H25/$I$10 -> 5.5830183
B26: Landscape architect | H26: =80000*0.4 -> 32000 | I26: =H26/$I$9 -> 320 | J26: =H26/$I$10 -> 0.37220122
B27: Structural engineer | H27: =400000*0.4 -> 160000 | I27: =H27/$I$9 -> 1600 | J27: =H27/$I$10 -> 1.8610061
B28: Civil engineer | H28: 75000 | I28: =H28/$I$9 -> 750 | J28: =H28/$I$10 -> 0.87234661
B29: Mechanical & Electrical engineer | H29: =220000*0.4 -> 88000 | I29: =H29/$I$9 -> 880 | J29: =H29/$I$10 -> 1.0235534
B30: Geotechnical engineer | H30: 35000 | I30: =H30/$I$9 -> 350 | J30: =H30/$I$10 -> 0.40709509
B31: Site Servicing Engineer | H31: 0 | I31: =H31/$I$9 -> 0 | J31: =H31/$I$10 -> 0
B32: Survey | H32: 20000 | I32: =H32/$I$9 -> 200 | J32: =H32/$I$10 -> 0.23262576
B33: Env Phase 3 Cost | H33: 0 | I33: =H33/$I$9 -> 0 | J33: =H33/$I$10 -> 0
I34: =H34/$I$9 -> 0 | J34: =H34/$I$10 -> 0
B35: Others | H35: 400000 | I35: =H35/$I$9 -> 4000 | J35: =H35/$I$10 -> 4.6525153
B36: Environmental consultant | H36: 0 | I36: =H36/$I$9 -> 0 | J36: =H36/$I$10 -> 0
B37: Interior design | H37: 0 | I37: =H37/$I$9 -> 0 | J37: =H37/$I$10 -> 0
B38: Traffic consultant | H38: 0 | I38: =H38/$I$9 -> 0 | J38: =H38/$I$10 -> 0
B39: Disbursements | H39: 0 | I39: =H39/$I$9 -> 0 | J39: =H39/$I$10 -> 0
B40: Professional fee contingency | G40: 0.1 | H40: =SUM(H25:H39)*G40 -> 129000 | I40: =H40/$I$9 -> 1290 | J40: =H40/$I$10 -> 1.5004362
B41: Total Professional Fees | G41: =H41/$H$89 -> 0.028848627 | H41: =SUM(H25:H40) -> 1419000 | I41: =SUM(I25:I40) -> 14190 | J41: =SUM(J25:J40) -> 16.504798 | K41: =+H41/H22 -> 0.0473 | L41: =+H41-H40 -> 1290000 | M41: =+H40 -> 129000 | N41: =+M41/L41 -> 0.1
B43: DEVELOPMENT MANAGEMENT
B45: Development Management Fee | H45: =3300000*0.38 -> 1254000 | I45: =H45/$I$9 -> 12540 | J45: =H45/$I$10 -> 14.585635
B46: Total Development Management Fee | G46: =H46/$H$89 -> 0.025494136 | H46: =SUM(H44:H45) -> 1254000 | I46: =SUM(I44:I45) -> 12540 | J46: =SUM(J44:J45) -> 14.585635
B48: PERMITS AND APPROVALS
B49: Development Permit | H49: 0 | I49: =H49/$I$9 -> 0 | J49: =H49/$I$10 -> 0
B50: Rezoning | H50: 0 | I50: =H50/$I$9 -> 0 | J50: =H50/$I$10 -> 0
B51: Building permit | H51: =250000*0.4 -> 100000 | I51: =H51/$I$9 -> 1000 | J51: =H51/$I$10 -> 1.1631288
B52: City Development charges | H52: =30000*100 -> 3000000 | I52: =H52/$I$9 -> 30000 | J52: =H52/$I$10 -> 34.893864
B53: Park Dedication Fee | H53: 0 | I53: =H53/$I$9 -> 0 | J53: =H53/$I$10 -> 0
B54: Other Development Charges | H54: 0 | I54: =H54/$I$9 -> 0 | J54: =H54/$I$10 -> 0
B55: Sub-Meter Installation Fee Credit | F55: 600 | H55: =-F55*I9 -> -60000 | I55: =H55/$I$9 -> -600 | J55: =H55/$I$10 -> -0.69787729
B56: Utilities Connection | H56: 0 | I56: =H56/$I$9 -> 0 | J56: =H56/$I$10 -> 0
B57: Land titles | H57: 0 | I57: =H57/$I$9 -> 0 | J57: =H57/$I$10 -> 0
B58: Permit and approval contingency | G58: 0.1 | H58: =SUM(H49:H57)*G58 -> 304000 | I58: =H58/$I$9 -> 3040 | J58: =H58/$I$10 -> 3.5359116
B59: Total Permit and Approvals | G59: =H59/$H$89 -> 0.067984362 | H59: =SUM(H49:H58) -> 3344000 | I59: =SUM(I49:I58) -> 33440 | J59: =SUM(J49:J58) -> 38.895028 | L59: =+H59-H58 -> 3040000 | M59: =+H58 -> 304000 | N59: =+M59/L59 -> 0.1
B61: MARKETINGAND LEASING
B62: Tenant Inducement | H62: 0 | I62: =H62/I9 -> 0 | J62: =H62/I10 -> 0
B63: Commissions & Incentive | H63: ='Operating Revenue and Expenses'!I27/12*1.5 -> 363375 | I63: =H63/I9 -> 3633.75 | J63: =H63/I10 -> 4.2265193
B64: Sales Staff | H64: 0 | I64: =H64/I9 -> 0 | J64: =H64/I10 -> 0
B65: Marketing | H65: ='Operating Revenue and Expenses'!I27/12*1.5 -> 363375 | I65: =H65/$I$9 -> 3633.75 | J65: =H65/$I$10 -> 4.2265193
B66: Total Marketing and Leasing | G66: =H66/$H$89 -> 0.01477501 | H66: =SUM(H62:H65) -> 726750 | I66: =SUM(I62:I65) -> 7267.5 | J66: =SUM(J62:J65) -> 8.4530387
B68: FINANCING AND INTEREST
B69: Appraisal | H69: 20000 | I69: =H69/$I$9 -> 200 | J69: =H69/$I$10 -> 0.23262576
B70: Legal fees | H70: 75000 | I70: =H70/$I$9 -> 750 | J70: =H70/$I$10 -> 0.87234661
B71: Property Taxes During Construction | F71: Tax rate | H71: 0 | I71: =H71/$I$9 -> 0 | J71: =H71/$I$10 -> 0
B72: Quantity Surveyor | H72: 0 | I72: =H72/$I$9 -> 0 | J72: =H72/$I$10 -> 0
B73: Insurance | H73: 0 | I73: =H73/$I$9 -> 0 | J73: =H73/$I$10 -> 0
B74: LC and Bonding | H74: 0 | I74: =H74/$I$9 -> 0 | J74: =H74/$I$10 -> 0
B75: Loan fees | H75: 480000 | I75: =H75/$I$9 -> 4800 | J75: =H75/$I$10 -> 5.5830183
B76: Bank's Legal / Other charges | H76: 0 | I76: =H76/$I$9 -> 0 | J76: =H76/$I$10 -> 0
B77: HST | H77: =HST!F18 -> 3820151.5 | I77: =H77/$I$9 -> 38201.515 | J77: =H77/$I$10 -> 44.433283
B78: Construction Loan Interest | F78: @ | G78: =Sensitivity!H15 -> 0.046666667 | H78: =-'Development Cash Flow'!E94 -> 2639932.5 | I78: =H78/$I$9 -> 26399.325 | J78: =H78/$I$10 -> 30.705816
B79: Financing contingency | G79: =+H79/(H80-H79) -> 0.071072356 | H79: =2000000*0.25 -> 500000 | I79: =H79/$I$9 -> 5000 | J79: =H79/$I$10 -> 5.8156441
B80: Total Financing and Interest Costs | G80: =H80/$H$89 -> 0.15319016 | H80: =SUM(H69:H79) -> 7535084 | I80: =SUM(I69:I79) -> 75350.84 | J80: =SUM(J69:J79) -> 87.642734 | L80: =+H80-H79 -> 7035084 | M80: =+H79 -> 500000 | N80: =+M80/L80 -> 0.071072356
B82: OPERATING INCOME DURING LEASE-UP
B83: Security Deposit | H83: =-'Development Cash Flow'!E22 -> -252757.01 | I83: =H83/$I$9 -> -2527.5701 | J83: =H83/$I$10 -> -2.9398896
B84: Revenue | H84: =-'Development Cash Flow'!E23 -> -1162250.2 | I84: =H84/$I$9 -> -11622.502 | J84: =H84/$I$10 -> -13.518467
B85: Vacancy Provision | H85: =-'Development Cash Flow'!E24 -> 29056.254 | I85: =H85/$I$9 -> 290.56254 | J85: =H85/$I$10 -> 0.33796166
B86: Operating Expenses | H86: =-'Development Cash Flow'!E25 -> 305899.28 | I86: =H86/$I$9 -> 3058.9928 | J86: =H86/$I$10 -> 3.5580027
B87: Total Income During Lease-up incl Sec Deposit | H87: =SUM(H83:H86) -> -1080051.6 | I87: =SUM(I83:I86) -> -10800.516 | J87: =SUM(J83:J86) -> -12.562392
B89: TOTAL DEVELOPMENT COSTS | H89: =SUM(H16,H22,H41,H59,H46,H66,H80,H87) -> 49187782 | I89: =H89/I9 -> 491877.82 | J89: =H89/I10 -> 572.11727 | L89: =+H89-H16 -> 43198782 | M89: =SUM(M21:M87) -> 2433000 | N89: =+M89/L89 -> 0.056321032

Sheet Sensitivity
J1: ="Currently running: "&CHOOSE(Sensitivity!$E$8,Sensitivity!$B$11,Sensitivity!$B$12,Sensitivity!$B$13) -> Currently running: Base Case
B3: =Cover!A10 -> Apartment Development Model
B4: =Cover!A12 -> Suburban / Urban Location
B5: Scenarios
D8: Select Scenario: | E8: 1
B9: SENSITIZED ASSUMPTIONS
B10: Capitalization Rate | H10: =CHOOSE($E$8,H11,H12,H13) -> 0.04
B11: Base Case | H11: 0.04
B12: Best Case | H12: 0.0375
B13: Worst Case | H13: 0.0425
B15: Construction Loan Interest Rate | H15: =CHOOSE($E$8,H16,H17,H18) -> 0.046666667
B16: Base Case | H16: =+'Debt Stack'!C20 -> 0.046666667
B17: Best Case | H17: =+H16-0.0025 -> 0.044166667
B18: Worst Case | H18: =+H16+0.0025 -> 0.049166667
B20: Construction Period (Months) | H20: =CHOOSE($E$8,H21,H22,H23) -> 18
B21: Base Case | H21: 18
B22: Best Case | H22: =H21-3 -> 15
B23: Worst Case | H23: =H21+3 -> 21
B25: Lease-up Period (Months) | H25: =CHOOSE($E$8,H26,H27,H28) -> 6
B26: Base Case | H26: 6
B27: Best Case | H27: =H26-2 -> 4
B28: Worst Case | H28: =H26+2 -> 8
B30: Operating Expense Varience | H30: =CHOOSE($E$8,H31,H32,H33) -> 0
B31: Base Case | H31: 0
B32: Best Case | H32: -0.05
B33: Worst Case | H33: 0.05

Sheet Debt Stack
H1: ='Executive Summary'!J1 -> Currently running: Base Case
B4: ='Executive Summary'!B3:I3 -> Apartment Development Model
B5: ='Executive Summary'!B4:I4 -> Suburban / Urban Location
B8: DEBT STACK
B11: Blended Construction Interest Rate Calucator
D12: Int Rate | E12: Component Int
B13: Total Equity | C13: =+'Development Cash Flow'!D109 -> 0.10142553
B14: Total Debt | C14: =1-C13 -> 0.89857447
B16: Total Debt | C16: 0.9
B17: Mezannine Debt | C17: 0.15 | D17: 0.08 | E17: =+C17*D17 -> 0.012
B18: Regular Bank Debt | C18: =+C16-C17 -> 0.75 | D18: 0.04 | E18: =+C18*D18 -> 0.03
B19: Total Debt | C19: =C17+C18 -> 0.9 | E19: =+E17+E18 -> 0.042
B20: Blended Construction Interest Rate | C20: =+E19/C19 -> 0.046666667
B25: Note 1: Double check the Total Debt Ratio from DCF page. | E25: ='Development Cash Flow'!D108 -> 0.89857447 | F25: =E25-C16 -> -0.0014255329 | G25: < Diff
B26: 2: Client to confirm if Mezannine Debt, otherwise take 0%

Sheet Development Cash Flow
B2: =Cover!A10 -> Apartment Development Model
B3: =Cover!A12 -> Suburban / Urban Location
B5: Cash Flow | I5: =YEAR(I7) -> 2022 | J5: =YEAR(J7) -> 2022 | K5: =YEAR(K7) -> 2022 | L5: =YEAR(L7) -> 2022 | M5: =YEAR(M7) -> 2022 | N5: =YEAR(N7) -> 2022 | O5: =YEAR(O7) -> 2022 | P5: =YEAR(P7) -> 2022 | ... CZ5: =YEAR(CZ7) -> 2029
I6: 1 | J6: 2 | K6: 3 | L6: 4 | M6: 5 | N6: 6 | O6: 7 | P6: 8 | Q6: 9 | R6: 10 | S6: 11 | T6: 12 | U6: 13 | V6: 14 | W6: 15 | X6: 16 | Y6: 17 | Z6: 18 | AA6: 19 | AB6: 20 | AC6: 21 | AD6: 22 | AE6: 23 | AF6: 24 | AG6: 25 | AH6: 26 | AI6: 27 | AJ6: 28 | AK6: 29 | AL6: 30 | AM6: 31 | AN6: 32 | AO6: 33 | AP6: 34 | AQ6: 35 | AR6: 36 | AS6: 37 | AT6: 38 | AU6: 39 | AV6: 40 | AW6: 41 | AX6: 42 | AY6: 43 | AZ6: 44 | BA6: 45 | BB6: 46 | BC6: 47 | BD6: 48 | BE6: 49 | BF6: 50 | BG6: 51 | BH6: 52 | BI6: 53 | BJ6: 54 | BK6: 55 | BL6: 56 | BM6: 57 | BN6: 58 | BO6: 59 | BP6: 60 | BQ6: 61 | BR6: 62 | BS6: 63 | BT6: 64 | BU6: 65 | BV6: 66 | BW6: 67 | BX6: 68 | BY6: 69 | BZ6: 70 | CA6: 71 | CB6: 72 | CC6: 73 | CD6: 74 | CE6: 75 | CF6: 76 | CG6: 77 | CH6: 78 | CI6: 79 | CJ6: 80 | CK6: 81 | CL6: 82 | CM6: 83 | CN6: 84 | CO6: 85 | CP6: 86 | CQ6: 87 | CR6: 88 | CS6: 89 | CT6: 90 | CU6: 91 | CV6: 92 | CW6: 93 | CX6: 94 | CY6: 95 | CZ6: 96
B7: Items | C7: Budget | D7: Variance | E7: Total Cashflow | F7: Start | G7: End | H7: Months | I7: =Schedule!D8 -> 44562 | J7: =EDATE(I7,1) -> 44593 | K7: =EDATE(J7,1) -> 44621 | L7: =EDATE(K7,1) -> 44652 | M7: =EDATE(L7,1) -> 44682 | N7: =EDATE(M7,1) -> 44713 | O7: =EDATE(N7,1) -> 44743 | P7: =EDATE(O7,1) -> 44774 | Q7: =EDATE(P7,1) -> 44805 | ... CZ7: =EDATE(CY7,1) -> 47453
B8: LEASE-UP SCHEDULE
B9: Number of Units Completed | C9: ='Development Costs'!$I$9 -> 100 | D9: =ROUND(C9-E9,0) -> 0 | E9: =SUM(I9:CZ9) -> 100 | I9: =IF(I7=Schedule!$E$17,'Development Cash Flow'!$C$9,0) -> 0 | J9: =IF(J7=Schedule!$E$17,'Development Cash Flow'!$C$9,0) -> 0 | K9: =IF(K7=Schedule!$E$17,'Development Cash Flow'!$C$9,0) -> 0 | L9: =IF(L7=Schedule!$E$17,'Development Cash Flow'!$C$9,0) -> 0 | M9: =IF(M7=Schedule!$E$17,'Development Cash Flow'!$C$9,0) -> 0 | N9: =IF(N7=Schedule!$E$17,'Development Cash Flow'!$C$9,0) -> 0 | O9: =IF(O7=Schedule!$E$17,'Development Cash Flow'!$C$9,0) -> 0 | P9: =IF(P7=Schedule!$E$17,'Development Cash Flow'!$C$9,0) -> 0 | ... CZ9: =IF(CZ7=Schedule!$E$17,'Development Cash Flow'!$C$9,0) -> 0
B10: Cumulative Units Complete | C10: ='Development Costs'!$I$9 -> 100 | D10: =ROUND(C10-E10,0) -> 0 | E10: =MAX(I10:CZ10) -> 100 | I10: =I9 -> 0 | J10: =I10+J9 -> 0 | K10: =J10+K9 -> 0 | L10: =K10+L9 -> 0 | M10: =L10+M9 -> 0 | N10: =M10+N9 -> 0 | O10: =N10+O9 -> 0 | P10: =O10+P9 -> 0 | Q10: =P10+Q9 -> 0 | ... CZ10: =CY10+CZ9 -> 100
B11: Percentage Completed | E11: =MAX(I11:CZ11) -> 1 | I11: =I10/'Development Costs'!$I$9 -> 0 | J11: =J10/'Development Costs'!$I$9 -> 0 | K11: =K10/'Development Costs'!$I$9 -> 0 | L11: =L10/'Development Costs'!$I$9 -> 0 | M11: =M10/'Development Costs'!$I$9 -> 0 | N11: =N10/'Development Costs'!$I$9 -> 0 | O11: =O10/'Development Costs'!$I$9 -> 0 | P11: =P10/'Development Costs'!$I$9 -> 0 | ... CZ11: =CZ10/'Development Costs'!$I$9 -> 1
B12: New Units Leased | C12: ='Development Costs'!$I$9 -> 100 | D12: =ROUND(C12-E12,0) -> 0 | E12: =SUM(I12:CZ12) -> 100 | F12: =Schedule!D19 -> 45474 | G12: =Schedule!E19 -> 45658 | H12: =DATEDIF(F12,G12,"m")+1 -> 7 | I12: =IF(AND(I$7<=$G12,I$7>=$F12,$H12<>0,$H12<>""),$C12/$H12,0) -> 0 | J12: =IF(AND(J$7<=$G12,J$7>=$F12,$H12<>0,$H12<>""),$C12/$H12,0) -> 0 | K12: =IF(AND(K$7<=$G12,K$7>=$F12,$H12<>0,$H12<>""),$C12/$H12,0) -> 0 | L12: =IF(AND(L$7<=$G12,L$7>=$F12,$H12<>0,$H12<>""),$C12/$H12,0) -> 0 | M12: =IF(AND(M$7<=$G12,M$7>=$F12,$H12<>0,$H12<>""),$C12/$H12,0) -> 0 | N12: =IF(AND(N$7<=$G12,N$7>=$F12,$H12<>0,$H12<>""),$C12/$H12,0) -> 0 | O12: =IF(AND(O$7<=$G12,O$7>=$F12,$H12<>0,$H12<>""),$C12/$H12,0) -> 0 | P12: =IF(AND(P$7<=$G12,P$7>=$F12,$H12<>0,$H12<>""),$C12/$H12,0) -> 0 | ... CZ12: =IF(AND(CZ$7<=$G12,CZ$7>=$F12,$H12<>0,$H12<>""),$C12/$H12,0) -> 0
B13: Cumulative Units Leased | C13: ='Development Costs'!$I$9 -> 100 | D13: =ROUND(C13-E13,0) -> 0 | E13: =MAX(I13:CZ13) -> 100 | I13: =I12 -> 0 | J13: =I13+J12 -> 0 | K13: =J13+K12 -> 0 | L13: =K13+L12 -> 0 | M13: =L13+M12 -> 0 | N13: =M13+N12 -> 0 | O13: =N13+O12 -> 0 | P13: =O13+P12 -> 0 | Q13: =P13+Q12 -> 0 | ... CZ13: =CY13+CZ12 -> 100
B14: Percentage Leased | E14: =MAX(I14:CZ14) -> 1 | I14: =I13/'Development Costs'!$I$9 -> 0 | J14: =J13/'Development Costs'!$I$9 -> 0 | K14: =K13/'Development Costs'!$I$9 -> 0 | L14: =L13/'Development Costs'!$I$9 -> 0 | M14: =M13/'Development Costs'!$I$9 -> 0 | N14: =N13/'Development Costs'!$I$9 -> 0 | O14: =O13/'Development Costs'!$I$9 -> 0 | P14: =P13/'Development Costs'!$I$9 -> 0 | ... CZ14: =CZ13/'Development Costs'!$I$9 -> 1
B15: Units Occupied | C15: ='Development Costs'!$I$9 -> 100 | D15: =ROUND(C15-E15,0) -> 0 | E15: =SUM(I15:CZ15) -> 100 | I15: 0 | J15: =IF(I$7>=$F$9,MIN(J10,J13)-I16,0) -> 0 | K15: =IF(J$7>=$F$9,MIN(K10,K13)-J16,0) -> 0 | L15: =IF(K$7>=$F$9,MIN(L10,L13)-K16,0) -> 0 | M15: =IF(L$7>=$F$9,MIN(M10,M13)-L16,0) -> 0 | N15: =IF(M$7>=$F$9,MIN(N10,N13)-M16,0) -> 0 | O15: =IF(N$7>=$F$9,MIN(O10,O13)-N16,0) -> 0 | P15: =IF(O$7>=$F$9,MIN(P10,P13)-O16,0) -> 0 | Q15: =IF(P$7>=$F$9,MIN(Q10,Q13)-P16,0) -> 0 | ... CZ15: =IF(CY$7>=$F$9,MIN(CZ10,CZ13)-CY16,0) -> 0
B16: Cumulative Units Occupied | C16: ='Development Costs'!$I$9 -> 100 | D16: =ROUND(C16-E16,0) -> 0 | E16: =MAX(I16:CZ16) -> 100 | I16: =I15 -> 0 | J16: =I16+J15 -> 0 | K16: =J16+K15 -> 0 | L16: =K16+L15 -> 0 | M16: =L16+M15 -> 0 | N16: =M16+N15 -> 0 | O16: =N16+O15 -> 0 | P16: =O16+P15 -> 0 | Q16: =P16+Q15 -> 0 | ... CZ16: =CY16+CZ15 -> 100
B17: Percentage Occupied | E17: =MAX(I17:CZ17) -> 1 | I17: =I16/'Development Costs'!$I$9 -> 0 | J17: =J16/'Development Costs'!$I$9 -> 0 | K17: =K16/'Development Costs'!$I$9 -> 0 | L17: =L16/'Development Costs'!$I$9 -> 0 | M17: =M16/'Development Costs'!$I$9 -> 0 | N17: =N16/'Development Costs'!$I$9 -> 0 | O17: =O16/'Development Costs'!$I$9 -> 0 | P17: =P16/'Development Costs'!$I$9 -> 0 | ... CZ17: =CZ16/'Development Costs'!$I$9 -> 1
B19: OPERATING INCOME
B20: Revenue Inflation Factor | I20: =(1+'10-Yr Cash Flow IRR'!$E$9)^(YEAR(I7)-YEAR(Schedule!$D$8)) -> 1 | J20: =(1+'10-Yr Cash Flow IRR'!$E$9)^(YEAR(J7)-YEAR(Schedule!$D$8)) -> 1 | K20: =(1+'10-Yr Cash Flow IRR'!$E$9)^(YEAR(K7)-YEAR(Schedule!$D$8)) -> 1 | L20: =(1+'10-Yr Cash Flow IRR'!$E$9)^(YEAR(L7)-YEAR(Schedule!$D$8)) -> 1 | M20: =(1+'10-Yr Cash Flow IRR'!$E$9)^(YEAR(M7)-YEAR(Schedule!$D$8)) -> 1 | N20: =(1+'10-Yr Cash Flow IRR'!$E$9)^(YEAR(N7)-YEAR(Schedule!$D$8)) -> 1 | O20: =(1+'10-Yr Cash Flow IRR'!$E$9)^(YEAR(O7)-YEAR(Schedule!$D$8)) -> 1 | P20: =(1+'10-Yr Cash Flow IRR'!$E$9)^(YEAR(P7)-YEAR(Schedule!$D$8)) -> 1 | ... CZ20: =(1+'10-Yr Cash Flow IRR'!$E$9)^(YEAR(CZ7)-YEAR(Schedule!$D$8)) -> 1.1486857
B21: Cost Inflation Factor | I21: =(1+'10-Yr Cash Flow IRR'!$E$10)^(YEAR(I7)-YEAR(Schedule!$D$8)) -> 1 | J21: =(1+'10-Yr Cash Flow IRR'!$E$9)^(YEAR(J7)-YEAR(Schedule!$D$8)) -> 1 | K21: =(1+'10-Yr Cash Flow IRR'!$E$9)^(YEAR(K7)-YEAR(Schedule!$D$8)) -> 1 | L21: =(1+'10-Yr Cash Flow IRR'!$E$9)^(YEAR(L7)-YEAR(Schedule!$D$8)) -> 1 | M21: =(1+'10-Yr Cash Flow IRR'!$E$9)^(YEAR(M7)-YEAR(Schedule!$D$8)) -> 1 | N21: =(1+'10-Yr Cash Flow IRR'!$E$9)^(YEAR(N7)-YEAR(Schedule!$D$8)) -> 1 | O21: =(1+'10-Yr Cash Flow IRR'!$E$9)^(YEAR(O7)-YEAR(Schedule!$D$8)) -> 1 | P21: =(1+'10-Yr Cash Flow IRR'!$E$9)^(YEAR(P7)-YEAR(Schedule!$D$8)) -> 1 | Q21: =(1+'10-Yr Cash Flow IRR'!$E$9)^(YEAR(Q7)-YEAR(Schedule!$D$8)) -> 1 | ... CZ21: =(1+'10-Yr Cash Flow IRR'!$E$9)^(YEAR(CZ7)-YEAR(Schedule!$D$8)) -> 1.1486857
B22: Security Deposit | C22: =-'Development Costs'!H83 -> 252757.01 | E22: =SUM(I22:CZ22) -> 252757.01 | I22: =+'Operating Revenue and Expenses'!$I$27/'Operating Revenue and Expenses'!$F$19/12*I12*I20 -> 0 | J22: =+'Operating Revenue and Expenses'!$I$27/'Operating Revenue and Expenses'!$F$19/12*J12*J20 -> 0 | K22: =+'Operating Revenue and Expenses'!$I$27/'Operating Revenue and Expenses'!$F$19/12*K12*K20 -> 0 | L22: =+'Operating Revenue and Expenses'!$I$27/'Operating Revenue and Expenses'!$F$19/12*L12*L20 -> 0 | M22: =+'Operating Revenue and Expenses'!$I$27/'Operating Revenue and Expenses'!$F$19/12*M12*M20 -> 0 | N22: =+'Operating Revenue and Expenses'!$I$27/'Operating Revenue and Expenses'!$F$19/12*N12*N20 -> 0 | O22: =+'Operating Revenue and Expenses'!$I$27/'Operating Revenue and Expenses'!$F$19/12*O12*O20 -> 0 | P22: =+'Operating Revenue and Expenses'!$I$27/'Operating Revenue and Expenses'!$F$19/12*P12*P20 -> 0 | ... CZ22: =+'Operating Revenue and Expenses'!$I$27/'Operating Revenue and Expenses'!$F$19/12*CZ12*CZ20 -> 0
B23: Revenue | C23: =-'Development Costs'!H84 -> 1162250.2 | D23: =ROUND(C23-E23,0) -> 0 | E23: =SUM(I23:CZ23) -> 1162250.2 | I23: =IF(I111="PUD",'Operating Revenue and Expenses'!$I$27/12*I$17*I$20,0) -> 0 | J23: =IF(J111="PUD",'Operating Revenue and Expenses'!$I$27/12*J$17*J$20,0) -> 0 | K23: =IF(K111="PUD",'Operating Revenue and Expenses'!$I$27/12*K$17*K$20,0) -> 0 | L23: =IF(L111="PUD",'Operating Revenue and Expenses'!$I$27/12*L$17*L$20,0) -> 0 | M23: =IF(M111="PUD",'Operating Revenue and Expenses'!$I$27/12*M$17*M$20,0) -> 0 | N23: =IF(N111="PUD",'Operating Revenue and Expenses'!$I$27/12*N$17*N$20,0) -> 0 | O23: =IF(O111="PUD",'Operating Revenue and Expenses'!$I$27/12*O$17*O$20,0) -> 0 | P23: =IF(P111="PUD",'Operating Revenue and Expenses'!$I$27/12*P$17*P$20,0) -> 0 | ... CZ23: =IF(CZ111="PUD",'Operating Revenue and Expenses'!$I$27/12*CZ$17*CZ$20,0) -> 0
B24: Vacancy Provision | C24: =-'Development Costs'!H85 -> -29056.254 | D24: =ROUND(C24-E24,0) -> 0 | E24: =SUM(I24:CZ24) -> -29056.254 | I24: =IF(I111="PUD",-'Operating Revenue and Expenses'!$I$28/12*I$17*I$20,0) -> 0 | J24: =IF(J111="PUD",-'Operating Revenue and Expenses'!$I$28/12*J$17*J$20,0) -> 0 | K24: =IF(K111="PUD",-'Operating Revenue and Expenses'!$I$28/12*K$17*K$20,0) -> 0 | L24: =IF(L111="PUD",-'Operating Revenue and Expenses'!$I$28/12*L$17*L$20,0) -> 0 | M24: =IF(M111="PUD",-'Operating Revenue and Expenses'!$I$28/12*M$17*M$20,0) -> 0 | N24: =IF(N111="PUD",-'Operating Revenue and Expenses'!$I$28/12*N$17*N$20,0) -> 0 | O24: =IF(O111="PUD",-'Operating Revenue and Expenses'!$I$28/12*O$17*O$20,0) -> 0 | P24: =IF(P111="PUD",-'Operating Revenue and Expenses'!$I$28/12*P$17*P$20,0) -> 0 | ... CZ24: =IF(CZ111="PUD",-'Operating Revenue and Expenses'!$I$28/12*CZ$17*CZ$20,0) -> 0
B25: Operating Expenses | C25: =-'Development Costs'!H86 -> -305899.28 | D25: =ROUND(C25-E25,0) -> 0 | E25: =SUM(I25:CZ25) -> -305899.28 | I25: =IF(I111="PUD",-'Operating Revenue and Expenses'!$I$45/12*I$17*I$21,0) -> 0 | J25: =IF(J111="PUD",-'Operating Revenue and Expenses'!$I$45/12*J$17*J$21,0) -> 0 | K25: =IF(K111="PUD",-'Operating Revenue and Expenses'!$I$45/12*K$17*K$21,0) -> 0 | L25: =IF(L111="PUD",-'Operating Revenue and Expenses'!$I$45/12*L$17*L$21,0) -> 0 | M25: =IF(M111="PUD",-'Operating Revenue and Expenses'!$I$45/12*M$17*M$21,0) -> 0 | N25: =IF(N111="PUD",-'Operating Revenue and Expenses'!$I$45/12*N$17*N$21,0) -> 0 | O25: =IF(O111="PUD",-'Operating Revenue and Expenses'!$I$45/12*O$17*O$21,0) -> 0 | P25: =IF(P111="PUD",-'Operating Revenue and Expenses'!$I$45/12*P$17*P$21,0) -> 0 | ... CZ25: =IF(CZ111="PUD",-'Operating Revenue and Expenses'!$I$45/12*CZ$17*CZ$21,0) -> 0
B26: NOI | C26: =SUM(C23:C25) -> 827294.62 | E26: =SUM(I26:CZ26)+E21 -> 827294.62 | I26: =SUM(I23:I25) -> 0 | J26: =SUM(J23:J25) -> 0 | K26: =SUM(K23:K25) -> 0 | L26: =SUM(L23:L25) -> 0 | M26: =SUM(M23:M25) -> 0 | N26: =SUM(N23:N25) -> 0 | O26: =SUM(O23:O25) -> 0 | P26: =SUM(P23:P25) -> 0 | ... CZ26: =SUM(CZ23:CZ25) -> 0
B28: LAND
B29: ='Development Costs'!B14 -> Land | C29: =-'Development Costs'!H14 -> -5650000 | D29: =ROUND(C29-E29,0) -> 0 | E29: =SUM(I29:CZ29) -> -5650000 | F29: =Schedule!D13 -> 44562 | G29: =Schedule!E13 -> 44562 | H29: =DATEDIF(F29,G29,"m")+1 -> 1 | I29: =IF(AND(I$7<=$G29,I$7>=$F29,$H29<>0,$H29<>""),$C29/$H29,0) -> -5650000 | J29: =IF(AND(J$7<=$G29,J$7>=$F29,$H29<>0,$H29<>""),$C29/$H29,0) -> 0 | K29: =IF(AND(K$7<=$G29,K$7>=$F29,$H29<>0,$H29<>""),$C29/$H29,0) -> 0 | L29: =IF(AND(L$7<=$G29,L$7>=$F29,$H29<>0,$H29<>""),$C29/$H29,0) -> 0 | M29: =IF(AND(M$7<=$G29,M$7>=$F29,$H29<>0,$H29<>""),$C29/$H29,0) -> 0 | N29: =IF(AND(N$7<=$G29,N$7>=$F29,$H29<>0,$H29<>""),$C29/$H29,0) -> 0 | O29: =IF(AND(O$7<=$G29,O$7>=$F29,$H29<>0,$H29<>""),$C29/$H29,0) -> 0 | P29: =IF(AND(P$7<=$G29,P$7>=$F29,$H29<>0,$H29<>""),$C29/$H29,0) -> 0 | ... CZ29: =IF(AND(CZ$7<=$G29,CZ$7>=$F29,$H29<>0,$H29<>""),$C29/$H29,0) -> 0
B30: ='Development Costs'!B15 -> Closing / Other Cost | C30: =-'Development Costs'!H15 -> -339000 | D30: =ROUND(C30-E30,0) -> 0 | E30: =SUM(I30:CZ30) -> -339000 | F30: =F29 -> 44562 | G30: =G29 -> 44562 | H30: =DATEDIF(F30,G30,"m")+1 -> 1 | I30: =IF(AND(I$7<=$G30,I$7>=$F30,$H30<>0,$H30<>""),$C30/$H30,0) -> -339000 | J30: =IF(AND(J$7<=$G30,J$7>=$F30,$H30<>0,$H30<>""),$C30/$H30,0) -> 0 | K30: =IF(AND(K$7<=$G30,K$7>=$F30,$H30<>0,$H30<>""),$C30/$H30,0) -> 0 | L30: =IF(AND(L$7<=$G30,L$7>=$F30,$H30<>0,$H30<>""),$C30/$H30,0) -> 0 | M30: =IF(AND(M$7<=$G30,M$7>=$F30,$H30<>0,$H30<>""),$C30/$H30,0) -> 0 | N30: =IF(AND(N$7<=$G30,N$7>=$F30,$H30<>0,$H30<>""),$C30/$H30,0) -> 0 | O30: =IF(AND(O$7<=$G30,O$7>=$F30,$H30<>0,$H30<>""),$C30/$H30,0) -> 0 | P30: =IF(AND(P$7<=$G30,P$7>=$F30,$H30<>0,$H30<>""),$C30/$H30,0) -> 0 | ... CZ30: =IF(AND(CZ$7<=$G30,CZ$7>=$F30,$H30<>0,$H30<>""),$C30/$H30,0) -> 0
B31: ='Development Costs'!B16 -> Total Land Costs | C31: =-'Development Costs'!H16 -> -5989000 | D31: =C31-E31 -> 0 | E31: =SUM(I31:CZ31) -> -5989000 | I31: =SUM(I29:I30) -> -5989000 | J31: =SUM(J29:J30) -> 0 | K31: =SUM(K29:K30) -> 0 | L31: =SUM(L29:L30) -> 0 | M31: =SUM(M29:M30) -> 0 | N31: =SUM(N29:N30) -> 0 | O31: =SUM(O29:O30) -> 0 | P31: =SUM(P29:P30) -> 0 | ... CZ31: =SUM(CZ29:CZ30) -> 0
B33: CONSTRUCTION
A34: Steep | B34: S Curve Option:
A35: Moderately Steep | B35: 2 | C35: S-curve StDev: | D35: =H36/B35 -> 9.5
A36: Moderate | B36: S Curve Distribution | C36: 1 | D36: =C36-E36 -> 0 | E36: =SUM(I36:CZ36) -> 1 | F36: =F41 -> 44986 | G36: =G41 -> 45536 | H36: =DATEDIF(F36,G36,"m")+1 -> 19 | I36: =IF(AND(I$7>=$F36,I$7<=$G36),(_xlfn.NORM.DIST((YEAR(I$7)-YEAR($F36))*12+MONTH(I$7)-MONTH($F36)+1,$H36/2,$D35,TRUE)-_xlfn.NORM.DIST((YEAR(I$7)-YEAR($F36))*12+MONTH(I$7)-MONTH($F36),$H36/2,$D35,TRUE))/(1-2*_xlfn.NORM.DIST(0,$H36/2,$D35,TRUE))*$C36,0) -> 0 | J36: =IF(AND(J$7>=$F36,J$7<=$G36),(_xlfn.NORM.DIST((YEAR(J$7)-YEAR($F36))*12+MONTH(J$7)-MONTH($F36)+1,$H36/2,$D35,TRUE)-_xlfn.NORM.DIST((YEAR(J$7)-YEAR($F36))*12+MONTH(J$7)-MONTH($F36),$H36/2,$D35,TRUE))/(1-2*_xlfn.NORM.DIST(0,$H36/2,$D35,TRUE))*$C36,0) -> 0 | K36: =IF(AND(K$7>=$F36,K$7<=$G36),(_xlfn.NORM.DIST((YEAR(K$7)-YEAR($F36))*12+MONTH(K$7)-MONTH($F36)+1,$H36/2,$D35,TRUE)-_xlfn.NORM.DIST((YEAR(K$7)-YEAR($F36))*12+MONTH(K$7)-MONTH($F36),$H36/2,$D35,TRUE))/(1-2*_xlfn.NORM.DIST(0,$H36/2,$D35,TRUE))*$C36,0) -> 0 | L36: =IF(AND(L$7>=$F36,L$7<=$G36),(_xlfn.NORM.DIST((YEAR(L$7)-YEAR($F36))*12+MONTH(L$7)-MONTH($F36)+1,$H36/2,$D35,TRUE)-_xlfn.NORM.DIST((YEAR(L$7)-YEAR($F36))*12+MONTH(L$7)-MONTH($F36),$H36/2,$D35,TRUE))/(1-2*_xlfn.NORM.DIST(0,$H36/2,$D35,TRUE))*$C36,0) -> 0 | M36: =IF(AND(M$7>=$F36,M$7<=$G36),(_xlfn.NORM.DIST((YEAR(M$7)-YEAR($F36))*12+MONTH(M$7)-MONTH($F36)+1,$H36/2,$D35,TRUE)-_xlfn.NORM.DIST((YEAR(M$7)-YEAR($F36))*12+MONTH(M$7)-MONTH($F36),$H36/2,$D35,TRUE))/(1-2*_xlfn.NORM.DIST(0,$H36/2,$D35,TRUE))*$C36,0) -> 0 | N36: =IF(AND(N$7>=$F36,N$7<=$G36),(_xlfn.NORM.DIST((YEAR(N$7)-YEAR($F36))*12+MONTH(N$7)-MONTH($F36)+1,$H36/2,$D35,TRUE)-_xlfn.NORM.DIST((YEAR(N$7)-YEAR($F36))*12+MONTH(N$7)-MONTH($F36),$H36/2,$D35,TRUE))/(1-2*_xlfn.NORM.DIST(0,$H36/2,$D35,TRUE))*$C36,0) -> 0 | O36: =IF(AND(O$7>=$F36,O$7<=$G36),(_xlfn.NORM.DIST((YEAR(O$7)-YEAR($F36))*12+MONTH(O$7)-MONTH($F36)+1,$H36/2,$D35,TRUE)-_xlfn.NORM.DIST((YEAR(O$7)-YEAR($F36))*12+MONTH(O$7)-MONTH($F36),$H36/2,$D35,TRUE))/(1-2*_xlfn.NORM.DIST(0,$H36/2,$D35,TRUE))*$C36,0) -> 0 | P36: =IF(AND(P$7>=$F36,P$7<=$G36),(_xlfn.NORM.DIST((YEAR(P$7)-YEAR($F36))*12+MONTH(P$7)-MONTH($F36)+1,$H36/2,$D35,TRUE)-_xlfn.NORM.DIST((YEAR(P$7)-YEAR($F36))*12+MONTH(P$7)-MONTH($F36),$H36/2,$D35,TRUE))/(1-2*_xlfn.NORM.DIST(0,$H36/2,$D35,TRUE))*$C36,0) -> 0 | ... CZ36: =IF(AND(CZ$7>=$F36,CZ$7<=$G36),(_xlfn.NORM.DIST((YEAR(CZ$7)-YEAR($F36))*12+MONTH(CZ$7)-MONTH($F36)+1,$H36/2,$D35,TRUE)-_xlfn.NORM.DIST((YEAR(CZ$7)-YEAR($F36))*12+MONTH(CZ$7)-MONTH($F36),$H36/2,$D35,TRUE))/(1-2*_xlfn.NORM.DIST(0,$H36/2,$D35,TRUE))*$C36,0) -> 0
A37: Moderately Flat | B37: Even Distribution | C37: 1 | D37: =C37-E37 -> 0 | E37: =SUM(I37:CZ37) -> 1 | F37: =F41 -> 44986 | G37: =G41 -> 45536 | H37: =DATEDIF(F37,G37,"m")+1 -> 19 | I37: =IF(AND(I$7<=$G37,I$7>=$F37,$H37<>0,$H37<>""),$C37/$H37,0) -> 0 | J37: =IF(AND(J$7<=$G37,J$7>=$F37,$H37<>0,$H37<>""),$C37/$H37,0) -> 0 | K37: =IF(AND(K$7<=$G37,K$7>=$F37,$H37<>0,$H37<>""),$C37/$H37,0) -> 0 | L37: =IF(AND(L$7<=$G37,L$7>=$F37,$H37<>0,$H37<>""),$C37/$H37,0) -> 0 | M37: =IF(AND(M$7<=$G37,M$7>=$F37,$H37<>0,$H37<>""),$C37/$H37,0) -> 0 | N37: =IF(AND(N$7<=$G37,N$7>=$F37,$H37<>0,$H37<>""),$C37/$H37,0) -> 0 | O37: =IF(AND(O$7<=$G37,O$7>=$F37,$H37<>0,$H37<>""),$C37/$H37,0) -> 0 | P37: =IF(AND(P$7<=$G37,P$7>=$F37,$H37<>0,$H37<>""),$C37/$H37,0) -> 0 | ... CZ37: =IF(AND(CZ$7<=$G37,CZ$7>=$F37,$H37<>0,$H37<>""),$C37/$H37,0) -> 0
B38: Construction Cost Option:
B39: 1
B40: Construction % Completion | I40: =CHOOSE($B$39,I36,I37) -> 0 | J40: =CHOOSE($B$39,J36,J37)+I40 -> 0 | K40: =CHOOSE($B$39,K36,K37)+J40 -> 0 | L40: =CHOOSE($B$39,L36,L37)+K40 -> 0 | M40: =CHOOSE($B$39,M36,M37)+L40 -> 0 | N40: =CHOOSE($B$39,N36,N37)+M40 -> 0 | O40: =CHOOSE($B$39,O36,O37)+N40 -> 0 | P40: =CHOOSE($B$39,P36,P37)+O40 -> 0 | Q40: =CHOOSE($B$39,Q36,Q37)+P40 -> 0 | ... CZ40: =CHOOSE($B$39,CZ36,CZ37)+CY40 -> 1
B41: ='Development Costs'!B19 -> Construction hard cost | C41: =-'Development Costs'!H19 -> -28500000 | D41: =ROUND(C41-E41,0) -> 0 | E41: =SUM(I41:CZ41) -> -28500000 | F41: =Schedule!D17 -> 44986 | G41: =Schedule!E17 -> 45536 | H41: =DATEDIF(F41,G41,"m")+1 -> 19 | I41: =I40*$C$41 -> 0 | J41: =(J40-I40)*$C$41 -> 0 | K41: =(K40-J40)*$C$41 -> 0 | L41: =(L40-K40)*$C$41 -> 0 | M41: =(M40-L40)*$C$41 -> 0 | N41: =(N40-M40)*$C$41 -> 0 | O41: =(O40-N40)*$C$41 -> 0 | P41: =(P40-O40)*$C$41 -> 0 | Q41: =(Q40-P40)*$C$41 -> 0 | ... CZ41: =(CZ40-CY40)*$C$41 -> 0
B42: ='Development Costs'!B20 -> Offsite/Sitework Costs | C42: =-'Development Costs'!H20 -> 0 | D42: =ROUND(C42-E42,0) -> 0 | E42: =SUM(I42:CZ42) -> 0 | F42: =F41 -> 44986 | G42: =G41 -> 45536 | H42: =DATEDIF(F42,G42,"m")+1 -> 19 | I42: =IF(AND(I$7<=$G42,I$7>=$F42,$H42<>0,$H42<>""),$C42/$H42,0) -> 0 | J42: =IF(AND(J$7<=$G42,J$7>=$F42,$H42<>0,$H42<>""),$C42/$H42,0) -> 0 | K42: =IF(AND(K$7<=$G42,K$7>=$F42,$H42<>0,$H42<>""),$C42/$H42,0) -> 0 | L42: =IF(AND(L$7<=$G42,L$7>=$F42,$H42<>0,$H42<>""),$C42/$H42,0) -> 0 | M42: =IF(AND(M$7<=$G42,M$7>=$F42,$H42<>0,$H42<>""),$C42/$H42,0) -> 0 | N42: =IF(AND(N$7<=$G42,N$7>=$F42,$H42<>0,$H42<>""),$C42/$H42,0) -> 0 | O42: =IF(AND(O$7<=$G42,O$7>=$F42,$H42<>0,$H42<>""),$C42/$H42,0) -> 0 | P42: =IF(AND(P$7<=$G42,P$7>=$F42,$H42<>0,$H42<>""),$C42/$H42,0) -> 0 | ... CZ42: =IF(AND(CZ$7<=$G42,CZ$7>=$F42,$H42<>0,$H42<>""),$C42/$H42,0) -> 0
B43: ='Development Costs'!B21 -> Construction contingency | C43: =-'Development Costs'!H21 -> -1500000 | D43: =ROUND(C43-E43,0) -> 0 | E43: =SUM(I43:CZ43) -> -1500000 | F43: =F41 -> 44986 | G43: =G41 -> 45536 | H43: =DATEDIF(F43,G43,"m")+1 -> 19 | I43: =IF(AND(I$7<=$G43,I$7>=$F43,$H43<>0,$H43<>""),$C43/$H43,0) -> 0 | J43: =IF(AND(J$7<=$G43,J$7>=$F43,$H43<>0,$H43<>""),$C43/$H43,0) -> 0 | K43: =IF(AND(K$7<=$G43,K$7>=$F43,$H43<>0,$H43<>""),$C43/$H43,0) -> 0 | L43: =IF(AND(L$7<=$G43,L$7>=$F43,$H43<>0,$H43<>""),$C43/$H43,0) -> 0 | M43: =IF(AND(M$7<=$G43,M$7>=$F43,$H43<>0,$H43<>""),$C43/$H43,0) -> 0 | N43: =IF(AND(N$7<=$G43,N$7>=$F43,$H43<>0,$H43<>""),$C43/$H43,0) -> 0 | O43: =IF(AND(O$7<=$G43,O$7>=$F43,$H43<>0,$H43<>""),$C43/$H43,0) -> 0 | P43: =IF(AND(P$7<=$G43,P$7>=$F43,$H43<>0,$H43<>""),$C43/$H43,0) -> 0 | ... CZ43: =IF(AND(CZ$7<=$G43,CZ$7>=$F43,$H43<>0,$H43<>""),$C43/$H43,0) -> 0
B44: ='Development Costs'!B22 -> Total Construction Costs | C44: =-'Development Costs'!H22 -> -30000000 | D44: =C44-E44 -> 0 | E44: =SUM(I44:CZ44) -> -30000000 | I44: =SUM(I41:I43) -> 0 | J44: =SUM(J41:J43) -> 0 | K44: =SUM(K41:K43) -> 0 | L44: =SUM(L41:L43) -> 0 | M44: =SUM(M41:M43) -> 0 | N44: =SUM(N41:N43) -> 0 | O44: =SUM(O41:O43) -> 0 | P44: =SUM(P41:P43) -> 0 | ... CZ44: =SUM(CZ41:CZ43) -> 0
B46: PROFESSIONAL FEES
B47: ='Development Costs'!B25 -> Architect | C47: =-'Development Costs'!H25 -> -480000 | D47: =ROUND(C47-E47,0) -> 0 | E47: =SUM(I47:CZ47) -> -480000 | F47: =Schedule!D15 -> 44593 | G47: =Schedule!E17 -> 45536 | H47: =DATEDIF(F47,G47,"m")+1 -> 32 | I47: =IF(AND(I$7<=$G47,I$7>=$F47,$H47<>0,$H47<>""),$C47/$H47,0) -> 0 | J47: =IF(AND(J$7<=$G47,J$7>=$F47,$H47<>0,$H47<>""),$C47/$H47,0) -> -15000 | K47: =IF(AND(K$7<=$G47,K$7>=$F47,$H47<>0,$H47<>""),$C47/$H47,0) -> -15000 | L47: =IF(AND(L$7<=$G47,L$7>=$F47,$H47<>0,$H47<>""),$C47/$H47,0) -> -15000 | M47: =IF(AND(M$7<=$G47,M$7>=$F47,$H47<>0,$H47<>""),$C47/$H47,0) -> -15000 | N47: =IF(AND(N$7<=$G47,N$7>=$F47,$H47<>0,$H47<>""),$C47/$H47,0) -> -15000 | O47: =IF(AND(O$7<=$G47,O$7>=$F47,$H47<>0,$H47<>""),$C47/$H47,0) -> -15000 | P47: =IF(AND(P$7<=$G47,P$7>=$F47,$H47<>0,$H47<>""),$C47/$H47,0) -> -15000 | ... CZ47: =IF(AND(CZ$7<=$G47,CZ$7>=$F47,$H47<>0,$H47<>""),$C47/$H47,0) -> 0
B48: ='Development Costs'!B26 -> Landscape architect | C48: =-'Development Costs'!H26 -> -32000 | D48: =ROUND(C48-E48,0) -> 0 | E48: =SUM(I48:CZ48) -> -32000 | F48: =F$47 -> 44593 | G48: =G$47 -> 45536 | H48: =DATEDIF(F48,G48,"m")+1 -> 32 | I48: =IF(AND(I$7<=$G48,I$7>=$F48,$H48<>0,$H48<>""),$C48/$H48,0) -> 0 | J48: =IF(AND(J$7<=$G48,J$7>=$F48,$H48<>0,$H48<>""),$C48/$H48,0) -> -1000 | K48: =IF(AND(K$7<=$G48,K$7>=$F48,$H48<>0,$H48<>""),$C48/$H48,0) -> -1000 | L48: =IF(AND(L$7<=$G48,L$7>=$F48,$H48<>0,$H48<>""),$C48/$H48,0) -> -1000 | M48: =IF(AND(M$7<=$G48,M$7>=$F48,$H48<>0,$H48<>""),$C48/$H48,0) -> -1000 | N48: =IF(AND(N$7<=$G48,N$7>=$F48,$H48<>0,$H48<>""),$C48/$H48,0) -> -1000 | O48: =IF(AND(O$7<=$G48,O$7>=$F48,$H48<>0,$H48<>""),$C48/$H48,0) -> -1000 | P48: =IF(AND(P$7<=$G48,P$7>=$F48,$H48<>0,$H48<>""),$C48/$H48,0) -> -1000 | ... CZ48: =IF(AND(CZ$7<=$G48,CZ$7>=$F48,$H48<>0,$H48<>""),$C48/$H48,0) -> 0
B49: ='Development Costs'!B27 -> Structural engineer | C49: =-'Development Costs'!H27 -> -160000 | D49: =ROUND(C49-E49,0) -> 0 | E49: =SUM(I49:CZ49) -> -160000 | F49: =F$47 -> 44593 | G49: =G$47 -> 45536 | H49: =DATEDIF(F49,G49,"m")+1 -> 32 | I49: =IF(AND(I$7<=$G49,I$7>=$F49,$H49<>0,$H49<>""),$C49/$H49,0) -> 0 | J49: =IF(AND(J$7<=$G49,J$7>=$F49,$H49<>0,$H49<>""),$C49/$H49,0) -> -5000 | K49: =IF(AND(K$7<=$G49,K$7>=$F49,$H49<>0,$H49<>""),$C49/$H49,0) -> -5000 | L49: =IF(AND(L$7<=$G49,L$7>=$F49,$H49<>0,$H49<>""),$C49/$H49,0) -> -5000 | M49: =IF(AND(M$7<=$G49,M$7>=$F49,$H49<>0,$H49<>""),$C49/$H49,0) -> -5000 | N49: =IF(AND(N$7<=$G49,N$7>=$F49,$H49<>0,$H49<>""),$C49/$H49,0) -> -5000 | O49: =IF(AND(O$7<=$G49,O$7>=$F49,$H49<>0,$H49<>""),$C49/$H49,0) -> -5000 | P49: =IF(AND(P$7<=$G49,P$7>=$F49,$H49<>0,$H49<>""),$C49/$H49,0) -> -5000 | ... CZ49: =IF(AND(CZ$7<=$G49,CZ$7>=$F49,$H49<>0,$H49<>""),$C49/$H49,0) -> 0
B50: ='Development Costs'!B28 -> Civil engineer | C50: =-'Development Costs'!H28 -> -75000 | D50: =ROUND(C50-E50,0) -> 0 | E50: =SUM(I50:CZ50) -> -75000 | F50: =F$47 -> 44593 | G50: =G$47 -> 45536 | H50: =DATEDIF(F50,G50,"m")+1 -> 32 | I50: =IF(AND(I$7<=$G50,I$7>=$F50,$H50<>0,$H50<>""),$C50/$H50,0) -> 0 | J50: =IF(AND(J$7<=$G50,J$7>=$F50,$H50<>0,$H50<>""),$C50/$H50,0) -> -2343.75 | K50: =IF(AND(K$7<=$G50,K$7>=$F50,$H50<>0,$H50<>""),$C50/$H50,0) -> -2343.75 | L50: =IF(AND(L$7<=$G50,L$7>=$F50,$H50<>0,$H50<>""),$C50/$H50,0) -> -2343.75 | M50: =IF(AND(M$7<=$G50,M$7>=$F50,$H50<>0,$H50<>""),$C50/$H50,0) -> -2343.75 | N50: =IF(AND(N$7<=$G50,N$7>=$F50,$H50<>0,$H50<>""),$C50/$H50,0) -> -2343.75 | O50: =IF(AND(O$7<=$G50,O$7>=$F50,$H50<>0,$H50<>""),$C50/$H50,0) -> -2343.75 | P50: =IF(AND(P$7<=$G50,P$7>=$F50,$H50<>0,$H50<>""),$C50/$H50,0) -> -2343.75 | ... CZ50: =IF(AND(CZ$7<=$G50,CZ$7>=$F50,$H50<>0,$H50<>""),$C50/$H50,0) -> 0
B51: ='Development Costs'!B29 -> Mechanical & Electrical engineer | C51: =-'Development Costs'!H29 -> -88000 | D51: =ROUND(C51-E51,0) -> 0 | E51: =SUM(I51:CZ51) -> -88000 | F51: =F$47 -> 44593 | G51: =G$47 -> 45536 | H51: =DATEDIF(F51,G51,"m")+1 -> 32 | I51: =IF(AND(I$7<=$G51,I$7>=$F51,$H51<>0,$H51<>""),$C51/$H51,0) -> 0 | J51: =IF(AND(J$7<=$G51,J$7>=$F51,$H51<>0,$H51<>""),$C51/$H51,0) -> -2750 | K51: =IF(AND(K$7<=$G51,K$7>=$F51,$H51<>0,$H51<>""),$C51/$H51,0) -> -2750 | L51: =IF(AND(L$7<=$G51,L$7>=$F51,$H51<>0,$H51<>""),$C51/$H51,0) -> -2750 | M51: =IF(AND(M$7<=$G51,M$7>=$F51,$H51<>0,$H51<>""),$C51/$H51,0) -> -2750 | N51: =IF(AND(N$7<=$G51,N$7>=$F51,$H51<>0,$H51<>""),$C51/$H51,0) -> -2750 | O51: =IF(AND(O$7<=$G51,O$7>=$F51,$H51<>0,$H51<>""),$C51/$H51,0) -> -2750 | P51: =IF(AND(P$7<=$G51,P$7>=$F51,$H51<>0,$H51<>""),$C51/$H51,0) -> -2750 | ... CZ51: =IF(AND(CZ$7<=$G51,CZ$7>=$F51,$H51<>0,$H51<>""),$C51/$H51,0) -> 0
B52: ='Development Costs'!B30 -> Geotechnical engineer | C52: =-'Development Costs'!H30 -> -35000 | D52: =ROUND(C52-E52,0) -> 0 | E52: =SUM(I52:CZ52) -> -35000 | F52: =F$47 -> 44593 | G52: =G$47 -> 45536 | H52: =DATEDIF(F52,G52,"m")+1 -> 32 | I52: =IF(AND(I$7<=$G52,I$7>=$F52,$H52<>0,$H52<>""),$C52/$H52,0) -> 0 | J52: =IF(AND(J$7<=$G52,J$7>=$F52,$H52<>0,$H52<>""),$C52/$H52,0) -> -1093.75 | K52: =IF(AND(K$7<=$G52,K$7>=$F52,$H52<>0,$H52<>""),$C52/$H52,0) -> -1093.75 | L52: =IF(AND(L$7<=$G52,L$7>=$F52,$H52<>0,$H52<>""),$C52/$H52,0) -> -1093.75 | M52: =IF(AND(M$7<=$G52,M$7>=$F52,$H52<>0,$H52<>""),$C52/$H52,0) -> -1093.75 | N52: =IF(AND(N$7<=$G52,N$7>=$F52,$H52<>0,$H52<>""),$C52/$H52,0) -> -1093.75 | O52: =IF(AND(O$7<=$G52,O$7>=$F52,$H52<>0,$H52<>""),$C52/$H52,0) -> -1093.75 | P52: =IF(AND(P$7<=$G52,P$7>=$F52,$H52<>0,$H52<>""),$C52/$H52,0) -> -1093.75 | ... CZ52: =IF(AND(CZ$7<=$G52,CZ$7>=$F52,$H52<>0,$H52<>""),$C52/$H52,0) -> 0
B53: ='Development Costs'!B31 -> Site Servicing Engineer | C53: =-'Development Costs'!H31 -> 0 | D53: =ROUND(C53-E53,0) -> 0 | E53: =SUM(I53:CZ53) -> 0 | F53: =F$47 -> 44593 | G53: =G$47 -> 45536 | H53: =DATEDIF(F53,G53,"m")+1 -> 32 | I53: =IF(AND(I$7<=$G53,I$7>=$F53,$H53<>0,$H53<>""),$C53/$H53,0) -> 0 | J53: =IF(AND(J$7<=$G53,J$7>=$F53,$H53<>0,$H53<>""),$C53/$H53,0) -> 0 | K53: =IF(AND(K$7<=$G53,K$7>=$F53,$H53<>0,$H53<>""),$C53/$H53,0) -> 0 | L53: =IF(AND(L$7<=$G53,L$7>=$F53,$H53<>0,$H53<>""),$C53/$H53,0) -> 0 | M53: =IF(AND(M$7<=$G53,M$7>=$F53,$H53<>0,$H53<>""),$C53/$H53,0) -> 0 | N53: =IF(AND(N$7<=$G53,N$7>=$F53,$H53<>0,$H53<>""),$C53/$H53,0) -> 0 | O53: =IF(AND(O$7<=$G53,O$7>=$F53,$H53<>0,$H53<>""),$C53/$H53,0) -> 0 | P53: =IF(AND(P$7<=$G53,P$7>=$F53,$H53<>0,$H53<>""),$C53/$H53,0) -> 0 | ... CZ53: =IF(AND(CZ$7<=$G53,CZ$7>=$F53,$H53<>0,$H53<>""),$C53/$H53,0) -> 0
B54: ='Development Costs'!B32 -> Survey | C54: =-'Development Costs'!H32 -> -20000 | D54: =ROUND(C54-E54,0) -> 0 | E54: =SUM(I54:CZ54) -> -20000 | F54: =F$47 -> 44593 | G54: =G$47 -> 45536 | H54: =DATEDIF(F54,G54,"m")+1 -> 32 | I54: =IF(AND(I$7<=$G54,I$7>=$F54,$H54<>0,$H54<>""),$C54/$H54,0) -> 0 | J54: =IF(AND(J$7<=$G54,J$7>=$F54,$H54<>0,$H54<>""),$C54/$H54,0) -> -625 | K54: =IF(AND(K$7<=$G54,K$7>=$F54,$H54<>0,$H54<>""),$C54/$H54,0) -> -625 | L54: =IF(AND(L$7<=$G54,L$7>=$F54,$H54<>0,$H54<>""),$C54/$H54,0) -> -625 | M54: =IF(AND(M$7<=$G54,M$7>=$F54,$H54<>0,$H54<>""),$C54/$H54,0) -> -625 | N54: =IF(AND(N$7<=$G54,N$7>=$F54,$H54<>0,$H54<>""),$C54/$H54,0) -> -625 | O54: =IF(AND(O$7<=$G54,O$7>=$F54,$H54<>0,$H54<>""),$C54/$H54,0) -> -625 | P54: =IF(AND(P$7<=$G54,P$7>=$F54,$H54<>0,$H54<>""),$C54/$H54,0) -> -625 | ... CZ54: =IF(AND(CZ$7<=$G54,CZ$7>=$F54,$H54<>0,$H54<>""),$C54/$H54,0) -> 0
B55: ='Development Costs'!B33 -> Env Phase 3 Cost | C55: =-'Development Costs'!H33 -> 0 | D55: =ROUND(C55-E55,0) -> 0 | E55: =SUM(I55:CZ55) -> 0 | F55: =F$47 -> 44593 | G55: =G$47 -> 45536 | H55: =DATEDIF(F55,G55,"m")+1 -> 32 | I55: =IF(AND(I$7<=$G55,I$7>=$F55,$H55<>0,$H55<>""),$C55/$H55,0) -> 0 | J55: =IF(AND(J$7<=$G55,J$7>=$F55,$H55<>0,$H55<>""),$C55/$H55,0) -> 0 | K55: =IF(AND(K$7<=$G55,K$7>=$F55,$H55<>0,$H55<>""),$C55/$H55,0) -> 0 | L55: =IF(AND(L$7<=$G55,L$7>=$F55,$H55<>0,$H55<>""),$C55/$H55,0) -> 0 | M55: =IF(AND(M$7<=$G55,M$7>=$F55,$H55<>0,$H55<>""),$C55/$H55,0) -> 0 | N55: =IF(AND(N$7<=$G55,N$7>=$F55,$H55<>0,$H55<>""),$C55/$H55,0) -> 0 | O55: =IF(AND(O$7<=$G55,O$7>=$F55,$H55<>0,$H55<>""),$C55/$H55,0) -> 0 | P55: =IF(AND(P$7<=$G55,P$7>=$F55,$H55<>0,$H55<>""),$C55/$H55,0) -> 0 | ... CZ55: =IF(AND(CZ$7<=$G55,CZ$7>=$F55,$H55<>0,$H55<>""),$C55/$H55,0) -> 0
B56: Other | C56: =-'Development Costs'!H35 -> -400000 | D56: =ROUND(C56-E56,0) -> 0 | E56: =SUM(I56:CZ56) -> -400000 | F56: =F$47 -> 44593 | G56: =G$47 -> 45536 | H56: =DATEDIF(F56,G56,"m")+1 -> 32 | I56: =IF(AND(I$7<=$G56,I$7>=$F56,$H56<>0,$H56<>""),$C56/$H56,0) -> 0 | J56: =IF(AND(J$7<=$G56,J$7>=$F56,$H56<>0,$H56<>""),$C56/$H56,0) -> -12500 | K56: =IF(AND(K$7<=$G56,K$7>=$F56,$H56<>0,$H56<>""),$C56/$H56,0) -> -12500 | L56: =IF(AND(L$7<=$G56,L$7>=$F56,$H56<>0,$H56<>""),$C56/$H56,0) -> -12500 | M56: =IF(AND(M$7<=$G56,M$7>=$F56,$H56<>0,$H56<>""),$C56/$H56,0) -> -12500 | N56: =IF(AND(N$7<=$G56,N$7>=$F56,$H56<>0,$H56<>""),$C56/$H56,0) -> -12500 | O56: =IF(AND(O$7<=$G56,O$7>=$F56,$H56<>0,$H56<>""),$C56/$H56,0) -> -12500 | P56: =IF(AND(P$7<=$G56,P$7>=$F56,$H56<>0,$H56<>""),$C56/$H56,0) -> -12500 | ... CZ56: =IF(AND(CZ$7<=$G56,CZ$7>=$F56,$H56<>0,$H56<>""),$C56/$H56,0) -> 0
B57: ='Development Costs'!B36 -> Environmental consultant | C57: =-'Development Costs'!H36 -> 0 | D57: =ROUND(C57-E57,0) -> 0 | E57: =SUM(I57:CZ57) -> 0 | F57: =F$47 -> 44593 | G57: =G$47 -> 45536 | H57: =DATEDIF(F57,G57,"m")+1 -> 32 | I57: =IF(AND(I$7<=$G57,I$7>=$F57,$H57<>0,$H57<>""),$C57/$H57,0) -> 0 | J57: =IF(AND(J$7<=$G57,J$7>=$F57,$H57<>0,$H57<>""),$C57/$H57,0) -> 0 | K57: =IF(AND(K$7<=$G57,K$7>=$F57,$H57<>0,$H57<>""),$C57/$H57,0) -> 0 | L57: =IF(AND(L$7<=$G57,L$7>=$F57,$H57<>0,$H57<>""),$C57/$H57,0) -> 0 | M57: =IF(AND(M$7<=$G57,M$7>=$F57,$H57<>0,$H57<>""),$C57/$H57,0) -> 0 | N57: =IF(AND(N$7<=$G57,N$7>=$F57,$H57<>0,$H57<>""),$C57/$H57,0) -> 0 | O57: =IF(AND(O$7<=$G57,O$7>=$F57,$H57<>0,$H57<>""),$C57/$H57,0) -> 0 | P57: =IF(AND(P$7<=$G57,P$7>=$F57,$H57<>0,$H57<>""),$C57/$H57,0) -> 0 | ... CZ57: =IF(AND(CZ$7<=$G57,CZ$7>=$F57,$H57<>0,$H57<>""),$C57/$H57,0) -> 0
B58: ='Development Costs'!B37 -> Interior design | C58: =-'Development Costs'!H37 -> 0 | D58: =ROUND(C58-E58,0) -> 0 | E58: =SUM(I58:CZ58) -> 0 | F58: =F$47 -> 44593 | G58: =G$47 -> 45536 | H58: =DATEDIF(F58,G58,"m")+1 -> 32 | I58: =IF(AND(I$7<=$G58,I$7>=$F58,$H58<>0,$H58<>""),$C58/$H58,0) -> 0 | J58: =IF(AND(J$7<=$G58,J$7>=$F58,$H58<>0,$H58<>""),$C58/$H58,0) -> 0 | K58: =IF(AND(K$7<=$G58,K$7>=$F58,$H58<>0,$H58<>""),$C58/$H58,0) -> 0 | L58: =IF(AND(L$7<=$G58,L$7>=$F58,$H58<>0,$H58<>""),$C58/$H58,0) -> 0 | M58: =IF(AND(M$7<=$G58,M$7>=$F58,$H58<>0,$H58<>""),$C58/$H58,0) -> 0 | N58: =IF(AND(N$7<=$G58,N$7>=$F58,$H58<>0,$H58<>""),$C58/$H58,0) -> 0 | O58: =IF(AND(O$7<=$G58,O$7>=$F58,$H58<>0,$H58<>""),$C58/$H58,0) -> 0 | P58: =IF(AND(P$7<=$G58,P$7>=$F58,$H58<>0,$H58<>""),$C58/$H58,0) -> 0 | ... CZ58: =IF(AND(CZ$7<=$G58,CZ$7>=$F58,$H58<>0,$H58<>""),$C58/$H58,0) -> 0
B59: ='Development Costs'!B38 -> Traffic consultant | C59: =-'Development Costs'!H38 -> 0 | D59: =ROUND(C59-E59,0) -> 0 | E59: =SUM(I59:CZ59) -> 0 | F59: =F$47 -> 44593 | G59: =G$47 -> 45536 | H59: =DATEDIF(F59,G59,"m")+1 -> 32 | I59: =IF(AND(I$7<=$G59,I$7>=$F59,$H59<>0,$H59<>""),$C59/$H59,0) -> 0 | J59: =IF(AND(J$7<=$G59,J$7>=$F59,$H59<>0,$H59<>""),$C59/$H59,0) -> 0 | K59: =IF(AND(K$7<=$G59,K$7>=$F59,$H59<>0,$H59<>""),$C59/$H59,0) -> 0 | L59: =IF(AND(L$7<=$G59,L$7>=$F59,$H59<>0,$H59<>""),$C59/$H59,0) -> 0 | M59: =IF(AND(M$7<=$G59,M$7>=$F59,$H59<>0,$H59<>""),$C59/$H59,0) -> 0 | N59: =IF(AND(N$7<=$G59,N$7>=$F59,$H59<>0,$H59<>""),$C59/$H59,0) -> 0 | O59: =IF(AND(O$7<=$G59,O$7>=$F59,$H59<>0,$H59<>""),$C59/$H59,0) -> 0 | P59: =IF(AND(P$7<=$G59,P$7>=$F59,$H59<>0,$H59<>""),$C59/$H59,0) -> 0 | ... CZ59: =IF(AND(CZ$7<=$G59,CZ$7>=$F59,$H59<>0,$H59<>""),$C59/$H59,0) -> 0
B60: ='Development Costs'!B39 -> Disbursements | C60: =-'Development Costs'!H39 -> 0 | D60: =ROUND(C60-E60,0) -> 0 | E60: =SUM(I60:CZ60) -> 0 | F60: =F$47 -> 44593 | G60: =G$47 -> 45536 | H60: =DATEDIF(F60,G60,"m")+1 -> 32 | I60: =IF(AND(I$7<=$G60,I$7>=$F60,$H60<>0,$H60<>""),$C60/$H60,0) -> 0 | J60: =IF(AND(J$7<=$G60,J$7>=$F60,$H60<>0,$H60<>""),$C60/$H60,0) -> 0 | K60: =IF(AND(K$7<=$G60,K$7>=$F60,$H60<>0,$H60<>""),$C60/$H60,0) -> 0 | L60: =IF(AND(L$7<=$G60,L$7>=$F60,$H60<>0,$H60<>""),$C60/$H60,0) -> 0 | M60: =IF(AND(M$7<=$G60,M$7>=$F60,$H60<>0,$H60<>""),$C60/$H60,0) -> 0 | N60: =IF(AND(N$7<=$G60,N$7>=$F60,$H60<>0,$H60<>""),$C60/$H60,0) -> 0 | O60: =IF(AND(O$7<=$G60,O$7>=$F60,$H60<>0,$H60<>""),$C60/$H60,0) -> 0 | P60: =IF(AND(P$7<=$G60,P$7>=$F60,$H60<>0,$H60<>""),$C60/$H60,0) -> 0 | ... CZ60: =IF(AND(CZ$7<=$G60,CZ$7>=$F60,$H60<>0,$H60<>""),$C60/$H60,0) -> 0
B61: ='Development Costs'!B40 -> Professional fee contingency | C61: =-'Development Costs'!H40 -> -129000 | D61: =ROUND(C61-E61,0) -> 0 | E61: =SUM(I61:CZ61) -> -129000 | F61: =F$47 -> 44593 | G61: =G$47 -> 45536 | H61: =DATEDIF(F61,G61,"m")+1 -> 32 | I61: =IF(AND(I$7<=$G61,I$7>=$F61,$H61<>0,$H61<>""),$C61/$H61,0) -> 0 | J61: =IF(AND(J$7<=$G61,J$7>=$F61,$H61<>0,$H61<>""),$C61/$H61,0) -> -4031.25 | K61: =IF(AND(K$7<=$G61,K$7>=$F61,$H61<>0,$H61<>""),$C61/$H61,0) -> -4031.25 | L61: =IF(AND(L$7<=$G61,L$7>=$F61,$H61<>0,$H61<>""),$C61/$H61,0) -> -4031.25 | M61: =IF(AND(M$7<=$G61,M$7>=$F61,$H61<>0,$H61<>""),$C61/$H61,0) -> -4031.25 | N61: =IF(AND(N$7<=$G61,N$7>=$F61,$H61<>0,$H61<>""),$C61/$H61,0) -> -4031.25 | O61: =IF(AND(O$7<=$G61,O$7>=$F61,$H61<>0,$H61<>""),$C61/$H61,0) -> -4031.25 | P61: =IF(AND(P$7<=$G61,P$7>=$F61,$H61<>0,$H61<>""),$C61/$H61,0) -> -4031.25 | ... CZ61: =IF(AND(CZ$7<=$G61,CZ$7>=$F61,$H61<>0,$H61<>""),$C61/$H61,0) -> 0
B62: ='Development Costs'!B41 -> Total Professional Fees | C62: =SUM(C47:C61) -> -1419000 | D62: =C62-E62 -> 0 | E62: =SUM(I62:CZ62) -> -1419000 | I62: =SUM(I47:I61) -> 0 | J62: =SUM(J47:J61) -> -44343.75 | K62: =SUM(K47:K61) -> -44343.75 | L62: =SUM(L47:L61) -> -44343.75 | M62: =SUM(M47:M61) -> -44343.75 | N62: =SUM(N47:N61) -> -44343.75 | O62: =SUM(O47:O61) -> -44343.75 | P62: =SUM(P47:P61) -> -44343.75 | ... CZ62: =SUM(CZ47:CZ61) -> 0
B64: DEVELOPMENT MANAGEMENT
B65: ='Development Costs'!B46 -> Total Development Management Fee | C65: =-'Development Costs'!H46 -> -1254000 | D65: =ROUND(C65-E65,0) -> 0 | E65: =SUM(I65:CZ65) -> -1254000 | F65: =Schedule!D13 -> 44562 | G65: =Schedule!E17 -> 45536 | H65: =DATEDIF(F65,G65,"m")+1 -> 33 | I65: =IF(AND(I$7<=$G65,I$7>=$F65,$H65<>0,$H65<>""),$C65/$H65,0) -> -38000 | J65: =IF(AND(J$7<=$G65,J$7>=$F65,$H65<>0,$H65<>""),$C65/$H65,0) -> -38000 | K65: =IF(AND(K$7<=$G65,K$7>=$F65,$H65<>0,$H65<>""),$C65/$H65,0) -> -38000 | L65: =IF(AND(L$7<=$G65,L$7>=$F65,$H65<>0,$H65<>""),$C65/$H65,0) -> -38000 | M65: =IF(AND(M$7<=$G65,M$7>=$F65,$H65<>0,$H65<>""),$C65/$H65,0) -> -38000 | N65: =IF(AND(N$7<=$G65,N$7>=$F65,$H65<>0,$H65<>""),$C65/$H65,0) -> -38000 | O65: =IF(AND(O$7<=$G65,O$7>=$F65,$H65<>0,$H65<>""),$C65/$H65,0) -> -38000 | P65: =IF(AND(P$7<=$G65,P$7>=$F65,$H65<>0,$H65<>""),$C65/$H65,0) -> -38000 | ... CZ65: =IF(AND(CZ$7<=$G65,CZ$7>=$F65,$H65<>0,$H65<>""),$C65/$H65,0) -> 0
B67: PERMIT AND APPROVALS
B68: ='Development Costs'!B49 -> Development Permit | C68: =-'Development Costs'!H49 -> 0 | D68: =ROUND(C68-E68,0) -> 0 | E68: =SUM(I68:CZ68) -> 0 | F68: =Schedule!D15 -> 44593 | G68: =Schedule!E15 -> 44958 | H68: =DATEDIF(F68,G68,"m")+1 -> 13 | I68: =IF(AND(I$7<=$G68,I$7>=$F68,$H68<>0,$H68<>""),$C68/$H68,0) -> 0 | J68: =IF(AND(J$7<=$G68,J$7>=$F68,$H68<>0,$H68<>""),$C68/$H68,0) -> 0 | K68: =IF(AND(K$7<=$G68,K$7>=$F68,$H68<>0,$H68<>""),$C68/$H68,0) -> 0 | L68: =IF(AND(L$7<=$G68,L$7>=$F68,$H68<>0,$H68<>""),$C68/$H68,0) -> 0 | M68: =IF(AND(M$7<=$G68,M$7>=$F68,$H68<>0,$H68<>""),$C68/$H68,0) -> 0 | N68: =IF(AND(N$7<=$G68,N$7>=$F68,$H68<>0,$H68<>""),$C68/$H68,0) -> 0 | O68: =IF(AND(O$7<=$G68,O$7>=$F68,$H68<>0,$H68<>""),$C68/$H68,0) -> 0 | P68: =IF(AND(P$7<=$G68,P$7>=$F68,$H68<>0,$H68<>""),$C68/$H68,0) -> 0 | ... CZ68: =IF(AND(CZ$7<=$G68,CZ$7>=$F68,$H68<>0,$H68<>""),$C68/$H68,0) -> 0
B69: ='Development Costs'!B50 -> Rezoning | C69: =-'Development Costs'!H50 -> 0 | D69: =ROUND(C69-E69,0) -> 0 | E69: =SUM(I69:CZ69) -> 0 | F69: =F68 -> 44593 | G69: =G68 -> 44958 | H69: =DATEDIF(F69,G69,"m")+1 -> 13 | I69: =IF(AND(I$7<=$G69,I$7>=$F69,$H69<>0,$H69<>""),$C69/$H69,0) -> 0 | J69: =IF(AND(J$7<=$G69,J$7>=$F69,$H69<>0,$H69<>""),$C69/$H69,0) -> 0 | K69: =IF(AND(K$7<=$G69,K$7>=$F69,$H69<>0,$H69<>""),$C69/$H69,0) -> 0 | L69: =IF(AND(L$7<=$G69,L$7>=$F69,$H69<>0,$H69<>""),$C69/$H69,0) -> 0 | M69: =IF(AND(M$7<=$G69,M$7>=$F69,$H69<>0,$H69<>""),$C69/$H69,0) -> 0 | N69: =IF(AND(N$7<=$G69,N$7>=$F69,$H69<>0,$H69<>""),$C69/$H69,0) -> 0 | O69: =IF(AND(O$7<=$G69,O$7>=$F69,$H69<>0,$H69<>""),$C69/$H69,0) -> 0 | P69: =IF(AND(P$7<=$G69,P$7>=$F69,$H69<>0,$H69<>""),$C69/$H69,0) -> 0 | ... CZ69: =IF(AND(CZ$7<=$G69,CZ$7>=$F69,$H69<>0,$H69<>""),$C69/$H69,0) -> 0
B70: ='Development Costs'!B51 -> Building permit | C70: =-'Development Costs'!H51 -> -100000 | D70: =ROUND(C70-E70,0) -> 0 | E70: =SUM(I70:CZ70) -> -100000 | F70: =F69 -> 44593 | G70: =G69 -> 44958 | H70: =DATEDIF(F70,G70,"m")+1 -> 13 | I70: =IF(AND(I$7<=$G70,I$7>=$F70,$H70<>0,$H70<>""),$C70/$H70,0) -> 0 | J70: =IF(AND(J$7<=$G70,J$7>=$F70,$H70<>0,$H70<>""),$C70/$H70,0) -> -7692.3077 | K70: =IF(AND(K$7<=$G70,K$7>=$F70,$H70<>0,$H70<>""),$C70/$H70,0) -> -7692.3077 | L70: =IF(AND(L$7<=$G70,L$7>=$F70,$H70<>0,$H70<>""),$C70/$H70,0) -> -7692.3077 | M70: =IF(AND(M$7<=$G70,M$7>=$F70,$H70<>0,$H70<>""),$C70/$H70,0) -> -7692.3077 | N70: =IF(AND(N$7<=$G70,N$7>=$F70,$H70<>0,$H70<>""),$C70/$H70,0) -> -7692.3077 | O70: =IF(AND(O$7<=$G70,O$7>=$F70,$H70<>0,$H70<>""),$C70/$H70,0) -> -7692.3077 | P70: =IF(AND(P$7<=$G70,P$7>=$F70,$H70<>0,$H70<>""),$C70/$H70,0) -> -7692.3077 | ... CZ70: =IF(AND(CZ$7<=$G70,CZ$7>=$F70,$H70<>0,$H70<>""),$C70/$H70,0) -> 0
B71: ='Development Costs'!B52 -> City Development charges | C71: =-'Development Costs'!H52 -> -3000000 | D71: =ROUND(C71-E71,0) -> 0 | E71: =SUM(I71:CZ71) -> -3000000 | F71: =F70 -> 44593 | G71: =G70 -> 44958 | H71: =DATEDIF(F71,G71,"m")+1 -> 13 | I71: =IF(AND(I$7<=$G71,I$7>=$F71,$H71<>0,$H71<>""),$C71/$H71,0) -> 0 | J71: =IF(AND(J$7<=$G71,J$7>=$F71,$H71<>0,$H71<>""),$C71/$H71,0) -> -230769.23 | K71: =IF(AND(K$7<=$G71,K$7>=$F71,$H71<>0,$H71<>""),$C71/$H71,0) -> -230769.23 | L71: =IF(AND(L$7<=$G71,L$7>=$F71,$H71<>0,$H71<>""),$C71/$H71,0) -> -230769.23 | M71: =IF(AND(M$7<=$G71,M$7>=$F71,$H71<>0,$H71<>""),$C71/$H71,0) -> -230769.23 | N71: =IF(AND(N$7<=$G71,N$7>=$F71,$H71<>0,$H71<>""),$C71/$H71,0) -> -230769.23 | O71: =IF(AND(O$7<=$G71,O$7>=$F71,$H71<>0,$H71<>""),$C71/$H71,0) -> -230769.23 | P71: =IF(AND(P$7<=$G71,P$7>=$F71,$H71<>0,$H71<>""),$C71/$H71,0) -> -230769.23 | ... CZ71: =IF(AND(CZ$7<=$G71,CZ$7>=$F71,$H71<>0,$H71<>""),$C71/$H71,0) -> 0
B72: ='Development Costs'!B53 -> Park Dedication Fee | C72: =-'Development Costs'!H53 -> 0 | D72: =ROUND(C72-E72,0) -> 0 | E72: =SUM(I72:CZ72) -> 0 | F72: =F71 -> 44593 | G72: =G71 -> 44958 | H72: =DATEDIF(F72,G72,"m")+1 -> 13 | I72: =IF(AND(I$7<=$G72,I$7>=$F72,$H72<>0,$H72<>""),$C72/$H72,0) -> 0 | J72: =IF(AND(J$7<=$G72,J$7>=$F72,$H72<>0,$H72<>""),$C72/$H72,0) -> 0 | K72: =IF(AND(K$7<=$G72,K$7>=$F72,$H72<>0,$H72<>""),$C72/$H72,0) -> 0 | L72: =IF(AND(L$7<=$G72,L$7>=$F72,$H72<>0,$H72<>""),$C72/$H72,0) -> 0 | M72: =IF(AND(M$7<=$G72,M$7>=$F72,$H72<>0,$H72<>""),$C72/$H72,0) -> 0 | N72: =IF(AND(N$7<=$G72,N$7>=$F72,$H72<>0,$H72<>""),$C72/$H72,0) -> 0 | O72: =IF(AND(O$7<=$G72,O$7>=$F72,$H72<>0,$H72<>""),$C72/$H72,0) -> 0 | P72: =IF(AND(P$7<=$G72,P$7>=$F72,$H72<>0,$H72<>""),$C72/$H72,0) -> 0 | ... CZ72: =IF(AND(CZ$7<=$G72,CZ$7>=$F72,$H72<>0,$H72<>""),$C72/$H72,0) -> 0
B73: ='Development Costs'!B54 -> Other Development Charges | C73: =-'Development Costs'!H54 -> 0 | D73: =ROUND(C73-E73,0) -> 0 | E73: =SUM(I73:CZ73) -> 0 | F73: =F72 -> 44593 | G73: =G72 -> 44958 | H73: =DATEDIF(F73,G73,"m")+1 -> 13 | I73: =IF(AND(I$7<=$G73,I$7>=$F73,$H73<>0,$H73<>""),$C73/$H73,0) -> 0 | J73: =IF(AND(J$7<=$G73,J$7>=$F73,$H73<>0,$H73<>""),$C73/$H73,0) -> 0 | K73: =IF(AND(K$7<=$G73,K$7>=$F73,$H73<>0,$H73<>""),$C73/$H73,0) -> 0 | L73: =IF(AND(L$7<=$G73,L$7>=$F73,$H73<>0,$H73<>""),$C73/$H73,0) -> 0 | M73: =IF(AND(M$7<=$G73,M$7>=$F73,$H73<>0,$H73<>""),$C73/$H73,0) -> 0 | N73: =IF(AND(N$7<=$G73,N$7>=$F73,$H73<>0,$H73<>""),$C73/$H73,0) -> 0 | O73: =IF(AND(O$7<=$G73,O$7>=$F73,$H73<>0,$H73<>""),$C73/$H73,0) -> 0 | P73: =IF(AND(P$7<=$G73,P$7>=$F73,$H73<>0,$H73<>""),$C73/$H73,0) -> 0 | ... CZ73: =IF(AND(CZ$7<=$G73,CZ$7>=$F73,$H73<>0,$H73<>""),$C73/$H73,0) -> 0
B74: ='Development Costs'!B55 -> Sub-Meter Installation Fee Credit | C74: =-'Development Costs'!H55 -> 60000 | E74: =SUM(I74:CZ74) -> 60000 | F74: =+G41 -> 45536 | G74: =+F74 -> 45536 | H74: =DATEDIF(F74,G74,"m")+1 -> 1 | I74: =IF(AND(I$7<=$G74,I$7>=$F74,$H74<>0,$H74<>""),$C74/$H74,0) -> 0 | J74: =IF(AND(J$7<=$G74,J$7>=$F74,$H74<>0,$H74<>""),$C74/$H74,0) -> 0 | K74: =IF(AND(K$7<=$G74,K$7>=$F74,$H74<>0,$H74<>""),$C74/$H74,0) -> 0 | L74: =IF(AND(L$7<=$G74,L$7>=$F74,$H74<>0,$H74<>""),$C74/$H74,0) -> 0 | M74: =IF(AND(M$7<=$G74,M$7>=$F74,$H74<>0,$H74<>""),$C74/$H74,0) -> 0 | N74: =IF(AND(N$7<=$G74,N$7>=$F74,$H74<>0,$H74<>""),$C74/$H74,0) -> 0 | O74: =IF(AND(O$7<=$G74,O$7>=$F74,$H74<>0,$H74<>""),$C74/$H74,0) -> 0 | P74: =IF(AND(P$7<=$G74,P$7>=$F74,$H74<>0,$H74<>""),$C74/$H74,0) -> 0 | ... CZ74: =IF(AND(CZ$7<=$G74,CZ$7>=$F74,$H74<>0,$H74<>""),$C74/$H74,0) -> 0
B75: ='Development Costs'!B56 -> Utilities Connection | C75: =-'Development Costs'!H56 -> 0 | D75: =ROUND(C75-E75,0) -> 0 | E75: =SUM(I75:CZ75) -> 0 | F75: =F$47 -> 44593 | G75: =G$47 -> 45536 | H75: =DATEDIF(F75,G75,"m")+1 -> 32 | I75: =IF(AND(I$7<=$G75,I$7>=$F75,$H75<>0,$H75<>""),$C75/$H75,0) -> 0 | J75: =IF(AND(J$7<=$G75,J$7>=$F75,$H75<>0,$H75<>""),$C75/$H75,0) -> 0 | K75: =IF(AND(K$7<=$G75,K$7>=$F75,$H75<>0,$H75<>""),$C75/$H75,0) -> 0 | L75: =IF(AND(L$7<=$G75,L$7>=$F75,$H75<>0,$H75<>""),$C75/$H75,0) -> 0 | M75: =IF(AND(M$7<=$G75,M$7>=$F75,$H75<>0,$H75<>""),$C75/$H75,0) -> 0 | N75: =IF(AND(N$7<=$G75,N$7>=$F75,$H75<>0,$H75<>""),$C75/$H75,0) -> 0 | O75: =IF(AND(O$7<=$G75,O$7>=$F75,$H75<>0,$H75<>""),$C75/$H75,0) -> 0 | P75: =IF(AND(P$7<=$G75,P$7>=$F75,$H75<>0,$H75<>""),$C75/$H75,0) -> 0 | ... CZ75: =IF(AND(CZ$7<=$G75,CZ$7>=$F75,$H75<>0,$H75<>""),$C75/$H75,0) -> 0
B76: ='Development Costs'!B57 -> Land titles | C76: =-'Development Costs'!H57 -> 0 | D76: =ROUND(C76-E76,0) -> 0 | E76: =SUM(I76:CZ76) -> 0 | F76: =F75 -> 44593 | G76: =G$47 -> 45536 | H76: =DATEDIF(F76,G76,"m")+1 -> 32 | I76: =IF(AND(I$7<=$G76,I$7>=$F76,$H76<>0,$H76<>""),$C76/$H76,0) -> 0 | J76: =IF(AND(J$7<=$G76,J$7>=$F76,$H76<>0,$H76<>""),$C76/$H76,0) -> 0 | K76: =IF(AND(K$7<=$G76,K$7>=$F76,$H76<>0,$H76<>""),$C76/$H76,0) -> 0 | L76: =IF(AND(L$7<=$G76,L$7>=$F76,$H76<>0,$H76<>""),$C76/$H76,0) -> 0 | M76: =IF(AND(M$7<=$G76,M$7>=$F76,$H76<>0,$H76<>""),$C76/$H76,0) -> 0 | N76: =IF(AND(N$7<=$G76,N$7>=$F76,$H76<>0,$H76<>""),$C76/$H76,0) -> 0 | O76: =IF(AND(O$7<=$G76,O$7>=$F76,$H76<>0,$H76<>""),$C76/$H76,0) -> 0 | P76: =IF(AND(P$7<=$G76,P$7>=$F76,$H76<>0,$H76<>""),$C76/$H76,0) -> 0 | ... CZ76: =IF(AND(CZ$7<=$G76,CZ$7>=$F76,$H76<>0,$H76<>""),$C76/$H76,0) -> 0
B77: ='Development Costs'!B58 -> Permit and approval contingency | C77: =-'Development Costs'!H58 -> -304000 | D77: =ROUND(C77-E77,0) -> 0 | E77: =SUM(I77:CZ77) -> -304000 | F77: =F$47 -> 44593 | G77: =G$47 -> 45536 | H77: =DATEDIF(F77,G77,"m")+1 -> 32 | I77: =IF(AND(I$7<=$G77,I$7>=$F77,$H77<>0,$H77<>""),$C77/$H77,0) -> 0 | J77: =IF(AND(J$7<=$G77,J$7>=$F77,$H77<>0,$H77<>""),$C77/$H77,0) -> -9500 | K77: =IF(AND(K$7<=$G77,K$7>=$F77,$H77<>0,$H77<>""),$C77/$H77,0) -> -9500 | L77: =IF(AND(L$7<=$G77,L$7>=$F77,$H77<>0,$H77<>""),$C77/$H77,0) -> -9500 | M77: =IF(AND(M$7<=$G77,M$7>=$F77,$H77<>0,$H77<>""),$C77/$H77,0) -> -9500 | N77: =IF(AND(N$7<=$G77,N$7>=$F77,$H77<>0,$H77<>""),$C77/$H77,0) -> -9500 | O77: =IF(AND(O$7<=$G77,O$7>=$F77,$H77<>0,$H77<>""),$C77/$H77,0) -> -9500 | P77: =IF(AND(P$7<=$G77,P$7>=$F77,$H77<>0,$H77<>""),$C77/$H77,0) -> -9500 | ... CZ77: =IF(AND(CZ$7<=$G77,CZ$7>=$F77,$H77<>0,$H77<>""),$C77/$H77,0) -> 0
B78: ='Development Costs'!B59 -> Total Permit and Approvals | C78: =-'Development Costs'!H59 -> -3344000 | D78: =C78-E78 -> 0 | E78: =SUM(I78:CZ78) -> -3344000 | I78: =SUM(I68:I77) -> 0 | J78: =SUM(J68:J77) -> -247961.54 | K78: =SUM(K68:K77) -> -247961.54 | L78: =SUM(L68:L77) -> -247961.54 | M78: =SUM(M68:M77) -> -247961.54 | N78: =SUM(N68:N77) -> -247961.54 | O78: =SUM(O68:O77) -> -247961.54 | P78: =SUM(P68:P77) -> -247961.54 | ... CZ78: =SUM(CZ68:CZ77) -> 0
B80: MARKETING AND LEASING
B81: ='Development Costs'!B65 -> Marketing | C81: =-'Development Costs'!H66 -> -726750 | D81: =ROUND(C81-E81,0) -> 0 | E81: =SUM(I81:CZ81) -> -726750 | F81: =Schedule!D19 -> 45474 | G81: =Schedule!E19 -> 45658 | H81: =DATEDIF(F81,G81,"m")+1 -> 7 | I81: =IF(AND(I$7<=$G81,I$7>=$F81,$H81<>0,$H81<>""),$C81/$H81,0) -> 0 | J81: =IF(AND(J$7<=$G81,J$7>=$F81,$H81<>0,$H81<>""),$C81/$H81,0) -> 0 | K81: =IF(AND(K$7<=$G81,K$7>=$F81,$H81<>0,$H81<>""),$C81/$H81,0) -> 0 | L81: =IF(AND(L$7<=$G81,L$7>=$F81,$H81<>0,$H81<>""),$C81/$H81,0) -> 0 | M81: =IF(AND(M$7<=$G81,M$7>=$F81,$H81<>0,$H81<>""),$C81/$H81,0) -> 0 | N81: =IF(AND(N$7<=$G81,N$7>=$F81,$H81<>0,$H81<>""),$C81/$H81,0) -> 0 | O81: =IF(AND(O$7<=$G81,O$7>=$F81,$H81<>0,$H81<>""),$C81/$H81,0) -> 0 | P81: =IF(AND(P$7<=$G81,P$7>=$F81,$H81<>0,$H81<>""),$C81/$H81,0) -> 0 | ... CZ81: =IF(AND(CZ$7<=$G81,CZ$7>=$F81,$H81<>0,$H81<>""),$C81/$H81,0) -> 0
B82: ='Development Costs'!B66 -> Total Marketing and Leasing | C82: =C81 -> -726750 | D82: =C82-E82 -> 0 | E82: =SUM(I82:CZ82) -> -726750 | I82: =SUM(I81:I81) -> 0 | J82: =SUM(J81:J81) -> 0 | K82: =SUM(K81:K81) -> 0 | L82: =SUM(L81:L81) -> 0 | M82: =SUM(M81:M81) -> 0 | N82: =SUM(N81:N81) -> 0 | O82: =SUM(O81:O81) -> 0 | P82: =SUM(P81:P81) -> 0 | ... CZ82: =SUM(CZ81:CZ81) -> 0
B84: FINANCING AND INTEREST
B85: ='Development Costs'!B69 -> Appraisal | C85: =-'Development Costs'!H69 -> -20000 | D85: =ROUND(C85-E85,0) -> 0 | E85: =SUM(I85:CZ85) -> -20000 | F85: =Schedule!D13 -> 44562 | G85: =Schedule!E13 -> 44562 | H85: =DATEDIF(F85,G85,"m")+1 -> 1 | I85: =IF(AND(I$7<=$G85,I$7>=$F85,$H85<>0,$H85<>""),$C85/$H85,0) -> -20000 | J85: =IF(AND(J$7<=$G85,J$7>=$F85,$H85<>0,$H85<>""),$C85/$H85,0) -> 0 | K85: =IF(AND(K$7<=$G85,K$7>=$F85,$H85<>0,$H85<>""),$C85/$H85,0) -> 0 | L85: =IF(AND(L$7<=$G85,L$7>=$F85,$H85<>0,$H85<>""),$C85/$H85,0) -> 0 | M85: =IF(AND(M$7<=$G85,M$7>=$F85,$H85<>0,$H85<>""),$C85/$H85,0) -> 0 | N85: =IF(AND(N$7<=$G85,N$7>=$F85,$H85<>0,$H85<>""),$C85/$H85,0) -> 0 | O85: =IF(AND(O$7<=$G85,O$7>=$F85,$H85<>0,$H85<>""),$C85/$H85,0) -> 0 | P85: =IF(AND(P$7<=$G85,P$7>=$F85,$H85<>0,$H85<>""),$C85/$H85,0) -> 0 | ... CZ85: =IF(AND(CZ$7<=$G85,CZ$7>=$F85,$H85<>0,$H85<>""),$C85/$H85,0) -> 0
B86: ='Development Costs'!B70 -> Legal fees | C86: =-'Development Costs'!H70 -> -75000 | D86: =ROUND(C86-E86,0) -> 0 | E86: =SUM(I86:CZ86) -> -75000 | F86: =F85 -> 44562 | G86: =G85 -> 44562 | H86: =DATEDIF(F86,G86,"m")+1 -> 1 | I86: =IF(AND(I$7<=$G86,I$7>=$F86,$H86<>0,$H86<>""),$C86/$H86,0) -> -75000 | J86: =IF(AND(J$7<=$G86,J$7>=$F86,$H86<>0,$H86<>""),$C86/$H86,0) -> 0 | K86: =IF(AND(K$7<=$G86,K$7>=$F86,$H86<>0,$H86<>""),$C86/$H86,0) -> 0 | L86: =IF(AND(L$7<=$G86,L$7>=$F86,$H86<>0,$H86<>""),$C86/$H86,0) -> 0 | M86: =IF(AND(M$7<=$G86,M$7>=$F86,$H86<>0,$H86<>""),$C86/$H86,0) -> 0 | N86: =IF(AND(N$7<=$G86,N$7>=$F86,$H86<>0,$H86<>""),$C86/$H86,0) -> 0 | O86: =IF(AND(O$7<=$G86,O$7>=$F86,$H86<>0,$H86<>""),$C86/$H86,0) -> 0 | P86: =IF(AND(P$7<=$G86,P$7>=$F86,$H86<>0,$H86<>""),$C86/$H86,0) -> 0 | ... CZ86: =IF(AND(CZ$7<=$G86,CZ$7>=$F86,$H86<>0,$H86<>""),$C86/$H86,0) -> 0
B87: ='Development Costs'!B71 -> Property Taxes During Construction | C87: =-'Development Costs'!H71 -> 0 | D87: =ROUND(C87-E87,0) -> 0 | E87: =SUM(I87:CZ87) -> 0 | F87: =Schedule!D15 -> 44593 | G87: =Schedule!E17 -> 45536 | H87: =DATEDIF(F87,G87,"m")+1 -> 32 | I87: =IF(AND(I$7<=$G87,I$7>=$F87,$H87<>0,$H87<>""),$C87/$H87,0) -> 0 | J87: =IF(AND(J$7<=$G87,J$7>=$F87,$H87<>0,$H87<>""),$C87/$H87,0) -> 0 | K87: =IF(AND(K$7<=$G87,K$7>=$F87,$H87<>0,$H87<>""),$C87/$H87,0) -> 0 | L87: =IF(AND(L$7<=$G87,L$7>=$F87,$H87<>0,$H87<>""),$C87/$H87,0) -> 0 | M87: =IF(AND(M$7<=$G87,M$7>=$F87,$H87<>0,$H87<>""),$C87/$H87,0) -> 0 | N87: =IF(AND(N$7<=$G87,N$7>=$F87,$H87<>0,$H87<>""),$C87/$H87,0) -> 0 | O87: =IF(AND(O$7<=$G87,O$7>=$F87,$H87<>0,$H87<>""),$C87/$H87,0) -> 0 | P87: =IF(AND(P$7<=$G87,P$7>=$F87,$H87<>0,$H87<>""),$C87/$H87,0) -> 0 | ... CZ87: =IF(AND(CZ$7<=$G87,CZ$7>=$F87,$H87<>0,$H87<>""),$C87/$H87,0) -> 0
B88: ='Development Costs'!B72 -> Quantity Surveyor | C88: =-'Development Costs'!H72 -> 0 | D88: =ROUND(C88-E88,0) -> 0 | E88: =SUM(I88:CZ88) -> 0 | F88: =F87 -> 44593 | G88: =G87 -> 45536 | H88: =DATEDIF(F88,G88,"m")+1 -> 32 | I88: =IF(AND(I$7<=$G88,I$7>=$F88,$H88<>0,$H88<>""),$C88/$H88,0) -> 0 | J88: =IF(AND(J$7<=$G88,J$7>=$F88,$H88<>0,$H88<>""),$C88/$H88,0) -> 0 | K88: =IF(AND(K$7<=$G88,K$7>=$F88,$H88<>0,$H88<>""),$C88/$H88,0) -> 0 | L88: =IF(AND(L$7<=$G88,L$7>=$F88,$H88<>0,$H88<>""),$C88/$H88,0) -> 0 | M88: =IF(AND(M$7<=$G88,M$7>=$F88,$H88<>0,$H88<>""),$C88/$H88,0) -> 0 | N88: =IF(AND(N$7<=$G88,N$7>=$F88,$H88<>0,$H88<>""),$C88/$H88,0) -> 0 | O88: =IF(AND(O$7<=$G88,O$7>=$F88,$H88<>0,$H88<>""),$C88/$H88,0) -> 0 | P88: =IF(AND(P$7<=$G88,P$7>=$F88,$H88<>0,$H88<>""),$C88/$H88,0) -> 0 | ... CZ88: =IF(AND(CZ$7<=$G88,CZ$7>=$F88,$H88<>0,$H88<>""),$C88/$H88,0) -> 0
B89: ='Development Costs'!B73 -> Insurance | C89: =-'Development Costs'!H73 -> 0 | D89: =ROUND(C89-E89,0) -> 0 | E89: =SUM(I89:CZ89) -> 0 | F89: =F$47 -> 44593 | G89: =G$47 -> 45536 | H89: =DATEDIF(F89,G89,"m")+1 -> 32 | I89: =IF(AND(I$7<=$G89,I$7>=$F89,$H89<>0,$H89<>""),$C89/$H89,0) -> 0 | J89: =IF(AND(J$7<=$G89,J$7>=$F89,$H89<>0,$H89<>""),$C89/$H89,0) -> 0 | K89: =IF(AND(K$7<=$G89,K$7>=$F89,$H89<>0,$H89<>""),$C89/$H89,0) -> 0 | L89: =IF(AND(L$7<=$G89,L$7>=$F89,$H89<>0,$H89<>""),$C89/$H89,0) -> 0 | M89: =IF(AND(M$7<=$G89,M$7>=$F89,$H89<>0,$H89<>""),$C89/$H89,0) -> 0 | N89: =IF(AND(N$7<=$G89,N$7>=$F89,$H89<>0,$H89<>""),$C89/$H89,0) -> 0 | O89: =IF(AND(O$7<=$G89,O$7>=$F89,$H89<>0,$H89<>""),$C89/$H89,0) -> 0 | P89: =IF(AND(P$7<=$G89,P$7>=$F89,$H89<>0,$H89<>""),$C89/$H89,0) -> 0 | ... CZ89: =IF(AND(CZ$7<=$G89,CZ$7>=$F89,$H89<>0,$H89<>""),$C89/$H89,0) -> 0
B90: ='Development Costs'!B74 -> LC and Bonding | C90: =-'Development Costs'!H74 -> 0 | D90: =ROUND(C90-E90,0) -> 0 | E90: =SUM(I90:CZ90) -> 0 | F90: =F$47 -> 44593 | G90: =G$47 -> 45536 | H90: =DATEDIF(F90,G90,"m")+1 -> 32 | I90: =IF(AND(I$7<=$G90,I$7>=$F90,$H90<>0,$H90<>""),$C90/$H90,0) -> 0 | J90: =IF(AND(J$7<=$G90,J$7>=$F90,$H90<>0,$H90<>""),$C90/$H90,0) -> 0 | K90: =IF(AND(K$7<=$G90,K$7>=$F90,$H90<>0,$H90<>""),$C90/$H90,0) -> 0 | L90: =IF(AND(L$7<=$G90,L$7>=$F90,$H90<>0,$H90<>""),$C90/$H90,0) -> 0 | M90: =IF(AND(M$7<=$G90,M$7>=$F90,$H90<>0,$H90<>""),$C90/$H90,0) -> 0 | N90: =IF(AND(N$7<=$G90,N$7>=$F90,$H90<>0,$H90<>""),$C90/$H90,0) -> 0 | O90: =IF(AND(O$7<=$G90,O$7>=$F90,$H90<>0,$H90<>""),$C90/$H90,0) -> 0 | P90: =IF(AND(P$7<=$G90,P$7>=$F90,$H90<>0,$H90<>""),$C90/$H90,0) -> 0 | ... CZ90: =IF(AND(CZ$7<=$G90,CZ$7>=$F90,$H90<>0,$H90<>""),$C90/$H90,0) -> 0
B91: ='Development Costs'!B75 -> Loan fees | C91: =-'Development Costs'!H75 -> -480000 | D91: =ROUND(C91-E91,0) -> 0 | E91: =SUM(I91:CZ91) -> -480000 | F91: =F$47 -> 44593 | G91: =G$47 -> 45536 | H91: =DATEDIF(F91,G91,"m")+1 -> 32 | I91: =IF(AND(I$7<=$G91,I$7>=$F91,$H91<>0,$H91<>""),$C91/$H91,0) -> 0 | J91: =IF(AND(J$7<=$G91,J$7>=$F91,$H91<>0,$H91<>""),$C91/$H91,0) -> -15000 | K91: =IF(AND(K$7<=$G91,K$7>=$F91,$H91<>0,$H91<>""),$C91/$H91,0) -> -15000 | L91: =IF(AND(L$7<=$G91,L$7>=$F91,$H91<>0,$H91<>""),$C91/$H91,0) -> -15000 | M91: =IF(AND(M$7<=$G91,M$7>=$F91,$H91<>0,$H91<>""),$C91/$H91,0) -> -15000 | N91: =IF(AND(N$7<=$G91,N$7>=$F91,$H91<>0,$H91<>""),$C91/$H91,0) -> -15000 | O91: =IF(AND(O$7<=$G91,O$7>=$F91,$H91<>0,$H91<>""),$C91/$H91,0) -> -15000 | P91: =IF(AND(P$7<=$G91,P$7>=$F91,$H91<>0,$H91<>""),$C91/$H91,0) -> -15000 | ... CZ91: =IF(AND(CZ$7<=$G91,CZ$7>=$F91,$H91<>0,$H91<>""),$C91/$H91,0) -> 0
B92: ='Development Costs'!B76 -> Bank's Legal / Other charges | C92: =-'Development Costs'!H76 -> 0 | D92: =ROUND(C92-E92,0) -> 0 | E92: =SUM(I92:CZ92) -> 0 | F92: =F$47 -> 44593 | G92: =G$47 -> 45536 | H92: =DATEDIF(F92,G92,"m")+1 -> 32 | I92: =IF(AND(I$7<=$G92,I$7>=$F92,$H92<>0,$H92<>""),$C92/$H92,0) -> 0 | J92: =IF(AND(J$7<=$G92,J$7>=$F92,$H92<>0,$H92<>""),$C92/$H92,0) -> 0 | K92: =IF(AND(K$7<=$G92,K$7>=$F92,$H92<>0,$H92<>""),$C92/$H92,0) -> 0 | L92: =IF(AND(L$7<=$G92,L$7>=$F92,$H92<>0,$H92<>""),$C92/$H92,0) -> 0 | M92: =IF(AND(M$7<=$G92,M$7>=$F92,$H92<>0,$H92<>""),$C92/$H92,0) -> 0 | N92: =IF(AND(N$7<=$G92,N$7>=$F92,$H92<>0,$H92<>""),$C92/$H92,0) -> 0 | O92: =IF(AND(O$7<=$G92,O$7>=$F92,$H92<>0,$H92<>""),$C92/$H92,0) -> 0 | P92: =IF(AND(P$7<=$G92,P$7>=$F92,$H92<>0,$H92<>""),$C92/$H92,0) -> 0 | ... CZ92: =IF(AND(CZ$7<=$G92,CZ$7>=$F92,$H92<>0,$H92<>""),$C92/$H92,0) -> 0
B93: ='Development Costs'!B77 -> HST | C93: =-'Development Costs'!H77 -> -3820151.5 | D93: =ROUND(C93-E93,0) -> 0 | E93: =SUM(I93:CZ93) -> -3820151.5 | I93: =$C$93/'Development Costs'!$I$9*I9 -> 0 | J93: =$C$93/'Development Costs'!$I$9*J9 -> 0 | K93: =$C$93/'Development Costs'!$I$9*K9 -> 0 | L93: =$C$93/'Development Costs'!$I$9*L9 -> 0 | M93: =$C$93/'Development Costs'!$I$9*M9 -> 0 | N93: =$C$93/'Development Costs'!$I$9*N9 -> 0 | O93: =$C$93/'Development Costs'!$I$9*O9 -> 0 | P93: =$C$93/'Development Costs'!$I$9*P9 -> 0 | ... BB93: =$C$93/'Development Costs'!$I$9*BB9 -> 0 | BC93: =-HST!F20 -> 0 | BD93: =$C$93/'Development Costs'!$I$9*BD9 -> 0 | BE93: =$C$93/'Development Costs'!$I$9*BE9 -> 0 | BF93: =$C$93/'Development Costs'!$I$9*BF9 -> 0 | BG93: =$C$93/'Development Costs'!$I$9*BG9 -> 0 | BH93: =$C$93/'Development Costs'!$I$9*BH9 -> 0 | BI93: =$C$93/'Development Costs'!$I$9*BI9-BC93 -> 0 | BJ93: =$C$93/'Development Costs'!$I$9*BJ9 -> 0 | BK93: =$C$93/'Development Costs'!$I$9*BK9 -> 0 | BL93: =$C$93/'Development Costs'!$I$9*BL9 -> 0 | BM93: =$C$93/'Development Costs'!$I$9*BM9 -> 0 | BN93: =$C$93/'Development Costs'!$I$9*BN9 -> 0 | BO93: =$C$93/'Development Costs'!$I$9*BO9 -> 0 | BP93: =$C$93/'Development Costs'!$I$9*BP9 -> 0 | BQ93: =$C$93/'Development Costs'!$I$9*BQ9 -> 0 | ... CZ93: =$C$93/'Development Costs'!$I$9*CZ9 -> 0
B94: ='Development Costs'!B78 -> Construction Loan Interest | C94: =E94 -> -2639932.5 | D94: =ROUND(C94-E94,0) -> 0 | E94: =SUM(I94:CZ94) -> -2639932.5 | I94: 0 | J94: =IF(J111="PUD",-'Development Costs'!$G$78/12*I108,0) -> -4363.3333 | K94: =IF(K111="PUD",-'Development Costs'!$G$78/12*J108,0) -> -5783.9211 | L94: =IF(L111="PUD",-'Development Costs'!$G$78/12*K108,0) -> -7210.0311 | M94: =IF(M111="PUD",-'Development Costs'!$G$78/12*L108,0) -> -8641.6867 | N94: =IF(N111="PUD",-'Development Costs'!$G$78/12*M108,0) -> -10078.911 | O94: =IF(O111="PUD",-'Development Costs'!$G$78/12*N108,0) -> -11521.724 | P94: =IF(P111="PUD",-'Development Costs'!$G$78/12*O108,0) -> -12970.148 | Q94: =IF(Q111="PUD",-'Development Costs'!$G$78/12*P108,0) -> -14424.204 | ... CZ94: =IF(CZ111="PUD",-'Development Costs'!$G$78/12*CY108,0) -> 0
B95: ='Development Costs'!B79 -> Financing contingency | C95: =-'Development Costs'!H79 -> -500000 | D95: =ROUND(C95-E95,0) -> 0 | E95: =SUM(I95:CZ95) -> -500000 | F95: =F$47 -> 44593 | G95: =G$47 -> 45536 | H95: =DATEDIF(F95,G95,"m")+1 -> 32 | I95: =IF(AND(I$7<=$G95,I$7>=$F95,$H95<>0,$H95<>""),$C95/$H95,0) -> 0 | J95: =IF(AND(J$7<=$G95,J$7>=$F95,$H95<>0,$H95<>""),$C95/$H95,0) -> -15625 | K95: =IF(AND(K$7<=$G95,K$7>=$F95,$H95<>0,$H95<>""),$C95/$H95,0) -> -15625 | L95: =IF(AND(L$7<=$G95,L$7>=$F95,$H95<>0,$H95<>""),$C95/$H95,0) -> -15625 | M95: =IF(AND(M$7<=$G95,M$7>=$F95,$H95<>0,$H95<>""),$C95/$H95,0) -> -15625 | N95: =IF(AND(N$7<=$G95,N$7>=$F95,$H95<>0,$H95<>""),$C95/$H95,0) -> -15625 | O95: =IF(AND(O$7<=$G95,O$7>=$F95,$H95<>0,$H95<>""),$C95/$H95,0) -> -15625 | P95: =IF(AND(P$7<=$G95,P$7>=$F95,$H95<>0,$H95<>""),$C95/$H95,0) -> -15625 | ... CZ95: =IF(AND(CZ$7<=$G95,CZ$7>=$F95,$H95<>0,$H95<>""),$C95/$H95,0) -> 0
B96: ='Development Costs'!B80 -> Total Financing and Interest Costs | C96: =SUM(C85:C95) -> -7535084 | D96: =ROUND(C96-E96,0) -> 0 | E96: =SUM(I96:CZ96) -> -7535084 | I96: =SUM(I85:I95) -> -95000 | J96: =SUM(J85:J95) -> -34988.333 | K96: =SUM(K85:K95) -> -36408.921 | L96: =SUM(L85:L95) -> -37835.031 | M96: =SUM(M85:M95) -> -39266.687 | N96: =SUM(N85:N95) -> -40703.911 | O96: =SUM(O85:O95) -> -42146.724 | P96: =SUM(P85:P95) -> -43595.148 | ... CZ96: =SUM(CZ85:CZ95) -> 0
B98: CONSTRUCTION LOAN
B99: Cash Flow before loan draws | C99: =SUM(C22,C26,C31,C44,C62,C65,C78,C82,C96) -> -49187782 | D99: =ROUND(C99-E99,0) -> 0 | E99: =SUM(E22,E26,E31,E44,E62,E65,E78,E82,E96) -> -49187782 | I99: =SUM(I22,I26,I31,I44,I62,I65,I78,I82,I96) -> -6122000 | J99: =SUM(J22,J26,J31,J44,J62,J65,J78,J82,J96) -> -365293.62 | K99: =SUM(K22,K26,K31,K44,K62,K65,K78,K82,K96) -> -366714.21 | L99: =SUM(L22,L26,L31,L44,L62,L65,L78,L82,L96) -> -368140.32 | M99: =SUM(M22,M26,M31,M44,M62,M65,M78,M82,M96) -> -369571.98 | N99: =SUM(N22,N26,N31,N44,N62,N65,N78,N82,N96) -> -371009.2 | O99: =SUM(O22,O26,O31,O44,O62,O65,O78,O82,O96) -> -372452.01 | P99: =SUM(P22,P26,P31,P44,P62,P65,P78,P82,P96) -> -373900.44 | ... CZ99: =SUM(CZ22,CZ26,CZ31,CZ44,CZ62,CZ65,CZ78,CZ82,CZ96) -> 0
B100: Construction Loan Draws | E100: =SUM(I100:CZ100) -> 44187782 | I100: =-I115 -> 1122000 | J100: =-J115 -> 365293.62 | K100: =-K115 -> 366714.21 | L100: =-L115 -> 368140.32 | M100: =-M115 -> 369571.98 | N100: =-N115 -> 371009.2 | O100: =-O115 -> 372452.01 | P100: =-P115 -> 373900.44 | ... CZ100: =-CZ115 -> 0
B101: Repayment of Construction Loan | E101: =SUM(I101:CZ101) -> -44187781 | I101: 0 | J101: =IF(AND(I94<0,J111="SLD"),-I108,0) -> 0 | K101: =IF(AND(J94<0,K111="SLD"),-J108,0) -> 0 | L101: =IF(AND(K94<0,L111="SLD"),-K108,0) -> 0 | M101: =IF(AND(L94<0,M111="SLD"),-L108,0) -> 0 | N101: =IF(AND(M94<0,N111="SLD"),-M108,0) -> 0 | O101: =IF(AND(N94<0,O111="SLD"),-N108,0) -> 0 | P101: =IF(AND(O94<0,P111="SLD"),-O108,0) -> 0 | Q101: =IF(AND(P94<0,Q111="SLD"),-P108,0) -> 0 | ... CZ101: =IF(AND(CY94<0,CZ111="SLD"),-CY108,0) -> 0
B103: Valuation at stabilization | I103: 0 | J103: =I26*12/Sensitivity!$H$10*(J111="SLD")*(I94<0) -> 0 | K103: =J26*12/Sensitivity!$H$10*(K111="SLD")*(J94<0) -> 0 | L103: =K26*12/Sensitivity!$H$10*(L111="SLD")*(K94<0) -> 0 | M103: =L26*12/Sensitivity!$H$10*(M111="SLD")*(L94<0) -> 0 | N103: =M26*12/Sensitivity!$H$10*(N111="SLD")*(M94<0) -> 0 | O103: =N26*12/Sensitivity!$H$10*(O111="SLD")*(N94<0) -> 0 | P103: =O26*12/Sensitivity!$H$10*(P111="SLD")*(O94<0) -> 0 | Q103: =P26*12/Sensitivity!$H$10*(Q111="SLD")*(P94<0) -> 0 | ... CZ103: =CY26*12/Sensitivity!$H$10*(CZ111="SLD")*(CY94<0) -> 0
B104: Selling Costs | I104: =-'10-Yr Cash Flow IRR'!$E$11*I103 -> 0 | J104: =-'10-Yr Cash Flow IRR'!$E$11*J103 -> 0 | K104: =-'10-Yr Cash Flow IRR'!$E$11*K103 -> 0 | L104: =-'10-Yr Cash Flow IRR'!$E$11*L103 -> 0 | M104: =-'10-Yr Cash Flow IRR'!$E$11*M103 -> 0 | N104: =-'10-Yr Cash Flow IRR'!$E$11*N103 -> 0 | O104: =-'10-Yr Cash Flow IRR'!$E$11*O103 -> 0 | P104: =-'10-Yr Cash Flow IRR'!$E$11*P103 -> 0 | ... CZ104: =-'10-Yr Cash Flow IRR'!$E$11*CZ103 -> 0
B105: Net Cash Flow - Equity | C105: =ROUND(SUM(C99:C104),0) -> -49187782 | D105: =SUM(D99:D100) -> 0 | E105: =ROUND(SUM(I105:CZ105),0) -> 5159940 | H105: =SUM(H99:H100) -> 0 | I105: =SUM(I99:I104) -> -5000000 | J105: =SUM(J99:J104) -> 1.7462298e-10 | K105: =SUM(K99:K104) -> -5.8207661e-11 | L105: =SUM(L99:L104) -> 2.910383e-10 | M105: =SUM(M99:M104) -> 3.4924597e-10 | N105: =SUM(N99:N104) -> 1.7462298e-10 | O105: =SUM(O99:O104) -> -4.0745363e-10 | P105: =SUM(P99:P104) -> -3.4924597e-10 | ... CZ105: =SUM(CZ99:CZ104) -> 0
F106: IRR | G106: =+(1+IRR(I105:CZ105,0.02))^12-1 -> 0.25094511
B107: Cumulative | D107: Loan to Cost:
B108: Construction Loan Balance | C108: =-MAX(I108:CZ108) -> -44198885 | D108: =+C108/C105 -> 0.89857447 | I108: =I100 -> 1122000 | J108: =ROUND(J100+I108+J101,0) -> 1487294 | K108: =ROUND(K100+J108+K101,0) -> 1854008 | L108: =ROUND(L100+K108+L101,0) -> 2222148 | M108: =ROUND(M100+L108+M101,0) -> 2591720 | N108: =ROUND(N100+M108+N101,0) -> 2962729 | O108: =ROUND(O100+N108+O101,0) -> 3335181 | P108: =ROUND(P100+O108+P101,0) -> 3709081 | Q108: =ROUND(Q100+P108+Q101,0) -> 4084435 | ... CZ108: =ROUND(CZ100+CY108+CZ101,0) -> 0
B109: Equity | C109: =E115 -> -5000000 | D109: =1-D108 -> 0.10142553 | I109: =-I105 -> 5000000 | J109: =(I111="PUD")*(I109-J105) -> 5000000 | K109: =(J111="PUD")*(J109-K105) -> 5000000 | L109: =(K111="PUD")*(K109-L105) -> 5000000 | M109: =(L111="PUD")*(L109-M105) -> 5000000 | N109: =(M111="PUD")*(M109-N105) -> 5000000 | O109: =(N111="PUD")*(N109-O105) -> 5000000 | P109: =(O111="PUD")*(O109-P105) -> 5000000 | Q109: =(P111="PUD")*(P109-Q105) -> 5000000 | ... CZ109: =(CY111="PUD")*(CY109-CZ105) -> 0
B111: Development Status | I111: =IF(I7<=Schedule!$E$21,"PUD","SLD") -> PUD | J111: =IF(J7<=Schedule!$E$21,"PUD","SLD") -> PUD | K111: =IF(K7<=Schedule!$E$21,"PUD","SLD") -> PUD | L111: =IF(L7<=Schedule!$E$21,"PUD","SLD") -> PUD | M111: =IF(M7<=Schedule!$E$21,"PUD","SLD") -> PUD | N111: =IF(N7<=Schedule!$E$21,"PUD","SLD") -> PUD | O111: =IF(O7<=Schedule!$E$21,"PUD","SLD") -> PUD | P111: =IF(P7<=Schedule!$E$21,"PUD","SLD") -> PUD | ... CZ111: =IF(CZ7<=Schedule!$E$21,"PUD","SLD") -> SLD
B113: Cost to Date | I113: =IF(I111="PUD",I99,0) -> -6122000 | J113: =IF(J111="PUD",I113+J99,0) -> -6487293.6 | K113: =IF(K111="PUD",J113+K99,0) -> -6854007.8 | L113: =IF(L111="PUD",K113+L99,0) -> -7222148.2 | M113: =IF(M111="PUD",L113+M99,0) -> -7591720.1 | N113: =IF(N111="PUD",M113+N99,0) -> -7962729.3 | O113: =IF(O111="PUD",N113+O99,0) -> -8335181.3 | P113: =IF(P111="PUD",O113+P99,0) -> -8709081.8 | Q113: =IF(Q111="PUD",P113+Q99,0) -> -9084436.3 | ... CZ113: =IF(CZ111="PUD",CY113+CZ99,0) -> 0
B115: Cost to Complete Financing | D115: =C105*(1-D108)-E115 -> 11103 | E115: -5000000 | I115: =IF(AND(I111="PUD",I113<$E$115),I113-$E$115,0) -> -1122000 | J115: =IF(AND(J111="PUD",J113<$E$115),J113-$E$115-SUM($I$115:I115),0) -> -365293.62 | K115: =IF(AND(K111="PUD",K113<$E$115),K113-$E$115-SUM($I$115:J115),0) -> -366714.21 | L115: =IF(AND(L111="PUD",L113<$E$115),L113-$E$115-SUM($I$115:K115),0) -> -368140.32 | M115: =IF(AND(M111="PUD",M113<$E$115),M113-$E$115-SUM($I$115:L115),0) -> -369571.98 | N115: =IF(AND(N111="PUD",N113<$E$115),N113-$E$115-SUM($I$115:M115),0) -> -371009.2 | O115: =IF(AND(O111="PUD",O113<$E$115),O113-$E$115-SUM($I$115:N115),0) -> -372452.01 | P115: =IF(AND(P111="PUD",P113<$E$115),P113-$E$115-SUM($I$115:O115),0) -> -373900.44 | Q115: =IF(AND(Q111="PUD",Q113<$E$115),Q113-$E$115-SUM($I$115:P115),0) -> -375354.49 | ... CZ115: =IF(AND(CZ111="PUD",CZ113<$E$115),CZ113-$E$115-SUM($I$115:CY115),0) -> 0
...

Sheet 10-Yr Cash Flow IRR
M1: ="Currently running: "&CHOOSE(Sensitivity!$E$8,Sensitivity!$B$11,Sensitivity!$B$12,Sensitivity!$B$13) -> Currently running: Base Case
A2: =Cover!A10 -> Apartment Development Model
A3: =Cover!A12 -> Suburban / Urban Location
A4: Stabilized Rental Cash Flow Analysis
B8: OTHER ASSUMPTIONS
B9: Annual Revenue Inflation | E9: 0.02 | H9: Annualized NOI at Stabilization | K9: ='Operating Revenue and Expenses'!I52 -> 2195867.5
B10: Annual Cost Inflation | E10: 0.02 | H10: Capitalization Rate | K10: ='Operating Revenue and Expenses'!E51 -> 0.04
B11: Selling Costs | E11: 0.01 | H11: Value | K11: =K9/K10 -> 54896688
B12: Min. NOI Coverage | E12: 1.1 | H12: Maximum Allowable Permanent Loan Amount | K12: =MIN(E13*K11,-PV(E14,E15,K9/E12)) -> 34760878
B13: Max. LTV @ Stabilization | E13: 0.75 | H13: Choose Loan Option: | K13: 1 | S13: Maximum Allowable Loan
B14: Permanent Loan Interest Rate | E14: 0.03 | H14: Permanent Loan Principal | K14: =IF(K13=1,K12,MIN(K12,'Development Cash Flow'!E100)) -> 34760878 | S14: Lesser of Construction Loan and Max Loan
B15: Loan Term (years) | E15: 25 | H15: Equity Requirement | K15: ='Development Costs'!H89-'10-Yr Cash Flow IRR'!K14 -> 14426905 | L15: =K14/K11 -> 0.63320537 | M15: LTV
B16: Construction Loan Ratio | E16: =+'Development Cash Flow'!D108 -> 0.89857447 | H16: Annual Debt Service | K16: =-PMT(E14/12,E15*12,K14)*12 -> 1978080.2 | L16: =K9/K16 -> 1.1101004 | M16: NOI Coverage
B19: YEAR | C19: 1 | D19: 2 | E19: 3 | F19: 4 | G19: 5 | H19: 6 | I19: 7 | J19: 8 | K19: 9 | L19: 10
C20: =YEAR(Schedule!D8) -> 2022 | D20: =C20+1 -> 2023 | E20: =D20+1 -> 2024 | F20: =E20+1 -> 2025 | G20: =F20+1 -> 2026 | H20: =G20+1 -> 2027 | I20: =H20+1 -> 2028 | J20: =I20+1 -> 2029 | K20: =J20+1 -> 2030 | L20: =K20+1 -> 2031
A21: Stabilized Holding Months | C21: =IF(C$20<YEAR(Schedule!$E$21),0,IF(C$20=YEAR(Schedule!$E$21),12-MONTH(Schedule!$E$21),12)) -> 0 | D21: =IF(D$20<YEAR(Schedule!$E$21),0,IF(D$20=YEAR(Schedule!$E$21),12-MONTH(Schedule!$E$21),12)) -> 0 | E21: =IF(E$20<YEAR(Schedule!$E$21),0,IF(E$20=YEAR(Schedule!$E$21),12-MONTH(Schedule!$E$21),12)) -> 0 | F21: =IF(F$20<YEAR(Schedule!$E$21),0,IF(F$20=YEAR(Schedule!$E$21),12-MONTH(Schedule!$E$21),12)) -> 10 | G21: =IF(G$20<YEAR(Schedule!$E$21),0,IF(G$20=YEAR(Schedule!$E$21),12-MONTH(Schedule!$E$21),12)) -> 12 | H21: =IF(H$20<YEAR(Schedule!$E$21),0,IF(H$20=YEAR(Schedule!$E$21),12-MONTH(Schedule!$E$21),12)) -> 12 | I21: =IF(I$20<YEAR(Schedule!$E$21),0,IF(I$20=YEAR(Schedule!$E$21),12-MONTH(Schedule!$E$21),12)) -> 12 | J21: =IF(J$20<YEAR(Schedule!$E$21),0,IF(J$20=YEAR(Schedule!$E$21),12-MONTH(Schedule!$E$21),12)) -> 12 | ... L21: =IF(L$20<YEAR(Schedule!$E$21),0,IF(L$20=YEAR(Schedule!$E$21),12-MONTH(Schedule!$E$21),12)) -> 12
A22: Revenue Inflation Factor | C22: =(1+$E$9)^(C20-YEAR(Schedule!$D$8)) -> 1 | D22: =(1+$E$9)^(D20-YEAR(Schedule!$D$8)) -> 1.02 | E22: =(1+$E$9)^(E20-YEAR(Schedule!$D$8)) -> 1.0404 | F22: =(1+$E$9)^(F20-YEAR(Schedule!$D$8)) -> 1.061208 | G22: =(1+$E$9)^(G20-YEAR(Schedule!$D$8)) -> 1.0824322 | H22: =(1+$E$9)^(H20-YEAR(Schedule!$D$8)) -> 1.1040808 | I22: =(1+$E$9)^(I20-YEAR(Schedule!$D$8)) -> 1.1261624 | J22: =(1+$E$9)^(J20-YEAR(Schedule!$D$8)) -> 1.1486857 | ... L22: =(1+$E$9)^(L20-YEAR(Schedule!$D$8)) -> 1.1950926
A23: Cost Inflation Factor | C23: =(1+$E$10)^(C20-YEAR(Schedule!$D$8)) -> 1 | D23: =(1+$E$10)^(D20-YEAR(Schedule!$D$8)) -> 1.02 | E23: =(1+$E$10)^(E20-YEAR(Schedule!$D$8)) -> 1.0404 | F23: =(1+$E$10)^(F20-YEAR(Schedule!$D$8)) -> 1.061208 | G23: =(1+$E$10)^(G20-YEAR(Schedule!$D$8)) -> 1.0824322 | H23: =(1+$E$10)^(H20-YEAR(Schedule!$D$8)) -> 1.1040808 | I23: =(1+$E$10)^(I20-YEAR(Schedule!$D$8)) -> 1.1261624 | J23: =(1+$E$10)^(J20-YEAR(Schedule!$D$8)) -> 1.1486857 | ... L23: =(1+$E$10)^(L20-YEAR(Schedule!$D$8)) -> 1.1950926
A26: Revenue | C26: =C$21/12*C$22*'Operating Revenue and Expenses'!$I$27 -> 0 | D26: =D$21/12*D$22*'Operating Revenue and Expenses'!$I$27 -> 0 | E26: =E$21/12*E$22*'Operating Revenue and Expenses'!$I$27 -> 0 | F26: =F$21/12*F$22*'Operating Revenue and Expenses'!$I$27 -> 2570776.4 | G26: =G$21/12*G$22*'Operating Revenue and Expenses'!$I$27 -> 3146630.3 | H26: =H$21/12*H$22*'Operating Revenue and Expenses'!$I$27 -> 3209562.9 | I26: =I$21/12*I$22*'Operating Revenue and Expenses'!$I$27 -> 3273754.2 | J26: =J$21/12*J$22*'Operating Revenue and Expenses'!$I$27 -> 3339229.2 | ... L26: =L$21/12*L$22*'Operating Revenue and Expenses'!$I$27 -> 3474134.1
A27: Vacancy Provision | C27: =-C$21/12*C$22*'Operating Revenue and Expenses'!$I$28 -> 0 | D27: =-D$21/12*D$22*'Operating Revenue and Expenses'!$I$28 -> 0 | E27: =-E$21/12*E$22*'Operating Revenue and Expenses'!$I$28 -> 0 | F27: =-F$21/12*F$22*'Operating Revenue and Expenses'!$I$28 -> -64269.41 | G27: =-G$21/12*G$22*'Operating Revenue and Expenses'!$I$28 -> -78665.757 | H27: =-H$21/12*H$22*'Operating Revenue and Expenses'!$I$28 -> -80239.072 | I27: =-I$21/12*I$22*'Operating Revenue and Expenses'!$I$28 -> -81843.854 | J27: =-J$21/12*J$22*'Operating Revenue and Expenses'!$I$28 -> -83480.731 | ... L27: =-L$21/12*L$22*'Operating Revenue and Expenses'!$I$28 -> -86853.352
A28: Operating Expenses | C28: =-C$21/12*C$23*'Operating Revenue and Expenses'!$I$45 -> 0 | D28: =-D$21/12*D$23*'Operating Revenue and Expenses'!$I$45 -> 0 | E28: =-E$21/12*E$23*'Operating Revenue and Expenses'!$I$45 -> 0 | F28: =-F$21/12*F$23*'Operating Revenue and Expenses'!$I$45 -> -676617.38 | G28: =-G$21/12*G$23*'Operating Revenue and Expenses'!$I$45 -> -828179.67 | H28: =-H$21/12*H$23*'Operating Revenue and Expenses'!$I$45 -> -844743.26 | I28: =-I$21/12*I$23*'Operating Revenue and Expenses'!$I$45 -> -861638.13 | J28: =-J$21/12*J$23*'Operating Revenue and Expenses'!$I$45 -> -878870.89 | ... L28: =-L$21/12*L$23*'Operating Revenue and Expenses'!$I$45 -> -914377.28
A29: Stabilized NOI | C29: =SUM(C26:C28) -> 0 | D29: =SUM(D26:D28) -> 0 | E29: =SUM(E26:E28) -> 0 | F29: =SUM(F26:F28) -> 1829889.6 | G29: =SUM(G26:G28) -> 2239784.9 | H29: =SUM(H26:H28) -> 2284580.6 | I29: =SUM(I26:I28) -> 2330272.2 | J29: =SUM(J26:J28) -> 2376877.6 | ... L29: =SUM(L26:L28) -> 2472903.5
A31: Development Cash Flow | C31: =IF(C20<=YEAR(Schedule!$E$21),SUMIFS('Development Cash Flow'!$I99:$CZ99,'Development Cash Flow'!$I5:$CZ5,C$20,'Development Cash Flow'!$I111:$CZ111,"PUD"),0) -> -10219281 | D31: =IF(D20<=YEAR(Schedule!$E$21),SUMIFS('Development Cash Flow'!$I99:$CZ99,'Development Cash Flow'!$I5:$CZ5,D$20,'Development Cash Flow'!$I111:$CZ111,"PUD"),0) -> -18420501 | E31: =IF(E20<=YEAR(Schedule!$E$21),SUMIFS('Development Cash Flow'!$I99:$CZ99,'Development Cash Flow'!$I5:$CZ5,E$20,'Development Cash Flow'!$I111:$CZ111,"PUD"),0) -> -20503330 | F31: =IF(F20<=YEAR(Schedule!$E$21),SUMIFS('Development Cash Flow'!$I99:$CZ99,'Development Cash Flow'!$I5:$CZ5,F$20,'Development Cash Flow'!$I111:$CZ111,"PUD"),0) -> -44670.336 | G31: =IF(G20<=YEAR(Schedule!$E$21),SUMIFS('Development Cash Flow'!$I99:$CZ99,'Development Cash Flow'!$I5:$CZ5,G$20,'Development Cash Flow'!$I111:$CZ111,"PUD"),0) -> 0 | H31: =IF(H20<=YEAR(Schedule!$E$21),SUMIFS('Development Cash Flow'!$I99:$CZ99,'Development Cash Flow'!$I5:$CZ5,H$20,'Development Cash Flow'!$I111:$CZ111,"PUD"),0) -> 0 | I31: =IF(I20<=YEAR(Schedule!$E$21),SUMIFS('Development Cash Flow'!$I99:$CZ99,'Development Cash Flow'!$I5:$CZ5,I$20,'Development Cash Flow'!$I111:$CZ111,"PUD"),0) -> 0 | J31: =IF(J20<=YEAR(Schedule!$E$21),SUMIFS('Development Cash Flow'!$I99:$CZ99,'Development Cash Flow'!$I5:$CZ5,J$20,'Development Cash Flow'!$I111:$CZ111,"PUD"),0) -> 0 | ... L31: =IF(L20<=YEAR(Schedule!$E$21),SUMIFS('Development Cash Flow'!$I99:$CZ99,'Development Cash Flow'!$I5:$CZ5,L$20,'Development Cash Flow'!$I111:$CZ111,"PUD"),0) -> 0
A32: Construction Loan Draw | C32: =IF(C34=MAX($C$34:$L$34),C57-C31-C34,C57-C31) -> 5219280.7 | D32: =IF(D34=MAX($C$34:$L$34),D57-D31-D34,D57-D31) -> 18420501 | E32: =IF(E34=MAX($C$34:$L$34),E57-E31-E34,E57-E31) -> 20503330 | F32: =IF(F34=MAX($C$34:$L$34),F57-F31-F34,F57-F31) -> -44143112 | G32: =IF(G34=MAX($C$34:$L$34),G57-G31-G34,G57-G31) -> 0 | H32: =IF(H34=MAX($C$34:$L$34),H57-H31-H34,H57-H31) -> 0 | I32: =IF(I34=MAX($C$34:$L$34),I57-I31-I34,I57-I31) -> 0 | J32: =IF(J34=MAX($C$34:$L$34),J57-J31-J34,J57-J31) -> 0 | ... L32: =IF(L34=MAX($C$34:$L$34),L57-L31-L34,L57-L31) -> 0
A33: Construction Loan Balance | C33: =C32 -> 5219280.7 | D33: =IF(AND(C33+D32<10,C33+D32>-10),0,C33+D32) -> 23639782 | E33: =IF(AND(D33+E32<10,D33+E32>-10),0,D33+E32) -> 44143112 | F33: =IF(AND(E33+F32<10,E33+F32>-10),0,E33+F32) -> 0 | G33: =IF(AND(F33+G32<10,F33+G32>-10),0,F33+G32) -> 0 | H33: =IF(AND(G33+H32<10,G33+H32>-10),0,G33+H32) -> 0 | I33: =IF(AND(H33+I32<10,H33+I32>-10),0,H33+I32) -> 0 | J33: =IF(AND(I33+J32<10,I33+J32>-10),0,I33+J32) -> 0 | K33: =IF(AND(J33+K32<10,J33+K32>-10),0,J33+K32) -> 0 | L33: =IF(AND(K33+L32<10,K33+L32>-10),0,K33+L32) -> 0
A34: Permanent Loan Balance | C34: 0 | D34: =IF(D20<YEAR(Schedule!$E$21),0,IF(D20=YEAR(Schedule!$E$21),$K$14,'10-Yr Cash Flow IRR'!C34+'10-Yr Cash Flow IRR'!C38)) -> 0 | E34: =IF(E20<YEAR(Schedule!$E$21),0,IF(E20=YEAR(Schedule!$E$21),$K$14,'10-Yr Cash Flow IRR'!D34+'10-Yr Cash Flow IRR'!D38)) -> 0 | F34: =IF(F20<YEAR(Schedule!$E$21),0,IF(F20=YEAR(Schedule!$E$21),$K$14,'10-Yr Cash Flow IRR'!E34+'10-Yr Cash Flow IRR'!E38)) -> 34760878 | G34: =IF(G20<YEAR(Schedule!$E$21),0,IF(G20=YEAR(Schedule!$E$21),$K$14,'10-Yr Cash Flow IRR'!F34+'10-Yr Cash Flow IRR'!F38)) -> 33972673 | H34: =IF(H20<YEAR(Schedule!$E$21),0,IF(H20=YEAR(Schedule!$E$21),$K$14,'10-Yr Cash Flow IRR'!G34+'10-Yr Cash Flow IRR'!G38)) -> 33000477 | I34: =IF(I20<YEAR(Schedule!$E$21),0,IF(I20=YEAR(Schedule!$E$21),$K$14,'10-Yr Cash Flow IRR'!H34+'10-Yr Cash Flow IRR'!H38)) -> 31998712 | J34: =IF(J20<YEAR(Schedule!$E$21),0,IF(J20=YEAR(Schedule!$E$21),$K$14,'10-Yr Cash Flow IRR'!I34+'10-Yr Cash Flow IRR'!I38)) -> 30966476 | K34: =IF(K20<YEAR(Schedule!$E$21),0,IF(K20=YEAR(Schedule!$E$21),$K$14,'10-Yr Cash Flow IRR'!J34+'10-Yr Cash Flow IRR'!J38)) -> 29902845 | L34: =IF(L20<YEAR(Schedule!$E$21),0,IF(L20=YEAR(Schedule!$E$21),$K$14,'10-Yr Cash Flow IRR'!K34+'10-Yr Cash Flow IRR'!K38)) -> 28806862
A36: Stabilized NOI | C36: =C29 -> 0 | D36: =D29 -> 0 | E36: =E29 -> 0 | F36: =F29 -> 1829889.6 | G36: =G29 -> 2239784.9 | H36: =H29 -> 2284580.6 | I36: =I29 -> 2330272.2 | J36: =J29 -> 2376877.6 | ... L36: =L29 -> 2472903.5
A37: Interest Payment | C37: =SUMIF($C$76:$C$195,C$20,$E76:$E195) -> 0 | D37: =SUMIF($C$76:$C$195,D$20,$E76:$E195) -> 0 | E37: =SUMIF($C$76:$C$195,E$20,$E76:$E195) -> 0 | F37: =SUMIF($C$76:$C$195,F$20,$E76:$E195) -> -860195.22 | G37: =SUMIF($C$76:$C$195,G$20,$E76:$E195) -> -1005884.8 | H37: =SUMIF($C$76:$C$195,H$20,$E76:$E195) -> -976314.56 | I37: =SUMIF($C$76:$C$195,I$20,$E76:$E195) -> -945844.9 | J37: =SUMIF($C$76:$C$195,J$20,$E76:$E195) -> -914448.47 | ... L37: =SUMIF($C$76:$C$195,L$20,$E76:$E195) -> -848761.72
A38: Prinpical Payment | C38: =SUMIF($C$76:$C$195,C$20,$D76:$D195) -> 0 | D38: =SUMIF($C$76:$C$195,D$20,$D76:$D195) -> 0 | E38: =SUMIF($C$76:$C$195,E$20,$D76:$D195) -> 0 | F38: =SUMIF($C$76:$C$195,F$20,$D76:$D195) -> -788204.92 | G38: =SUMIF($C$76:$C$195,G$20,$D76:$D195) -> -972195.36 | H38: =SUMIF($C$76:$C$195,H$20,$D76:$D195) -> -1001765.6 | I38: =SUMIF($C$76:$C$195,I$20,$D76:$D195) -> -1032235.3 | J38: =SUMIF($C$76:$C$195,J$20,$D76:$D195) -> -1063631.7 | ... L38: =SUMIF($C$76:$C$195,L$20,$D76:$D195) -> -1129318.4
A39: Income before Tax | C39: =SUM(C36:C38) -> 0 | D39: =SUM(D36:D38) -> 0 | E39: =SUM(E36:E38) -> 0 | F39: =SUM(F36:F38) -> 181489.45 | G39: =SUM(G36:G38) -> 261704.69 | H39: =SUM(H36:H38) -> 306500.39 | I39: =SUM(I36:I38) -> 352192 | J39: =SUM(J36:J38) -> 398797.44 | ... L39: =SUM(L36:L38) -> 494823.3
A41: ="Valuation @ "&TEXT(Sensitivity!H13,"0.00%")&" Cap rate" -> Valuation @ 4.25% Cap rate | C41: =IF(AND(C21<>0,C20>=YEAR(Schedule!$E$21)),'10-Yr Cash Flow IRR'!C36/'10-Yr Cash Flow IRR'!C21*12/Sensitivity!$H$13,0) -> 0 | D41: =IF(AND(D21<>0,D20>=YEAR(Schedule!$E$21)),'10-Yr Cash Flow IRR'!D36/'10-Yr Cash Flow IRR'!D21*12/Sensitivity!$H$13,0) -> 0 | E41: =IF(AND(E21<>0,E20>=YEAR(Schedule!$E$21)),'10-Yr Cash Flow IRR'!E36/'10-Yr Cash Flow IRR'!E21*12/Sensitivity!$H$13,0) -> 0 | F41: =IF(AND(F21<>0,F20>=YEAR(Schedule!$E$21)),'10-Yr Cash Flow IRR'!F36/'10-Yr Cash Flow IRR'!F21*12/Sensitivity!$H$13,0) -> 51667471 | G41: =IF(AND(G21<>0,G20>=YEAR(Schedule!$E$21)),'10-Yr Cash Flow IRR'!G36/'10-Yr Cash Flow IRR'!G21*12/Sensitivity!$H$13,0) -> 52700820 | H41: =IF(AND(H21<>0,H20>=YEAR(Schedule!$E$21)),'10-Yr Cash Flow IRR'!H36/'10-Yr Cash Flow IRR'!H21*12/Sensitivity!$H$13,0) -> 53754837 | I41: =IF(AND(I21<>0,I20>=YEAR(Schedule!$E$21)),'10-Yr Cash Flow IRR'!I36/'10-Yr Cash Flow IRR'!I21*12/Sensitivity!$H$13,0) -> 54829933 | J41: =IF(AND(J21<>0,J20>=YEAR(Schedule!$E$21)),'10-Yr Cash Flow IRR'!J36/'10-Yr Cash Flow IRR'!J21*12/Sensitivity!$H$13,0) -> 55926532 | ... L41: =IF(AND(L21<>0,L20>=YEAR(Schedule!$E$21)),'10-Yr Cash Flow IRR'!L36/'10-Yr Cash Flow IRR'!L21*12/Sensitivity!$H$13,0) -> 58185964
A42: ="Less: Selling Cost @ "&TEXT($E$11,"0.00%") -> Less: Selling Cost @ 1.00% | C42: =-$E$11*C41 -> 0 | D42: =-$E$11*D41 -> 0 | E42: =-$E$11*E41 -> 0 | F42: =-$E$11*F41 -> -516674.71 | G42: =-$E$11*G41 -> -527008.2 | H42: =-$E$11*H41 -> -537548.37 | I42: =-$E$11*I41 -> -548299.33 | J42: =-$E$11*J41 -> -559265.32 | ... L42: =-$E$11*L41 -> -581859.64
A43: Less: Loan Balance | C43: =-C$34 -> 0 | D43: =-D$34 -> 0 | E43: =-E$34 -> 0 | F43: =-F$34 -> -34760878 | G43: =-G$34 -> -33972673 | H43: =-H$34 -> -33000477 | I43: =-I$34 -> -31998712 | J43: =-J$34 -> -30966476 | ... L43: =-L$34 -> -28806862
A44: Net Proceeds from Sale | C44: =SUM(C41:C43) -> 0 | D44: =SUM(D41:D43) -> 0 | E44: =SUM(E41:E43) -> 0 | F44: =SUM(F41:F43) -> 16389919 | G44: =SUM(G41:G43) -> 18201139 | H44: =SUM(H41:H43) -> 20216811 | I44: =SUM(I41:I43) -> 22282922 | J44: =SUM(J41:J43) -> 24400790 | ... L44: =SUM(L41:L43) -> 28797243
A46: ="Valuation @ "&TEXT(Sensitivity!H10,"0.00%")&" Cap rate" -> Valuation @ 4.00% Cap rate | C46: =IF(AND(C21<>0,C20>=YEAR(Schedule!$E$21)),'10-Yr Cash Flow IRR'!C36/'10-Yr Cash Flow IRR'!C21*12/Sensitivity!$H$10,0) -> 0 | D46: =IF(AND(D21<>0,D20>=YEAR(Schedule!$E$21)),'10-Yr Cash Flow IRR'!D36/'10-Yr Cash Flow IRR'!D21*12/Sensitivity!$H$10,0) -> 0 | E46: =IF(AND(E21<>0,E20>=YEAR(Schedule!$E$21)),'10-Yr Cash Flow IRR'!E36/'10-Yr Cash Flow IRR'!E21*12/Sensitivity!$H$10,0) -> 0 | F46: =IF(AND(F21<>0,F20>=YEAR(Schedule!$E$21)),'10-Yr Cash Flow IRR'!F36/'10-Yr Cash Flow IRR'!F21*12/Sensitivity!$H$10,0) -> 54896688 | G46: =IF(AND(G21<>0,G20>=YEAR(Schedule!$E$21)),'10-Yr Cash Flow IRR'!G36/'10-Yr Cash Flow IRR'!G21*12/Sensitivity!$H$10,0) -> 55994622 | H46: =IF(AND(H21<>0,H20>=YEAR(Schedule!$E$21)),'10-Yr Cash Flow IRR'!H36/'10-Yr Cash Flow IRR'!H21*12/Sensitivity!$H$10,0) -> 57114514 | I46: =IF(AND(I21<>0,I20>=YEAR(Schedule!$E$21)),'10-Yr Cash Flow IRR'!I36/'10-Yr Cash Flow IRR'!I21*12/Sensitivity!$H$10,0) -> 58256804 | J46: =IF(AND(J21<>0,J20>=YEAR(Schedule!$E$21)),'10-Yr Cash Flow IRR'!J36/'10-Yr Cash Flow IRR'!J21*12/Sensitivity!$H$10,0) -> 59421940 | ... L46: =IF(AND(L21<>0,L20>=YEAR(Schedule!$E$21)),'10-Yr Cash Flow IRR'!L36/'10-Yr Cash Flow IRR'!L21*12/Sensitivity!$H$10,0) -> 61822587
A47: ="Less: Selling Cost @ "&TEXT($E$11,"0.00%") -> Less: Selling Cost @ 1.00% | C47: =-$E$11*C46 -> 0 | D47: =-$E$11*D46 -> 0 | E47: =-$E$11*E46 -> 0 | F47: =-$E$11*F46 -> -548966.88 | G47: =-$E$11*G46 -> -559946.22 | H47: =-$E$11*H46 -> -571145.14 | I47: =-$E$11*I46 -> -582568.04 | J47: =-$E$11*J46 -> -594219.4 | ... L47: =-$E$11*L46 -> -618225.87
A48: Less: Loan Balance | C48: =-C$34 -> 0 | D48: =-D$34 -> 0 | E48: =-E$34 -> 0 | F48: =-F$34 -> -34760878 | G48: =-G$34 -> -33972673 | H48: =-H$34 -> -33000477 | I48: =-I$34 -> -31998712 | J48: =-J$34 -> -30966476 | ... L48: =-L$34 -> -28806862
A49: Net Proceeds from Sale | C49: =SUM(C46:C48) -> 0 | D49: =SUM(D46:D48) -> 0 | E49: =SUM(E46:E48) -> 0 | F49: =SUM(F46:F48) -> 19586843 | G49: =SUM(G46:G48) -> 21462003 | H49: =SUM(H46:H48) -> 23542892 | I49: =SUM(I46:I48) -> 25675525 | J49: =SUM(J46:J48) -> 27861245 | ... L49: =SUM(L46:L48) -> 32397499
A51: ="Valuation @ "&TEXT(Sensitivity!H12,"0.00%")&" Cap rate" -> Valuation @ 3.75% Cap rate | C51: =IF(AND(C21<>0,C20>=YEAR(Schedule!$E$21)),'10-Yr Cash Flow IRR'!C36/'10-Yr Cash Flow IRR'!C21*12/Sensitivity!$H$12,0) -> 0 | D51: =IF(AND(D21<>0,D20>=YEAR(Schedule!$E$21)),'10-Yr Cash Flow IRR'!D36/'10-Yr Cash Flow IRR'!D21*12/Sensitivity!$H$12,0) -> 0 | E51: =IF(AND(E21<>0,E20>=YEAR(Schedule!$E$21)),'10-Yr Cash Flow IRR'!E36/'10-Yr Cash Flow IRR'!E21*12/Sensitivity!$H$12,0) -> 0 | F51: =IF(AND(F21<>0,F20>=YEAR(Schedule!$E$21)),'10-Yr Cash Flow IRR'!F36/'10-Yr Cash Flow IRR'!F21*12/Sensitivity!$H$12,0) -> 58556467 | G51: =IF(AND(G21<>0,G20>=YEAR(Schedule!$E$21)),'10-Yr Cash Flow IRR'!G36/'10-Yr Cash Flow IRR'!G21*12/Sensitivity!$H$12,0) -> 59727596 | H51: =IF(AND(H21<>0,H20>=YEAR(Schedule!$E$21)),'10-Yr Cash Flow IRR'!H36/'10-Yr Cash Flow IRR'!H21*12/Sensitivity!$H$12,0) -> 60922148 | I51: =IF(AND(I21<>0,I20>=YEAR(Schedule!$E$21)),'10-Yr Cash Flow IRR'!I36/'10-Yr Cash Flow IRR'!I21*12/Sensitivity!$H$12,0) -> 62140591 | J51: =IF(AND(J21<>0,J20>=YEAR(Schedule!$E$21)),'10-Yr Cash Flow IRR'!J36/'10-Yr Cash Flow IRR'!J21*12/Sensitivity!$H$12,0) -> 63383403 | ... L51: =IF(AND(L21<>0,L20>=YEAR(Schedule!$E$21)),'10-Yr Cash Flow IRR'!L36/'10-Yr Cash Flow IRR'!L21*12/Sensitivity!$H$12,0) -> 65944093
A52: ="Less: Selling Cost @ "&TEXT($E$11,"0.00%") -> Less: Selling Cost @ 1.00% | C52: =-$E$11*C51 -> 0 | D52: =-$E$11*D51 -> 0 | E52: =-$E$11*E51 -> 0 | F52: =-$E$11*F51 -> -585564.67 | G52: =-$E$11*G51 -> -597275.96 | H52: =-$E$11*H51 -> -609221.48 | I52: =-$E$11*I51 -> -621405.91 | J52: =-$E$11*J51 -> -633834.03 | ... L52: =-$E$11*L51 -> -659440.93
A53: Less: Loan Balance | C53: =-C$34 -> 0 | D53: =-D$34 -> 0 | E53: =-E$34 -> 0 | F53: =-F$34 -> -34760878 | G53: =-G$34 -> -33972673 | H53: =-H$34 -> -33000477 | I53: =-I$34 -> -31998712 | J53: =-J$34 -> -30966476 | ... L53: =-L$34 -> -28806862
A54: Net Proceeds from Sale | C54: =SUM(C51:C53) -> 0 | D54: =SUM(D51:D53) -> 0 | E54: =SUM(E51:E53) -> 0 | F54: =SUM(F51:F53) -> 23210025 | G54: =SUM(G51:G53) -> 25157648 | H54: =SUM(H51:H53) -> 27312450 | I54: =SUM(I51:I53) -> 29520474 | J54: =SUM(J51:J53) -> 31783093 | ... L54: =SUM(L51:L53) -> 36477790
B56: IRR CALCULATION | D56: ="Based on valuation @ "&TEXT(Sensitivity!H10,"0.00%")&" Cap rate" -> Based on valuation @ 4.00% Cap rate
A57: Equity Investment | C57: =ROUND(SUMIFS('Development Cash Flow'!$I105:$CZ105,'Development Cash Flow'!$I5:$CZ5,C$20,'Development Cash Flow'!$I111:$CZ111,"PUD"),0) -> -5000000 | D57: =ROUND(IF(D34=MAX($C34:$L34),-$K$15-SUM($C$57:C57),0)+SUMIFS('Development Cash Flow'!$I105:$CZ105,'Development Cash Flow'!$I5:$CZ5,D$20,'Development Cash Flow'!$I111:$CZ111,"PUD"),0) -> 0 | E57: =ROUND(IF(E34=MAX($C34:$L34),-$K$15-SUM($C$57:D57),0)+SUMIFS('Development Cash Flow'!$I105:$CZ105,'Development Cash Flow'!$I5:$CZ5,E$20,'Development Cash Flow'!$I111:$CZ111,"PUD"),0) -> 0 | F57: =ROUND(IF(F34=MAX($C34:$L34),-$K$15-SUM($C$57:E57),0)+SUMIFS('Development Cash Flow'!$I105:$CZ105,'Development Cash Flow'!$I5:$CZ5,F$20,'Development Cash Flow'!$I111:$CZ111,"PUD"),0) -> -9426905 | G57: =ROUND(IF(G34=MAX($C34:$L34),-$K$15-SUM($C$57:F57),0)+SUMIFS('Development Cash Flow'!$I105:$CZ105,'Development Cash Flow'!$I5:$CZ5,G$20,'Development Cash Flow'!$I111:$CZ111,"PUD"),0) -> 0 | H57: =ROUND(IF(H34=MAX($C34:$L34),-$K$15-SUM($C$57:G57),0)+SUMIFS('Development Cash Flow'!$I105:$CZ105,'Development Cash Flow'!$I5:$CZ5,H$20,'Development Cash Flow'!$I111:$CZ111,"PUD"),0) -> 0 | I57: =ROUND(IF(I34=MAX($C34:$L34),-$K$15-SUM($C$57:H57),0)+SUMIFS('Development Cash Flow'!$I105:$CZ105,'Development Cash Flow'!$I5:$CZ5,I$20,'Development Cash Flow'!$I111:$CZ111,"PUD"),0) -> 0 | J57: =ROUND(IF(J34=MAX($C34:$L34),-$K$15-SUM($C$57:I57),0)+SUMIFS('Development Cash Flow'!$I105:$CZ105,'Development Cash Flow'!$I5:$CZ5,J$20,'Development Cash Flow'!$I111:$CZ111,"PUD"),0) -> 0 | K57: =ROUND(IF(K34=MAX($C34:$L34),-$K$15-SUM($C$57:J57),0)+SUMIFS('Development Cash Flow'!$I105:$CZ105,'Development Cash Flow'!$I5:$CZ5,K$20,'Development Cash Flow'!$I111:$CZ111,"PUD"),0) -> 0 | L57: =ROUND(IF(L34=MAX($C34:$L34),-$K$15-SUM($C$57:K57),0)+SUMIFS('Development Cash Flow'!$I105:$CZ105,'Development Cash Flow'!$I5:$CZ5,L$20,'Development Cash Flow'!$I111:$CZ111,"PUD"),0) -> 0
A58: Income before Tax | C58: =C39 -> 0 | D58: =D39 -> 0 | E58: =E39 -> 0 | F58: =F39 -> 181489.45 | G58: =G39 -> 261704.69 | H58: =H39 -> 306500.39 | I58: =I39 -> 352192 | J58: =J39 -> 398797.44 | ... L58: =L39 -> 494823.3
A60: 5 | B60: -year cash flow | C60: =IF(C$19<=$A60,SUM(C$57:C$58),0)+IF(C$19=$A60,C$49,0) -> -5000000 | D60: =IF(D$19<=$A60,SUM(D$57:D$58),0)+IF(D$19=$A60,D$49,0) -> 0 | E60: =IF(E$19<=$A60,SUM(E$57:E$58),0)+IF(E$19=$A60,E$49,0) -> 0 | F60: =IF(F$19<=$A60,SUM(F$57:F$58),0)+IF(F$19=$A60,F$49,0) -> -9245415.5 | G60: =IF(G$19<=$A60,SUM(G$57:G$58),0)+IF(G$19=$A60,G$49,0) -> 21723707 | H60: =IF(H$19<=$A60,SUM(H$57:H$58),0)+IF(H$19=$A60,H$49,0) -> 0 | I60: =IF(I$19<=$A60,SUM(I$57:I$58),0)+IF(I$19=$A60,I$49,0) -> 0 | J60: =IF(J$19<=$A60,SUM(J$57:J$58),0)+IF(J$19=$A60,J$49,0) -> 0 | ... L60: =IF(L$19<=$A60,SUM(L$57:L$58),0)+IF(L$19=$A60,L$49,0) -> 0
A61: IRR | B61: =IFERROR(IRR(C60:L60),"-") -> 0.20592816
A63: 7 | B63: -year cash flow | C63: =IF(C$19<=$A63,SUM(C$57:C$58),0)+IF(C$19=$A63,C$49,0) -> -5000000 | D63: =IF(D$19<=$A63,SUM(D$57:D$58),0)+IF(D$19=$A63,D$49,0) -> 0 | E63: =IF(E$19<=$A63,SUM(E$57:E$58),0)+IF(E$19=$A63,E$49,0) -> 0 | F63: =IF(F$19<=$A63,SUM(F$57:F$58),0)+IF(F$19=$A63,F$49,0) -> -9245415.5 | G63: =IF(G$19<=$A63,SUM(G$57:G$58),0)+IF(G$19=$A63,G$49,0) -> 261704.69 | H63: =IF(H$19<=$A63,SUM(H$57:H$58),0)+IF(H$19=$A63,H$49,0) -> 306500.39 | I63: =IF(I$19<=$A63,SUM(I$57:I$58),0)+IF(I$19=$A63,I$49,0) -> 26027717 | J63: =IF(J$19<=$A63,SUM(J$57:J$58),0)+IF(J$19=$A63,J$49,0) -> 0 | ... L63: =IF(L$19<=$A63,SUM(L$57:L$58),0)+IF(L$19=$A63,L$49,0) -> 0
A64: IRR | B64: =IRR(C63:L63) -> 0.16122754
A66: 10 | B66: -year cash flow | C66: =IF(C$19<=$A66,SUM(C$57:C$58),0)+IF(C$19=$A66,C$49,0) -> -5000000 | D66: =IF(D$19<=$A66,SUM(D$57:D$58),0)+IF(D$19=$A66,D$49,0) -> 0 | E66: =IF(E$19<=$A66,SUM(E$57:E$58),0)+IF(E$19=$A66,E$49,0) -> 0 | F66: =IF(F$19<=$A66,SUM(F$57:F$58),0)+IF(F$19=$A66,F$49,0) -> -9245415.5 | G66: =IF(G$19<=$A66,SUM(G$57:G$58),0)+IF(G$19=$A66,G$49,0) -> 261704.69 | H66: =IF(H$19<=$A66,SUM(H$57:H$58),0)+IF(H$19=$A66,H$49,0) -> 306500.39 | I66: =IF(I$19<=$A66,SUM(I$57:I$58),0)+IF(I$19=$A66,I$49,0) -> 352192 | J66: =IF(J$19<=$A66,SUM(J$57:J$58),0)+IF(J$19=$A66,J$49,0) -> 398797.44 | ... L66: =IF(L$19<=$A66,SUM(L$57:L$58),0)+IF(L$19=$A66,L$49,0) -> 32892323
A67: IRR | B67: =IRR(C66:L66) -> 0.13515738
A74: Loan Amortization Schedule
A75: Period | B75: Month | C75: Year | D75: Principal | E75: Interest | F75: Beginning Balance | G75: Ending Balance
A76: 1 | B76: =EDATE(Schedule!$E$21,1) -> 45717 | C76: =YEAR(B76) -> 2025 | D76: =PPMT($E$14/12,A76,$E$15*12,$F$76) -> -77937.82 | E76: =IPMT($E$14/12,A76,$E$15*12,$F$76) -> -86902.194 | F76: =K14 -> 34760878 | G76: =F76+D76 -> 34682940
A77: 2 | B77: =EDATE(B76,1) -> 45748 | C77: =YEAR(B77) -> 2025 | D77: =PPMT($E$14/12,A77,$E$15*12,$F$76) -> -78132.665 | E77: =IPMT($E$14/12,A77,$E$15*12,$F$76) -> -86707.349 | F77: =G76 -> 34682940 | G77: =F77+D77 -> 34604807
A78: 3 | B78: =EDATE(B77,1) -> 45778 | C78: =YEAR(B78) -> 2025 | D78: =PPMT($E$14/12,A78,$E$15*12,$F$76) -> -78327.996 | E78: =IPMT($E$14/12,A78,$E$15*12,$F$76) -> -86512.018 | F78: =G77 -> 34604807 | G78: =F78+D78 -> 34526479
A79: 4 | B79: =EDATE(B78,1) -> 45809 | C79: =YEAR(B79) -> 2025 | D79: =PPMT($E$14/12,A79,$E$15*12,$F$76) -> -78523.816 | E79: =IPMT($E$14/12,A79,$E$15*12,$F$76) -> -86316.198 | F79: =G78 -> 34526479 | G79: =F79+D79 -> 34447955
A80: 5 | B80: =EDATE(B79,1) -> 45839 | C80: =YEAR(B80) -> 2025 | D80: =PPMT($E$14/12,A80,$E$15*12,$F$76) -> -78720.126 | E80: =IPMT($E$14/12,A80,$E$15*12,$F$76) -> -86119.888 | F80: =G79 -> 34447955 | G80: =F80+D80 -> 34369235
A81: 6 | B81: =EDATE(B80,1) -> 45870 | C81: =YEAR(B81) -> 2025 | D81: =PPMT($E$14/12,A81,$E$15*12,$F$76) -> -78916.926 | E81: =IPMT($E$14/12,A81,$E$15*12,$F$76) -> -85923.088 | F81: =G80 -> 34369235 | G81: =F81+D81 -> 34290318
A82: 7 | B82: =EDATE(B81,1) -> 45901 | C82: =YEAR(B82) -> 2025 | D82: =PPMT($E$14/12,A82,$E$15*12,$F$76) -> -79114.219 | E82: =IPMT($E$14/12,A82,$E$15*12,$F$76) -> -85725.795 | F82: =G81 -> 34290318 | G82: =F82+D82 -> 34211204
A83: 8 | B83: =EDATE(B82,1) -> 45931 | C83: =YEAR(B83) -> 2025 | D83: =PPMT($E$14/12,A83,$E$15*12,$F$76) -> -79312.004 | E83: =IPMT($E$14/12,A83,$E$15*12,$F$76) -> -85528.01 | F83: =G82 -> 34211204 | G83: =F83+D83 -> 34131892
A84: 9 | B84: =EDATE(B83,1) -> 45962 | C84: =YEAR(B84) -> 2025 | D84: =PPMT($E$14/12,A84,$E$15*12,$F$76) -> -79510.284 | E84: =IPMT($E$14/12,A84,$E$15*12,$F$76) -> -85329.73 | F84: =G83 -> 34131892 | G84: =F84+D84 -> 34052382
A85: 10 | B85: =EDATE(B84,1) -> 45992 | C85: =YEAR(B85) -> 2025 | D85: =PPMT($E$14/12,A85,$E$15*12,$F$76) -> -79709.06 | E85: =IPMT($E$14/12,A85,$E$15*12,$F$76) -> -85130.954 | F85: =G84 -> 34052382 | G85: =F85+D85 -> 33972673
A86: 11 | B86: =EDATE(B85,1) -> 46023 | C86: =YEAR(B86) -> 2026 | D86: =PPMT($E$14/12,A86,$E$15*12,$F$76) -> -79908.333 | E86: =IPMT($E$14/12,A86,$E$15*12,$F$76) -> -84931.682 | F86: =G85 -> 33972673 | G86: =F86+D86 -> 33892764
A87: 12 | B87: =EDATE(B86,1) -> 46054 | C87: =YEAR(B87) -> 2026 | D87: =PPMT($E$14/12,A87,$E$15*12,$F$76) -> -80108.103 | E87: =IPMT($E$14/12,A87,$E$15*12,$F$76) -> -84731.911 | F87: =G86 -> 33892764 | G87: =F87+D87 -> 33812656
A88: 13 | B88: =EDATE(B87,1) -> 46082 | C88: =YEAR(B88) -> 2026 | D88: =PPMT($E$14/12,A88,$E$15*12,$F$76) -> -80308.374 | E88: =IPMT($E$14/12,A88,$E$15*12,$F$76) -> -84531.64 | F88: =G87 -> 33812656 | G88: =F88+D88 -> 33732348
... A195: 120 | B195: =EDATE(B194,1) -> 49341 | C195: =YEAR(B195) -> 2035 | D195: =PPMT($E$14/12,A195,$E$15*12,$F$76) -> -104903.42 | E195: =IPMT($E$14/12,A195,$E$15*12,$F$76) -> -59936.598 | F195: =G194 -> 23974639 | G195: =F195+D195 -> 23869736

Sheet HST
K1: ='Executive Summary'!J1 -> Currently running: Base Case
B4: ='Executive Summary'!B3:I3 -> Apartment Development Model
B5: ='Executive Summary'!B4:I4 -> Suburban / Urban Location
B8: HST ON SELF SUPPLY
H10: Consideration | I10: HST | J10: Federal | K10: Provincial
H11: for HST | I11: Payable | J11: Rebate | K11: Rebate
B13: AVERAGE PRICE PER UNIT | F13: =F31 -> 516674.71 | H13: =IFERROR(IF(AND($F13>=0,$F13<=368200),$F13/1.052,IF(AND($F13>=368200,$F13<=424850),($F13+28350)/1.133,IF(AND($F13>=424850,$F13<=484500),($F13+52350)/1.193,IF($F13>=484500,($F13+24000)/1.13)))),0) -> 478473.19 | I13: =H13*0.13 -> 62201.515 | J13: =IF(6300*((450000-$H13)/100000)<0,0,IF(AND($C13>=0,$C13<=368200),($H13*5%)*36%,IF($C13>=368200,6300*(450000-$H13)/100000))) -> 0 | K13: =IF(AND($H13*8%*75%>=0,$H13*8%*75%<=24000),$H13*8%*75%,24000) -> 24000 | M13: =+H13 -> 478473.19 | N13: < consideration for CRA purposes
M14: =+M13*0.13 -> 62201.515 | N14: < applicable HST @ 13%
B15: NET HST PAYABLE UNDER SELF SUPPLY RULE PER UNIT | F15: =I13-K13-J13 -> 38201.515 | M15: =-K13-J13 -> -24000 | N15: < Max Rebate applicable
B16: EFFECTIVE HST RATE | F16: =F15/F13 -> 0.073937266 | M16: =+M13+M14+M15 -> 516674.71 | N16: < Sale or Purchase Price inclusive of HST
B18: HST PAYABLE ON RES COMPONENT | F18: =F15*F29 -> 3820151.5
B23: VALUE FOR HST PURPOSES | F23: ='Executive Summary'!G11*1 -> 51667471 | H23: Assuming 100% of higher cap value (ref to Exec Summ)
H24: Keep an eye on this value number
B25: LESS RETAIL COMPONENT: | F25: 0
B27: NET RESIDENTIAL SALES | F27: =F23-F25 -> 51667471
B29: NO. OF RESIDENTIAL UNITS | F29: ='Operating Revenue and Expenses'!F19 -> 100
B31: AVERAGE PRICE PER UNIT | F31: =F27/F29 -> 516674.71 | M31: =IFERROR(IF(AND(#REF!>=0,#REF!<=368200),#REF!/1.052,IF(AND(#REF!>=368200,#REF!<=424850),(#REF!+28350)/1.133,IF(AND(#REF!>=424850,#REF!<=484500),(#REF!+52350)/1.193,IF(#REF!>=484500,(#REF!+24000)/1.13)))),0) -> 0
B36: Note: This is a rough approximation of the estimate and a formal appraisal at or around completion will be required to estimate accurate amount/s.
